Workbook

Sheet DATA
A2: ASSET REF | B2: ASSET NAME | C2: PO NUMBER | D2: ACC REF | E2: CONTRACTOR / CONSULTANTS | F2: INITIAL | G2: CONTRACTOR / CONSULTANT / DIRECT ACTUAL | H2: PACKAGE | I2: CODE 1 | J2: CODE 2 | K2: CODE 3 | L2: CODE 4 | M2: ACC 1 | N2: ACC 2 | O2: ACC 3
A3: 1.TB.01.003.01 | B3: AMAALAYachtClub | C3: 2210224 | D3: 003C13 | E3: Soil Improvement Contracting | F3: SOIL IMPROVE | G3: Contractor | H3: Triple Bay Wide Ground Improvement | I3: CN | J3: =RIGHT(A3,2) -> 01 | K3: =I3&"."&D3 -> CN.003C13 | L3: =E3&" - "&C3 -> Soil Improvement Contracting - 2210224 | M3: ="1TB01006"&"."&J3&"."&I3&"."&D3&".00" -> 1TB01006.01.CN.003C13.00 | N3: ="1TB01006"&"."&J3&"."&I3&"."&D3&".01" -> 1TB01006.01.CN.003C13.01 | O3: ="1TB01006"&"."&J3&"."&I3&"."&D3&".02" -> 1TB01006.01.CN.003C13.02
A4: 1.TB.01.003.01 | B4: AMAALAYachtClub | C4: 2210167 | D4: 003D04 | E4: Applied Technology and Management Inc (Dubai BR) | F4: APPLIED TECH | G4: Consultant | H4: Rapid Peer Review of AMAALA Existing Design of Yachting and Marina Facilities | I4: PS | J4: =RIGHT(A4,2) -> 01 | K4: =I4&"."&D4 -> PS.003D04 | L4: =E4&" - "&C4 -> Applied Technology and Management Inc (Dubai BR) - 2210167 | M4: ="1TB01006"&"."&J4&"."&I4&"."&D4&".00" -> 1TB01006.01.PS.003D04.00 | N4: ="1TB01006"&"."&J4&"."&I4&"."&D4&".01" -> 1TB01006.01.PS.003D04.01 | O4: ="1TB01006"&"."&J4&"."&I4&"."&D4&".02" -> 1TB01006.01.PS.003D04.02
A5: 1.TB.01.003.01 | B5: AMAALAYachtClub | C5: 2200445 | D5: 003D01 | E5: Dewan Architects & Engineers | F5: DEWAN | G5: Consultant | H5: Triple Bay Hijaz Yacht Club - Lead Consultant Services | I5: PS | J5: =RIGHT(A5,2) -> 01 | K5: =I5&"."&D5 -> PS.003D01 | L5: =E5&" - "&C5 -> Dewan Architects & Engineers - 2200445 | M5: ="1TB01006"&"."&J5&"."&I5&"."&D5&".00" -> 1TB01006.01.PS.003D01.00 | N5: ="1TB01006"&"."&J5&"."&I5&"."&D5&".01" -> 1TB01006.01.PS.003D01.01 | O5: ="1TB01006"&"."&J5&"."&I5&"."&D5&".02" -> 1TB01006.01.PS.003D01.02
A6: 1.TB.01.003.01 | B6: AMAALAYachtClub | C6: 2200375 | D6: 003D03 | E6: HKS Architects Limited | F6: HKS | G6: Consultant | H6: Triple Bay Marine Yacht Club - Design Architect Consultancy Services | I6: PS | J6: =RIGHT(A6,2) -> 01 | K6: =I6&"."&D6 -> PS.003D03 | L6: =E6&" - "&C6 -> HKS Architects Limited - 2200375 | M6: ="1TB01006"&"."&J6&"."&I6&"."&D6&".00" -> 1TB01006.01.PS.003D03.00 | N6: ="1TB01006"&"."&J6&"."&I6&"."&D6&".01" -> 1TB01006.01.PS.003D03.01 | O6: ="1TB01006"&"."&J6&"."&I6&"."&D6&".02" -> 1TB01006.01.PS.003D03.02
A7: 1.TB.01.003.01 | B7: AMAALAYachtClub | C7: 2200010 | D7: 003D02 | E7: HKS Architects Limited | F7: HKS | G7: Consultant | H7: Design Competition | I7: PS | J7: =RIGHT(A7,2) -> 01 | K7: =I7&"."&D7 -> PS.003D02 | L7: =E7&" - "&C7 -> HKS Architects Limited - 2200010 | M7: ="1TB01006"&"."&J7&"."&I7&"."&D7&".00" -> 1TB01006.01.PS.003D02.00 | N7: ="1TB01006"&"."&J7&"."&I7&"."&D7&".01" -> 1TB01006.01.PS.003D02.01 | O7: ="1TB01006"&"."&J7&"."&I7&"."&D7&".02" -> 1TB01006.01.PS.003D02.02
A8: 1.TB.01.003.01 | B8: AMAALAYachtClub | C8: 2220032 | D8: 003C14 | E8: NSCC International Saudi Contracting | F8: NSCC | G8: Contractor | H8: Triple Bay Piling - Beach, RSMLI, Yacht Club and Marina Village Precinct (Hotel 1 and 2) | I8: CN | J8: =RIGHT(A8,2) -> 01 | K8: =I8&"."&D8 -> CN.003C14 | L8: =E8&" - "&C8 -> NSCC International Saudi Contracting - 2220032 | M8: ="1TB01006"&"."&J8&"."&I8&"."&D8&".00" -> 1TB01006.01.CN.003C14.00 | N8: ="1TB01006"&"."&J8&"."&I8&"."&D8&".01" -> 1TB01006.01.CN.003C14.01 | O8: ="1TB01006"&"."&J8&"."&I8&"."&D8&".02" -> 1TB01006.01.CN.003C14.02
A9: 1.TB.01.003.01 | B9: AMAALAYachtClub | C9: 2220038 | D9: 003C20 | E9: Green Business Certification Inc | F9: GREEN BUSSINESS | G9: Direct Actuals | H9: Sustainability Accreditation, third party technical reviews and verification of LEED-registered AMAALA Projects | I9: CN | J9: =RIGHT(A9,2) -> 01 | K9: =I9&"."&D9 -> CN.003C20 | L9: =E9&" - "&C9 -> Green Business Certification Inc - 2220038 | M9: ="1TB01006"&"."&J9&"."&I9&"."&D9&".00" -> 1TB01006.01.CN.003C20.00 | N9: ="1TB01006"&"."&J9&"."&I9&"."&D9&".01" -> 1TB01006.01.CN.003C20.01 | O9: ="1TB01006"&"."&J9&"."&I9&"."&D9&".02" -> 1TB01006.01.CN.003C20.02
A10: 1.TB.01.003.01 | B10: AMAALAYachtClub | C10: 2230023 | D10: 003C03 | E10: Saudi Arabian Baytur Construction Company | F10: BAYTUR | G10: Contractor | H10: Construction Contract - Site Enabling, Civil Works, Structural Concrete, Structural Steel, BOH Finishes, Building Envelope, MEP Including Tertiary Infrastructure & ICT/ELV | I10: CN | J10: =RIGHT(A10,2) -> 01 | K10: =I10&"."&D10 -> CN.003C03 | L10: =E10&" - "&C10 -> Saudi Arabian Baytur Construction Company - 2230023 | M10: ="1TB01006"&"."&J10&"."&I10&"."&D10&".00" -> 1TB01006.01.CN.003C03.00 | N10: ="1TB01006"&"."&J10&"."&I10&"."&D10&".01" -> 1TB01006.01.CN.003C03.01 | O10: ="1TB01006"&"."&J10&"."&I10&"."&D10&".02" -> 1TB01006.01.CN.003C03.02
A11: 1.TB.01.003.01 | B11: AMAALAYachtClub | C11: 2230042 | D11: 003D05 | E11: LANGAN International UK, LTD | F11: LANGAN INNTERNATIONAL | G11: Consultant | H11: Geotechnical Consultancy Services (Yacht Club) - Peer Review | I11: PS | J11: =RIGHT(A11,2) -> 01 | K11: =I11&"."&D11 -> PS.003D05 | L11: =E11&" - "&C11 -> LANGAN International UK, LTD - 2230042 | M11: ="1TB01006"&"."&J11&"."&I11&"."&D11&".00" -> 1TB01006.01.PS.003D05.00 | N11: ="1TB01006"&"."&J11&"."&I11&"."&D11&".01" -> 1TB01006.01.PS.003D05.01 | O11: ="1TB01006"&"."&J11&"."&I11&"."&D11&".02" -> 1TB01006.01.PS.003D05.02
A12: 1.TB.01.003.01 | B12: AMAALAYachtClub | C12: 2230075 | D12: 003C21 | E12: Medtel - W.N | F12: MEDTEL | G12: Contractor | H12: Sto Façade Mock-Up | I12: CN | J12: =RIGHT(A12,2) -> 01 | K12: =I12&"."&D12 -> CN.003C21 | L12: =E12&" - "&C12 -> Medtel - W.N - 2230075 | M12: ="1TB01006"&"."&J12&"."&I12&"."&D12&".00" -> 1TB01006.01.CN.003C21.00 | N12: ="1TB01006"&"."&J12&"."&I12&"."&D12&".01" -> 1TB01006.01.CN.003C21.01 | O12: ="1TB01006"&"."&J12&"."&I12&"."&D12&".02" -> 1TB01006.01.CN.003C21.02
A13: 1.TB.01.003.01 | B13: AMAALAYachtClub | C13: 2230031 | D13: 003F02 | E13: Saudi Consolidated Engineering Company - Khatib & Alami | F13: KHATIB & ALAMI | G13: Consultant | H13: Construction Supervision Services - AMAALA Yacht Club (Call off Order No: 003) | I13: MS | J13: =RIGHT(A13,2) -> 01 | K13: =I13&"."&D13 -> MS.003F02 | L13: =E13&" - "&C13 -> Saudi Consolidated Engineering Company - Khatib & Alami - 2230031 | M13: ="1TB01006"&"."&J13&"."&I13&"."&D13&".00" -> 1TB01006.01.MS.003F02.00 | N13: ="1TB01006"&"."&J13&"."&I13&"."&D13&".01" -> 1TB01006.01.MS.003F02.01 | O13: ="1TB01006"&"."&J13&"."&I13&"."&D13&".02" -> 1TB01006.01.MS.003F02.02
A14: 1.TB.01.003.01 | B14: AMAALAYachtClub | C14: 699226 | D14: 003D06 | E14: Ministry of Municipality and Rural Affairs | F14: MINISTRY | G14: Direct Actuals | H14: Permit Fees | I14: PS | J14: =RIGHT(A14,2) -> 01 | K14: =I14&"."&D14 -> PS.003D06 | L14: =E14&" - "&C14 -> Ministry of Municipality and Rural Affairs - 699226 | M14: ="1TB01006"&"."&J14&"."&I14&"."&D14&".00" -> 1TB01006.01.PS.003D06.00 | N14: ="1TB01006"&"."&J14&"."&I14&"."&D14&".01" -> 1TB01006.01.PS.003D06.01 | O14: ="1TB01006"&"."&J14&"."&I14&"."&D14&".02" -> 1TB01006.01.PS.003D06.02
... A31: 1.TB.01.003.01 | B31: AMAALAYachtClub | C31: 2250145 | D31: 003C37 | E31: Hassan Allam Construction Saudi Limited | F31: HASSAN ALLAM | G31: Contractor | H31: Scaffolding Services | I31: CN | J31: =RIGHT(A31,2) -> 01 | K31: =I31&"."&D31 -> CN.003C37 | L31: =E31&" - "&C31 -> Hassan Allam Construction Saudi Limited - 2250145 | M31: ="1TB01006"&"."&J31&"."&I31&"."&D31&".00" -> 1TB01006.01.CN.003C37.00 | N31: ="1TB01006"&"."&J31&"."&I31&"."&D31&".01" -> 1TB01006.01.CN.003C37.01 | O31: ="1TB01006"&"."&J31&"."&I31&"."&D31&".02" -> 1TB01006.01.CN.003C37.02
A32: 1.TB.01.003.01 | B32: AMAALAYachtClub | C32: BAYTUR_PAYMENT | D32: 003C66 | E32: Sami General Contracting Est. | F32: SAMI GENEERAL | G32: Contractor | H32: Payment On Behalf Of Saudi Arabian Baytur (Jan/Feb) | I32: CN | J32: =RIGHT(A32,2) -> 01 | K32: =I32&"."&D32 -> CN.003C66 | L32: =E32&" - "&C32 -> Sami General Contracting Est. - BAYTUR_PAYMENT | M32: ="1TB01006"&"."&J32&"."&I32&"."&D32&".00" -> 1TB01006.01.CN.003C66.00 | N32: ="1TB01006"&"."&J32&"."&I32&"."&D32&".01" -> 1TB01006.01.CN.003C66.01 | O32: ="1TB01006"&"."&J32&"."&I32&"."&D32&".02" -> 1TB01006.01.CN.003C66.02
A33: 1.TB.01.003.01 | B33: AMAALAYachtClub | C33: BAYTUR_PAYMENT | D33: 003C42 | E33: Saad Al Easa - Metal Industry | F33: SAAD | G33: Contractor | H33: Payment On Behalf Of Saudi Arabian Baytur (Jan/Feb) | I33: CN | J33: =RIGHT(A33,2) -> 01 | K33: =I33&"."&D33 -> CN.003C42 | L33: =E33&" - "&C33 -> Saad Al Easa - Metal Industry - BAYTUR_PAYMENT | M33: ="1TB01006"&"."&J33&"."&I33&"."&D33&".00" -> 1TB01006.01.CN.003C42.00 | N33: ="1TB01006"&"."&J33&"."&I33&"."&D33&".01" -> 1TB01006.01.CN.003C42.01 | O33: ="1TB01006"&"."&J33&"."&I33&"."&D33&".02" -> 1TB01006.01.CN.003C42.02
A34: 1.TB.01.003.01 | B34: AMAALAYachtClub | C34: BAYTUR_PAYMENT | D34: 003C70 | E34: Aldrees Petroleum and Transport Services Company | F34: ALDREES | G34: Contractor | H34: Payment On Behalf Of Saudi Arabian Baytur (Jan/Feb) | I34: CN | J34: =RIGHT(A34,2) -> 01 | K34: =I34&"."&D34 -> CN.003C70 | L34: =E34&" - "&C34 -> Aldrees Petroleum and Transport Services Company - BAYTUR_PAYMENT | M34: ="1TB01006"&"."&J34&"."&I34&"."&D34&".00" -> 1TB01006.01.CN.003C70.00 | N34: ="1TB01006"&"."&J34&"."&I34&"."&D34&".01" -> 1TB01006.01.CN.003C70.01 | O34: ="1TB01006"&"."&J34&"."&I34&"."&D34&".02" -> 1TB01006.01.CN.003C70.02
A35: 1.TB.01.003.01 | B35: AMAALAYachtClub | C35: BAYTUR_PAYMENT | D35: 003C69 | E35: Salim Hamed Cleaning | F35: SALIM | G35: Contractor | H35: Payment On Behalf Of Saudi Arabian Baytur (Jan/Feb) | I35: CN | J35: =RIGHT(A35,2) -> 01 | K35: =I35&"."&D35 -> CN.003C69 | L35: =E35&" - "&C35 -> Salim Hamed Cleaning - BAYTUR_PAYMENT | M35: ="1TB01006"&"."&J35&"."&I35&"."&D35&".00" -> 1TB01006.01.CN.003C69.00 | N35: ="1TB01006"&"."&J35&"."&I35&"."&D35&".01" -> 1TB01006.01.CN.003C69.01 | O35: ="1TB01006"&"."&J35&"."&I35&"."&D35&".02" -> 1TB01006.01.CN.003C69.02
A36: 1.TB.01.003.01 | B36: AMAALAYachtClub | C36: BAYTUR_PAYMENT | D36: 003C65 | E36: Eastern Horizon Foundation Transportation Comp. | F36: EASTERN | G36: Contractor | H36: Payment On Behalf Of Saudi Arabian Baytur (Jan/Feb) | I36: CN | J36: =RIGHT(A36,2) -> 01 | K36: =I36&"."&D36 -> CN.003C65 | L36: =E36&" - "&C36 -> Eastern Horizon Foundation Transportation Comp. - BAYTUR_PAYMENT | M36: ="1TB01006"&"."&J36&"."&I36&"."&D36&".00" -> 1TB01006.01.CN.003C65.00 | N36: ="1TB01006"&"."&J36&"."&I36&"."&D36&".01" -> 1TB01006.01.CN.003C65.01 | O36: ="1TB01006"&"."&J36&"."&I36&"."&D36&".02" -> 1TB01006.01.CN.003C65.02
A37: 1.TB.01.003.01 | B37: AMAALAYachtClub | C37: BAYTUR_PAYMENT | D37: 003C64 | E37: JAK Generation Cont. Co. LLC | F37: JAK | G37: Contractor | H37: Payment On Behalf Of Saudi Arabian Baytur (Jan/Feb) | I37: CN | J37: =RIGHT(A37,2) -> 01 | K37: =I37&"."&D37 -> CN.003C64 | L37: =E37&" - "&C37 -> JAK Generation Cont. Co. LLC - BAYTUR_PAYMENT | M37: ="1TB01006"&"."&J37&"."&I37&"."&D37&".00" -> 1TB01006.01.CN.003C64.00 | N37: ="1TB01006"&"."&J37&"."&I37&"."&D37&".01" -> 1TB01006.01.CN.003C64.01 | O37: ="1TB01006"&"."&J37&"."&I37&"."&D37&".02" -> 1TB01006.01.CN.003C64.02
A38: 1.TB.01.003.01 | B38: AMAALAYachtClub | C38: BAYTUR_PAYMENT | D38: 003C67 | E38: Clean Coast For Contracting | F38: CLEAN COAST | G38: Contractor | H38: Payment On Behalf Of Saudi Arabian Baytur (Jan/Feb) | I38: CN | J38: =RIGHT(A38,2) -> 01 | K38: =I38&"."&D38 -> CN.003C67 | L38: =E38&" - "&C38 -> Clean Coast For Contracting - BAYTUR_PAYMENT | M38: ="1TB01006"&"."&J38&"."&I38&"."&D38&".00" -> 1TB01006.01.CN.003C67.00 | N38: ="1TB01006"&"."&J38&"."&I38&"."&D38&".01" -> 1TB01006.01.CN.003C67.01 | O38: ="1TB01006"&"."&J38&"."&I38&"."&D38&".02" -> 1TB01006.01.CN.003C67.02
A39: 1.TB.01.003.01 | B39: AMAALAYachtClub | C39: BAYTUR_PAYMENT | D39: 003C61 | E39: Al Rai Modern Water Factory | F39: AL RAI | G39: Contractor | H39: Payment On Behalf Of Saudi Arabian Baytur (Jan/Feb) | I39: CN | J39: =RIGHT(A39,2) -> 01 | K39: =I39&"."&D39 -> CN.003C61 | L39: =E39&" - "&C39 -> Al Rai Modern Water Factory - BAYTUR_PAYMENT | M39: ="1TB01006"&"."&J39&"."&I39&"."&D39&".00" -> 1TB01006.01.CN.003C61.00 | N39: ="1TB01006"&"."&J39&"."&I39&"."&D39&".01" -> 1TB01006.01.CN.003C61.01 | O39: ="1TB01006"&"."&J39&"."&I39&"."&D39&".02" -> 1TB01006.01.CN.003C61.02
A40: 1.TB.01.003.01 | B40: AMAALAYachtClub | C40: BAYTUR_PAYMENT | D40: 003C57 | E40: Juffali Technical Equipment Company | F40: JUFFALI TTECHNICAL | G40: Contractor | H40: Payment On Behalf Of Saudi Arabian Baytur (Jan/Feb) | I40: CN | J40: =RIGHT(A40,2) -> 01 | K40: =I40&"."&D40 -> CN.003C57 | L40: =E40&" - "&C40 -> Juffali Technical Equipment Company - BAYTUR_PAYMENT | M40: ="1TB01006"&"."&J40&"."&I40&"."&D40&".00" -> 1TB01006.01.CN.003C57.00 | N40: ="1TB01006"&"."&J40&"."&I40&"."&D40&".01" -> 1TB01006.01.CN.003C57.01 | O40: ="1TB01006"&"."&J40&"."&I40&"."&D40&".02" -> 1TB01006.01.CN.003C57.02
A41: 1.TB.01.003.01 | B41: AMAALAYachtClub | C41: BAYTUR_PAYMENT | D41: 003C63 | E41: Intelligent General Cont. Co - Equipment - Industrial Forklift & 5ton | F41: INTELLIGENT | G41: Contractor | H41: Payment On Behalf Of Saudi Arabian Baytur (Jan/Feb) | I41: CN | J41: =RIGHT(A41,2) -> 01 | K41: =I41&"."&D41 -> CN.003C63 | L41: =E41&" - "&C41 -> Intelligent General Cont. Co - Equipment - Industrial Forklift & 5ton - BAYTUR_PAYMENT | M41: ="1TB01006"&"."&J41&"."&I41&"."&D41&".00" -> 1TB01006.01.CN.003C63.00 | N41: ="1TB01006"&"."&J41&"."&I41&"."&D41&".01" -> 1TB01006.01.CN.003C63.01 | O41: ="1TB01006"&"."&J41&"."&I41&"."&D41&".02" -> 1TB01006.01.CN.003C63.02
A42: 1.TB.01.003.01 | B42: AMAALAYachtClub | C42: BAYTUR_PAYMENT | D42: 003C71 | E42: Al-Anan Travels and Tours | F42: AL ANAN | G42: Contractor | H42: Payment On Behalf Of Saudi Arabian Baytur (Jan/Feb) | I42: CN | J42: =RIGHT(A42,2) -> 01 | K42: =I42&"."&D42 -> CN.003C71 | L42: =E42&" - "&C42 -> Al-Anan Travels and Tours - BAYTUR_PAYMENT | M42: ="1TB01006"&"."&J42&"."&I42&"."&D42&".00" -> 1TB01006.01.CN.003C71.00 | N42: ="1TB01006"&"."&J42&"."&I42&"."&D42&".01" -> 1TB01006.01.CN.003C71.01 | O42: ="1TB01006"&"."&J42&"."&I42&"."&D42&".02" -> 1TB01006.01.CN.003C71.02
A43: 1.TB.01.003.01 | B43: AMAALAYachtClub | C43: BAYTUR_PAYMENT | D43: 003C58 | E43: Madar Building Material Co. | F43: MADAR BUIILDING | G43: Contractor | H43: Payment On Behalf Of Saudi Arabian Baytur (Jan/Feb) | I43: CN | J43: =RIGHT(A43,2) -> 01 | K43: =I43&"."&D43 -> CN.003C58 | L43: =E43&" - "&C43 -> Madar Building Material Co. - BAYTUR_PAYMENT | M43: ="1TB01006"&"."&J43&"."&I43&"."&D43&".00" -> 1TB01006.01.CN.003C58.00 | N43: ="1TB01006"&"."&J43&"."&I43&"."&D43&".01" -> 1TB01006.01.CN.003C58.01 | O43: ="1TB01006"&"."&J43&"."&I43&"."&D43&".02" -> 1TB01006.01.CN.003C58.02
... A90: 1.TB.01.003.01 | B90: AMAALAYachtClub | C90: BAYTUR_PAYMENT | D90: 003C79 | E90: Glsan Contracting Company | F90: GLSAN | G90: Contractor | H90: Payment On Behalf Of Saudi Arabian Baytur (Mar) | I90: CN | J90: =RIGHT(A90,2) -> 01 | K90: =I90&"."&D90 -> CN.003C79 | L90: =E90&" - "&C90 -> Glsan Contracting Company - BAYTUR_PAYMENT | M90: ="1TB01006"&"."&J90&"."&I90&"."&D90&".00" -> 1TB01006.01.CN.003C79.00 | N90: ="1TB01006"&"."&J90&"."&I90&"."&D90&".01" -> 1TB01006.01.CN.003C79.01 | O90: ="1TB01006"&"."&J90&"."&I90&"."&D90&".02" -> 1TB01006.01.CN.003C79.02
A91: 1.TB.01.003.01 | B91: AMAALAYachtClub | C91: 2250184 | D91: 003F10 | E91: Jensen Hughes Saudi Arabia, LLC | F91: JENSEN | G91: Consultant | H91: Third-Party Authority for Fire and Life Safety Review & Certification Endorsement (Call off Order No: 031) | I91: PS | J91: =RIGHT(A91,2) -> 01 | K91: =I91&"."&D91 -> PS.003F10 | L91: =E91&" - "&C91 -> Jensen Hughes Saudi Arabia, LLC - 2250184 | M91: ="1TB01006"&"."&J91&"."&I91&"."&D91&".00" -> 1TB01006.01.PS.003F10.00 | N91: ="1TB01006"&"."&J91&"."&I91&"."&D91&".01" -> 1TB01006.01.PS.003F10.01 | O91: ="1TB01006"&"."&J91&"."&I91&"."&D91&".02" -> 1TB01006.01.PS.003F10.02
A92: 1.TB.01.003.01 | B92: AMAALAYachtClub | C92: BAYTUR_PAYMENT | D92: 003C81 | E92: Jameel Mohammed Hussain Alqatafa Cont.Est. | F92: JAMEEL | G92: Contractor | H92: Payment On Behalf Of Saudi Arabian Baytur (Mar) | I92: CN | J92: =RIGHT(A92,2) -> 01 | K92: =I92&"."&D92 -> CN.003C81 | L92: =E92&" - "&C92 -> Jameel Mohammed Hussain Alqatafa Cont.Est. - BAYTUR_PAYMENT | M92: ="1TB01006"&"."&J92&"."&I92&"."&D92&".00" -> 1TB01006.01.CN.003C81.00 | N92: ="1TB01006"&"."&J92&"."&I92&"."&D92&".01" -> 1TB01006.01.CN.003C81.01 | O92: ="1TB01006"&"."&J92&"."&I92&"."&D92&".02" -> 1TB01006.01.CN.003C81.02
A93: 1.TB.01.003.01 | B93: AMAALAYachtClub | C93: BAYTUR_PAYMENT | D93: 003C89 | E93: Issam Kabani and Partners | F93: ISSAM KABBANI | G93: Contractor | H93: Payment On Behalf Of Saudi Arabian Baytur (Mar) | I93: CN | J93: =RIGHT(A93,2) -> 01 | K93: =I93&"."&D93 -> CN.003C89 | L93: =E93&" - "&C93 -> Issam Kabani and Partners - BAYTUR_PAYMENT | M93: ="1TB01006"&"."&J93&"."&I93&"."&D93&".00" -> 1TB01006.01.CN.003C89.00 | N93: ="1TB01006"&"."&J93&"."&I93&"."&D93&".01" -> 1TB01006.01.CN.003C89.01 | O93: ="1TB01006"&"."&J93&"."&I93&"."&D93&".02" -> 1TB01006.01.CN.003C89.02
A94: 1.TB.01.003.01 | B94: AMAALAYachtClub | C94: BAYTUR_PAYMENT | D94: 003C90 | E94: Saad Al Easa - Metal Industry | F94: SAAD | G94: Contractor | H94: Payment On Behalf Of Saudi Arabian Baytur (Mar) | I94: CN | J94: =RIGHT(A94,2) -> 01 | K94: =I94&"."&D94 -> CN.003C90 | L94: =E94&" - "&C94 -> Saad Al Easa - Metal Industry - BAYTUR_PAYMENT | M94: ="1TB01006"&"."&J94&"."&I94&"."&D94&".00" -> 1TB01006.01.CN.003C90.00 | N94: ="1TB01006"&"."&J94&"."&I94&"."&D94&".01" -> 1TB01006.01.CN.003C90.01 | O94: ="1TB01006"&"."&J94&"."&I94&"."&D94&".02" -> 1TB01006.01.CN.003C90.02
A95: 1.TB.01.003.01 | B95: AMAALAYachtClub | C95: BAYTUR_PAYMENT | D95: 003C91 | E95: Medtel - W.N | F95: MEDTEL | G95: Contractor | H95: Payment On Behalf Of Saudi Arabian Baytur (Mar) | I95: CN | J95: =RIGHT(A95,2) -> 01 | K95: =I95&"."&D95 -> CN.003C91 | L95: =E95&" - "&C95 -> Medtel - W.N - BAYTUR_PAYMENT | M95: ="1TB01006"&"."&J95&"."&I95&"."&D95&".00" -> 1TB01006.01.CN.003C91.00 | N95: ="1TB01006"&"."&J95&"."&I95&"."&D95&".01" -> 1TB01006.01.CN.003C91.01 | O95: ="1TB01006"&"."&J95&"."&I95&"."&D95&".02" -> 1TB01006.01.CN.003C91.02
A96: 1.TB.01.003.01 | B96: AMAALAYachtClub | C96: BAYTUR_PAYMENT | D96: 003C82 | E96: Gesr Alarab | F96: GESR | G96: Contractor | H96: Payment On Behalf Of Saudi Arabian Baytur (Mar) | I96: CN | J96: =RIGHT(A96,2) -> 01 | K96: =I96&"."&D96 -> CN.003C82 | L96: =E96&" - "&C96 -> Gesr Alarab - BAYTUR_PAYMENT | M96: ="1TB01006"&"."&J96&"."&I96&"."&D96&".00" -> 1TB01006.01.CN.003C82.00 | N96: ="1TB01006"&"."&J96&"."&I96&"."&D96&".01" -> 1TB01006.01.CN.003C82.01 | O96: ="1TB01006"&"."&J96&"."&I96&"."&D96&".02" -> 1TB01006.01.CN.003C82.02
A97: 1.TB.01.003.01 | B97: AMAALAYachtClub | C97: BAYTUR_PAYMENT | D97: 003C80 | E97: Glsan Contracting Company | F97: GLSAN | G97: Contractor | H97: Payment On Behalf Of Saudi Arabian Baytur (Mar) | I97: CN | J97: =RIGHT(A97,2) -> 01 | K97: =I97&"."&D97 -> CN.003C80 | L97: =E97&" - "&C97 -> Glsan Contracting Company - BAYTUR_PAYMENT | M97: ="1TB01006"&"."&J97&"."&I97&"."&D97&".00" -> 1TB01006.01.CN.003C80.00 | N97: ="1TB01006"&"."&J97&"."&I97&"."&D97&".01" -> 1TB01006.01.CN.003C80.01 | O97: ="1TB01006"&"."&J97&"."&I97&"."&D97&".02" -> 1TB01006.01.CN.003C80.02
A98: 1.TB.01.003.01 | B98: AMAALAYachtClub | C98: N/A | D98: 003CXX | E98: Ahmed Bin Salem Bin Dagher Al-Balawi Est. | F98: AHMED BIN SALEM | G98: Contractor | H98: Payment On Behalf Of Saudi Arabian Baytur (Mar)_CONTRACT CANCELLED_CONTRACT VALUE SAR 22,058.81 | I98: CN | J98: =RIGHT(A98,2) -> 01 | K98: =I98&"."&D98 -> CN.003CXX | L98: =E98&" - "&C98 -> Ahmed Bin Salem Bin Dagher Al-Balawi Est. - N/A | M98: ="1TB01006"&"."&J98&"."&I98&"."&D98&".00" -> 1TB01006.01.CN.003CXX.00 | N98: ="1TB01006"&"."&J98&"."&I98&"."&D98&".01" -> 1TB01006.01.CN.003CXX.01 | O98: ="1TB01006"&"."&J98&"."&I98&"."&D98&".02" -> 1TB01006.01.CN.003CXX.02
A99: 1.TB.01.003.01 | B99: AMAALAYachtClub | C99: BAYTUR_PAYMENT | D99: 003C149 | E99: Clean Coast For Contracting | F99: CLEAN COAST | G99: Contractor | H99: Payment On Behalf Of Saudi Arabian Baytur (Mar) | I99: CN | J99: =RIGHT(A99,2) -> 01 | K99: =I99&"."&D99 -> CN.003C149 | L99: =E99&" - "&C99 -> Clean Coast For Contracting - BAYTUR_PAYMENT | M99: ="1TB01006"&"."&J99&"."&I99&"."&D99&".00" -> 1TB01006.01.CN.003C149.00 | N99: ="1TB01006"&"."&J99&"."&I99&"."&D99&".01" -> 1TB01006.01.CN.003C149.01 | O99: ="1TB01006"&"."&J99&"."&I99&"."&D99&".02" -> 1TB01006.01.CN.003C149.02
A100: 1.TB.01.003.01 | B100: AMAALAYachtClub | C100: 2250196 | D100: 003C150 | E100: Al Rajhi Company For Cooperative Insurance | F100: AL RAJHI | G100: Contractor | H100: OCIP Insurance Premium - Declaration 9 | I100: CN | J100: =RIGHT(A100,2) -> 01 | K100: =I100&"."&D100 -> CN.003C150 | L100: =E100&" - "&C100 -> Al Rajhi Company For Cooperative Insurance - 2250196 | M100: ="1TB01006"&"."&J100&"."&I100&"."&D100&".00" -> 1TB01006.01.CN.003C150.00 | N100: ="1TB01006"&"."&J100&"."&I100&"."&D100&".01" -> 1TB01006.01.CN.003C150.01 | O100: ="1TB01006"&"."&J100&"."&I100&"."&D100&".02" -> 1TB01006.01.CN.003C150.02
A101: 1.TB.01.003.01 | B101: AMAALAYachtClub | C101: BAYTUR_PAYMENT | D101: 003C125 | E101: Yaz Development Contracting | F101: YAZ | G101: Contractor | H101: Payment On Behalf Of Saudi Arabian Baytur (Apr) | I101: CN | J101: =RIGHT(A101,2) -> 01 | K101: =I101&"."&D101 -> CN.003C125 | L101: =E101&" - "&C101 -> Yaz Development Contracting - BAYTUR_PAYMENT | M101: ="1TB01006"&"."&J101&"."&I101&"."&D101&".00" -> 1TB01006.01.CN.003C125.00 | N101: ="1TB01006"&"."&J101&"."&I101&"."&D101&".01" -> 1TB01006.01.CN.003C125.01 | O101: ="1TB01006"&"."&J101&"."&I101&"."&D101&".02" -> 1TB01006.01.CN.003C125.02
A102: 1.TB.01.003.01 | B102: AMAALAYachtClub | C102: BAYTUR_PAYMENT | D102: 003C124 | E102: Gesr Alarab | F102: GESR | G102: Contractor | H102: Payment On Behalf Of Saudi Arabian Baytur (Apr) | I102: CN | J102: =RIGHT(A102,2) -> 01 | K102: =I102&"."&D102 -> CN.003C124 | L102: =E102&" - "&C102 -> Gesr Alarab - BAYTUR_PAYMENT | M102: ="1TB01006"&"."&J102&"."&I102&"."&D102&".00" -> 1TB01006.01.CN.003C124.00 | N102: ="1TB01006"&"."&J102&"."&I102&"."&D102&".01" -> 1TB01006.01.CN.003C124.01 | O102: ="1TB01006"&"."&J102&"."&I102&"."&D102&".02" -> 1TB01006.01.CN.003C124.02
A103: 1.TB.01.003.01 | B103: AMAALAYachtClub | C103: BAYTUR_PAYMENT | D103: 003C117 | E103: Abeer Manawer Al-Shamari Contracting Est. | F103: ABEER | G103: Contractor | H103: Payment On Behalf Of Saudi Arabian Baytur (Apr) | I103: CN | J103: =RIGHT(A103,2) -> 01 | K103: =I103&"."&D103 -> CN.003C117 | L103: =E103&" - "&C103 -> Abeer Manawer Al-Shamari Contracting Est. - BAYTUR_PAYMENT | M103: ="1TB01006"&"."&J103&"."&I103&"."&D103&".00" -> 1TB01006.01.CN.003C117.00 | N103: ="1TB01006"&"."&J103&"."&I103&"."&D103&".01" -> 1TB01006.01.CN.003C117.01 | O103: ="1TB01006"&"."&J103&"."&I103&"."&D103&".02" -> 1TB01006.01.CN.003C117.02
A104: 1.TB.01.003.01 | B104: AMAALAYachtClub | C104: BAYTUR_PAYMENT | D104: 003C109 | E104: Glsan Contracting Company | F104: GLSAN | G104: Contractor | H104: Payment On Behalf Of Saudi Arabian Baytur (Apr) | I104: CN | J104: =RIGHT(A104,2) -> 01 | K104: =I104&"."&D104 -> CN.003C109 | L104: =E104&" - "&C104 -> Glsan Contracting Company - BAYTUR_PAYMENT | M104: ="1TB01006"&"."&J104&"."&I104&"."&D104&".00" -> 1TB01006.01.CN.003C109.00 | N104: ="1TB01006"&"."&J104&"."&I104&"."&D104&".01" -> 1TB01006.01.CN.003C109.01 | O104: ="1TB01006"&"."&J104&"."&I104&"."&D104&".02" -> 1TB01006.01.CN.003C109.02
A105: 1.TB.01.003.01 | B105: AMAALAYachtClub | C105: BAYTUR_PAYMENT | D105: 003C76 | E105: Wood Expert | F105: WOOD | G105: Contractor | H105: Payment On Behalf Of Saudi Arabian Baytur (Apr) | I105: CN | J105: =RIGHT(A105,2) -> 01 | K105: =I105&"."&D105 -> CN.003C76 | L105: =E105&" - "&C105 -> Wood Expert - BAYTUR_PAYMENT | M105: ="1TB01006"&"."&J105&"."&I105&"."&D105&".00" -> 1TB01006.01.CN.003C76.00 | N105: ="1TB01006"&"."&J105&"."&I105&"."&D105&".01" -> 1TB01006.01.CN.003C76.01 | O105: ="1TB01006"&"."&J105&"."&I105&"."&D105&".02" -> 1TB01006.01.CN.003C76.02
A106: 1.TB.01.003.01 | B106: AMAALAYachtClub | C106: BAYTUR_PAYMENT | D106: 003C146 | E106: Al Tala'a International Transportation Co. | F106: AL TALA'A | G106: Contractor | H106: Payment On Behalf Of Saudi Arabian Baytur (Apr) | I106: CN | J106: =RIGHT(A106,2) -> 01 | K106: =I106&"."&D106 -> CN.003C146 | L106: =E106&" - "&C106 -> Al Tala'a International Transportation Co. - BAYTUR_PAYMENT | M106: ="1TB01006"&"."&J106&"."&I106&"."&D106&".00" -> 1TB01006.01.CN.003C146.00 | N106: ="1TB01006"&"."&J106&"."&I106&"."&D106&".01" -> 1TB01006.01.CN.003C146.01 | O106: ="1TB01006"&"."&J106&"."&I106&"."&D106&".02" -> 1TB01006.01.CN.003C146.02
A107: 1.TB.01.003.01 | B107: AMAALAYachtClub | C107: BAYTUR_PAYMENT | D107: 003C144 | E107: Glsan Contracting Company | F107: GLSAN | G107: Contractor | H107: Payment On Behalf Of Saudi Arabian Baytur (Apr) | I107: CN | J107: =RIGHT(A107,2) -> 01 | K107: =I107&"."&D107 -> CN.003C144 | L107: =E107&" - "&C107 -> Glsan Contracting Company - BAYTUR_PAYMENT | M107: ="1TB01006"&"."&J107&"."&I107&"."&D107&".00" -> 1TB01006.01.CN.003C144.00 | N107: ="1TB01006"&"."&J107&"."&I107&"."&D107&".01" -> 1TB01006.01.CN.003C144.01 | O107: ="1TB01006"&"."&J107&"."&I107&"."&D107&".02" -> 1TB01006.01.CN.003C144.02
A108: 1.TB.01.003.01 | B108: AMAALAYachtClub | C108: BAYTUR_PAYMENT | D108: 003C143 | E108: M Mohammad Alharbi Medical Company | F108: AL HARBI | G108: Contractor | H108: Payment On Behalf Of Saudi Arabian Baytur (Apr) | I108: CN | J108: =RIGHT(A108,2) -> 01 | K108: =I108&"."&D108 -> CN.003C143 | L108: =E108&" - "&C108 -> M Mohammad Alharbi Medical Company - BAYTUR_PAYMENT | M108: ="1TB01006"&"."&J108&"."&I108&"."&D108&".00" -> 1TB01006.01.CN.003C143.00 | N108: ="1TB01006"&"."&J108&"."&I108&"."&D108&".01" -> 1TB01006.01.CN.003C143.01 | O108: ="1TB01006"&"."&J108&"."&I108&"."&D108&".02" -> 1TB01006.01.CN.003C143.02
A109: 1.TB.01.003.01 | B109: AMAALAYachtClub | C109: BAYTUR_PAYMENT | D109: 003C139 | E109: Clean Coast For Contracting | F109: CLEAN COAST | G109: Contractor | H109: Payment On Behalf Of Saudi Arabian Baytur (Apr) | I109: CN | J109: =RIGHT(A109,2) -> 01 | K109: =I109&"."&D109 -> CN.003C139 | L109: =E109&" - "&C109 -> Clean Coast For Contracting - BAYTUR_PAYMENT | M109: ="1TB01006"&"."&J109&"."&I109&"."&D109&".00" -> 1TB01006.01.CN.003C139.00 | N109: ="1TB01006"&"."&J109&"."&I109&"."&D109&".01" -> 1TB01006.01.CN.003C139.01 | O109: ="1TB01006"&"."&J109&"."&I109&"."&D109&".02" -> 1TB01006.01.CN.003C139.02
A110: 1.TB.01.003.01 | B110: AMAALAYachtClub | C110: BAYTUR_PAYMENT | D110: 003C137 | E110: JAK Generation Cont. Co. LLC | F110: JAK | G110: Contractor | H110: Payment On Behalf Of Saudi Arabian Baytur (Apr) | I110: CN | J110: =RIGHT(A110,2) -> 01 | K110: =I110&"."&D110 -> CN.003C137 | L110: =E110&" - "&C110 -> JAK Generation Cont. Co. LLC - BAYTUR_PAYMENT | M110: ="1TB01006"&"."&J110&"."&I110&"."&D110&".00" -> 1TB01006.01.CN.003C137.00 | N110: ="1TB01006"&"."&J110&"."&I110&"."&D110&".01" -> 1TB01006.01.CN.003C137.01 | O110: ="1TB01006"&"."&J110&"."&I110&"."&D110&".02" -> 1TB01006.01.CN.003C137.02
A111: 1.TB.01.003.01 | B111: AMAALAYachtClub | C111: BAYTUR_PAYMENT | D111: 003C138 | E111: Sami General Contracting Est. | F111: SAMI GENEERAL | G111: Contractor | H111: Payment On Behalf Of Saudi Arabian Baytur (Apr) | I111: CN | J111: =RIGHT(A111,2) -> 01 | K111: =I111&"."&D111 -> CN.003C138 | L111: =E111&" - "&C111 -> Sami General Contracting Est. - BAYTUR_PAYMENT | M111: ="1TB01006"&"."&J111&"."&I111&"."&D111&".00" -> 1TB01006.01.CN.003C138.00 | N111: ="1TB01006"&"."&J111&"."&I111&"."&D111&".01" -> 1TB01006.01.CN.003C138.01 | O111: ="1TB01006"&"."&J111&"."&I111&"."&D111&".02" -> 1TB01006.01.CN.003C138.02
A112: 1.TB.01.003.01 | B112: AMAALAYachtClub | C112: BAYTUR_PAYMENT | D112: 003C135 | E112: Al Rai Modern Water Factory | F112: AL RAI | G112: Contractor | H112: Payment On Behalf Of Saudi Arabian Baytur (Apr) | I112: CN | J112: =RIGHT(A112,2) -> 01 | K112: =I112&"."&D112 -> CN.003C135 | L112: =E112&" - "&C112 -> Al Rai Modern Water Factory - BAYTUR_PAYMENT | M112: ="1TB01006"&"."&J112&"."&I112&"."&D112&".00" -> 1TB01006.01.CN.003C135.00 | N112: ="1TB01006"&"."&J112&"."&I112&"."&D112&".01" -> 1TB01006.01.CN.003C135.01 | O112: ="1TB01006"&"."&J112&"."&I112&"."&D112&".02" -> 1TB01006.01.CN.003C135.02
... A293: 1.TB.01.003.01 | B293: AMAALAYachtClub | C293: BAYTUR_PAYMENT | D293: 003C307 | E293: Glsan Contracting Company | F293: GLSAN | G293: Contractor | H293: Payment On Behalf Of Saudi Arabian Baytur (Nov/Dec) | I293: CN | J293: =RIGHT(A293,2) -> 01 | K293: =I293&"."&D293 -> CN.003C307 | L293: =E293&" - "&C293 -> Glsan Contracting Company - BAYTUR_PAYMENT | M293: ="1TB01006"&"."&J293&"."&I293&"."&D293&".00" -> 1TB01006.01.CN.003C307.00 | N293: ="1TB01006"&"."&J293&"."&I293&"."&D293&".01" -> 1TB01006.01.CN.003C307.01 | O293: ="1TB01006"&"."&J293&"."&I293&"."&D293&".02" -> 1TB01006.01.CN.003C307.02
A294: 1.TB.01.009.01 | B294: MH3 | C294: KORTEK | D294: 009C05 | E294: KTH - MEP Works Package - 2240072 | F294: KORTEK | G294: Contractor | I294: CN | J294: =RIGHT(A294,2) -> 01 | K294: =I294&"."&D294 -> CN.009C05 | L294: =E294&" - "&C294 -> KTH - MEP Works Package - 2240072 - KORTEK | M294: ="1TB01006"&"."&J294&"."&I294&"."&D294&".00" -> 1TB01006.01.CN.009C05.00 | N294: ="1TB01006"&"."&J294&"."&I294&"."&D294&".01" -> 1TB01006.01.CN.009C05.01 | O294: ="1TB01006"&"."&J294&"."&I294&"."&D294&".02" -> 1TB01006.01.CN.009C05.02
A295: 1.TB.01.012.01 | B295: Four Seasons | C295: Alcatop | D295: 012C33 | E295: ALC - Alcatop Package - Fourseasons | F295: ALCATOP | G295: Contractor | I295: CN | J295: =RIGHT(A295,2) -> 01 | K295: =I295&"."&D295 -> CN.012C33 | L295: =E295&" - "&C295 -> ALC - Alcatop Package - Fourseasons - Alcatop | M295: ="1TB01006"&"."&J295&"."&I295&"."&D295&".00" -> 1TB01006.01.CN.012C33.00 | N295: ="1TB01006"&"."&J295&"."&I295&"."&D295&".01" -> 1TB01006.01.CN.012C33.01 | O295: ="1TB01006"&"."&J295&"."&I295&"."&D295&".02" -> 1TB01006.01.CN.012C33.02
A296: 1.TB.01.003.01 | B296: AMAALAYachtClub | C296: Al Futtaim Pioneer | D296: 003C328 | E296: Al Futtaim Pioneer Elevators | F296: Al Futtaim | G296: Contractor | I296: CN | J296: =RIGHT(A296,2) -> 01 | K296: =I296&"."&D296 -> CN.003C328 | L296: =E296&" - "&C296 -> Al Futtaim Pioneer Elevators - Al Futtaim Pioneer | M296: ="1TB01006"&"."&J296&"."&I296&"."&D296&".00" -> 1TB01006.01.CN.003C328.00 | N296: ="1TB01006"&"."&J296&"."&I296&"."&D296&".01" -> 1TB01006.01.CN.003C328.01 | O296: ="1TB01006"&"."&J296&"."&I296&"."&D296&".02" -> 1TB01006.01.CN.003C328.02
A297: 1.TB.01.003.01 | B297: AMAALAYachtClub | D297: 003D14 | E297: TRA - Zatca Integration with Reachware | F297: TRA | G297: Consultant | H297: Reachware installation | I297: FFEOSE | J297: =RIGHT(A297,2) -> 01 | K297: =I297&"."&D297 -> FFEOSE.003D14 | L297: =E297&" - "&C297 -> TRA - Zatca Integration with Reachware - | M297: ="1TB01006"&"."&J297&"."&I297&"."&D297&".00" -> 1TB01006.01.FFEOSE.003D14.00 | N297: ="1TB01006"&"."&J297&"."&I297&"."&D297&".01" -> 1TB01006.01.FFEOSE.003D14.01 | O297: ="1TB01006"&"."&J297&"."&I297&"."&D297&".02" -> 1TB01006.01.FFEOSE.003D14.02
A298: 1.TB.01.003.01 | B298: AMAALAYachtClub | D298: 003D14 | E298: TRA - Zatca Integration with Reachware | F298: TRA | G298: Consultant | H298: Reachware installation | I298: FFEOSE | J298: =RIGHT(A298,2) -> 01 | K298: =I298&"."&D298 -> FFEOSE.003D14 | L298: =E298&" - "&C298 -> TRA - Zatca Integration with Reachware - | M298: ="1TB01006"&"."&J298&"."&I298&"."&D298&".00" -> 1TB01006.01.FFEOSE.003D14.00 | N298: ="1TB01006"&"."&J298&"."&I298&"."&D298&".01" -> 1TB01006.01.FFEOSE.003D14.01 | O298: ="1TB01006"&"."&J298&"."&I298&"."&D298&".02" -> 1TB01006.01.FFEOSE.003D14.02
A299: 1.TB.01.006.99 | B299: VBH_PROJECT WIDE | C299: 2230277 | D299: 006C22 | E299: Shandong Tiejun Electric Power Engineering Co. LTD. Branch | F299: SHANDONG | G299: Contractor | I299: CN | J299: =RIGHT(A299,2) -> 99 | K299: =I299&"."&D299 -> CN.006C22 | L299: =E299&" - "&C299 -> Shandong Tiejun Electric Power Engineering Co. LTD. Branch - 2230277 | M299: ="1TB01006"&"."&J299&"."&I299&"."&D299&".00" -> 1TB01006.99.CN.006C22.00 | N299: ="1TB01006"&"."&J299&"."&I299&"."&D299&".01" -> 1TB01006.99.CN.006C22.01 | O299: ="1TB01006"&"."&J299&"."&I299&"."&D299&".02" -> 1TB01006.99.CN.006C22.02
A300: 1.TB.01.009.99 | B300: MH3 | C300: IMAR MH3 | D300: 009C09 | E300: IMAR Overseas Saudi Arabia Co. W.L.L. | F300: IMAR | G300: Contractor | I300: CN | J300: =RIGHT(A300,2) -> 99 | K300: =I300&"."&D300 -> CN.009C09 | L300: =E300&" - "&C300 -> IMAR Overseas Saudi Arabia Co. W.L.L. - IMAR MH3 | M300: ="1TB01006"&"."&J300&"."&I300&"."&D300&".00" -> 1TB01006.99.CN.009C09.00 | N300: ="1TB01006"&"."&J300&"."&I300&"."&D300&".01" -> 1TB01006.99.CN.009C09.01 | O300: ="1TB01006"&"."&J300&"."&I300&"."&D300&".02" -> 1TB01006.99.CN.009C09.02
A301: 1.TB.01.009.99 | B301: MH3 | C301: FIBREX LLC | D301: 009C35 | E301: Fibrex LLC | F301: FIBREX | G301: Contractor | I301: CN | J301: =RIGHT(A301,2) -> 99 | K301: =I301&"."&D301 -> CN.009C35 | L301: =E301&" - "&C301 -> Fibrex LLC - FIBREX LLC | M301: ="1TB01006"&"."&J301&"."&I301&"."&D301&".00" -> 1TB01006.99.CN.009C35.00 | N301: ="1TB01006"&"."&J301&"."&I301&"."&D301&".01" -> 1TB01006.99.CN.009C35.01 | O301: ="1TB01006"&"."&J301&"."&I301&"."&D301&".02" -> 1TB01006.99.CN.009C35.02
A302: 1.TB.01.009.99 | B302: AMAALAYachtClub | C302: OCIP Insurance | D302: 003C314 | E302: RJT- OCIP Insurance Premium - Declaration 11 | F302: OCIP Insurance | G302: Contractor | I302: CN | J302: =RIGHT(A302,2) -> 99 | K302: =I302&"."&D302 -> CN.003C314 | L302: =E302&" - "&C302 -> RJT- OCIP Insurance Premium - Declaration 11 - OCIP Insurance | M302: ="1TB01006"&"."&J302&"."&I302&"."&D302&".00" -> 1TB01006.99.CN.003C314.00 | N302: ="1TB01006"&"."&J302&"."&I302&"."&D302&".01" -> 1TB01006.99.CN.003C314.01 | O302: ="1TB01006"&"."&J302&"."&I302&"."&D302&".02" -> 1TB01006.99.CN.003C314.02
A303: 1.TB.01.003.01 | B303: AMAALAYachtClub | C303: Operation Systems | D303: 003D20 | E303: Samtiah Arabis Ltd - Operation systems | F303: Samtiah Arabia - Operations systems | G303: Contractor | I303: FFEOSE | J303: =RIGHT(A303,2) -> 01 | K303: =I303&"."&D303 -> FFEOSE.003D20 | L303: =E303&" - "&C303 -> Samtiah Arabis Ltd - Operation systems - Operation Systems | M303: ="1TB01006"&"."&J303&"."&I303&"."&D303&".00" -> 1TB01006.01.FFEOSE.003D20.00 | N303: ="1TB01006"&"."&J303&"."&I303&"."&D303&".01" -> 1TB01006.01.FFEOSE.003D20.01 | O303: ="1TB01006"&"."&J303&"."&I303&"."&D303&".02" -> 1TB01006.01.FFEOSE.003D20.02
B319: Village Boutique Branded Condos
B320: Village Boutique Residence
B321: Village Boutique Hotel
B322: Village Boutique Hotel-Project Wide

Sheet Data Input
A1: PROGRAMME: | B1: MARINA VILLAGE (PROGRAMME 1_TRIPLE BAY)
A2: PROGRAMME CODE: | B2: 1TB01003
A3: ASSET NAME: | B3: AMAALA YACHT CLUB | E3: UPDATE INFORMATION IN RED EACH MONTH
A4: ASSET CODE: | B4: 1TB01003.01
A5: Client: | B5: AMAALA
A6: Location: | B6: AL WAJH SAUDI ARABIA
A7: REPORT NO: | B7: MONTHLY REPORT NO. 49
A8: REPORTING PERIOD: | B8: OCTOBER 2026
A9: AMAALA Ref | B9: AMAALA/AYC/MONTHLY REPORT 01
A10: AMAALA Ref | B10: AMAALA/AYC/MONTHLY REPORT 01
A11: Report No Short: | B11: NO. 49
E12: Done | F12: Not Done
A13: TO DO | E13: √ | F13: X
A14: MOM | B14: MINUTES OF MEETINGS | C14: X | E14: √
A15: EXECUTIVE SUMMARY | B15: EXECUTIVE SUMMARY DASHBOARD | C15: X | E15: √
A16: EXECUTIVE SUMMARY | B16: STAKEHOLDER EXECUTIVE REVIEW | C16: X | E16: √
A17: EXECUTIVE SUMMARY | B17: EARLY WARNINGS | C17: X | E17: √
A18: EXECUTIVE SUMMARY | B18: ACC | C18: X | E18: √
A19: SCHEDULE A | B19: LEVEL 1 - EXECUTIVE SUMMARY | C19: X | E19: √
A20: SCHEDULE B | B20: LEVEL 2 - DETAILED SUMMARY | C20: X | E20: √
A21: SCHEDULE C | B21: CHANGE MANAGEMENT TRACKER | C21: X | E21: √
A22: SCHEDULE D | B22: RISK AND OPPORTUNITIES | C22: X | E22: √
A23: SCHEDULE E | B23: CLAIMS AND DISPUTES | C23: X | E23: √
A24: SCHEDULE F | B24: PROVISIONAL SUMS | C24: X | E24: √
A25: SCHEDULE G | B25: BONDS AND INSURANCE TRACKING LOG | C25: X | E25: √
A26: SCHEDULE H | B26: INVOICE AND PAYMENT TRACKING LOG | C26: X | E26: √
A27: SCHEDULE I | B27: CASH FLOW
A28: SCHEDULE J | B28: BUDGET TRANSFER TRACKER
A29: SCHEDULE K | B29: PROCUREMENT STATUS
A31: Distribution
A32: Head of Commercial: | C32: Paul Donaghy
A33: Executive Commercial Director: | C33: Shane Fairfield
A34: Senior Commercial Director: | C34: Michael Hansen
A35: Associate Commercial Director: | C35: Blake Lombard
A37: Senior Project Director: | C37: Christopher Burke
A39: Project Team
A40: Executive Project Director:
A41: Senior Project Director: | C41: Christopher Burke
A42: Planning Director | C42: Sudhakaran Kodicheth
A43: Senior Design Director:
A44: Senior Commercial Director: | C44: Michael Hansen
A45: Associate Commercial Director | C45: Blake Lombard
A46: Procurement Lead (Red Sea): | C46: Joe Honeine
A47: Asst. Manager - Quantity Surveying: | C47: Jose Chavenia

Sheet dropdowns
J1: 1 | K1: 2 | L1: 3 | M1: 4 | N1: 5 | O1: 6 | P1: 7 | Q1: 8
B2: Initiated By: | C2: Approval Status | D2: Yes/No: | E2: VE | F2: Change Initiated by | G2: Approval Status Claims: | H2: Contractor or Sub Contractor | I2: Packages | J2: Contractor Details | L2: PS Drop down | M2: Insurances | N2: COST REPORT EFFECTIVE FIGURE | O2: Reporting Period | P2: REFF PO Ref | Q2: VENDOR TYPE
B3: Design Development | C3: APPROVED | D3: YES | E3: Contract | F3: Consultant | G3: Rejected | H3: ALS - Early Works | I3: DAE -Prf Fees | J3: DEWAN ARCHI | L3: PENDING | M3: Professional Indemnity | N3: ACTIVE | O3: Monthly Report No 1 - Oct'22 | P3: 2200340 | Q3: Contractor
B4: Scope Gap | C4: REJECTED | D4: NO | E4: Consultant | F4: Contractor | G4: Approved | H4: JVD - Early Works | I4: HKL (Design Comp Fees)-Prf Fees | J4: HKS Design Consultant | L4: EXPENDED | M4: Third Party Liability | N4: NOT ACTIVE | O4: Monthly Report No 2 - Nov'22 | P4: 2200317 | Q4: Contractor
B5: Scope Overlap | C5: PENDING | E5: Contractor | F5: Employer | G5: Pending | H5: ALS - Main Works | I5: HKL (Design Architect)-Prf Fees | J5: HKS Design Consultant | L5: PARTIALLY EXPENDED | M5: Workmens Compensation | O5: Monthly Report No 3 - Dec'22 | P5: 2200571 | Q5: Contractor
B6: Provisional Sum | C6: REVISED & RE-SUBMIT | G6: Approved inc. in Lump Sum | H6: Five Oceans Marine Survey | I6: ATM-Prf Fees | J6: ATM | M6: Contractors all Risk | O6: Monthly Report No 4 - Jan'23 | P6: 2200571 | Q6: Contractor
B7: Final Account | C7: SUPERSEDED | G7: Approved (Authority) | H7: Becon Development Co | I7: T&T-Prf Fees | J7: Turner & Townsend | M7: Advance Payment Bond | O7: Monthly Report No 5 - Feb'23
B8: Operator's Change | C8: CANCELLED | G8: Approved (proceed to ERI) | H8: WSP Consultants | I8: LUI-Prf Fees | J8: SIC | M8: Performance Bond | O8: Monthly Report No 6 - Mar'23
B9: Contractor's Performance | C9: TRANSFERRED | H9: Five Oceans Coral Relocation | I9: ZFP-Prf Fees | J9: NSCC | M9: Retention Bond | O9: Monthly Report No 7 - Apr'23
B10: EOT - Contractor's Performance | C10: REVIEW COMPLETE | I10: KAA-Mgt Fees | J10: KAA | M10: Marine and Hull | O10: Monthly Report No 8 - May'23
B11: Extension of Time (EOT) | I11: ECC-Mgt Fees | J11: GBC | M11: Plant and Equipment | O11: Monthly Report No 9 - Jun'23
B12: Omission | I12: ECC-Mgt Fees (Accom & Transpo) | J12: CML | M12: Vehicle | O12: Monthly Report No 10 - Jul'23
B13: Omission - Contractor Performance | I13: CML-Mgt Fees | J13: Foster + Partners | M13: Trade License | O13: Monthly Report No 11 - Aug'23
B14: Scope transfer - Contractor's Performance | I14: SOI TB Ground Improvement Works | J14: Langan | O14: Monthly Report No 12 - Sep'23
B15: Contractor's Performance | I15: SOI TB Ground Improvement Works (PS) | J15: Areen | O15: Monthly Report No 13 - Oct'23
B16: Prelims | E16: Initiated By Amaala Representative | G16: Status | I16: GST-LEED Fees | J16: Al Rahji Takaful | O16: Monthly Report No 14 - Nov'23
B17: Back Charge | E17: BLAKE | G17: RFC - Pending from Contractor / Consultant | I17: NSCC - Piling | J17: Baytur | O17: Monthly Report No 15 - Dec'23
E18: FOWZULLAH | G18: RFC - Pending from Engineer | I18: GBC - Sustainability Accreditation | J18: DEPA | O18: Monthly Report No 16 - Jan'24
B19: Project Stage | E19: HANEEF | G19: RFC - Pending to Upload on Aconex | I19: Jensen Hughes-Prf Fees COO 30 | J19: Medtel | O19: Monthly Report No 17 - Feb'24
B20: Pre Contract Variation | E20: JOSE | G20: RFC - Pending for Approval on Aconex | I20: Langan-Prf Fees | J20: New Contractor | O20: Monthly Report No 18 - Mar'24
B21: Post Contract Variation | E21: MIKE . H | G21: RFC - Approved | I21: Langan-Prf Fees (Provisional) | J21: ESCCO | O21: Monthly Report No 19 - Apr'24
B22: Consultant Variation | E22: SHIHAM | G22: RFC - Rejected | I22: Jensen Hughes-Prf Fees | J22: RAQTAN | O22: Monthly Report No 20 - May'24
B23: Pre Contract - Consultant Variation | E23: VASEEF | G23: RFC - Cancelled | I23: Executive Architect Services | J23: ARMETAL | O23: Monthly Report No 21 - Jun'24
B24: Post Contract - Consultant Variation | E24: VEDHAKUMAR | G24: PVO - Pending from Contractor / Consultant | I24: MOM - Building Permit Fee | J24: ALUTEC | O24: Monthly Report No 22 - Jul'24
E25: CLOSED | G25: PVO - Pending from Engineer | I25: Saudi Baytur - Main Works | J25: Al Fanar | O25: Monthly Report No 23 - Aug'24
E26: OTHER | G26: PVO - Pending to Upload on Aconex | I26: SAB - Civil and Arch Works, MEPD & ICT/ELV | J26: Abu Dhabi Precast | O26: Monthly Report No 24 - Sep'24
G27: PVO - Pending for Approval on Aconex | I27: New Contract - Civil and Arch Works, MEPD & ICT/ELV | J27: HAS | O27: Monthly Report No 25 - Oct'24
G28: PVO - Rejected | I28: SAB - Civil and Arch Works | J28: MASS - GRC Works | O28: Monthly Report No 26 - Nov'24
G29: VO - Pending from Contractor / Consultant | I29: SAB - MEPD | J29: Tamimi | O29: Monthly Report No 27 - Dec'24
G30: VO - Pending from Engineer | I30: SAB - ICT / ELV | J30: MAS | O30: Monthly Report No 28 - Jan'25
B31: ACTIONEE | G31: VO - Pending to Upload on Aconex | I31: Medtel - STO Façade Mock-up | J31: KORTEC | O31: Monthly Report No 29 - Feb'25
B32: CLIENT | G32: VO - Pending for Approval on Aconex | I32: ESCCO - Vertical Transport | J32: ALCATOP | O32: Monthly Report No 30 - March'25
B33: ENGINEER | G33: VO - Rejected | I33: Hard and Soft Landscaping | J33: AL FUTTAIM
B34: CONSULTANT | G34: DVO - Pending from Contractor / Consultant | I34: DEPA Interior Fitout | J34: EURO CONSULT
B35: DESIGN CONSULTANT | G35: DVO - Pending from Engineer | I35: FF&E and OSE Procurement Agent | J35: JensenHuges
B36: CONTRACTOR | G36: DVO - Pending to Upload on Aconex | I36: Façade & Glazing Works | J36: TEIJUN
G37: DVO - Pending for Approval on Aconex | I37: RAQTAN - Kitchen and Laundry | J37: IMAR MH3
G38: DVO - Accepted | I38: Loose FF&E items (FOH) | J38: FIBREX MH3
G39: DVO - Rejected | I39: Loose FF&E items (BOH)
I40: Areen - FF&E OS&E Items
I41: Art Work
I42: Al Rahji Takaful - Owner Controlled Insurance Program
C43: PROGRAM NAME | D43: PROGRAM CODE | E43: PROJECT NAME | F43: PROJECT CODE | G43: ASSET | H43: ASSET CODE | I43: ARMETAL - Reflective ceiling
I44: ABU DHABI PRECAST - GRC Cladding
C45: MARINA VILLAGE | D45: 1.TB.01.100 | E45: MARINA LIFESTYLE HOTEL & VILLAGE | F45: 1.TB.01.002 | G45: MARINA LIFESTYLE BRANDED CONDOS | H45: 1.TB.01.002.02 | I45: Al Fanar - MEP Labour Supply
B46: SR.NO. | C46: TRIPLE BAY CENTRAL | D46: 1.TB.02.200 | E46: AMAALA YATCH CLUB | F46: 1.TB.01.003 | G46: MARINA LIFESTYLE HOTEL | H46: 1.TB.01.002.03 | I46: MAS - Amphitheatre
C47: WELLNESS CORE | D47: 1.TB.03.300 | E47: RED SEA MARINE LIFE INSTITUTE | F47: 1.TB.01.005 | G47: LUXURY VILLAGE DISTRICT | H47: 1.TB.01.002.01 | I47: MAS - Labour Supply - Wet Works
B48: 1 | C48: TRIPLE BAY WIDE | D48: 1.TB.04.400 | E48: VILLAGE BOUTIQUE HOTEL | F48: 1.TB.01.006 | G48: AMAALA YATCH CLUB | H48: 1.TB.01.003.01 | I48: MAS - Various Works
B49: 2 | C49: OCEAN GOLF | D49: 1.TB.05.500 | E49: MARINA HOTEL 3 | F49: 1.TB.01.009 | G49: RED SEA MARINE LIFE INSTITUTE | H49: 1.TB.01.005.01 | I49: Marina Village Wide - MS Budget Hold
B50: 3 | C50: TRIPLE BAY EAST | D50: 1.TB.06.600 | E50: FLOATING DIVING CLUB | F50: 1.TB.01.001 | G50: VILLAGE BOUTIQUE BRANDED CONDOS | H50: 1.TB.01.006.01 | I50: Marina Village Wide - CN Budget Hold
B51: 4 | C51: TRIPLE BAY SOUTH | D51: 1.TB.07.700 | E51: THE MARINA | F51: 1.TB.01.031 | G51: VILLAGE BOUTIQUE BRANDED VILLAS | H51: 1.TB.01.006.02 | I51: HAS - External Scaffolding Works
B52: 5 | C52: CIVIC ASSETS | D52: 1.TB.09.035 | G52: VILLAGE BOUTIQUE HOTEL | H52: 1.TB.01.006.03 | I52: MASS - GRC Repair Works
B53: 6 | C53: FOURSEASON | D53: 1.TB.12.100 | E53: FOURSEASONS | F53: 1.TB.01.012 | G53: MARINA HOTEL 3 | H53: 1.TB.01.009.01 | I53: GST- Sustainability Accreditation Services
B54: 7 | G54: FLOATING DIVING CLUB | H54: 1.TB.01.001.01 | I54: Enviro - Deep Cleaning
B55: 8 | G55: THE MARINA | H55: 1.TB.01.031.01 | I55: Extraordinary Cart - Buggy Cart | O55: Monthly Report No 13 - Oct'23
B56: 9 | C56: FOURSEASON | D56: 1.TB.12.100 | E56: FOURSEASONS | F56: 1.TB.01.012 | G56: FOURSEASONS | H56: 1.TB.01.012.01 | I56: Alutec - Aluminum and Glazing Works
B57: 10 | I57: AlFalak Electronic - HPE Servers | N57: External Factors – Authorities led change
B58: 11 | I58: Sevenrooms Inc | N58: External Factors – BoD instructed change
I59: Infor Co | N59: External Factors – Operator’s change
I60: Reachware Integration | N60: External Factors – Third party damage
N61: Logistics – Accommodation constraints
I62: Prelims - Emaar Suhali | N62: Logistics – Constructability reasons
I63: Prelims - Mohammad Alharbi Medical Company | N63: Project Management – Cost reduction
I64: Prelims - Al Anan Travels and Tours | N64: Project Management – Late appointment – Consultant
I65: Prelims - Al drees Petroleum | N65: Project Management – Late appointment – Contractor
I66: Prelims - Salim Hamed Cleaning | N66: Project Management – Late appointment – Operator
I67: Prelims - Clean Coast for Contracting | N67: Project Management – Scope – gap / omission
I68: Prelims - Sami General Contracting | N68: Project Management – Scope – new
I69: Prelims - Eastern Horizons Foundation Transportation Comp | N69: Project Management – Scope – overlap
I70: Prelims - Jak Generation Cont Co LLC | N70: Provisional Sums
I71: Prelims - Intelligent General Cont Co Equipment | N71: Revenue related – Aesthetic enhancement
I72: Prelims - Al Rai Modern Water Factory | N72: Revenue related – Guest experience
I73: Direct Works - Madar Building material Co | N73: Revenue related – Revenue enhancement
... I76: Direct Works - Abu Dhabi Precast | N76: Supply chain – Contractor performance
I77: Direct Works - SAMIF
I78: Direct Works - SAUDI MANPOWER SOLUTIONS CO | N78: Design Development/Improvement
I79: Direct Works - Fosam Company LTD | N79: Scope Gap
I80: Direct Works - Glow Arabia Trading | N80: Scope Overlap
I81: Direct Works - HRFA | N81: Provisional Sum
I82: Direct Works - NESMA | N82: Final Account
N83: Operator's Change
I84: Prelims - NEXTWARE INTERNATIONAL SUPPLY | N84: Contractor's Performance
I85: Direct Works - BROOQ ALAMAAN TRAD COMPANY | N85: EOT due to Contractor's Performance
I86: Direct Works - Abeer Munawer Al Shamari | N86: Extension of Time (EOT)
I87: Direct Works - Yaz Development Contracting | N87: Back Charge
I88: Direct Works - Naffco
I89: Direct Works - GESR Alarab
I90: Direct Works - Jameel Mohamed Hussain Alqatafa Cont Est
I91: Prelims - Virtual Projects DMCC
I92: Direct Works - MEDTEL
I93: Prelims - Raddad Al adinah
I94: Direct Works - Noreom
I95: Direct Works - Isam Kabani & Partners
I96: Direct Works - ARABIAN TESTING EVOLUTION COMPANY
I97: Prelims - Ahmed Bin Salem Bin Dagher
I99: Prelims - Bahamdoon Trading
I100: Direct Works - Wood Expert
... I152: Jensen Hughes
I153: =DATA!L294 -> KTH - MEP Works Package - 2240072 - KORTEK
I154: ALC - Alcatop Package - Fourseasons
...

Sheet MoM
D3: TRIPLE BAY - MARINA VILLAGE - AYC - MONTHLY REPORT
D11: MINUTES OF MEETING
D25: FINANCIAL OVERVIEW | M25: * PROCUREMENT STATUS (CONSTRUCTION RELATED WORKS ONLY) | U25: KEY PERFORMANCE INDICATORS (KPI)
D26: Description | G26: Date Reported | H26: Action | I26: Resolved | M26: Description | P26: Date Reported | Q26: Action | R26: Resolved | U26: Description | X26: Date | Y26: Action | Z26: Resolved
D27: PVO related to NSCC : 1. Savings indicated in the NSCC's PVO to be revisited/reevaluated 2. Since it is a D&B Contract and NSCC proposed design is fit for the purpose, then AMAALA may not be entitled to savings. 3. Notice to NSCC to be issued to proceed with the works to expedite the progress at site 4. Ben advised the changes to be evaluated fairly/ reasonably to pay provided they continue with the works . (For info, BL/MH confirmed Soil investigation report and bore hole (3 No) reports issued to NSCC during RFP stage) | G27: 44874 | H27: Commercial | I27: In Process | U27: Currently 2 No of claims are under review, to be evaluated fairly. | X27: 44874 | Y27: Commercial | Z27: In Process
AD29: 2452499.7
M43: * PROVISIONAL SUMS STATUS (CONSTRUCTION RELATED WORKS ONLY)
D44: KEY PERIOD MOVEMENTS | M44: Description | P44: Date Reported | Q44: Action | R44: Resolved
D45: Description | G45: Date Reported | H45: Action | I45: Resolved
U47: PACKAGE PROGRAMME STATUS
U49: Description | X49: Date | Y49: Action | Z49: Resolved
M53: CHANGE MANAGEMENT OVERVIEW
M54: Description | P54: Date Reported | Q54: Action | R54: Resolved
D65: CURRENT COMMITTED VALUE VS WORKS COMPLETE
D66: Description | G66: Date Reported | H66: Action | I66: Resolved
D67: Dewan fees to be merged in NSCC's final account settlement | G67: 44874 | H67: Commercial | I67: In Process
U72: GENERAL COMMENTS
U74: Description | X74: Date | Y74: Action | Z74: Resolved
E123: Condemned | F123: 0% - 20%
E124: Poor | F124: 21% - 39%
E125: Fair | F125: 40% - 59%
E126: Good | F126: 60% - 75%
E127: As New | F127: 76% - 100%
D183: Option 1 | F183: AED
D184: Option 2 | F184: OMR
D185: Option 3 | F185: 1
D186: 2
D188: 0
D191: BUA ft² | E191: =#REF! -> #REF! | F191: =#REF! -> #REF! | G191: =#REF! -> #REF! | I191: =IF($D$186=1,E191)+IF($D$186=2,F191)+IF($D$186=3,G191)+IF($D$186=4,H191) -> #REF!
D192: GFA ft² | E192: =#REF! -> #REF! | F192: =#REF! -> #REF! | G192: =#REF! -> #REF! | I192: =IF($D$186=1,E192)+IF($D$186=2,F192)+IF($D$186=3,G192)+IF($D$186=4,H192) -> #REF!
D195: BUA m² | E195: =E191/#REF! -> #REF! | F195: =F191/#REF! -> #REF! | G195: =G191/#REF! -> #REF! | I195: =IF($D$186=1,E195)+IF($D$186=2,F195)+IF($D$186=3,G195)+IF($D$186=4,H195) -> #REF!
D196: GFA m² | E196: =E192/#REF! -> #REF! | F196: =F192/#REF! -> #REF! | G196: =G192/#REF! -> #REF! | I196: =IF($D$186=1,E196)+IF($D$186=2,F196)+IF($D$186=3,G196)+IF($D$186=4,H196) -> #REF!
D197: Efficiency | E197: =E196/E195 -> #REF! | F197: =F196/F195 -> #REF! | G197: =G196/G195 -> #REF! | I197: =IF($D$186=1,E197)+IF($D$186=2,F197)+IF($D$186=3,G197)+IF($D$186=4,H197) -> #REF!

Sheet Cover
G25: 33
G26: 35
H39: 45675

Sheet Index
A2: ='Data Input'!A1&" - "&'Data Input'!B1 -> PROGRAMME: - MARINA VILLAGE (PROGRAMME 1_TRIPLE BAY)
A3: ='Data Input'!A2&" - "&'Data Input'!B2 -> PROGRAMME CODE: - 1TB01003
A4: ='Data Input'!A3&" - "&'Data Input'!B3 -> ASSET NAME: - AMAALA YACHT CLUB
A5: ='Data Input'!A4&" - "&'Data Input'!B4 -> ASSET CODE: - 1TB01003.01
A6: ='Data Input'!A7&" - "&'Data Input'!B7 -> REPORT NO: - MONTHLY REPORT NO. 49
A7: ='Data Input'!A8&" - "&'Data Input'!B8 -> REPORTING PERIOD: - OCTOBER 2026
A9: INDEX
G13: PAGE NO
A14: ='Data Input'!A15&" - "&'Data Input'!B15 -> EXECUTIVE SUMMARY - EXECUTIVE SUMMARY DASHBOARD | G14: 2
A15: ='Data Input'!A16&" - "&'Data Input'!B16 -> EXECUTIVE SUMMARY - STAKEHOLDER EXECUTIVE REVIEW | G15: 3
A16: ='Data Input'!A17&" - "&'Data Input'!B17 -> EXECUTIVE SUMMARY - EARLY WARNINGS | G16: 5 | I16: 5,6
A17: ='Data Input'!A18&" - "&'Data Input'!B18 -> EXECUTIVE SUMMARY - ACC | G17: 8 | I17: 7,12
A18: COST REPORT EXECUTIVE SUMMARY - LEVEL 1 | G18: 16
A19: COST REPORT EXECUTIVE SUMMARY - LEVEL 2 | G19: 17
A20: ='Data Input'!A19&" - "&'Data Input'!B19 -> SCHEDULE A - LEVEL 1 - EXECUTIVE SUMMARY | G20: 18
A21: ='Data Input'!A20&" - "&'Data Input'!B20 -> SCHEDULE B - LEVEL 2 - DETAILED SUMMARY | G21: 19 | I21: 16,19
A22: ='Data Input'!A21&" - "&'Data Input'!B21 -> SCHEDULE C - CHANGE MANAGEMENT TRACKER | G22: 23 | I22: 20,26
A23: ='Data Input'!A22&" - "&'Data Input'!B22 -> SCHEDULE D - RISK AND OPPORTUNITIES | G23: 31
A24: ='Data Input'!A23&" - "&'Data Input'!B23 -> SCHEDULE E - CLAIMS AND DISPUTES | G24: 32
A25: ='Data Input'!A24&" - "&'Data Input'!B24 -> SCHEDULE F - PROVISIONAL SUMS | G25: 33
A26: ='Data Input'!A25&" - "&'Data Input'!B25 -> SCHEDULE G - BONDS AND INSURANCE TRACKING LOG | G26: 34 | I26: 30,32
A27: ='Data Input'!A26&" - "&'Data Input'!B26 -> SCHEDULE H - INVOICE AND PAYMENT TRACKING LOG | G27: 37
A28: ='Data Input'!A27&" - "&'Data Input'!B27 -> SCHEDULE I - CASH FLOW | G28: 65
A29: ='Data Input'!A28&" - "&'Data Input'!B28 -> SCHEDULE J - BUDGET TRANSFER TRACKER | G29: 66
A30: ='Data Input'!A29&" - "&'Data Input'!B29 -> SCHEDULE K - PROCUREMENT STATUS | G30: 85
A32: Distribution
A33: ='Data Input'!A32&" - "&'Data Input'!C32 -> Head of Commercial: - Paul Donaghy
A34: ='Data Input'!A33&" - "&'Data Input'!C33 -> Executive Commercial Director: - Shane Fairfield
A35: ='Data Input'!A34&" - "&'Data Input'!C34 -> Senior Commercial Director: - Michael Hansen
A36: ='Data Input'!A35&" - "&'Data Input'!C35 -> Associate Commercial Director: - Blake Lombard
A37: ='Data Input'!A37&" - "&'Data Input'!C37 -> Senior Project Director: - Christopher Burke
A39: PREPARED BY : | D39: REVIEWED BY : | G39: APPROVED BY :
A44: ='Data Input'!A47&" - "&'Data Input'!C47 -> Asst. Manager - Quantity Surveying: - Jose Chavenia | D44: ='Data Input'!A45&" - "&'Data Input'!C45 -> Associate Commercial Director - Blake Lombard | G44: ='Data Input'!A34&" - "&'Data Input'!C34 -> Senior Commercial Director: - Michael Hansen

Sheet Executive Summary
D3: TRIPLE BAY - MARINA VILLAGE - AMAALA YACHT CLUB - MONTHLY REPORT
D25: FINANCIAL OVERVIEW | M25: * PROCUREMENT STATUS (CONSTRUCTION RELATED WORKS ONLY) | U25: KEY PERFORMANCE INDICATORS (KPI)
E27: October 2026 | G27: September 2026 | I27: Period Movement | M27: Contractor / Consultant Package | N27: Original pkg Budget | O27: Revised Package Budget | P27: Variance | Q27: Contract Award | R27: (Saving) / Additional | U27: DETERMINED VARIATION ORDERS (DVO)
D28: Approved / Current Budget | E28: ='Schedule A'!I36 -> 5.8384755e+08 | G28: 5.8449291e+08 | I28: =E28-G28 -> -645354.74 | M28: =D89 -> Construction Works | V28: Total | W28: Previous | X28: Current
M29: PS.003D01 - Dewan Architect | N29: 5973808 | O29: ='Schedule B'!H17 -> 5973808 | P29: =O29-N29 -> 0 | Q29: ='Schedule B'!H17 -> 5973808 | R29: =Q29-N29 -> 0 | U29: Value of PVO (Planned) | V29: =SUMIFS('Schedule C'!$AG$21:$AG$1240,'Schedule C'!$AF$21:$AF$1240,"ACTIVE",'Schedule C'!$AY$21:$AY$1240,"ACTIVE") -> 33878350 | W29: 33878350 | X29: =V29-W29 -> 0
D30: Contracts Awarded | E30: ='Schedule B'!H29+'Schedule B'!H45+'Schedule B'!H73+'Schedule B'!H170+'Schedule B'!H223 -> 5.5345242e+08 | G30: 5.5345242e+08 | I30: =E30-G30 -> 0 | M30: PS.003D02 - HKS Architect - Competition | N30: 555960.36 | O30: ='Schedule B'!H18 -> 555960.36 | P30: =O30-N30 -> 0 | Q30: ='Schedule B'!H18 -> 555960.36 | R30: =Q30-N30 -> 0 | U30: Value of DVO (Actual) | V30: =SUMIFS('Schedule C'!$AZ$21:$AZ$1240,'Schedule C'!$AF$21:$AF$1240,"ACTIVE",'Schedule C'!$AY$21:$AY$1240,"ACTIVE") -> 6873283.8 | W30: 6873283.8 | X30: =V30-W30 -> 0
M31: PS.003D03 - HKS Architect - Design | N31: 10891204 | O31: ='Schedule B'!H19 -> 10891204 | P31: =O31-N31 -> 0 | Q31: ='Schedule B'!H19 -> 10891204 | R31: =Q31-N31 -> 0 | U31: Variance % PVO vs DVO | V31: =IFERROR(((V30-V29)/V30),0) -> -3.9289905 | W31: -3.9289905 | X31: =IFERROR(((X30-X29)/X30),0) -> 0
D32: Committed Procurement Packages | E32: 0 | G32: 0 | I32: =E32-G32 -> 0 | M32: PS.003D04 - Applied Technology | N32: 93750 | O32: ='Schedule B'!H20 -> 93750 | P32: =O32-N32 -> 0 | Q32: ='Schedule B'!H20 -> 93750 | R32: =Q32-N32 -> 0 | U32: Count of DVO Closed | V32: =COUNTIF('Schedule C'!$AY$21:$AY$369,"ACTIVE") -> 118 | W32: 118 | X32: =V32-W32 -> 0
M33: ='Schedule B'!A33&" - "&'Schedule B'!C33 -> MS.003F02 - Khatib & Alami 2230031 | N33: 17975993 | O33: 17975993 | P33: =O33-N33 -> 0 | Q33: ='Schedule B'!H33 -> 13059930 | R33: =Q33-N33 -> -4916063 | U33: DVO Pending < 30 days | V33: =COUNTIFS('Schedule C'!$BA$21:$BA$369,"PENDING",'Schedule C'!$BF$21:$BF$369,"<30") -> 2 | W33: 0 | X33: =V33-W33 -> 2
D34: Determined Variation Orders (DVO) | E34: =+'Schedule B'!I240 -> 6820135.5 | G34: 6820135.5 | I34: =E34-G34 -> 0 | M34: ='Schedule B'!A21&" - "&'Schedule B'!C21 -> PS.003D05 - Langan International UK Limited 2230042 | N34: =+'Schedule B'!H21 -> 172368.42 | O34: =+N34 -> 172368.42 | P34: =O34-N34 -> 0 | Q34: =+'Schedule B'!H21 -> 172368.42 | R34: =Q34-N34 -> 0 | U34: DVO Pending > 30 < 60 days | V34: =COUNTIFS('Schedule C'!$BA$21:$BA$369,"PENDING",'Schedule C'!$BF$21:$BF$369,"<60",'Schedule C'!$BF$21:$BF$369,">=30") -> 1 | W34: 1 | X34: =V34-W34 -> 0
M35: ='Schedule B'!A23&" - "&'Schedule B'!C23 -> PS.003D06 - Ministry of Municipality and Rural Affairs (Tabuk) | N35: =+'Schedule B'!H23 -> 45677.6 | O35: =+N35 -> 45677.6 | P35: =O35-N35 -> 0 | Q35: =+'Schedule B'!H23 -> 45677.6 | R35: =Q35-N35 -> 0 | U35: DVO Pending < 60 > 90 days | V35: =COUNTIFS('Schedule C'!$BA$21:$BA$369,"PENDING",'Schedule C'!$BF$21:$BF$369,"<90",'Schedule C'!$BF$21:$BF$369,">=60") -> 4 | W35: 4 | X35: =V35-W35 -> 0
D36: Committed Costs | E36: =E34+E30+E32 -> 5.6027255e+08 | G36: =G34+G30+G32 -> 5.6027255e+08 | I36: =I34+I30+I32 -> 0 | M36: ='Schedule B'!A22&" - "&'Schedule B'!C22 -> PS.003F01 - Zuhair Fayez and Partners 2230041 | N36: =+'Schedule B'!H22 -> 106231.5 | O36: =+N36 -> 106231.5 | P36: =O36-N36 -> 0 | Q36: =+O36 -> 106231.5 | R36: =Q36-N36 -> 0 | U36: DVO Overdue (>90 days) | V36: =COUNTIFS('Schedule C'!$BA$21:$BA$369,"PENDING",'Schedule C'!$BF$21:$BF$369,">=90") -> 13 | W36: 15 | X36: =V36-W36 -> -2
M37: ='Schedule B'!A24&" - "&'Schedule B'!C24 -> PS.003F04 - Jensen Hughes Saudi Arabia Co 2230180 | N37: =+'Schedule B'!H24 -> 127291.9 | O37: =+N37 -> 127291.9 | P37: =O37-N37 -> 0 | Q37: =+'Schedule B'!H24 -> 127291.9 | R37: =Q37-N37 -> 0
D38: Potential Variation Orders (PVO) | E38: ='Schedule A'!K32+'Schedule A'!H32 -> -16136787 | G38: -16136787 | I38: =E38-G38 -> 0 | M38: PS.003F10 - Langan-Prf Fees COO 30 | O38: =+'Schedule B'!F25 -> 38103.2 | P38: =O38-N38 -> 38103.2 | Q38: 38103.2 | R38: =Q38-N38 -> 38103.2 | U38: 90 DAY CASH FLOWS | V38: MARCH | W38: 2026 | Y38: FORECAST
M39: CN.003C20 - Green Business Cert | N39: 4500 | O39: ='Schedule B'!H71 -> 23094.49 | P39: =O39-N39 -> 18594.49 | Q39: ='Schedule B'!H71 -> 23094.49 | R39: =Q39-N39 -> 18594.49 | U39: VARIANCE | V39: =EOMONTH(W39,-1) -> 46022 | W39: =EOMONTH(X39,-1) -> 46053 | X39: =EOMONTH(Y39,-1) -> 46081 | Y39: =EOMONTH(DATEVALUE(V38&W38),0) -> 46112 | Z39: =EOMONTH(Y39,1) -> 46142
D40: Request for Change (RFC) | E40: ='Schedule A'!L32 -> 3585562.5 | G40: 3801447.7 | I40: =E40-G40 -> -215885.19 | M40: CN.003C13 - SOI TB Gr Improvement | N40: 3082688.7 | O40: =2799717+282972 -> 3082689 | P40: =O40-N40 -> 0.3 | Q40: ='Schedule B'!H69+'Schedule B'!H70 -> 3082689 | R40: =Q40-N40 -> 0.3 | U40: NSCC - Triple Bay Piling (AYC only) | V40: =+'Schedule I'!EI11 -> 0 | W40: =+'Schedule I'!EL11 -> 0 | X40: =+'Schedule I'!EO11 -> 0 | Y40: ='Schedule I'!EP11 -> 0 | Z40: ='Schedule I'!EQ11 -> 0
M41: CN.003C13 - NSCC - Piling - AYC Only | N41: 18698534 | O41: ='Schedule K'!E13 -> 18698534 | P41: =O41-N41 -> 0 | Q41: ='Schedule B'!H77 -> 18698534 | R41: =Q41-N41 -> 0 | U41: DEWAN Architecture | V41: =+'Schedule I'!EI12 -> 0 | W41: =+'Schedule I'!EL12 -> 0 | X41: =+'Schedule I'!EO12 -> 0 | Y41: =+'Schedule I'!EP12 -> 0 | Z41: =+'Schedule I'!EQ12 -> 0
D42: Approved Claims | E42: ='Schedule A'!N32 -> 0 | G42: 0 | I42: =E42-G42 -> 0 | M42: ='Schedule B'!A79&" - "&'Schedule B'!B79 -> CN.003C03 - SAB - Civil and Arch Works, MEPD & ICT/ELV | N42: =105487634.633009+59394214.4019838+4871026.39111685 -> 1.6975288e+08 | O42: =176445278+87209550+9846492 -> 273501320 | P42: =O42-N42 -> 1.0374844e+08 | Q42: ='Schedule B'!H79 -> 2.6095541e+08 | R42: =Q42-N42 -> 91202539 | U42: SIC TB Ground Improvement Works | V42: =+'Schedule I'!EI13 -> 0 | W42: =+'Schedule I'!EL13 -> 0 | X42: =+'Schedule I'!EO13 -> 0 | Y42: =+'Schedule I'!EP13 -> 0 | Z42: =+'Schedule I'!EQ13 -> 0
M43: Direct Payments for SAB's Subcontractors and Suppliers | N43: 0 | O43: 0 | P43: =O43-N43 -> 0 | Q43: =+E94 -> 42594260 | R43: =Q43-N43 -> 42594260 | U43: GBC - Sustainability Accreditation | V43: =+'Schedule I'!EI14 -> 0 | W43: =+'Schedule I'!EL14 -> 0 | X43: =+'Schedule I'!EO14 -> 0 | Y43: =+'Schedule I'!EP14 -> 0 | Z43: =+'Schedule I'!EQ14 -> 0 | AH43: =H68+I48 -> -215885.19
D44: Early Warnings | E44: ='Schedule A'!M32 -> 32891649 | G44: 32891649 | I44: =E44-G44 -> 0 | M44: ='Schedule B'!A148&" - "&'Schedule B'!C148 -> CN.003C21 - STO Façade Mock-up -(MWN) 2230075 | N44: 0 | O44: 0 | P44: =O44-N44 -> 0 | Q44: =+'Schedule B'!H148 -> 834298.55 | R44: =Q44-N44 -> 834298.55 | U44: HKS - Design Competition | V44: =+'Schedule I'!EI15 -> 0 | W44: =+'Schedule I'!EL15 -> 0 | X44: =+'Schedule I'!EO15 -> 0 | Y44: =+'Schedule I'!EP15 -> 0 | Z44: =+'Schedule I'!EQ15 -> 0
M45: ='Schedule B'!A149&" - "&'Schedule B'!C149 -> CN.003F03 - Vertical Transportation (ESCCO) 2230178 | N45: 2153851 | O45: =+'Schedule K'!F17 -> 2675473 | P45: =O45-N45 -> 521622.03 | Q45: ='Schedule B'!H149 -> 2675473 | R45: =Q45-N45 -> 521622.03 | U45: HKS - Design Architect | V45: =+'Schedule I'!EI16 -> 0 | W45: =+'Schedule I'!EL16 -> 0 | X45: =+'Schedule I'!EO16 -> 0 | Y45: =+'Schedule I'!EP16 -> 0 | Z45: =+'Schedule I'!EQ16 -> 0
D46: Uncommitted Cost | E46: =E42+E40+E38+E44 -> 20340424 | G46: =G42+G40+G38+G44 -> 20556309 | I46: =I42+I40+I38+I44 -> -215885.19 | M46: ='Schedule B'!A150&" - "&'Schedule B'!C150 -> CN.003C08 - Kitchen & Laundry Works (Al Raqtan) 2230205 | N46: =+'Schedule K'!C21 -> 5907720 | O46: =+'Schedule K'!E21 -> 4695209 | P46: =O46-N46 -> -1212511 | Q46: =+'Schedule B'!H150 -> 4695209 | R46: =Q46-N46 -> -1212511 | U46: ATM - Rapid review | V46: =+'Schedule I'!EI17 -> 0 | W46: =+'Schedule I'!EL17 -> 0 | X46: =+'Schedule I'!EO17 -> 0 | Y46: =+'Schedule I'!EP17 -> 0 | Z46: =+'Schedule I'!EQ17 -> 0
M47: ='Schedule B'!A151&" - "&'Schedule B'!C151 -> CN.003C09 - Fitout Works (DEPA) | N47: 27478729 | O47: =+' Schedule J SS'!G86 -> 62092796 | P47: =O47-N47 -> 34614067 | Q47: 75969227 | R47: =Q47-N47 -> 48490498 | U47: SAB - AMAALA Yacht Club Construction Contract | V47: =+'Schedule I'!EI18 -> 5755976.9 | W47: =+'Schedule I'!EL18 -> -2856041.1 | X47: =+'Schedule I'!EO18 -> -3483605.8 | Y47: =+'Schedule I'!EP18 -> 0 | Z47: =+'Schedule I'!EQ18 -> 1787346
D48: Current Budget Hold | E48: ='Schedule A'!O34 -> 0 | G48: 0 | I48: =E48-G48 -> 0 | M48: ='Schedule B'!A152&" - "&'Schedule B'!C152 -> CN.003C27 - Façade & Glazing Works (Alutec) | N48: 0 | O48: 0 | P48: =O48-N48 -> 0 | Q48: ='Schedule B'!F152 -> 29899671 | R48: =Q48-N48 -> 29899671 | U48: LANGAN International UK, LTD | V48: =+'Schedule I'!EI19 -> 0 | W48: =+'Schedule I'!EL19 -> 0 | X48: =+'Schedule I'!EO19 -> 0 | Y48: =+'Schedule I'!EP19 -> 0 | Z48: =+'Schedule I'!EQ19 -> 0
M49: MS.003F07 - Euro Consult (COO 6) | N49: 0 | O49: 182184.38 | P49: =O49-N49 -> 182184.38 | Q49: 182184.38 | R49: =Q49-N49 -> 182184.38 | U49: Medtel - W.N. WLL | V49: =+'Schedule I'!EI20 -> 0 | W49: =+'Schedule I'!EL20 -> 0 | X49: =+'Schedule I'!EO20 -> 0 | Y49: =+'Schedule I'!EP20 -> 0 | Z49: =+'Schedule I'!EQ20 -> 0
D50: Projected Cost to Complete | E50: =E48+E46+E36 -> 5.8061298e+08 | G50: =G48+G46+G36 -> 5.8082886e+08 | I50: =I48+I46+I36 -> -215885.19 | M50: MS.003F09 - Euro Consult (COO 27) | N50: 0 | O50: 54000 | P50: =O50-N50 -> 54000 | Q50: 54000 | R50: =Q50-N50 -> 54000 | U50: Raqtan (Kitchen & Laundry) | V50: =+'Schedule I'!EI21 -> 0 | W50: =+'Schedule I'!EL21 -> 0 | X50: =+'Schedule I'!EO21 -> 0 | Y50: =+'Schedule I'!EP21 -> 159337 | Z50: =+'Schedule I'!EQ21 -> 0
M51: FFEOSE.003F06 - FF&E and OSE Procurement Agent (Areen Design Ltd) | N51: 0 | O51: 1107465.9 | P51: =O51-N51 -> 1107465.9 | Q51: 1107465.9 | R51: =Q51-N51 -> 1107465.9 | U51: ESCCO (Vertical Transportation) | V51: =+'Schedule I'!EI22 -> 0 | W51: =+'Schedule I'!EL22 -> 0 | X51: =+'Schedule I'!EO22 -> 0 | Y51: =+'Schedule I'!EP22 -> 334075.28 | Z51: =+'Schedule I'!EQ22 -> 52335.24 | AH51: =V29-V30 -> 27005067
D52: KEY PERIOD MOVEMENTS | M52: PS.003F08 - CML (Independent Commissioning Agent) COO 7 | N52: 0 | O52: 2406500 | P52: =O52-N52 -> 2406500 | Q52: 2406500 | R52: =Q52-N52 -> 2406500 | U52: Khatib & Alami (Management Supervison) | V52: =+'Schedule I'!EI23 -> 0 | W52: =+'Schedule I'!EL23 -> 0 | X52: =+'Schedule I'!EO23 -> 0 | Y52: =+'Schedule I'!EP23 -> 0 | Z52: =+'Schedule I'!EQ23 -> 78720
D53: Description | H53: Amount | M53: ='Schedule B'!A153&" - "&'Schedule B'!C153 -> CN.003C31 - MAS - Wet Works | N53: 0 | O53: 4004000 | P53: =O53-N53 -> 4004000 | Q53: 4004000 | R53: =Q53-N53 -> 4004000 | U53: DEPA (Interior Fitout) | V53: =+'Schedule I'!EI24 -> 0 | W53: =+'Schedule I'!EL24 -> 0 | X53: =+'Schedule I'!EO24 -> 0 | Y53: =+'Schedule I'!EP24 -> 1737945 | Z53: =+'Schedule I'!EQ24 -> 3226545.6
D54: DVO High Level Overview | H54: =+H124 -> 0 | M54: ='Schedule B'!A154&" - "&'Schedule B'!C154 -> CN.003C32 - MAS - Amphitheatre Works | N54: 0 | O54: 1078892.3 | P54: =O54-N54 -> 1078892.3 | Q54: 1078892.3 | R54: =Q54-N54 -> 1078892.3 | U54: ALUTEC | V54: =+'Schedule I'!EI25 -> 0 | W54: =+'Schedule I'!EL25 -> 0 | X54: =+'Schedule I'!EO25 -> 0 | Y54: =+'Schedule I'!EP25 -> 0 | Z54: =+'Schedule I'!EQ25 -> 49611.16
M55: ='Schedule B'!A155&" - "&'Schedule B'!C155 -> CN.003C34 - Al Fanar - MEP Labour Supply | N55: 0 | O55: 23125000 | P55: =O55-N55 -> 23125000 | Q55: 23125000 | R55: =Q55-N55 -> 23125000 | U55: Areen Design | V55: =+'Schedule I'!EI26 -> 0 | W55: =+'Schedule I'!EL26 -> 0 | X55: =+'Schedule I'!EO26 -> 0 | Y55: =+'Schedule I'!EP26 -> 0 | Z55: =+'Schedule I'!EQ26 -> 4331572.5
D56: PVO High Level Overview | H56: =H141 -> 0 | M56: ='Schedule B'!A157&" - "&'Schedule B'!C157 -> CN.003C34 - ARMETAL - Reflective ceiling | N56: 0 | O56: 7129950 | P56: =O56-N56 -> 7129950 | Q56: 7129950 | R56: =Q56-N56 -> 7129950 | U56: =+'Schedule I'!B27 -> MAS Labour | V56: =+'Schedule I'!EI27 -> 0 | W56: =+'Schedule I'!EL27 -> 0 | X56: =+'Schedule I'!EO27 -> 0 | Y56: =+'Schedule I'!EP27 -> 0 | Z56: =+'Schedule I'!EQ27 -> 1016402.2
M57: ='Schedule B'!A158&" - "&'Schedule B'!C158 -> CN.003C34 - Al Rahji Takaful - Owner Controlled Insurance Program | N57: 0 | O57: =+'Schedule B'!F158 -> 89047.06 | P57: =O57-N57 -> 89047.06 | Q57: 73970.78 | R57: =Q57-N57 -> 73970.78 | U57: =+'Schedule I'!B28 -> MAS Amphitheatre | V57: =+'Schedule I'!EI28 -> 0 | W57: =+'Schedule I'!EL28 -> 0 | X57: =+'Schedule I'!EO28 -> 0 | Y57: =+'Schedule I'!EP28 -> 0 | Z57: =+'Schedule I'!EQ28 -> 0
M58: ='Schedule B'!A160&" - "&'Schedule B'!C160 -> CN.003C35 - HASSAN ALLAM - External Scaffoldings | N58: 0 | O58: 3096124.9 | P58: =O58-N58 -> 3096124.9 | Q58: 3096124.9 | R58: =Q58-N58 -> 3096124.9 | U58: =+'Schedule I'!B29 -> Al Fanar Labour | V58: =+'Schedule I'!EI29 -> 0 | W58: =+'Schedule I'!EL29 -> 0 | X58: =+'Schedule I'!EO29 -> 0 | Y58: =+'Schedule I'!EP29 -> 1972028 | Z58: =+'Schedule I'!EQ29 -> 0
D59: RFC High Level Overview | H59: =H164 -> -215885.19 | M59: PS.003F12 - GST - Sustainability Accreditation Services | N59: 0 | O59: 133000 | P59: =O59-N59 -> 133000 | Q59: 133000 | R59: =Q59-N59 -> 133000 | U59: =+'Schedule I'!B30 -> CML | V59: =+'Schedule I'!EI30 -> 0 | W59: =+'Schedule I'!EL30 -> 0 | X59: =+'Schedule I'!EO30 -> 0 | Y59: =+'Schedule I'!EP30 -> 241100 | Z59: =+'Schedule I'!EQ30 -> 164253.85
M60: CN.003CF13 - Enviro - Deep Cleaning | N60: 0 | O60: 799625.31 | P60: =O60-N60 -> 799625.31 | Q60: 799625.31 | R60: =Q60-N60 -> 799625.31 | U60: =+'Schedule I'!B31 -> EuroConsult | V60: =+'Schedule I'!EI31 -> 0 | W60: =+'Schedule I'!EL31 -> 0 | X60: =+'Schedule I'!EO31 -> 0 | Y60: =+'Schedule I'!EP31 -> 15762.54 | Z60: =+'Schedule I'!EQ31 -> 0
M61: ='Schedule B'!A207&" - "&'Schedule B'!C207 -> FFEOSE.003F02 - Loose FF&E Items (FOH) | N61: 12800000 | O61: =+'Schedule K'!F22 -> 25558750 | P61: =O61-N61 -> 12758750 | Q61: Included in the SEED Fund issued as VO to Areen | R61: =IF(SUM(Q61)<=0,0,-SUM(O61)) -> 0 | U61: EuroConsult (Accom and Transport) | V61: =+'Schedule I'!EI32 -> 0 | W61: =+'Schedule I'!EL32 -> 0 | X61: =+'Schedule I'!EO32 -> 0 | Y61: =+'Schedule I'!EP32 -> 0 | Z61: =+'Schedule I'!EQ32 -> 0
D62: Early Warnings/Contract Award | H62: =H200 -> 0 | M62: ='Schedule B'!A208&" - "&'Schedule B'!C208 -> Included in FF&E FOH - Loose FF&E Items (BOH) | N62: 340000 | O62: =+'Schedule K'!F23 -> 470000 | P62: =O62-N62 -> 130000 | R62: =IF(SUM(Q62)<=0,0,-SUM(O62)) -> 0 | U62: Hassan Allam | V62: =+'Schedule I'!EI33 -> 0 | W62: =+'Schedule I'!EL33 -> 0 | X62: =+'Schedule I'!EO33 -> 0 | Y62: =+'Schedule I'!EP33 -> 0 | Z62: =+'Schedule I'!EQ33 -> 0 | AH62: 224
M63: ='Schedule B'!A209&" - "&'Schedule B'!C209 -> FFEOSE.003F02 - OS&E Items | N63: 3543829 | O63: =+'Schedule K'!F24 -> 8681174.6 | P63: =O63-N63 -> 5137345.6 | R63: =IF(SUM(Q63)<=0,0,-SUM(O63)) -> 0 | U63: ARMetal | V63: =+'Schedule I'!EI34 -> 0 | W63: =+'Schedule I'!EL34 -> 0 | X63: =+'Schedule I'!EO34 -> 0 | Y63: =+'Schedule I'!EP34 -> 0 | Z63: =+'Schedule I'!EQ34 -> 0 | AH63: 8
M64: ='Schedule B'!A210&" - "&'Schedule B'!C210 -> Included in OS&E - Art Works | N64: 2400000 | O64: =+'Schedule K'!F25 -> 2874723 | P64: =O64-N64 -> 474723 | R64: =IF(SUM(Q64)<=0,0,-SUM(O64)) -> 0 | U64: Total | V64: =SUM(V40:V63) -> 5755976.9 | W64: =SUM(W40:W63) -> -2856041.1 | X64: =SUM(X40:X63) -> -3483605.8 | Y64: =SUM(Y40:Y63) -> 4460247.8 | Z64: =SUM(Z40:Z63) -> 10706787 | AH64: =SUM(AH62:AH63) -> 232
M65: FFEOSE.003F11 - Extraordinary Cart | N65: 0 | O65: =+'Schedule B'!H212 -> 397876 | P65: =O65-N65 -> 397876 | Q65: 397876 | R65: =Q65-N65 -> 397876
D66: Current Budget Hold Movement for this Month | H66: =H232 -> 0 | M66: FFEOSE.003D09 - Saudico Electronic Systems | N66: 0 | O66: 353487.06 | P66: =O66-N66 -> 353487.06 | Q66: 353487.06 | R66: =Q66-N66 -> 353487.06 | U66: FORMAL NOTICE OF CLAIM
M67: FFEOSE.003D07 - Birch Street | N67: 0 | O67: 115998.98 | P67: =O67-N67 -> 115998.98 | Q67: 115998.98 | R67: =Q67-N67 -> 115998.98 | V67: Total | W67: Previous | X67: Current | AB67: Claims Pending < 120 > 180 days | AC67: =COUNTIFS('Schedule E'!BQ$13:BQ$42,"<180",'Schedule E'!BQ$13:BQ$42,">=120") -> 0 | AD67: 1 | AE67: =AC67-AD67 -> -1
D68: Total | H68: =+H66+H62+H59+H56+H54 -> -215885.19 | M68: FFEOSE.003D10 - AlFalak Electronic - HPE Servers | N68: 0 | O68: 16655 | P68: =O68-N68 -> 16655 | Q68: 16655 | R68: =Q68-N68 -> 16655 | U68: Amount Claimed | V68: ='Schedule E'!AP14+'Schedule E'!AP15+'Schedule E'!AP16+'Schedule E'!AP17+'Schedule E'!AP18+'Schedule E'!AP32 -> 6747085.3 | W68: 6747085.3 | X68: =V68-W68 -> 0
D69: CURRENT COMMITTED VALUE VS WORKS COMPLETE | M69: FFEOSE.003D15 - Saudico Electronic Systems | N69: 0 | O69: 34719 | P69: =O69-N69 -> 34719 | Q69: 34719 | R69: =Q69-N69 -> 34719 | U69: Amount Granted | V69: 0 | W69: 0 | X69: 0
M70: FFEOSE.003D11 - Sevenrooms Inc | N70: 0 | O70: 3633.9 | P70: =O70-N70 -> 3633.9 | Q70: 3633.9 | R70: =Q70-N70 -> 3633.9 | U70: EOT Claimed (Time only) | V70: =+'Schedule E'!AB14+'Schedule E'!AB15+'Schedule E'!AB34+'Schedule E'!AB35+'Schedule E'!AB44 -> 668 | W70: 668 | X70: =V70-W70 -> 0
D71: Contractor / Consultant Package | E71: Current Committed Value (Incl PS) | F71: Application Received to date (incl Accrual) | G71: Certified Works to Date | H71: Works to Complete | I71: % Certified | M71: FFEOSE.003D12 - Saudico Electronic Systems | N71: 0 | O71: 58307.19 | P71: =O71-N71 -> 58307.19 | Q71: 58307.19 | R71: =Q71-N71 -> 58307.19 | U71: EOT Granted (Time only) | V71: =+'Schedule E'!AD14+96+'Schedule E'!AD34+'Schedule E'!AD35+'Schedule E'!AD44 -> 378 | W71: 378 | X71: =V71-W71 -> 0
D72: =PROPER('Schedule B'!C15) -> Professional Services | E72: =SUM(E73:E82) -> 25075830 | F72: =SUM(F73:F82) -> 24713375 | G72: =SUM(G73:G82) -> 24672063 | H72: =SUM(H73:H82) -> 403767.52 | I72: =+G72/E72 -> 0.98389814 | M72: FFEOSE.003D14 - Reachware Integration | N72: 0 | O72: 57135 | P72: =O72-N72 -> 57135 | Q72: 57135 | R72: =Q72-N72 -> 57135 | U72: Claims Pending < 60 days | V72: =COUNTIF('Schedule E'!BQ$13:BQ$47,"<60") -> 0 | W72: 0 | X72: =V72-W72 -> 0
D73: ='Schedule B'!A17&" - "&'Schedule B'!C17 -> PS.003D01 - Dewan Architects & Engineers 2200445 | E73: ='Schedule B'!K17 -> 9290526.1 | F73: =+'Schedule H DAE'!J69 -> 9068064.5 | G73: =+'Schedule B'!U17 -> 9026746.1 | H73: =E73-G73 -> 263780 | I73: =+G73/E73 -> 0.97160764 | M73: Total | N73: =SUM(N29:N72) -> 2.8210501e+08 | O73: =SUM(O29:O72) -> 4.8257775e+08 | P73: =SUM(P29:P72) -> 2.0047274e+08 | Q73: =SUM(Q29:Q72) -> 5.1472072e+08 | R73: =SUM(R29:R72) -> 2.5169954e+08 | U73: Claims Pending > 60 < 120 days | V73: =COUNTIFS('Schedule E'!BQ$13:BQ$47,"<120",'Schedule E'!BQ$13:BQ$47,">=60") -> 0 | W73: 0 | X73: =V73-W73 -> 0
D74: ='Schedule B'!A18&" - "&'Schedule B'!C18 -> PS.003D02 - HKS Architects Ltd - Design Competition Fees 2200010 | E74: ='Schedule B'!K18 -> 555960.36 | F74: =+'Schedule H HKS 1'!J37 -> 555960 | G74: =+'Schedule B'!U18 -> 555960 | H74: =E74-G74 -> 0.36 | I74: =+G74/E74 -> 0.99999935 | U74: Claims Overdue (>180 days) | V74: =COUNTIF('Schedule E'!BQ$13:BQ$347,">=180") -> 3 | W74: 3 | X74: =V74-W74 -> 0
D75: ='Schedule B'!A19&" - "&'Schedule B'!C19 -> PS.003D03 - HKS Architects Ltd - Design Architect Fees 2200375 | E75: ='Schedule B'!K19 -> 10801429 | F75: =+'Schedule H HKS 2'!J37 -> 10801428 | G75: =+'Schedule B'!U19 -> 10801428 | H75: =E75-G75 -> 0.54 | I75: =+G75/E75 -> 0.99999995 | M75: ='Schedule B'!A156&" - "&'Schedule B'!C156 -> CN.100C01 (MVW) - Hard and Soft Landscaping | N75: 13329116 | O75: =+'Schedule K'!F28 -> 0 | P75: =O75-N75 -> -13329116 | Q75: 19746261 | R75: =Q75-N75 -> 6417145.1
D76: ='Schedule B'!A20&" - "&'Schedule B'!C20 -> PS.003D04 - Applied Technology and Management Inc (Dubai BR)s 2210167 | E76: ='Schedule B'!K20 -> 93750 | F76: =+'Schedule H ATM'!J37 -> 93750 | G76: =+'Schedule B'!U20 -> 93750 | H76: =E76-G76 -> 0 | I76: =+G76/E76 -> 1
D77: ='Schedule B'!A21&" - "&'Schedule B'!C21 -> PS.003D05 - Langan International UK Limited 2230042 | E77: =+'Schedule B'!K21 -> 170469.9 | F77: =+'Schedule H LIU'!J37 -> 168421.05 | G77: =+'Schedule B'!U21 -> 168421.05 | H77: =E77-G77 -> 2048.85 | I77: =+G77/E77 -> 0.98798116 | M77: * PROVISIONAL SUMS STATUS (CONSTRUCTION RELATED WORKS ONLY) | U77: PACKAGE PROGRAMME STATUS
D78: ='Schedule B'!A22&" - "&'Schedule B'!C22 -> PS.003F01 - Zuhair Fayez and Partners 2230041 | E78: =+'Schedule B'!K22 -> 106231.5 | F78: =+'Schedule H ZFP'!J37 -> 106231.5 | G78: =+'Schedule B'!U22 -> 106231.5 | H78: =E78-G78 -> 0 | I78: =+G78/E78 -> 1
D79: ='Schedule B'!A24&" - "&'Schedule B'!C24 -> PS.003F04 - Jensen Hughes Saudi Arabia Co 2230180 | E79: =+'Schedule B'!K24 -> 70591.9 | F79: 0 | G79: =+'Schedule B'!U24 -> 0 | H79: =E79-G79 -> 70591.9 | I79: =+G79/E79 -> 0 | M79: Contractor / Consultant Package | N79: Number of PS packages | O79: PS Budget | P79: No expended PS pkg's | Q79: PS Award | R79: Remaining to Spend | U79: Contractor / Consultant Package | V79: Commencement Date | W79: Original Completion Date | X79: EOT Received | Y79: EOT Granted | Z79: Revised Comp Date
D80: =+M38 -> PS.003F10 - Langan-Prf Fees COO 30 | E80: =+'Schedule B'!K25 -> 14303.2 | F80: 0 | G80: =+'Schedule B'!U39 -> 0 | H80: =E80-G80 -> 14303.2 | I80: =+G80/E80 -> 0 | M80: =D89 -> Construction Works | U80: =D72 -> Professional Services
D81: ='Schedule B'!A23&" - "&'Schedule B'!C23 -> PS.003D06 - Ministry of Municipality and Rural Affairs (Tabuk) | E81: =+'Schedule B'!K23 -> 45677.6 | F81: 45677.6 | G81: =+'Schedule B'!U23 -> 45677.6 | H81: =E81-G81 -> 0 | I81: =+G81/E81 -> 1 | M81: CN.003C13 - SOI TB Ground Improvement Works | N81: 1 | O81: ='Schedule B'!H70 -> 282972 | P81: 0 | Q81: 0 | R81: =O81-Q81 -> 282972 | U81: =D73 -> PS.003D01 - Dewan Architects & Engineers 2200445
D82: ='Schedule B'!A26&" - "&'Schedule B'!C26 -> PS.003F08 - CML (Independent Commissioning Agent) COO 7 | E82: =+'Schedule B'!K26 -> 3926890.5 | F82: =+'Schedule H'!R39 -> 3873841.8 | G82: =+'Schedule H'!S39 -> 3873847.9 | H82: =E82-G82 -> 53042.67 | I82: =+G82/E82 -> 0.98649245 | M82: PS.003D05 - Langan International UK Limited 2230042 | N82: 1 | O82: 3947.37 | P82: 0 | Q82: 0 | R82: =O82-Q82 -> 3947.37 | U82: =+D74 -> PS.003D02 - HKS Architects Ltd - Design Competition Fees 2200010 | V82: Completed | W82: Completed
D83: =PROPER('Schedule B'!C31) -> Management Supervision | E83: =SUM(E84:E86) -> 14368091 | F83: =SUM(F84:F86) -> 14261137 | G83: =SUM(G84:G86) -> 14265378 | H83: =SUM(H84:H86) -> 102713.74 | I83: =+G83/E83 -> 0.99285126 | U83: =+D76 -> PS.003D04 - Applied Technology and Management Inc (Dubai BR)s 2210167 | V83: Completed | W83: Completed
D84: ='Schedule B'!A33&" - "&'Schedule B'!C33 -> MS.003F02 - Khatib & Alami 2230031 | E84: =+'Schedule B'!K33 -> 14131907 | F84: =+'Schedule H KAA'!J41 -> 14078459 | G84: =+'Schedule B'!U33 -> 14082700 | H84: =E84-G84 -> 49207 | I84: =+G84/E84 -> 0.99651802 | M84: PROPOSED VARIATION ORDER (PVO) | U84: =+D77 -> PS.003D05 - Langan International UK Limited 2230042 | V84: Completed | W84: Completed
D85: MS.003F07 - Euro Consult (COO 6) | E85: =+'Schedule B'!K34 -> 182184.38 | F85: =+'Schedule H'!R40 -> 128677.64 | G85: =+'Schedule H'!S40 -> 128677.64 | H85: =E85-G85 -> 53506.74 | I85: =+G85/E85 -> 0.70630446 | N85: Total | O85: Previous | P85: Period | U85: =+D78 -> PS.003F01 - Zuhair Fayez and Partners 2230041 | V85: Completed | W85: Completed
D86: MS.003F09 - Euro Consult (COO 27) | E86: =+'Schedule B'!H35 -> 54000 | F86: =+'Schedule H'!R41 -> 54000 | G86: =+'Schedule H'!S41 -> 54000 | H86: =E86-G86 -> 0 | I86: =+G86/E86 -> 1 | M86: Total PVO's | N86: =SUM(N87:N90) -> 184 | O86: 182 | P86: =SUM(P87:P90) -> 2 | U86: =+D79 -> PS.003F04 - Jensen Hughes Saudi Arabia Co 2230180
D87: =PROPER('Schedule B'!C47) -> Commercial Management | E87: =SUM(E88) -> 0 | F87: =SUM(F88) -> 0 | G87: =SUM(G88) -> 0 | H87: =SUM(H88) -> 0 | M87: PVO Approved | N87: ='Schedule C'!AE7 -> 144 | O87: 144 | P87: =N87-O87 -> 0 | U87: =+M38 -> PS.003F10 - Langan-Prf Fees COO 30
D88: No Awarded Contracts | E88: 0 | F88: 0 | G88: 0 | H88: =E88-G88 -> 0 | I88: 0 | M88: PVO Pending | N88: ='Schedule C'!AE8 -> 24 | O88: 22 | P88: =N88-O88 -> 2 | U88: PS.003F08 - CML (Independent Commissioning Agent) COO 7
D89: =PROPER('Schedule B'!C65) -> Construction Works | E89: =SUM(E90:E104) -> 4.7502821e+08 | F89: =SUM(F90:F104) -> 6.500238e+08 | G89: =SUM(G90:G104) -> 4.5405716e+08 | H89: =SUM(H90:H104) -> 20971052 | I89: =+G89/E89 -> 0.95585304 | M89: Cancelled (Not to Proceed) | N89: ='Schedule C'!AE6 -> 16 | O89: 16 | P89: =N89-O89 -> 0 | U89: =D83 -> Management Supervision
D90: ='Schedule B'!A71&" - "&'Schedule B'!C71 -> CN.003C20 - Green Business Certification Inc.2220038 | E90: ='Schedule B'!K71 -> 22585.01 | F90: =+'Schedule H GBC'!J37 -> 18000.113 | G90: =+'Schedule B'!U71 -> 18000.113 | H90: =E90-G90 -> 4584.8975 | I90: =+G90/E90 -> 0.79699378 | M90: Superseded (PVO Replaced) | N90: ='Schedule C'!AE9 -> 0 | O90: 0 | P90: =N90-O90 -> 0 | U90: =D84 -> MS.003F02 - Khatib & Alami 2230031 | V90: 44969 | W90: =+W99 -> 45716 | Z90: =+Y90+W90 -> 45716
D91: ='Schedule B'!A69&" - "&'Schedule B'!C69 -> CN.003C13 - SOI TB Ground Improvement Works 2210224 | E91: ='Schedule B'!K69+'Schedule B'!K70 -> 3082689 | F91: =+'Schedule H SIC'!J40 -> 1748735.9 | G91: =+'Schedule B'!U69 -> 1748735.9 | H91: =E91-G91 -> 1333953.1 | I91: =+G91/E91 -> 0.56727615 | U91: MS.003F07 - Euro Consult (COO 6)
D92: ='Schedule B'!A77&" - "&'Schedule B'!C77 -> CN.003C13 - NSCC - Triple Bay Piling (AYC only) 2220032 | E92: ='Schedule B'!K77 -> 16458382 | F92: =+'Schedule H NSCC'!J114 -> 23335059 | G92: =+'Schedule B'!U77 -> 16458382 | H92: =E92-G92 -> -0.030000003 | I92: =+G92/E92 -> 1 | M92: VARIATIONS (VO) | U92: MS.003F09 - Euro Consult (COO 27)
D93: ='Schedule B'!A79&" - "&'Schedule B'!C79 -> CN.003C03 - Structural Concrete, Wet Trades, BOH Fit out, Pools and Water Features, Structural Steel, Glazing, Glass Balustrades, Aluminum Soffits, SFS and GRC, Render Façade, Roof Waterproofing, MEP, ICT/ELV - (SAB) 2230023 | E93: =+'Schedule B'!K79 -> 1.6993991e+08 | F93: =+'Schedule H SAB'!J33 -> 2.7425499e+08 | G93: =+'Schedule H SAB'!AD43 -> 1.7059208e+08 | H93: =E93-G93 -> -652177.96 | I93: =+G93/E93 -> 1.0038377 | N93: Total | O93: Previous | P93: Period | U93: =D87 -> Commercial Management
D94: Direct Payments for SAB's Subcontractors and Suppliers | E94: =SUM('Schedule B'!F81:F145) -> 42594260 | F94: =+E94 -> 42594260 | G94: =+F94 -> 42594260 | H94: =E94-G94 -> 0 | I94: =+G94/E94 -> 1 | M94: Total VO's | N94: =SUM(N95:N98) -> 166 | O94: 164 | P94: =SUM(P95:P98) -> 2 | U94: =D88 -> No Awarded Contracts
D95: ='Schedule B'!A148&" - "&'Schedule B'!C148 -> CN.003C21 - STO Façade Mock-up -(MWN) 2230075 | E95: =+'Schedule B'!K148 -> 819298.55 | F95: =+'Schedule H Medtel'!J37 -> 819298.55 | G95: =+'Schedule B'!U148 -> 819298.55 | H95: =E95-G95 -> 0 | I95: =+G95/E95 -> 1 | M95: VO's Issued / Approved | N95: =+'Schedule C'!AK7 -> 139 | O95: 137 | P95: =N95-O95 -> 2 | U95: =D89 -> Construction Works
D96: ='Schedule B'!A152&" - "&'Schedule B'!C152 -> CN.003C27 - Façade & Glazing Works (Alutec) | E96: =+'Schedule B'!K152 -> 30474502 | F96: =+'Schedule H ALUTEC'!J37 -> 48279533 | G96: =+'Schedule H ALUTEC'!U37 -> 29131817 | H96: =E96-G96 -> 1342684.3 | I96: =+G96/E96 -> 0.95594073 | M96: VO Pending | N96: =+'Schedule C'!AK8 -> 14 | O96: 14 | P96: =N96-O96 -> 0 | U96: =$D$90 -> CN.003C20 - Green Business Certification Inc.2220038 | V96: Completed | W96: Completed
D97: ='Schedule B'!A149&" - "&'Schedule B'!C149 -> CN.003F03 - Vertical Transportation (ESCCO) 2230178 | E97: =+'Schedule B'!K149 -> 2773546 | F97: =+'Schedule H ESCCO'!J37 -> 1990337.8 | G97: =+'Schedule B'!U149 -> 1982337.7 | H97: =E97-G97 -> 791208.34 | I97: =+G97/E97 -> 0.71473041 | M97: Superseded (VO Replaced) | N97: =+'Schedule C'!AK9 -> 0 | O97: 0 | P97: =N97-O97 -> 0 | U97: =+D91 -> CN.003C13 - SOI TB Ground Improvement Works 2210224 | V97: 44474 | W97: 44557 | X97: 30 | Y97: 30 | Z97: =+Y97+W97 -> 44587
D98: CN.003C09 - Interior Fitout Works (DEPA) | E98: =+'Schedule B'!K151 -> 80210582 | F98: =+'Schedule H DEPA'!J39 -> 91261011 | G98: =+'Schedule H DEPA'!U39 -> 65072967 | H98: =E98-G98 -> 15137615 | I98: =+G98/E98 -> 0.81127659 | M98: Cancelled (Not to Proceed) | N98: =+'Schedule C'!AK6 -> 13 | O98: 13 | P98: =N98-O98 -> 0 | U98: =+D92 -> CN.003C13 - NSCC - Triple Bay Piling (AYC only) 2220032 | V98: 44644 | W98: 45066 | X98: 156 | Y98: 96 | Z98: =W98+Y98 -> 45162
D99: =+M53 -> CN.003C31 - MAS - Wet Works | E99: =+'Schedule B'!K153 -> 22360118 | F99: ='Schedule H MAS (Wet Works)'!J36 -> 23384183 | G99: ='Schedule H MAS (Wet Works)'!U36 -> 22345856 | H99: =E99-G99 -> 14261.79 | I99: =+G99/E99 -> 0.99936218 | U99: =+D93 -> CN.003C03 - Structural Concrete, Wet Trades, BOH Fit out, Pools and Water Features, Structural Steel, Glazing, Glass Balustrades, Aluminum Soffits, SFS and GRC, Render Façade, Roof Waterproofing, MEP, ICT/ELV - (SAB) 2230023 | V99: 44938 | W99: 45716 | Y99: 0 | Z99: =+Y99+W99 -> 45716
D100: =+M54 -> CN.003C32 - MAS - Amphitheatre Works | E100: =+'Schedule B'!K154 -> 1284550.4 | F100: ='Schedule H MAS (Amphitheatre)'!J37 -> 1395241.2 | G100: ='Schedule H MAS (Amphitheatre)'!U37 -> 1211278.8 | H100: =E100-G100 -> 73271.515 | I100: =+G100/E100 -> 0.94295941
D101: =M55 -> CN.003C34 - Al Fanar - MEP Labour Supply | E101: =+'Schedule B'!K155 -> 94625593 | F101: =+'Schedule H'!R38 -> 1.3121359e+08 | G101: =+'Schedule H'!S38 -> 92352575 | H101: =E101-G101 -> 2273018.1 | I101: =+G101/E101 -> 0.97597882 | M101: DETERMINED VARIATION ORDERS (DVO) | U101: =+D97 -> CN.003F03 - Vertical Transportation (ESCCO) 2230178
D102: =+M56 -> CN.003C34 - ARMETAL - Reflective ceiling | E102: =+'Schedule B'!K157 -> 7197028.5 | F102: =+'Schedule H'!R43 -> 6633442.8 | G102: =+'Schedule H'!S43 -> 6633442.8 | H102: =E102-G102 -> 563585.73 | I102: =+G102/E102 -> 0.92169189 | N102: Total | O102: Previous | P102: Period | U102: =+D98 -> CN.003C09 - Interior Fitout Works (DEPA) | V102: 45223 | W102: 45639 | Y102: 0 | Z102: =W102+Y102 -> 45639
D103: =+M57 -> CN.003C34 - Al Rahji Takaful - Owner Controlled Insurance Program | E103: =+'Schedule B'!K158 -> 89047.06 | F103: 0 | G103: 0 | H103: =E103-G103 -> 89047.06 | I103: =+G103/E103 -> 0 | M103: Total DVO's | N103: =SUM(N104:N107) -> 146 | O103: 146 | P103: =SUM(P104:P107) -> 0 | U103: =D96 -> CN.003C27 - Façade & Glazing Works (Alutec) | V103: 45656 | W103: 45656 | Z103: =W103+Y103 -> 45656
D104: =+M58 -> CN.003C35 - HASSAN ALLAM - External Scaffoldings | E104: =+'Schedule B'!K160 -> 3096124.9 | F104: =+'Schedule H'!R42 -> 3096124.9 | G104: =+'Schedule H'!S42 -> 3096124.9 | H104: =E104-G104 -> 0 | I104: =+G104/E104 -> 1 | M104: DVO Approved | N104: ='Schedule C'!AX7 -> 118 | O104: 118 | P104: =N104-O104 -> 0 | U104: CN.003C31 - MAS - Wet Works | V104: 45581 | W104: =+V104+60 -> 45641 | Z104: =+W104 -> 45641
D105: =PROPER('Schedule B'!C187) -> Client Cost | E105: =SUM(E106) -> 0 | F105: =SUM(F106) -> 0 | G105: =SUM(G106) -> 0 | H105: =SUM(H106) -> 0 | M105: DVO Pending | N105: ='Schedule C'!AX8 -> 20 | O105: 20 | P105: =N105-O105 -> 0 | U105: CN.003C32 - MAS - Amphitheatre Works | V105: 64 Calendar days from Commencement Date
D106: No Awarded Contracts | E106: 0 | F106: 0 | G106: 0 | H106: =E106-G106 -> 0 | I106: 0 | M106: Cancelled (Not to Proceed) | N106: ='Schedule C'!AX6 -> 8 | O106: 8 | P106: =N106-O106 -> 0 | U106: CN.003C34 - Al Fanar - MEP Labour Supply
D107: =('Schedule B'!C202) -> FF&E AND OS&E | E107: =SUM(E108:E118) -> 44435278 | F107: =SUM(F108:F118) -> 31470988 | G107: =SUM(G108:G118) -> 29205221 | H107: =SUM(H108:H118) -> 15230057 | M107: Superseded (DVO Replaced) | N107: ='Schedule C'!AX9 -> 0 | O107: 0 | P107: =N107-O107 -> 0 | U107: =+M56 -> CN.003C34 - ARMETAL - Reflective ceiling
D108: ='Schedule B'!A150&" - "&'Schedule B'!C150 -> CN.003C08 - Kitchen & Laundry Works (Al Raqtan) 2230205 | E108: =+'Schedule B'!K150 -> 4705352 | F108: =+'Schedule H RAQTAN'!J37 -> 6151689.1 | G108: =+'Schedule H RAQTAN'!V37 -> 3837547.3 | H108: =E108-G108 -> 867804.7 | I108: =+G108/E108 -> 0.81557072 | M108: DETERMINED VARIATION ORDERS (DVO) | U108: =+M58 -> CN.003C35 - HASSAN ALLAM - External Scaffoldings
D109: FFEOSE.003F06 - FF&E and OSE Procurement Agent (Areen Design Ltd) | E109: ='Schedule B'!F204 -> 1107465.9 | F109: =+'Schedule H AREEN'!J37 -> 25319299 | G109: =+'Schedule H AREEN'!U37 -> 25367674 | H109: =+E109+E110-G109 -> 13324440 | I109: =(G109)/(E109+E110) -> 0.65562905 | N109: Total | O109: Contractor value | P109: PVO Value | U109: =D107 -> FF&E AND OS&E
D110: FFEOSE.003F06.02 - FF&E and OSE (VO to Areen Design Ltd) | E110: =+'Schedule B'!K207+'Schedule B'!K208+'Schedule B'!K209+'Schedule B'!K210 -> 37584648 | M110: Total DVO's | N110: =SUM(N112:N115) -> 138 | U110: =D108 -> CN.003C08 - Kitchen & Laundry Works (Al Raqtan) 2230205 | V110: 45071 | W110: 45646 | Z110: =+Y110+W110 -> 45646
D111: FFEOSE.003F11 - Extraordinary Cart | E111: 397876 | F111: 0 | G111: 0 | H111: =E111-G111 -> 397876 | I111: =+G111/E111 -> 0 | U111: FFEOSE.003F06 - FF&E and OSE Procurement Agent (Areen Design Ltd) | V111: 45307 | W111: 45673 | Z111: =+Y111+W111 -> 45673
D112: FFEOSE.003D09 - Saudico Electronic Systems | E112: 353487.06 | F112: 0 | G112: 0 | H112: =E112-G112 -> 353487.06 | I112: =+G112/E112 -> 0 | M112: C-Sub pending Amaala review | N112: =COUNTIFS('Schedule C'!BA$20:BA$369,"PENDING",'Schedule C'!AZ$20:AZ$369,"") -> 15 | O112: =SUMIFS('Schedule C'!$AS$20:$AS$83,'Schedule C'!$BA$20:$BA$83,"PENDING",'Schedule C'!$AZ$20:$AZ$83,"") -> 0 | P112: =SUMIFS('Schedule C'!$AG$20:$AG$83,'Schedule C'!$BA$20:$BA$83,"PENDING",'Schedule C'!$AZ$20:$AZ$83,"") -> 0 | U112: FFEOSE.003F11 - Extraordinary Cart
D113: FFEOSE.003D07 - Birch Street | E113: 115998.98 | F113: 0 | G113: 0 | H113: =E113-G113 -> 115998.98 | I113: =+G113/E113 -> 0 | M113: C-Sub outstanding | N113: =COUNTIFS('Schedule C'!BA$20:BA$369,"PENDING",'Schedule C'!AZ$20:AZ$369,"<>") -> 5 | O113: =SUMIFS('Schedule C'!$AS$20:$AS$83,'Schedule C'!$BA$20:$BA$83,"PENDING",'Schedule C'!$AZ$20:$AZ$83,"<>") -> 0 | P113: =SUMIFS('Schedule C'!$AG$20:$AG$83,'Schedule C'!$BA$20:$BA$83,"PENDING",'Schedule C'!$AZ$20:$AZ$83,"<>") -> 0 | U113: FFEOSE.003D09 - Saudico Electronic Systems
D114: FFEOSE.003D10 - AlFalak Electronic - HPE Servers | E114: 16655 | F114: 0 | G114: 0 | H114: =E114-G114 -> 16655 | I114: =+G114/E114 -> 0 | U114: FFEOSE.003D07 - Birch Street
D115: FFEOSE.003D15 - Saudico Electronic Systems | E115: 34719 | F115: 0 | G115: 0 | H115: =E115-G115 -> 34719 | I115: =+G115/E115 -> 0 | M115: DVO's Approved | N115: =COUNTIF('Schedule C'!$BA$20:$BA$369,"APPROVED") -> 118 | O115: =SUMIF('Schedule C'!$BA20:$BA369,"APPROVED",'Schedule C'!$AS20:$AS369) -> 3174007.2 | P115: =SUMIF('Schedule C'!$BA20:$BA369,"APPROVED",'Schedule C'!$AG20:$AG369) -> 33878350 | U115: FFEOSE.003D10 - AlFalak Electronic - HPE Servers
D116: FFEOSE.003D11 - Sevenrooms Inc | E116: 3633.9 | F116: 0 | G116: 0 | H116: =E116-G116 -> 3633.9 | I116: =+G116/E116 -> 0 | U116: FFEOSE.003D15 - Saudico Electronic Systems
D117: FFEOSE.003D12 - Saudico Electronic Systems | E117: 58307.19 | F117: 0 | G117: 0 | H117: =E117-G117 -> 58307.19 | I117: =+G117/E117 -> 0 | U117: FFEOSE.003D11 - Sevenrooms Inc
D118: FFEOSE.003D14 - Reachware Integration | E118: 57135 | F118: 0 | G118: 0 | H118: =E118-G118 -> 57135 | I118: =+G118/E118 -> 0 | U118: FFEOSE.003D12 - Saudico Electronic Systems
D119: Total | E119: =E72+E83+E87+E89+E105+E107 -> 5.5890741e+08 | F119: =F72+F83+F87+F89+F105+F107 -> 7.204693e+08 | G119: =G72+G83+G87+G89+G105+G107 -> 5.2219982e+08 | H119: =H72+H83+H87+H89+H105+H107 -> 36707589 | I119: =+G119/E119 -> 0.93432259 | U119: FFEOSE.003D12 - Saudico Electronic Systems
D120: =+G120-E120 -> -213967.98 | E120: =+'Schedule A'!S36 -> 5.2241379e+08 | F120: =+D120-E119 -> -5.5912138e+08 | G120: =+'Schedule H'!S45 -> 5.2219982e+08 | H120: =+G120-G119 -> 0 | I120: Check Payment Certified at Zero: | N120: =+M120-G120 -> -5.2219982e+08
E121: =+E120-G119 -> 213967.98
D122: KEY PERIOD MOVEMENTS | H122: =I50-H121 -> -215885.19 | N122: CHECK:
D123: Description | H123: Amount
D124: DVO High Level Overview | H124: =SUM(H125:I140) -> 0 | M124: =H124-I34 -> 0 | N124: CHECK:
...

Sheet Stakeholder Executive Review
A2: ='Data Input'!A1&" - "&'Data Input'!B1 -> PROGRAMME: - MARINA VILLAGE (PROGRAMME 1_TRIPLE BAY)
A3: ='Data Input'!A2&" - "&'Data Input'!B2 -> PROGRAMME CODE: - 1TB01003
A4: ='Data Input'!A3&" - "&'Data Input'!B3 -> ASSET NAME: - AMAALA YACHT CLUB
A5: ='Data Input'!A4&" - "&'Data Input'!B4 -> ASSET CODE: - 1TB01003.01
A6: ='Data Input'!A7&" - "&'Data Input'!B7 -> REPORT NO: - MONTHLY REPORT NO. 49
A7: ='Data Input'!A8&" - "&'Data Input'!B8 -> REPORTING PERIOD: - OCTOBER 2026
E9: COMMITTED | H9: UNCOMITTED | Q9: PERIOD MOVEMENT
B10: Approved Baseline Budget | C10: Approved Budget Transfers | D10: Current Approved Budget | E10: Approved Contracts + Direct Actual | F10: Approved Contract Changes (DVOs+PVOs) | G10: Total Approved Commitments | H10: Pending Contracts | I10: Pending Contract Changes (PVOs) | J10: Total Commitments (Approved & Pending) | K10: Early Warnings & RFC | L10: EAC Based on Awarded Packages | M10: Remaining Budget Before EW | N10: Remaining Budget after EW | O10: To Procure (Forecasted Contract Award Value) | P10: Forecasted EAC Including all awards | Q10: ='Schedule B'!X12 -> SEPTEMBER 2026 | R10: Variance | S10: Comments | U10: MH3 Aconex - CN Budget Hold | V10: Variance | W10: MVW | X10: Other Prog 1 Assets | Y10: BTR under Process
B11: A | C11: B | D11: C = (A + B) | E11: D | F11: E | G11: F = (D + E) | H11: G | I11: H | J11: I = (F + G + H) | K11: J | L11: K = (I + J) | M11: L = (F - I) | N11: M = (F - (I+J)) | O11: N | P11: O = (K + N) | Q11: P | R11: Q = (O - P)
D12: To match with "Approved Budget" in Aconex | G12: To match with "Current Commitments" in Aconex | J12: To match with "All Commitments" in Aconex
A13: Professional Services | B13: =SUM(B14:B26) -> 28761589 | C13: =SUM(C14:C26) -> -6705327.7 | D13: =SUM(D14:D26) -> 22056262 | E13: =SUM(E14:E26) -> 22056262 | F13: =SUM(F14:F26) -> 3171766.9 | G13: =SUM(G14:G26) -> 25228028 | H13: =SUM(H14:H26) -> 0 | I13: =SUM(I14:I26) -> 101675.08 | ... R13: =SUM(R14:R26) -> 0 | U13: 1.1835694e+08 | V13: =L13-U13 -> -93046430
A14: ='Schedule B'!C17 -> Dewan Architects & Engineers 2200445 | B14: ='Schedule B'!E17 -> 5973808 | C14: ='Schedule B'!F17 -> 0 | D14: =SUM(B14:C14) -> 5973808 | E14: ='Schedule B'!H17 -> 5973808 | F14: ='Schedule B'!I17+'Schedule B'!J17 -> 3316718.1 | G14: =SUM(E14:F14) -> 9290526.1 | I14: ='Schedule B'!M17 -> 0 | J14: =SUM(G14:I14) -> 9290526.1 | K14: ='Schedule B'!N17+'Schedule B'!O17 -> 0 | L14: =SUM(J14:K14) -> 9290526.1 | M14: =IF(SUM(D14-J14)<0,0,SUM(D14-J14)) -> 0 | N14: =IF(SUM(D14-L14)<0,0,SUM(D14-L14)) -> 0 | P14: =L14+O14 -> 9290526.1 | Q14: ='Schedule B'!X17 -> 9290526.1 | R14: =P14-Q14 -> 0
A15: ='Schedule B'!C18 -> HKS Architects Ltd - Design Competition Fees 2200010 | B15: ='Schedule B'!E18 -> 555960.36 | C15: ='Schedule B'!F18 -> 0 | D15: =SUM(B15:C15) -> 555960.36 | E15: ='Schedule B'!H18 -> 555960.36 | F15: ='Schedule B'!I18+'Schedule B'!J18 -> 0 | G15: =SUM(E15:F15) -> 555960.36 | I15: ='Schedule B'!M18 -> 0 | J15: =SUM(G15:I15) -> 555960.36 | K15: ='Schedule B'!N18+'Schedule B'!O18 -> 0 | L15: =SUM(J15:K15) -> 555960.36 | M15: =IF(SUM(D15-J15)<0,0,SUM(D15-J15)) -> 0 | N15: =IF(SUM(D15-L15)<0,0,SUM(D15-L15)) -> 0 | P15: =L15+O15 -> 555960.36 | Q15: ='Schedule B'!X18 -> 555960.36 | R15: =P15-Q15 -> 0 | S15: Closed - Final account executed.
A16: ='Schedule B'!C19 -> HKS Architects Ltd - Design Architect Fees 2200375 | B16: ='Schedule B'!E19 -> 10891204 | C16: ='Schedule B'!F19 -> 0 | D16: =SUM(B16:C16) -> 10891204 | E16: ='Schedule B'!H19 -> 10891204 | F16: ='Schedule B'!I19+'Schedule B'!J19 -> -89775 | G16: =SUM(E16:F16) -> 10801429 | I16: ='Schedule B'!M19 -> 0 | J16: =SUM(G16:I16) -> 10801429 | K16: ='Schedule B'!N19+'Schedule B'!O19 -> 0 | L16: =SUM(J16:K16) -> 10801429 | M16: =IF(SUM(D16-J16)<0,0,SUM(D16-J16))*0 -> 0 | N16: =IF(SUM(D16-L16)<0,0,SUM(D16-L16))*0 -> 0 | P16: =L16+O16 -> 10801429 | Q16: ='Schedule B'!X19 -> 10801429 | R16: =P16-Q16 -> 0 | S16: Closed - Final account executed.
A17: ='Schedule B'!C20 -> Applied Technology and Management Inc (Dubai BR)s 2210167 | B17: ='Schedule B'!E20 -> 93750 | C17: ='Schedule B'!F20 -> 0 | D17: =SUM(B17:C17) -> 93750 | E17: ='Schedule B'!H20 -> 93750 | F17: ='Schedule B'!I20+'Schedule B'!J20 -> 0 | G17: =SUM(E17:F17) -> 93750 | I17: ='Schedule B'!M20 -> 0 | J17: =SUM(G17:I17) -> 93750 | K17: ='Schedule B'!N20+'Schedule B'!O20 -> 0 | L17: =SUM(J17:K17) -> 93750 | M17: =IF(SUM(D17-J17)<0,0,SUM(D17-J17)) -> 0 | N17: =IF(SUM(D17-L17)<0,0,SUM(D17-L17)) -> 0 | P17: =L17+O17 -> 93750 | Q17: ='Schedule B'!X20 -> 93750 | R17: =P17-Q17 -> 0 | S17: Closed - Final account executed.
A18: ='Schedule B'!C21 -> Langan International UK Limited 2230042 | B18: ='Schedule B'!E21 -> 0 | C18: ='Schedule B'!F21 -> 172368.42 | D18: =SUM(B18:C18) -> 172368.42 | E18: ='Schedule B'!H21 -> 172368.42 | F18: ='Schedule B'!I21+'Schedule B'!J21 -> -1898.52 | G18: =SUM(E18:F18) -> 170469.9 | I18: ='Schedule B'!M21 -> 0 | J18: =SUM(G18:I18) -> 170469.9 | K18: ='Schedule B'!N21+'Schedule B'!O21 -> 0 | L18: =SUM(J18:K18) -> 170469.9 | M18: =IF(SUM(D18-J18)<0,0,SUM(D18-J18)) -> 1898.52 | N18: =IF(SUM(D18-L18)<0,0,SUM(D18-L18)) -> 1898.52 | P18: =L18+O18 -> 170469.9 | Q18: ='Schedule B'!X21 -> 170469.9 | R18: =P18-Q18 -> 0 | S18: Closed - Final account executed.
A19: ='Schedule B'!C22 -> Zuhair Fayez and Partners 2230041 | B19: ='Schedule B'!E22 -> 0 | C19: ='Schedule B'!F22 -> 106231.5 | D19: =SUM(B19:C19) -> 106231.5 | E19: ='Schedule B'!H22 -> 106231.5 | F19: ='Schedule B'!I22+'Schedule B'!J22 -> 0 | G19: =SUM(E19:F19) -> 106231.5 | I19: ='Schedule B'!M22 -> 0 | J19: =SUM(G19:I19) -> 106231.5 | K19: ='Schedule B'!N22+'Schedule B'!O22 -> 0 | L19: =SUM(J19:K19) -> 106231.5 | M19: =IF(SUM(D19-J19)<0,0,SUM(D19-J19)) -> 0 | N19: =IF(SUM(D19-L19)<0,0,SUM(D19-L19)) -> 0 | P19: =L19+O19 -> 106231.5 | Q19: ='Schedule B'!X22 -> 106231.5 | R19: =P19-Q19 -> 0 | S19: Closed - Final account executed.
A20: ='Schedule B'!C23 -> Ministry of Municipality and Rural Affairs (Tabuk) | B20: ='Schedule B'!E23 -> 0 | C20: ='Schedule B'!F23 -> 45677.6 | D20: =SUM(B20:C20) -> 45677.6 | E20: ='Schedule B'!H23 -> 45677.6 | F20: ='Schedule B'!I23+'Schedule B'!J23 -> 0 | G20: =SUM(E20:F20) -> 45677.6 | I20: ='Schedule B'!M23 -> 0 | J20: =SUM(G20:I20) -> 45677.6 | K20: ='Schedule B'!N23+'Schedule B'!O23 -> 0 | L20: =SUM(J20:K20) -> 45677.6 | M20: =IF(SUM(D20-J20)<0,0,SUM(D20-J20)) -> 0 | N20: =IF(SUM(D20-L20)<0,0,SUM(D20-L20)) -> 0 | P20: =L20+O20 -> 45677.6 | Q20: ='Schedule B'!X23 -> 45677.6 | R20: =P20-Q20 -> 0 | S20: Closed - Payment to Tabuk Municipality
A21: ='Schedule B'!C24 -> Jensen Hughes Saudi Arabia Co 2230180 | B21: ='Schedule B'!E24 -> 0 | C21: ='Schedule B'!F24 -> 127291.9 | D21: =SUM(B21:C21) -> 127291.9 | E21: ='Schedule B'!H24 -> 127291.9 | F21: ='Schedule B'!I24+'Schedule B'!J24 -> -56700 | G21: =SUM(E21:F21) -> 70591.9 | I21: ='Schedule B'!M24 -> 0 | J21: =SUM(G21:I21) -> 70591.9 | K21: ='Schedule B'!N24+'Schedule B'!O24 -> 0 | L21: =SUM(J21:K21) -> 70591.9 | M21: =IF(SUM(D21-J21)<0,0,SUM(D21-J21)) -> 56700 | N21: =IF(SUM(D21-L21)<0,0,SUM(D21-L21)) -> 56700 | P21: =L21+O21 -> 70591.9 | Q21: ='Schedule B'!X24 -> 70591.9 | R21: =P21-Q21 -> 0
A22: ='Schedule B'!C25 -> Jensen Hughes Saudi Arabia Co 2250184 | B22: ='Schedule B'!E25 -> 0 | C22: ='Schedule B'!F25 -> 38103.2 | D22: =SUM(B22:C22) -> 38103.2 | E22: ='Schedule B'!H25 -> 38103.2 | F22: ='Schedule B'!I25+'Schedule B'!J25 -> -23800 | G22: =SUM(E22:F22) -> 14303.2 | J22: =SUM(G22:I22) -> 14303.2 | K22: ='Schedule B'!N25+'Schedule B'!O25 -> 0 | L22: =SUM(J22:K22) -> 14303.2 | M22: =IF(SUM(D22-J22)<0,0,SUM(D22-J22)) -> 23800 | N22: =IF(SUM(D22-L22)<0,0,SUM(D22-L22)) -> 23800 | P22: =L22+O22 -> 14303.2 | Q22: ='Schedule B'!X25 -> 14303.2 | R22: =P22-Q22 -> 0
A23: ='Schedule B'!C26 -> CML (Independent Commissioning Agent) COO 7 | B23: ='Schedule B'!E26 -> 0 | C23: ='Schedule B'!F26 -> 2406500 | D23: =SUM(B23:C23) -> 2406500 | E23: ='Schedule B'!H26 -> 2406500 | F23: ='Schedule B'!I26+'Schedule B'!J26 -> 1520390.5 | G23: =SUM(E23:F23) -> 3926890.5 | I23: ='Schedule B'!M26 -> 101675.08 | J23: =SUM(G23:I23) -> 4028565.6 | K23: ='Schedule B'!N26+'Schedule B'!O26 -> 0 | L23: =SUM(J23:K23) -> 4028565.6 | M23: =IF(SUM(D23-J23)<0,0,SUM(D23-J23)) -> 0 | N23: =IF(SUM(D23-L23)<0,0,SUM(D23-L23)) -> 0 | P23: =L23+O23 -> 4028565.6 | Q23: ='Schedule B'!X26 -> 4028565.6 | R23: =P23-Q23 -> 0
A24: ='Schedule B'!C27 -> GST - Sustainability Accreditation Services | B24: ='Schedule B'!E27 -> 0 | C24: ='Schedule B'!F27 -> 133000 | D24: =SUM(B24:C24) -> 133000 | E24: ='Schedule B'!H27 -> 133000 | F24: ='Schedule B'!I27+'Schedule B'!J27 -> 0 | G24: =SUM(E24:F24) -> 133000 | I24: ='Schedule B'!M27 -> 0 | J24: =SUM(G24:I24) -> 133000 | K24: ='Schedule B'!N27+'Schedule B'!O27 -> 0 | L24: =SUM(J24:K24) -> 133000 | M24: =IF(SUM(D24-J24)<0,0,SUM(D24-J24)) -> 0 | N24: =IF(SUM(D24-L24)<0,0,SUM(D24-L24)) -> 0 | P24: =L24+O24 -> 133000 | Q24: ='Schedule B'!X27 -> 133000 | R24: =P24-Q24 -> 0
A26: ='Schedule B'!C245 -> Remaining budget - Professional Fees | B26: ='Schedule B'!E245 -> 11246867 | C26: ='Schedule B'!F245 -> -9734500.3 | D26: =SUM(B26:C26) -> 1512366.5 | E26: ='Schedule B'!H245 -> 1512366.5 | F26: ='Schedule B'!I245+'Schedule B'!J245 -> -1493168.2 | G26: =SUM(E26:F26) -> 19198.32 | H26: ='Schedule B'!K245*0 -> 0 | I26: ='Schedule B'!M245 -> 0 | J26: =SUM(G26:I26) -> 19198.32 | K26: ='Schedule B'!N245+'Schedule B'!O245 -> 0 | L26: =IF(SUM(J26:K26)<0,0,SUM(J26:K26))*0 -> 0 | M26: =IF(SUM(H26+I26)<0,0,SUM(H26+I26)) -> 0 | N26: =IF(SUM(J26+K26)<0,0,SUM(J26+K26)) -> 19198.32 | P26: =L26+O26 -> 0 | Q26: ='Schedule B'!X245*0 -> 0 | R26: =P26-Q26 -> 0 | AC26: =IF(SUM(J26:K26)<0,0,SUM(J26:K26)) -> 19198.32
A27: Management Supervision | B27: =SUM(B28:B32) -> 17975993 | C27: =SUM(C28:C32) -> -4937063.3 | D27: =SUM(D28:D32) -> 13038930 | E27: =SUM(E28:E32) -> 13038930 | F27: =SUM(F28:F32) -> 1329161.4 | G27: =SUM(G28:G32) -> 14368091 | H27: =SUM(H28:H32) -> 0 | I27: =SUM(I28:I32) -> -53507 | ... R27: =SUM(R28:R32) -> 0
A28: ='Schedule B'!C33 -> Khatib & Alami 2230031 | B28: ='Schedule B'!E33 -> 0 | C28: ='Schedule B'!F33 -> 13059930 | D28: =SUM(B28:C28) -> 13059930 | E28: ='Schedule B'!H33 -> 13059930 | F28: ='Schedule B'!I33+'Schedule B'!J33 -> 1071977 | G28: =SUM(E28:F28) -> 14131907 | I28: ='Schedule B'!M33 -> 0 | J28: =SUM(G28:I28) -> 14131907 | K28: ='Schedule B'!N33+'Schedule B'!O33 -> -49207 | L28: =SUM(J28:K28) -> 14082700 | M28: =IF(SUM(D28-J28)<0,0,SUM(D28-J28))*0 -> 0 | N28: =IF(SUM(D28-L28)<0,0,SUM(D28-L28))*0 -> 0 | P28: =L28+O28 -> 14082700 | Q28: ='Schedule B'!X33 -> 14082700 | R28: =P28-Q28 -> 0
A29: ='Schedule B'!C34 -> Euro Consult (COO 6) | B29: ='Schedule B'!E34 -> 0 | C29: ='Schedule B'!F34 -> 182184.38 | D29: =SUM(B29:C29) -> 182184.38 | E29: ='Schedule B'!H34 -> 182184.38 | F29: ='Schedule B'!I34+'Schedule B'!J34 -> 0 | G29: =SUM(E29:F29) -> 182184.38 | I29: ='Schedule B'!M34 -> -53507 | J29: =SUM(G29:I29) -> 128677.38 | K29: ='Schedule B'!N34+'Schedule B'!O34 -> 0 | L29: =SUM(J29:K29) -> 128677.38 | M29: =IF(SUM(D29-J29)<0,0,SUM(D29-J29)) -> 53507 | N29: =IF(SUM(D29-L29)<0,0,SUM(D29-L29)) -> 53507 | P29: =L29+O29 -> 128677.38 | Q29: ='Schedule B'!X34 -> 128677.38 | R29: =P29-Q29 -> 0
A30: ='Schedule B'!C35 -> Euro Consult (COO 27) | B30: ='Schedule B'!E35 -> 0 | C30: ='Schedule B'!F35 -> 54000 | D30: =SUM(B30:C30) -> 54000 | E30: ='Schedule B'!H35 -> 54000 | F30: ='Schedule B'!I35+'Schedule B'!J35 -> 0 | G30: =SUM(E30:F30) -> 54000 | I30: ='Schedule B'!M35 -> 0 | J30: =SUM(G30:I30) -> 54000 | L30: =SUM(J30:K30) -> 54000 | M30: =IF(SUM(D30-J30)<0,0,SUM(D30-J30)) -> 0 | N30: =IF(SUM(D30-L30)<0,0,SUM(D30-L30)) -> 0 | P30: =L30+O30 -> 54000 | Q30: ='Schedule B'!X35 -> 54000 | R30: =P30-Q30 -> 0
A32: ='Schedule B'!C250 -> Remaining budget - Management Supervision | B32: ='Schedule B'!E250 -> 17975993 | C32: ='Schedule B'!F250 -> -18233178 | D32: =SUM(B32:C32) -> -257184.38 | E32: ='Schedule B'!H250 -> -257184.38 | F32: ='Schedule B'!I250+'Schedule B'!J250 -> 257184.38 | G32: =SUM(E32:F32) -> 1.0477379e-09 | H32: ='Schedule B'!K250*0 -> 0 | I32: ='Schedule B'!M250 -> 0 | J32: =SUM(G32:I32) -> 1.0477379e-09 | K32: ='Schedule B'!N250+'Schedule B'!O250 -> 49207 | L32: =IF(SUM(J32:K32)<0,0,SUM(J32:K32))*0 -> 0 | M32: =IF(SUM(H32+I32)<0,0,SUM(H32+I32)) -> 0 | N32: =IF(SUM(J32+K32)<0,0,SUM(J32+K32)) -> 49207 | P32: =L32+O32 -> 0 | Q32: ='Schedule B'!X250*0 -> 0 | R32: =P32-Q32 -> 0
A33: Commercial Management | B33: =B34 -> 1198399.6 | C33: =C34 -> -1198399.6 | D33: =D34 -> 0 | E33: =E34 -> 0 | F33: =F34 -> 0 | G33: =G34 -> 0 | H33: =H34 -> 0 | I33: =I34 -> 0 | ... R33: =R34 -> 0 | T33: 2.1005213e+08
A34: ='Schedule B'!C251 -> Remaining budget - Commercial Management | B34: ='Schedule B'!E251 -> 1198399.6 | C34: ='Schedule B'!F251 -> -1198399.6 | D34: =SUM(B34:C34) -> 0 | E34: ='Schedule B'!H251 -> 0 | F34: ='Schedule B'!I251+'Schedule B'!J251 -> 0 | G34: =SUM(E34:F34) -> 0 | I34: ='Schedule B'!M251 -> 0 | J34: =SUM(G34:I34) -> 0 | K34: ='Schedule B'!N251+'Schedule B'!O251 -> 0 | L34: =SUM(J34:K34) -> 0 | M34: =IF(SUM(G34+I34)<0,0,SUM(G34+I34)) -> 0 | N34: =IF(SUM(J34+K34)<0,0,SUM(J34+K34)) -> 0 | O34: 0 | P34: =L34+O34 -> 0 | Q34: ='Schedule B'!X251 -> 0 | R34: =P34-Q34 -> 0
A35: Construction | B35: =SUM(B36:B130) -> 2.4341895e+08 | C35: =SUM(C36:C130) -> 2.6516033e+08 | D35: =SUM(D36:D130) -> 5.0857928e+08 | E35: =SUM(E36:E130) -> 5.0857928e+08 | F35: =SUM(F36:F130) -> -5794907.3 | G35: =SUM(G36:G130) -> 5.0278437e+08 | H35: =SUM(H36:H130) -> 0 | I35: =SUM(I36:I130) -> -164010 | ... R35: =SUM(R36:R130) -> -215885.19 | T35: =P35-D35 -> -10715139 | U35: 229543628 | V35: =#REF!-U35 -> #REF! | W35: =#REF! -> #REF! | X35: =V35-W35-Y35 -> #REF! | Y35: 189345.67
A36: ='Schedule B'!C69 -> SOI TB Ground Improvement Works 2210224 | B36: ='Schedule B'!E69 -> 2799717 | C36: ='Schedule B'!F69 -> 0 | D36: =B36+C36 -> 2799717 | E36: ='Schedule B'!H69 -> 2799717 | F36: ='Schedule B'!I69+'Schedule B'!J69 -> 0 | G36: =E36+F36 -> 2799717 | I36: ='Schedule B'!M69 -> 0 | J36: =SUM(G36:I36) -> 2799717 | K36: ='Schedule B'!N69+'Schedule B'!O69 -> -500000 | L36: =J36+K36 -> 2299717 | M36: =IF(SUM(D36-J36)<0,0,SUM(D36-J36)) -> 0 | N36: =IF(SUM(D36-L36)<0,0,SUM(D36-L36)) -> 500000 | P36: =L36+O36 -> 2299717 | Q36: ='Schedule B'!X69 -> 2299717 | R36: =P36-Q36 -> 0 | T36: =SUM(#REF!) -> #REF!
A37: ='Schedule B'!C70 -> SOI TB Ground Improvement Works 2210224 PROVISIONAL SUMS | B37: ='Schedule B'!E70 -> 282972 | C37: ='Schedule B'!F70 -> 0 | D37: =B37+C37 -> 282972 | E37: ='Schedule B'!H70 -> 282972 | F37: ='Schedule B'!I70+'Schedule B'!J70 -> 0 | G37: =E37+F37 -> 282972 | I37: ='Schedule B'!M70 -> 0 | J37: =SUM(G37:I37) -> 282972 | K37: ='Schedule B'!N70+'Schedule B'!O70 -> -282972 | L37: =J37+K37 -> 0 | M37: =IF(SUM(D37-J37)<0,0,SUM(D37-J37)) -> 0 | N37: =IF(SUM(D37-L37)<0,0,SUM(D37-L37)) -> 282972 | P37: =L37+O37 -> 0 | Q37: ='Schedule B'!X70 -> 0 | R37: =P37-Q37 -> 0 | T37: =SUM(#REF!) -> #REF!
A38: ='Schedule B'!C71 -> Green Business Certification Inc.2220038 | B38: ='Schedule B'!E71 -> 4500 | C38: ='Schedule B'!F71 -> 18594.49 | D38: =B38+C38 -> 23094.49 | E38: ='Schedule B'!H71 -> 23094.49 | F38: ='Schedule B'!I71+'Schedule B'!J71 -> -509.48 | G38: =E38+F38 -> 22585.01 | I38: ='Schedule B'!M71 -> 0 | J38: =SUM(G38:I38) -> 22585.01 | K38: ='Schedule B'!N71+'Schedule B'!O71 -> 0 | L38: =J38+K38 -> 22585.01 | M38: =IF(SUM(D38-J38)<0,0,SUM(D38-J38)) -> 509.48 | N38: =IF(SUM(D38-L38)<0,0,SUM(D38-L38)) -> 509.48 | P38: =L38+O38 -> 22585.01 | Q38: ='Schedule B'!X71 -> 22585.01 | R38: =P38-Q38 -> 0 | T38: =SUM(#REF!) -> #REF!
D39: =B39+C39 -> 0 | G39: =E39+F39 -> 0 | J39: =SUM(G39:I39) -> 0 | L39: =J39+K39 -> 0 | M39: =D39-J39 -> 0 | N39: =D39-L39 -> 0 | P39: =L39+O39 -> 0 | R39: =P39-Q39 -> 0 | T39: =SUM(#REF!) -> #REF!
A40: ='Schedule B'!C77 -> NSCC - Triple Bay Piling (AYC only) 2220032 | B40: ='Schedule B'!E77 -> 18698534 | C40: ='Schedule B'!F77 -> 0 | D40: =B40+C40 -> 18698534 | E40: ='Schedule B'!H77 -> 18698534 | F40: ='Schedule B'!I77+'Schedule B'!J77 -> -2240152.5 | G40: =E40+F40 -> 16458382 | I40: ='Schedule B'!M77 -> 0 | J40: =SUM(G40:I40) -> 16458382 | K40: ='Schedule B'!N77+'Schedule B'!O77 -> 0 | L40: =J40+K40 -> 16458382 | M40: =IF(SUM(D40-J40)<0,0,SUM(D40-J40))*0 -> 0 | N40: =IF(SUM(D40-L40)<0,0,SUM(D40-L40))*0 -> 0 | P40: =L40+O40 -> 16458382 | Q40: ='Schedule B'!X77 -> 16458382 | R40: =P40-Q40 -> 0 | S40: Closed - Final account executed.
A41: ='Schedule B'!C79 -> Structural Concrete, Wet Trades, BOH Fit out, Pools and Water Features, Structural Steel, Glazing, Glass Balustrades, Aluminum Soffits, SFS and GRC, Render Façade, Roof Waterproofing, MEP, ICT/ELV - (SAB) 2230023 | B41: ='Schedule B'!E79 -> 0 | C41: ='Schedule B'!F79 -> 2.6095541e+08 | D41: =B41+C41 -> 2.6095541e+08 | E41: ='Schedule B'!H79 -> 2.6095541e+08 | F41: ='Schedule B'!I79+'Schedule B'!J79 -> -91015508 | G41: =E41+F41 -> 1.6993991e+08 | I41: ='Schedule B'!M79 -> -19683046 | J41: =SUM(G41:I41) -> 150256861 | K41: ='Schedule B'!N79+'Schedule B'!O79 -> 20732557 | L41: =J41+K41 -> 1.7098942e+08 | M41: =IF(SUM(D41-J41)<0,0,SUM(D41-J41))*0 -> 0 | N41: =IF(SUM(D41-L41)<0,0,SUM(D41-L41)) -> 89965997 | P41: =L41+O41 -> 1.7098942e+08 | Q41: ='Schedule B'!X79 -> 1.7240176e+08 | R41: =P41-Q41 -> -1412346.4
A43: Direct Payment to SAB's Subcontractors and Suppliers
A44: ='Schedule B'!C81 -> Prelims - Mohammad Alharbi Medical Company | B44: ='Schedule B'!E81 -> 0 | C44: ='Schedule B'!F81 -> 134895.4 | D44: =B44+C44 -> 134895.4 | E44: ='Schedule B'!H81 -> 134895.4 | F44: ='Schedule B'!I81+'Schedule B'!J81 -> 0 | G44: =E44+F44 -> 134895.4 | I44: ='Schedule B'!M81 -> 0 | J44: =SUM(G44:I44) -> 134895.4 | K44: ='Schedule B'!N81+'Schedule B'!O81 -> 0 | L44: =J44+K44 -> 134895.4 | M44: =IF(SUM(D44-J44)<0,0,SUM(D44-J44))*0 -> 0 | N44: =IF(SUM(D44-L44)<0,0,SUM(D44-L44)) -> 0 | P44: =L44+O44 -> 134895.4 | Q44: ='Schedule B'!X81 -> 134895.4 | R44: =P44-Q44 -> 0
A45: ='Schedule B'!C82 -> Prelims - Al Anan Travels and Tours | B45: ='Schedule B'!E82 -> 0 | C45: ='Schedule B'!F82 -> 103373.74 | D45: =B45+C45 -> 103373.74 | E45: ='Schedule B'!H82 -> 103373.74 | F45: ='Schedule B'!I82+'Schedule B'!J82 -> 0 | G45: =E45+F45 -> 103373.74 | I45: ='Schedule B'!M82 -> 0 | J45: =SUM(G45:I45) -> 103373.74 | K45: ='Schedule B'!N82+'Schedule B'!O82 -> 0 | L45: =J45+K45 -> 103373.74 | M45: =IF(SUM(D45-J45)<0,0,SUM(D45-J45))*0 -> 0 | N45: =IF(SUM(D45-L45)<0,0,SUM(D45-L45)) -> 0 | P45: =L45+O45 -> 103373.74 | Q45: ='Schedule B'!X82 -> 103373.74 | R45: =P45-Q45 -> 0
A46: ='Schedule B'!C83 -> Prelims - Al drees Petroleum | B46: ='Schedule B'!E83 -> 0 | C46: ='Schedule B'!F83 -> 34782.61 | D46: =B46+C46 -> 34782.61 | E46: ='Schedule B'!H83 -> 34782.61 | F46: ='Schedule B'!I83+'Schedule B'!J83 -> 0 | G46: =E46+F46 -> 34782.61 | I46: ='Schedule B'!M83 -> 0 | J46: =SUM(G46:I46) -> 34782.61 | K46: ='Schedule B'!N83+'Schedule B'!O83 -> 0 | L46: =J46+K46 -> 34782.61 | M46: =IF(SUM(D46-J46)<0,0,SUM(D46-J46))*0 -> 0 | N46: =IF(SUM(D46-L46)<0,0,SUM(D46-L46)) -> 0 | P46: =L46+O46 -> 34782.61 | Q46: ='Schedule B'!X83 -> 34782.61 | R46: =P46-Q46 -> 0
A47: ='Schedule B'!C84 -> Prelims - Salim Hamed Cleaning | B47: ='Schedule B'!E84 -> 0 | C47: ='Schedule B'!F84 -> 31306.1 | D47: =B47+C47 -> 31306.1 | E47: ='Schedule B'!H84 -> 31306.1 | F47: ='Schedule B'!I84+'Schedule B'!J84 -> 0 | G47: =E47+F47 -> 31306.1 | I47: ='Schedule B'!M84 -> 0 | J47: =SUM(G47:I47) -> 31306.1 | K47: ='Schedule B'!N84+'Schedule B'!O84 -> 0 | L47: =J47+K47 -> 31306.1 | M47: =IF(SUM(D47-J47)<0,0,SUM(D47-J47))*0 -> 0 | N47: =IF(SUM(D47-L47)<0,0,SUM(D47-L47)) -> 0 | P47: =L47+O47 -> 31306.1 | Q47: ='Schedule B'!X84 -> 31306.1 | R47: =P47-Q47 -> 0
A48: ='Schedule B'!C85 -> Prelims - Clean Coast for Contracting | B48: ='Schedule B'!E85 -> 0 | C48: ='Schedule B'!F85 -> 252583.81 | D48: =B48+C48 -> 252583.81 | E48: ='Schedule B'!H85 -> 252583.81 | F48: ='Schedule B'!I85+'Schedule B'!J85 -> 0 | G48: =E48+F48 -> 252583.81 | I48: ='Schedule B'!M85 -> 0 | J48: =SUM(G48:I48) -> 252583.81 | K48: ='Schedule B'!N85+'Schedule B'!O85 -> 0 | L48: =J48+K48 -> 252583.81 | M48: =IF(SUM(D48-J48)<0,0,SUM(D48-J48))*0 -> 0 | N48: =IF(SUM(D48-L48)<0,0,SUM(D48-L48)) -> 0 | P48: =L48+O48 -> 252583.81 | Q48: ='Schedule B'!X85 -> 252583.81 | R48: =P48-Q48 -> 0
A49: ='Schedule B'!C86 -> Prelims - Sami General Contracting | B49: ='Schedule B'!E86 -> 0 | C49: ='Schedule B'!F86 -> 273350 | D49: =B49+C49 -> 273350 | E49: ='Schedule B'!H86 -> 273350 | F49: ='Schedule B'!I86+'Schedule B'!J86 -> 0 | G49: =E49+F49 -> 273350 | I49: ='Schedule B'!M86 -> 0 | J49: =SUM(G49:I49) -> 273350 | K49: ='Schedule B'!N86+'Schedule B'!O86 -> 0 | L49: =J49+K49 -> 273350 | M49: =IF(SUM(D49-J49)<0,0,SUM(D49-J49))*0 -> 0 | N49: =IF(SUM(D49-L49)<0,0,SUM(D49-L49)) -> 0 | P49: =L49+O49 -> 273350 | Q49: ='Schedule B'!X86 -> 273350 | R49: =P49-Q49 -> 0
A50: ='Schedule B'!C87 -> Prelims - Eastern Horizons Foundation Transportation Comp | B50: ='Schedule B'!E87 -> 0 | C50: ='Schedule B'!F87 -> 14349 | D50: =B50+C50 -> 14349 | E50: ='Schedule B'!H87 -> 14349 | F50: ='Schedule B'!I87+'Schedule B'!J87 -> 0 | G50: =E50+F50 -> 14349 | I50: ='Schedule B'!M87 -> 0 | J50: =SUM(G50:I50) -> 14349 | K50: ='Schedule B'!N87+'Schedule B'!O87 -> 0 | L50: =J50+K50 -> 14349 | M50: =IF(SUM(D50-J50)<0,0,SUM(D50-J50))*0 -> 0 | N50: =IF(SUM(D50-L50)<0,0,SUM(D50-L50)) -> 0 | P50: =L50+O50 -> 14349 | Q50: ='Schedule B'!X87 -> 14349 | R50: =P50-Q50 -> 0
A51: ='Schedule B'!C88 -> Prelims - Jak Generation Cont Co LLC | B51: ='Schedule B'!E88 -> 0 | C51: ='Schedule B'!F88 -> 369751.45 | D51: =B51+C51 -> 369751.45 | E51: ='Schedule B'!H88 -> 369751.45 | F51: ='Schedule B'!I88+'Schedule B'!J88 -> 0 | G51: =E51+F51 -> 369751.45 | I51: ='Schedule B'!M88 -> 0 | J51: =SUM(G51:I51) -> 369751.45 | K51: ='Schedule B'!N88+'Schedule B'!O88 -> 0 | L51: =J51+K51 -> 369751.45 | M51: =IF(SUM(D51-J51)<0,0,SUM(D51-J51))*0 -> 0 | N51: =IF(SUM(D51-L51)<0,0,SUM(D51-L51)) -> 0 | P51: =L51+O51 -> 369751.45 | Q51: ='Schedule B'!X88 -> 369751.45 | R51: =P51-Q51 -> 0
A52: ='Schedule B'!C89 -> Prelims - Intelligent General Cont Co Equipment | B52: ='Schedule B'!E89 -> 0 | C52: ='Schedule B'!F89 -> 758870.17 | D52: =B52+C52 -> 758870.17 | E52: ='Schedule B'!H89 -> 758870.17 | F52: ='Schedule B'!I89+'Schedule B'!J89 -> 0 | G52: =E52+F52 -> 758870.17 | I52: ='Schedule B'!M89 -> 0 | J52: =SUM(G52:I52) -> 758870.17 | K52: ='Schedule B'!N89+'Schedule B'!O89 -> 0 | L52: =J52+K52 -> 758870.17 | M52: =IF(SUM(D52-J52)<0,0,SUM(D52-J52))*0 -> 0 | N52: =IF(SUM(D52-L52)<0,0,SUM(D52-L52)) -> 0 | P52: =L52+O52 -> 758870.17 | Q52: ='Schedule B'!X89 -> 758870.17 | R52: =P52-Q52 -> 0
A53: ='Schedule B'!C90 -> Prelims - Al Rai Modern Water Factory | B53: ='Schedule B'!E90 -> 0 | C53: ='Schedule B'!F90 -> 318320.5 | D53: =B53+C53 -> 318320.5 | E53: ='Schedule B'!H90 -> 318320.5 | F53: ='Schedule B'!I90+'Schedule B'!J90 -> 0 | G53: =E53+F53 -> 318320.5 | I53: ='Schedule B'!M90 -> 0 | J53: =SUM(G53:I53) -> 318320.5 | K53: ='Schedule B'!N90+'Schedule B'!O90 -> 0 | L53: =J53+K53 -> 318320.5 | M53: =IF(SUM(D53-J53)<0,0,SUM(D53-J53))*0 -> 0 | N53: =IF(SUM(D53-L53)<0,0,SUM(D53-L53)) -> 0 | P53: =L53+O53 -> 318320.5 | Q53: ='Schedule B'!X90 -> 318320.5 | R53: =P53-Q53 -> 0
A54: ='Schedule B'!C91 -> Prelims - NEXTWARE INTERNATIONAL SUPPLY | B54: ='Schedule B'!E91 -> 0 | C54: ='Schedule B'!F91 -> 1845 | D54: =B54+C54 -> 1845 | E54: ='Schedule B'!H91 -> 1845 | F54: ='Schedule B'!I91+'Schedule B'!J91 -> 0 | G54: =E54+F54 -> 1845 | I54: ='Schedule B'!M91 -> 0 | J54: =SUM(G54:I54) -> 1845 | K54: ='Schedule B'!N91+'Schedule B'!O91 -> 0 | L54: =J54+K54 -> 1845 | M54: =IF(SUM(D54-J54)<0,0,SUM(D54-J54))*0 -> 0 | N54: =IF(SUM(D54-L54)<0,0,SUM(D54-L54)) -> 0 | P54: =L54+O54 -> 1845 | Q54: ='Schedule B'!X91 -> 1845 | R54: =P54-Q54 -> 0
A55: ='Schedule B'!C92 -> Prelims - Virtual Projects DMCC | B55: ='Schedule B'!E92 -> 0 | C55: ='Schedule B'!F92 -> 51948.13 | D55: =B55+C55 -> 51948.13 | E55: ='Schedule B'!H92 -> 51948.13 | F55: ='Schedule B'!I92+'Schedule B'!J92 -> 0 | G55: =E55+F55 -> 51948.13 | I55: ='Schedule B'!M92 -> 0 | J55: =SUM(G55:I55) -> 51948.13 | K55: ='Schedule B'!N92+'Schedule B'!O92 -> 0 | L55: =J55+K55 -> 51948.13 | M55: =IF(SUM(D55-J55)<0,0,SUM(D55-J55))*0 -> 0 | N55: =IF(SUM(D55-L55)<0,0,SUM(D55-L55)) -> 0 | P55: =L55+O55 -> 51948.13 | Q55: ='Schedule B'!X92 -> 51948.13 | R55: =P55-Q55 -> 0
... A109: ='Schedule B'!C146 -> Tamimi (SAB Accommodation Payment) | B109: ='Schedule B'!E146 -> 0 | C109: ='Schedule B'!F146 -> 0 | D109: =B109+C109 -> 0 | E109: ='Schedule B'!H146 -> 0 | F109: ='Schedule B'!I146+'Schedule B'!J146 -> 0 | G109: =E109+F109 -> 0 | I109: ='Schedule B'!M146 -> 0 | J109: =SUM(G109:I109) -> 0 | K109: ='Schedule B'!N146+'Schedule B'!O146 -> 0 | L109: =J109+K109 -> 0 | M109: =IF(SUM(D109-J109)<0,0,SUM(D109-J109))*0 -> 0 | N109: =IF(SUM(D109-L109)<0,0,SUM(D109-L109)) -> 0 | P109: =L109+O109 -> 0 | Q109: ='Schedule B'!X146 -> 0 | R109: =P109-Q109 -> 0
A112: ='Schedule B'!C148 -> STO Façade Mock-up -(MWN) 2230075 | B112: ='Schedule B'!E148 -> 0 | C112: ='Schedule B'!F148 -> 834298.55 | D112: =B112+C112 -> 834298.55 | E112: ='Schedule B'!H148 -> 834298.55 | F112: ='Schedule B'!I148+'Schedule B'!J148 -> -15000 | G112: =E112+F112 -> 819298.55 | I112: ='Schedule B'!M148 -> 0 | J112: =SUM(G112:I112) -> 819298.55 | K112: ='Schedule B'!N148+'Schedule B'!O148 -> 0 | L112: =J112+K112 -> 819298.55 | M112: =IF(SUM(D112-J112)<0,0,SUM(D112-J112))*0 -> 0 | N112: =IF(SUM(D112-L112)<0,0,SUM(D112-L112))*0 -> 0 | P112: =L112+O112 -> 819298.55 | Q112: ='Schedule B'!X148 -> 819298.55 | R112: =P112-Q112 -> 0 | S112: Closed - Final account executed.
A113: ='Schedule B'!C149 -> Vertical Transportation (ESCCO) 2230178 | B113: ='Schedule B'!E149 -> 0 | C113: ='Schedule B'!F149 -> 2675473 | D113: =B113+C113 -> 2675473 | E113: ='Schedule B'!H149 -> 2675473 | F113: ='Schedule B'!I149+'Schedule B'!J149 -> 98073 | G113: =E113+F113 -> 2773546 | I113: ='Schedule B'!M149 -> 765046.05 | J113: =SUM(G113:I113) -> 3538592 | K113: ='Schedule B'!N149+'Schedule B'!O149 -> -215675 | L113: =J113+K113 -> 3322917 | M113: =IF(SUM(D113-J113)<0,0,SUM(D113-J113)) -> 0 | N113: =IF(SUM(D113-L113)<0,0,SUM(D113-L113)) -> 0 | P113: =L113+O113 -> 3322917 | Q113: ='Schedule B'!X149 -> 3322917 | R113: =P113-Q113 -> 0
A114: ='Schedule B'!C150 -> Kitchen & Laundry Works (Al Raqtan) 2230205 | B114: ='Schedule B'!E150 -> 0 | C114: ='Schedule B'!F150 -> 4695209 | D114: =B114+C114 -> 4695209 | E114: ='Schedule B'!H150 -> 4695209 | F114: ='Schedule B'!I150+'Schedule B'!J150 -> 10143 | G114: =E114+F114 -> 4705352 | I114: ='Schedule B'!M150 -> 0 | J114: =SUM(G114:I114) -> 4705352 | K114: ='Schedule B'!N150+'Schedule B'!O150 -> 1365246.5 | L114: =J114+K114 -> 6070598.5 | M114: =IF(SUM(D114-J114)<0,0,SUM(D114-J114)) -> 0 | N114: =IF(SUM(D114-L114)<0,0,SUM(D114-L114)) -> 0 | P114: =L114+O114 -> 6070598.5 | Q114: ='Schedule B'!X150 -> 6070598.4 | R114: =P114-Q114 -> 0 | U114: Total Commitment | V114: Balance Budget | W114: To Procure | X114: EW
A115: ='Schedule B'!C151 -> Fitout Works (DEPA) | B115: ='Schedule B'!E151 -> 0 | C115: ='Schedule B'!F151 -> 75969227 | D115: =B115+C115 -> 75969227 | E115: ='Schedule B'!H151 -> 75969227 | F115: ='Schedule B'!I151+'Schedule B'!J151 -> 4241355.2 | G115: =E115+F115 -> 80210582 | I115: ='Schedule B'!M151 -> -842054.38 | J115: =SUM(G115:I115) -> 79368528 | K115: ='Schedule B'!N151+'Schedule B'!O151 -> 12754372 | L115: =J115+K115 -> 92122900 | M115: =IF(SUM(D115-J115)<0,0,SUM(D115-J115)) -> 0 | N115: =IF(SUM(D115-L115)<0,0,SUM(D115-L115)) -> 0 | P115: =L115+O115 -> 92122900 | Q115: ='Schedule B'!X151 -> 90926439 | R115: =P115-Q115 -> 1196461.2
A116: ='Schedule B'!C152 -> Façade & Glazing Works (Alutec) | B116: ='Schedule B'!E152 -> 0 | C116: ='Schedule B'!F152 -> 29899671 | D116: =B116+C116 -> 29899671 | E116: ='Schedule B'!H152 -> 29899671 | F116: ='Schedule B'!I152+'Schedule B'!J152 -> 574831.03 | G116: =E116+F116 -> 30474502 | I116: ='Schedule B'!M152 -> -112821 | J116: =SUM(G116:I116) -> 30361681 | K116: ='Schedule B'!N152+'Schedule B'!O152 -> 491334 | L116: =J116+K116 -> 30853015 | M116: =IF(SUM(D116-J116)<0,0,SUM(D116-J116)) -> 0 | N116: =IF(SUM(D116-L116)<0,0,SUM(D116-L116)) -> 0 | P116: =L116+O116 -> 30853015 | Q116: ='Schedule B'!X152 -> 30853015 | R116: =P116-Q116 -> 0
A117: ='Schedule B'!C156 -> Hard and Soft Landscaping | B117: ='Schedule B'!E156 -> 0 | C117: ='Schedule B'!F156 -> 0 | D117: =B117+C117 -> 0 | E117: ='Schedule B'!H156 -> 0 | F117: ='Schedule B'!I156+'Schedule B'!J156 -> 0 | G117: =E117+F117 -> 0 | I117: ='Schedule B'!M156 -> 0 | J117: =SUM(G117:I117) -> 0 | K117: ='Schedule B'!N156+'Schedule B'!O156 -> 0 | L117: =J117+K117 -> 0 | M117: =IF(SUM(D117-J117)<0,0,SUM(D117-J117)) -> 0 | N117: =IF(SUM(D117-L117)<0,0,SUM(D117-L117)) -> 0 | P117: =L117+O117 -> 0 | Q117: ='Schedule B'!X156 -> 0 | R117: =P117-Q117 -> 0 | S117: Package Awarded under MVW - Budget transfer has not taken place - Request to Remove from EW | T117: =SUM(#REF!) -> #REF!
A118: ='Schedule B'!C153 -> MAS - Wet Works | B118: ='Schedule B'!E153 -> 0 | C118: ='Schedule B'!F153 -> 4004000 | D118: =B118+C118 -> 4004000 | E118: ='Schedule B'!H153 -> 4004000 | F118: ='Schedule B'!I153+'Schedule B'!J153 -> 18356118 | G118: =E118+F118 -> 22360118 | I118: ='Schedule B'!M153 -> 160876.21 | J118: =SUM(G118:I118) -> 22520994 | K118: ='Schedule B'!N153+'Schedule B'!O153 -> 0 | L118: =J118+K118 -> 22520994 | M118: =IF(SUM(D118-J118)<0,0,SUM(D118-J118)) -> 0 | N118: =IF(SUM(D118-L118)<0,0,SUM(D118-L118)) -> 0 | P118: =L118+O118 -> 22520994 | Q118: ='Schedule B'!X153 -> 22520994 | R118: =P118-Q118 -> 0
A119: ='Schedule B'!C154 -> MAS - Amphitheatre Works | B119: ='Schedule B'!E154 -> 0 | C119: ='Schedule B'!F154 -> 1078892.3 | D119: =B119+C119 -> 1078892.3 | E119: ='Schedule B'!H154 -> 1078892.3 | F119: ='Schedule B'!I154+'Schedule B'!J154 -> 205658.08 | G119: =E119+F119 -> 1284550.4 | I119: ='Schedule B'!M154 -> 0 | J119: =SUM(G119:I119) -> 1284550.4 | K119: ='Schedule B'!N154+'Schedule B'!O154 -> -9520 | L119: =J119+K119 -> 1275030.4 | M119: =IF(SUM(D119-J119)<0,0,SUM(D119-J119)) -> 0 | N119: =IF(SUM(D119-L119)<0,0,SUM(D119-L119)) -> 0 | P119: =L119+O119 -> 1275030.4 | Q119: ='Schedule B'!X154 -> 1275030.4 | R119: =P119-Q119 -> 0
A120: ='Schedule B'!C155 -> Al Fanar - MEP Labour Supply | B120: ='Schedule B'!E155 -> 0 | C120: ='Schedule B'!F155 -> 23125000 | D120: =B120+C120 -> 23125000 | E120: ='Schedule B'!H155 -> 23125000 | F120: ='Schedule B'!I155+'Schedule B'!J155 -> 71500593 | G120: =E120+F120 -> 94625593 | I120: ='Schedule B'!M155 -> 786453.46 | J120: =SUM(G120:I120) -> 95412047 | K120: ='Schedule B'!N155+'Schedule B'!O155 -> 128285 | L120: =J120+K120 -> 95540332 | M120: =IF(SUM(D120-J120)<0,0,SUM(D120-J120)) -> 0 | N120: =IF(SUM(D120-L120)<0,0,SUM(D120-L120)) -> 0 | P120: =L120+O120 -> 95540332 | Q120: ='Schedule B'!X155 -> 95540332 | R120: =P120-Q120 -> 0
A121: ='Schedule B'!C157 -> ARMETAL - Reflective ceiling | B121: ='Schedule B'!E157 -> 0 | C121: ='Schedule B'!F157 -> 7129950 | D121: =B121+C121 -> 7129950 | E121: ='Schedule B'!H157 -> 7129950 | F121: ='Schedule B'!I157+'Schedule B'!J157 -> 67078.55 | G121: =E121+F121 -> 7197028.5 | I121: ='Schedule B'!M157 -> 0 | J121: =SUM(G121:I121) -> 7197028.5 | K121: ='Schedule B'!N157+'Schedule B'!O157 -> 0 | L121: =J121+K121 -> 7197028.5 | M121: =IF(SUM(D121-J121)<0,0,SUM(D121-J121)) -> 0 | N121: =IF(SUM(D121-L121)<0,0,SUM(D121-L121)) -> 0 | P121: =L121+O121 -> 7197028.5 | Q121: ='Schedule B'!X157 -> 7197028.5 | R121: =P121-Q121 -> 0
A122: ='Schedule B'!C158 -> Al Rahji Takaful - Owner Controlled Insurance Program | B122: ='Schedule B'!E158 -> 0 | C122: ='Schedule B'!F158 -> 89047.06 | D122: =B122+C122 -> 89047.06 | E122: ='Schedule B'!H158 -> 89047.06 | F122: ='Schedule B'!I158+'Schedule B'!J158 -> 0 | G122: =E122+F122 -> 89047.06 | I122: ='Schedule B'!M158 -> 0 | J122: =SUM(G122:I122) -> 89047.06 | K122: ='Schedule B'!N158+'Schedule B'!O158 -> 0 | L122: =J122+K122 -> 89047.06 | M122: =IF(SUM(D122-J122)<0,0,SUM(D122-J122)) -> 0 | N122: =IF(SUM(D122-L122)<0,0,SUM(D122-L122)) -> 0 | P122: =L122+O122 -> 89047.06 | Q122: ='Schedule B'!X158 -> 89047.06 | R122: =P122-Q122 -> 0
A123: ='Schedule B'!C159 -> ABU DHABI PRECAST - GRC Cladding | B123: ='Schedule B'!E159 -> 0 | C123: ='Schedule B'!F159 -> 0 | D123: =B123+C123 -> 0 | E123: ='Schedule B'!H159 -> 0 | F123: ='Schedule B'!I159+'Schedule B'!J159 -> 0 | G123: =E123+F123 -> 0 | I123: ='Schedule B'!M159 -> 0 | J123: =SUM(G123:I123) -> 0 | K123: ='Schedule B'!N159+'Schedule B'!O159 -> 0 | L123: =J123+K123 -> 0 | M123: =IF(SUM(D123-J123)<0,0,SUM(D123-J123)) -> 0 | N123: =IF(SUM(D123-L123)<0,0,SUM(D123-L123)) -> 0 | P123: =L123+O123 -> 0 | Q123: ='Schedule B'!X159 -> 0 | R123: =P123-Q123 -> 0 | S123: GRC Cladding to Abu Dhabi Precast (Withdrawn)
A124: ='Schedule B'!C160 -> HASSAN ALLAM - External Scaffoldings | B124: ='Schedule B'!E160 -> 0 | C124: ='Schedule B'!F160 -> 3096124.9 | D124: =B124+C124 -> 3096124.9 | E124: ='Schedule B'!H160 -> 3096124.9 | F124: ='Schedule B'!I160 -> 0 | G124: =E124+F124 -> 3096124.9 | I124: ='Schedule B'!M160 -> 0 | J124: =SUM(G124:I124) -> 3096124.9 | K124: ='Schedule B'!N160+'Schedule B'!O160 -> 0 | L124: =J124+K124 -> 3096124.9 | M124: =IF(SUM(D124-J124)<0,0,SUM(D124-J124)) -> 0 | N124: =IF(SUM(D124-L124)<0,0,SUM(D124-L124)) -> 0 | P124: =L124+O124 -> 3096124.9 | Q124: ='Schedule B'!X160 -> 3096124.9 | R124: =P124-Q124 -> 0
A125: ='Schedule B'!C161 -> Enviro - Deep Cleaning | B125: ='Schedule B'!E161 -> 0 | C125: ='Schedule B'!F161 -> 799625.31 | D125: =B125+C125 -> 799625.31 | E125: ='Schedule B'!H161 -> 799625.31 | F125: ='Schedule B'!I161 -> 0 | G125: =E125+F125 -> 799625.31 | I125: ='Schedule B'!M161 -> 0 | J125: =SUM(G125:I125) -> 799625.31 | K125: ='Schedule B'!N161+'Schedule B'!O161 -> 0 | L125: =J125+K125 -> 799625.31 | M125: =IF(SUM(D125-J125)<0,0,SUM(D125-J125)) -> 0 | N125: =IF(SUM(D125-L125)<0,0,SUM(D125-L125)) -> 0 | P125: =L125+O125 -> 799625.31 | Q125: ='Schedule B'!X161 -> 799625.31 | R125: =P125-Q125 -> 0 | S125: New Contract Award
A126: ='Schedule B'!C162 -> KTH - MEP Works Package - 2240072 - KORTEK | B126: ='Schedule B'!E162 -> 0 | C126: ='Schedule B'!F162 -> 0 | D126: =B126+C126 -> 0 | E126: ='Schedule B'!H162 -> 0 | F126: ='Schedule B'!I162 -> 0 | G126: =E126+F126 -> 0 | I126: ='Schedule B'!M162 -> 583143.7 | J126: =SUM(G126:I126) -> 583143.7 | K126: ='Schedule B'!N162+'Schedule B'!O162 -> 367770 | L126: =J126+K126 -> 950913.7 | M126: =IF(SUM(D126-J126)<0,0,SUM(D126-J126)) -> 0 | N126: =IF(SUM(D126-L126)<0,0,SUM(D126-L126)) -> 0 | P126: =L126+O126 -> 950913.7 | Q126: ='Schedule B'!X162 -> 950913.7 | R126: =P126-Q126 -> 0 | S126: New Contract Award
A127: ='Schedule B'!C163 -> ALC - Alcatop Package - Fourseasons - Alcatop | B127: ='Schedule B'!E163 -> 0 | C127: ='Schedule B'!F163 -> 0 | D127: =B127+C127 -> 0 | E127: ='Schedule B'!H163 -> 0 | F127: ='Schedule B'!I163 -> 0 | G127: =E127+F127 -> 0 | I127: ='Schedule B'!M163 -> 0 | J127: =SUM(G127:I127) -> 0 | K127: ='Schedule B'!N163+'Schedule B'!O163 -> 150000 | L127: =J127+K127 -> 150000 | M127: =IF(SUM(D127-J127)<0,0,SUM(D127-J127)) -> 0 | N127: =IF(SUM(D127-L127)<0,0,SUM(D127-L127)) -> 0 | P127: =L127+O127 -> 150000 | Q127: ='Schedule B'!X163 -> 150000 | R127: =P127-Q127 -> 0 | S127: New Contract Award
A128: ='Schedule B'!C164 -> Al Futtaim Pioneer Elevators - Al Futtaim Pioneer | B128: ='Schedule B'!E164 -> 0 | C128: ='Schedule B'!F164 -> 691955 | D128: =B128+C128 -> 691955 | E128: ='Schedule B'!H164 -> 691955 | F128: ='Schedule B'!I164 -> 0 | G128: =E128+F128 -> 691955 | I128: ='Schedule B'!M164 -> 0 | J128: =SUM(G128:I128) -> 691955 | K128: ='Schedule B'!N164+'Schedule B'!O164 -> 0 | L128: =J128+K128 -> 691955 | M128: =IF(SUM(D128-J128)<0,0,SUM(D128-J128)) -> 0 | N128: =IF(SUM(D128-L128)<0,0,SUM(D128-L128)) -> 0 | P128: =L128+O128 -> 691955 | Q128: ='Schedule B'!X164 -> 691955 | R128: =P128-Q128 -> 0 | S128: New Contract Award
D129: =B129+C129 -> 0 | G129: =E129+F129 -> 0 | L129: =J129+K129 -> 0 | M129: =D129-J129 -> 0 | N129: =D129-L129 -> 0 | P129: =L129+O129 -> 0 | R129: =P129-Q129 -> 0 | T129: =SUM(#REF!) -> #REF!
A130: ='Schedule B'!C256 -> Remaining budget - Construction Works | B130: ='Schedule B'!E256 -> 2.2163323e+08 | C130: ='Schedule B'!F256 -> -1.9249642e+08 | D130: =B130+C130 -> 29136815 | E130: ='Schedule B'!H256 -> 29136815 | F130: ='Schedule B'!I256+'Schedule B'!J256 -> -7577587.8 | G130: =SUM(E130:F130) -> 21559228 | H130: ='Schedule B'!K256*0 -> 0 | I130: ='Schedule B'!M256 -> 18178392 | J130: =SUM(G130:I130) -> 39737619 | K130: =('Schedule B'!N256+'Schedule B'!O256) -> -36097262 | L130: =IF(SUM(J130:K130)<0,0,SUM(J130:K130))*0 -> 0 | M130: =IF(SUM(H130+I130)<0,0,SUM(H130+I130)) -> 18178392 | N130: =IF(SUM(J130+K130)<0,0,SUM(J130+K130)) -> 3640356.9 | P130: =L130+O130 -> 0 | Q130: ='Schedule B'!X256 -> 0 | R130: =P130-Q130 -> 0 | T130: =-K35 -> 1115864.7 | AC130: =SUM(G130-(J130+K130)) -> 17918871 | AE130: =235150316-217358910.58 -> 17791405
A131: FF&E | B131: =SUM(B132:B148) -> 24991549 | C131: =SUM(C132:C148) -> 15106817 | D131: =SUM(D132:D148) -> 40098366 | E131: =SUM(E132:E148) -> 40098366 | F131: =SUM(F132:F148) -> 851779 | G131: =SUM(G132:G148) -> 40950145 | H131: =SUM(H132:H148) -> 0 | I131: =SUM(I132:I148) -> 0 | ... R131: =SUM(R132:R148) -> 0 | W131: 1.2891014e+08
A132: ='Schedule B'!C204 -> FF&E and OSE Procurement Agent (Areen Design Ltd) | B132: ='Schedule B'!E204 -> 0 | C132: ='Schedule B'!F204 -> 1107465.9 | D132: =SUM(B132:C132) -> 1107465.9 | E132: ='Schedule B'!H204 -> 1107465.9 | F132: ='Schedule B'!I204+'Schedule B'!J204 -> 851779 | G132: =SUM(E132:F132) -> 1959244.9 | I132: ='Schedule B'!M204 -> 0 | J132: =SUM(G132:I132) -> 1959244.9 | K132: ='Schedule B'!N204+'Schedule B'!O204 -> 0 | L132: =SUM(J132:K132) -> 1959244.9 | M132: =IF(SUM(D132-J132)<0,0,SUM(D132-J132)) -> 0 | N132: =IF(SUM(D132-L132)<0,0,SUM(D132-L132)) -> 0 | P132: =L132+O132 -> 1959244.9 | Q132: ='Schedule B'!X204 -> 1959244.9 | R132: =P132-Q132 -> 0
A133: ='Schedule B'!C207 -> Loose FF&E Items (FOH) | B133: ='Schedule B'!E207 -> 0 | C133: ='Schedule B'!F207 -> 22998648 | D133: =B133+C133 -> 22998648 | E133: ='Schedule B'!H207 -> 22998648 | F133: ='Schedule B'!I207+'Schedule B'!J207 -> 0 | G133: =SUM(E133:F133) -> 22998648 | I133: ='Schedule B'!M207 -> 0 | J133: =SUM(G133:I133) -> 22998648 | K133: ='Schedule B'!N207+'Schedule B'!O207 -> 0 | L133: =J133+K133 -> 22998648 | M133: =IF(SUM(D133-J133)<0,0,SUM(D133-J133)) -> 0 | N133: =IF(SUM(D133-L133)<0,0,SUM(D133-L133)) -> 0 | P133: =L133+O133 -> 22998648 | Q133: ='Schedule B'!X207 -> 22998648 | R133: =P133-Q133 -> 0
A134: ='Schedule B'!C208 -> Loose FF&E Items (BOH) | B134: ='Schedule B'!E208 -> 0 | C134: ='Schedule B'!F208 -> 0 | D134: =B134+C134 -> 0 | E134: 0 | F134: ='Schedule B'!I208+'Schedule B'!J208 -> 0 | G134: =SUM(E134:F134) -> 0 | H134: ='Schedule B'!H208 -> 0 | I134: ='Schedule B'!M208 -> 0 | J134: =SUM(G134:I134) -> 0 | K134: ='Schedule B'!N208+'Schedule B'!O208 -> 0 | L134: =J134+K134 -> 0 | M134: =IF(SUM(D134-J134)<0,0,SUM(D134-J134)) -> 0 | N134: =IF(SUM(D134-L134)<0,0,SUM(D134-L134)) -> 0 | P134: =L134+O134 -> 0 | Q134: ='Schedule B'!X208 -> 0 | R134: =P134-Q134 -> 0
A135: ='Schedule B'!C209 -> OS&E Items | B135: ='Schedule B'!E209 -> 0 | C135: ='Schedule B'!F209 -> 14586000 | D135: =B135+C135 -> 14586000 | E135: ='Schedule B'!H209 -> 14586000 | F135: ='Schedule B'!I209+'Schedule B'!J209 -> 0 | G135: =SUM(E135:F135) -> 14586000 | I135: ='Schedule B'!M209 -> 0 | J135: =SUM(G135:I135) -> 14586000 | K135: ='Schedule B'!N209+'Schedule B'!O209 -> 429156 | L135: =J135+K135 -> 15015156 | M135: =IF(SUM(D135-J135)<0,0,SUM(D135-J135)) -> 0 | N135: =IF(SUM(D135-L135)<0,0,SUM(D135-L135)) -> 0 | P135: =L135+O135 -> 15015156 | Q135: ='Schedule B'!X209 -> 15015156 | R135: =P135-Q135 -> 0
A136: ='Schedule B'!C210 -> Art Works | B136: ='Schedule B'!E210 -> 0 | C136: ='Schedule B'!F210 -> 0 | D136: =B136+C136 -> 0 | E136: ='Schedule B'!H210 -> 0 | F136: ='Schedule B'!I210+'Schedule B'!J210 -> 0 | G136: =SUM(E136:F136) -> 0 | I136: ='Schedule B'!M210 -> 0 | J136: =SUM(G136:I136) -> 0 | K136: ='Schedule B'!N210+'Schedule B'!O210 -> 0 | L136: =J136+K136 -> 0 | M136: =IF(SUM(D136-J136)<0,0,SUM(D136-J136)) -> 0 | N136: =IF(SUM(D136-L136)<0,0,SUM(D136-L136)) -> 0 | P136: =L136+O136 -> 0 | Q136: ='Schedule B'!X210 -> 0 | R136: =P136-Q136 -> 0
A137: ='Schedule B'!C212 -> Extraordinary Cart | B137: ='Schedule B'!E212 -> 0 | C137: ='Schedule B'!F212 -> 397876 | D137: =B137+C137 -> 397876 | E137: ='Schedule B'!H212 -> 397876 | F137: ='Schedule B'!I212+'Schedule B'!J212 -> 0 | G137: =SUM(E137:F137) -> 397876 | I137: ='Schedule B'!M212 -> 0 | J137: =SUM(G137:I137) -> 397876 | K137: ='Schedule B'!N212+'Schedule B'!O212 -> 0 | L137: =J137+K137 -> 397876 | M137: =IF(SUM(D137-J137)<0,0,SUM(D137-J137)) -> 0 | N137: =IF(SUM(D137-L137)<0,0,SUM(D137-L137)) -> 0 | P137: =L137+O137 -> 397876 | Q137: ='Schedule B'!X212 -> 397876 | R137: =P137-Q137 -> 0
A138: ='Schedule B'!C213 -> Saudico Electronic Systems | B138: ='Schedule B'!E213 -> 0 | C138: ='Schedule B'!F213 -> 353487.06 | D138: =B138+C138 -> 353487.06 | E138: ='Schedule B'!H213 -> 353487.06 | F138: ='Schedule B'!I213+'Schedule B'!J213 -> 0 | G138: =SUM(E138:F138) -> 353487.06 | I138: ='Schedule B'!M213 -> 0 | J138: =SUM(G138:I138) -> 353487.06 | K138: ='Schedule B'!N213+'Schedule B'!O213 -> 0 | L138: =J138+K138 -> 353487.06 | M138: =IF(SUM(D138-J138)<0,0,SUM(D138-J138)) -> 0 | N138: =IF(SUM(D138-L138)<0,0,SUM(D138-L138)) -> 0 | P138: =L138+O138 -> 353487.06 | Q138: ='Schedule B'!X213 -> 353487.06 | R138: =P138-Q138 -> 0
A139: ='Schedule B'!C214 -> Birch Street | B139: ='Schedule B'!E214 -> 0 | C139: ='Schedule B'!F214 -> 115998.98 | D139: =B139+C139 -> 115998.98 | E139: ='Schedule B'!H214 -> 115998.98 | F139: ='Schedule B'!I214+'Schedule B'!J214 -> 0 | G139: =SUM(E139:F139) -> 115998.98 | I139: ='Schedule B'!M214 -> 0 | J139: =SUM(G139:I139) -> 115998.98 | K139: ='Schedule B'!N214+'Schedule B'!O214 -> 0 | L139: =J139+K139 -> 115998.98 | M139: =IF(SUM(D139-J139)<0,0,SUM(D139-J139)) -> 0 | N139: =IF(SUM(D139-L139)<0,0,SUM(D139-L139)) -> 0 | P139: =L139+O139 -> 115998.98 | Q139: ='Schedule B'!X214 -> 115998.98 | R139: =P139-Q139 -> 0
A140: ='Schedule B'!C215 -> AlFalak Electronic - HPE Servers | B140: ='Schedule B'!E215 -> 0 | C140: ='Schedule B'!F215 -> 16655 | D140: =B140+C140 -> 16655 | E140: ='Schedule B'!H215 -> 16655 | F140: ='Schedule B'!I215+'Schedule B'!J215 -> 0 | G140: =SUM(E140:F140) -> 16655 | I140: ='Schedule B'!M215 -> 0 | J140: =SUM(G140:I140) -> 16655 | K140: ='Schedule B'!N215+'Schedule B'!O215 -> 0 | L140: =J140+K140 -> 16655 | M140: =IF(SUM(D140-J140)<0,0,SUM(D140-J140)) -> 0 | N140: =IF(SUM(D140-L140)<0,0,SUM(D140-L140)) -> 0 | P140: =L140+O140 -> 16655 | Q140: ='Schedule B'!X215 -> 16655 | R140: =P140-Q140 -> 0
A141: ='Schedule B'!C216 -> Saudico Electronic Systems | B141: ='Schedule B'!E216 -> 0 | C141: ='Schedule B'!F216 -> 34719 | D141: =B141+C141 -> 34719 | E141: ='Schedule B'!H216 -> 34719 | F141: ='Schedule B'!I216+'Schedule B'!J216 -> 0 | G141: =SUM(E141:F141) -> 34719 | I141: ='Schedule B'!M216 -> 0 | J141: =SUM(G141:I141) -> 34719 | K141: ='Schedule B'!N216+'Schedule B'!O216 -> 0 | L141: =J141+K141 -> 34719 | M141: =IF(SUM(D141-J141)<0,0,SUM(D141-J141)) -> 0 | N141: =IF(SUM(D141-L141)<0,0,SUM(D141-L141)) -> 0 | P141: =L141+O141 -> 34719 | Q141: ='Schedule B'!X216 -> 34719 | R141: =P141-Q141 -> 0
A142: ='Schedule B'!C217 -> Sevenrooms Inc | B142: ='Schedule B'!E217 -> 0 | C142: ='Schedule B'!F217 -> 32751.56 | D142: =B142+C142 -> 32751.56 | E142: ='Schedule B'!H217 -> 32751.56 | F142: ='Schedule B'!I217+'Schedule B'!J217 -> 0 | G142: =SUM(E142:F142) -> 32751.56 | I142: ='Schedule B'!M217 -> 0 | J142: =SUM(G142:I142) -> 32751.56 | K142: ='Schedule B'!N217+'Schedule B'!O217 -> 0 | L142: =J142+K142 -> 32751.56 | M142: =IF(SUM(D142-J142)<0,0,SUM(D142-J142)) -> 0 | N142: =IF(SUM(D142-L142)<0,0,SUM(D142-L142)) -> 0 | P142: =L142+O142 -> 32751.56 | Q142: ='Schedule B'!X217 -> 32751.56 | R142: =P142-Q142 -> 0
A143: ='Schedule B'!C218 -> Infor Saudi Arabia Limited | B143: ='Schedule B'!E218 -> 0 | C143: ='Schedule B'!F218 -> 58307.19 | D143: =B143+C143 -> 58307.19 | E143: ='Schedule B'!H218 -> 58307.19 | F143: ='Schedule B'!I218+'Schedule B'!J218 -> 0 | G143: =SUM(E143:F143) -> 58307.19 | I143: ='Schedule B'!M218 -> 0 | J143: =SUM(G143:I143) -> 58307.19 | K143: ='Schedule B'!N218+'Schedule B'!O218 -> 0 | L143: =J143+K143 -> 58307.19 | M143: =IF(SUM(D143-J143)<0,0,SUM(D143-J143)) -> 0 | N143: =IF(SUM(D143-L143)<0,0,SUM(D143-L143)) -> 0 | P143: =L143+O143 -> 58307.19 | Q143: ='Schedule B'!X218 -> 58307.19 | R143: =P143-Q143 -> 0
A144: ='Schedule B'!C219 -> TRA - Zatca Integration with Reachware | B144: ='Schedule B'!E219 -> 0 | C144: ='Schedule B'!F219 -> 57135 | D144: =B144+C144 -> 57135 | E144: ='Schedule B'!H219 -> 57135 | F144: ='Schedule B'!I219+'Schedule B'!J219 -> 0 | G144: =SUM(E144:F144) -> 57135 | I144: ='Schedule B'!M219 -> 0 | J144: =SUM(G144:I144) -> 57135 | K144: ='Schedule B'!N219+'Schedule B'!O219 -> 0 | L144: =J144+K144 -> 57135 | M144: =IF(SUM(D144-J144)<0,0,SUM(D144-J144)) -> 0 | N144: =IF(SUM(D144-L144)<0,0,SUM(D144-L144)) -> 0 | P144: =L144+O144 -> 57135 | Q144: ='Schedule B'!X219 -> 57135 | R144: =P144-Q144 -> 0
A145: ='Schedule B'!C220 -> PeopleVine Implementation | B145: ='Schedule B'!E220 -> 0 | C145: ='Schedule B'!F220 -> 336187.5 | D145: =B145+C145 -> 336187.5 | E145: ='Schedule B'!H220 -> 336187.5 | F145: ='Schedule B'!I220+'Schedule B'!J220 -> 0 | G145: =SUM(E145:F145) -> 336187.5 | I145: ='Schedule B'!M220 -> 0 | J145: =SUM(G145:I145) -> 336187.5 | K145: ='Schedule B'!N220+'Schedule B'!O220 -> 0 | L145: =J145+K145 -> 336187.5 | M145: =IF(SUM(D145-J145)<0,0,SUM(D145-J145)) -> 0 | N145: =IF(SUM(D145-L145)<0,0,SUM(D145-L145)) -> 0 | P145: =L145+O145 -> 336187.5 | Q145: ='Schedule B'!X220 -> 336187.5 | R145: =P145-Q145 -> 0
D146: =B146+C146 -> 0 | L146: =J146+K146 -> 0 | P146: =L146+O146 -> 0
A147: ='Schedule B'!C261 -> Remaining budget - FF&E and OSE | B147: ='Schedule B'!E261 -> 24991549 | C147: ='Schedule B'!F261 -> -24988414 | D147: =B147+C147 -> 3135.11 | E147: ='Schedule B'!H261 -> 3135.11 | F147: ='Schedule B'!I261+'Schedule B'!J261 -> 0 | G147: =SUM(E147:F147) -> 3135.11 | H147: ='Schedule B'!K261*0 -> 0 | I147: ='Schedule B'!M261 -> 0 | J147: =SUM(G147:I147) -> 3135.11 | K147: =('Schedule B'!N261+'Schedule B'!O261) -> -429156 | L147: =IF(SUM(J147:K147)<0,0,SUM(J147:K147)) -> 0 | M147: =IF(SUM(H147+I147)<0,0,SUM(H147+I147)) -> 0 | N147: =IF(SUM(J147+K147)<0,0,SUM(J147+K147)) -> 0 | P147: =L147+O147 -> 0 | Q147: ='Schedule B'!X261 -> 0 | R147: =P147-Q147 -> 0
D148: =SUM(B148:C148) -> 0 | G148: =SUM(E148:F148) -> 0 | J148: =SUM(G148:I148) -> 0 | L148: =SUM(J148:K148) -> 0 | M148: =D148-J148 -> 0 | N148: =D148-L148 -> 0 | P148: =L148+O148 -> 0 | R148: =P148-Q148 -> 0
A149: Total Development Budget | B149: =B131+B35+B33+B27+B13 -> 3.1634649e+08 | C149: =C131+C35+C33+C27+C13 -> 2.6742635e+08 | D149: =D131+D35+D33+D27+D13 -> 5.8377284e+08 | E149: =E131+E35+E33+E27+E13 -> 5.8377284e+08 | F149: =F131+F35+F33+F27+F13 -> -442200 | G149: =G131+G35+G33+G27+G13 -> 5.8333064e+08 | H149: =H131+H35+H33+H27+H13 -> 0 | I149: =I131+I35+I33+I27+I13 -> -115841.92 | ... R149: =R131+R35+R33+R27+R13 -> -215885.19 | T149: =P35-D35 -> -10715139 | AC149: =+'Level 01'!I33 -> 0 | AD149: =+AC149+R149 -> -215885.19 | AE149: Check Zero | AF149: =+'Schedule B'!Y268 -> -215885.19 | AG149: =+AF149+AC149 -> -215885.19
A151: Early Warning / Budget Overrun | P151: =P149-D149 -> -4956648 | AC151: =-'Level 01'!H27 -> 3234573.3 | AD151: =+AC151+P151 -> -1722074.7 | AE151: Check Zero | AF151: =+'Schedule B'!S268 -> -3234573.3 | AG151: =+AF151+AC151 -> 0
P152: =+'Schedule B'!S268 -> -3234573.3 | R152: =+Q149-P149 -> 215885.19 | S152: =+'Schedule B'!Y268 -> -215885.19
G153: =+G149-E149 -> -442200 | L153: =+'Schedule B'!Q268-'Schedule B'!Q266 -> 5.8061298e+08 | P153: =+P152-P151 -> 1722074.7 | S153: =+S152-R149 -> 0 | AB153: Check:
G154: =+'Schedule B'!K268 -> 5.8384755e+08 | L154: =+L153-L149 -> 1796788.5 | P154: 347793.9 | R154: =+'Schedule B'!Y268 -> -215885.19
G155: =+G154-G149 -> 516913.83 | P155: 569838.42 | R155: =+R149-R154 -> 0
P156: =+P155+P154+P151 -> -4039015.7 | Q156: =+'Additional Budget Sum (19Dec)'!I26 -> 1.0125851e+08 | R156: =+Q156-P156 -> 1.0529752e+08
K157: =+K135+K115+K114+K41+K40+#REF!+K14 -> #REF! | P157: =+'Schedule B'!Q268 -> 5.8061298e+08
K158: =+#REF! -> #REF! | P158: =+P157-P149 -> 1796788.5
K159: =+K158-K157 -> #REF!

Sheet Level 01
A1: Triple Bay Portfolio Cost Report Executive Summary Programme 1 - Amaala Yacht Club
A2: =+'Data Input'!B8 -> OCTOBER 2026
A5: Program 1 - AMAALA Yacht Club | B5: Professional Services | C5: Management supervision | D5: Commercial Management | E5: Early Works Constructions | F5: Construction Works | G5: FF&E | H5: Total AMAALA Yacht Club
B6: SAR | C6: SAR | D6: SAR | E6: SAR | F6: SAR | G6: SAR | H6: SAR | I6: =+F27-F35 -> -7993697.6
A8: Development Budget | B8: =+'Level 02'!G19 -> 22056262 | C8: =+'Level 02'!G24 -> 13038930 | D8: =+'Level 02'!G27 -> 0 | E8: =+'Level 02'!G31 -> 3105783.5 | F8: =+'Level 02'!G125 -> 5.0548857e+08 | G8: ='Level 02'!G140 -> 40158003 | H8: =SUM(B8:G8) -> 5.8384755e+08 | I8: =+'Schedule B'!H268 -> 5.8384755e+08 | J8: =+I8-H8 -> 0 | K8: ZERO CHECK:
A10: Commitments
A11: Contract Awards | B11: ='Level 02'!H19 -> 20543895 | C11: ='Level 02'!H24 -> 13296114 | D11: ='Level 02'!H27 -> 0 | E11: ='Level 02'!H31 -> 3105783.5 | F11: ='Level 02'!H125 -> 4.7635176e+08 | G11: ='Level 02'!H140 -> 40154868 | H11: =SUM(B11:G11) -> 5.5345242e+08 | I11: ='Executive Summary'!E30 -> 5.5345242e+08 | J11: =+I11-H11 -> 0 | K11: ZERO CHECK:
A12: DVO's | B12: ='Level 02'!I19 -> 4664935.1 | C12: ='Level 02'!I24 -> 1071977 | D12: ='Level 02'!I27 -> 0 | E12: ='Level 02'!I31 -> -509.48 | F12: ='Level 02'!I125 -> 231953.84 | G12: ='Level 02'!I140 -> 851779 | H12: =SUM(B12:G12) -> 6820135.5 | I12: ='Schedule A'!G32 -> 6820135.5 | J12: =+I12-H12 -> 0 | K12: ZERO CHECK:
A13: PVO's | B13: =+'Level 02'!J19 -> 0 | C13: =+'Level 02'!J24 -> 0 | D13: =+'Level 02'!J27 -> 0 | E13: =+'Level 02'!J31 -> 0 | F13: =+'Level 02'!J125 -> 1993436.1 | G13: =+'Level 02'!J140 -> 0 | H13: =SUM(B13:G13) -> 1993436.1 | I13: ='Schedule A'!H32 -> 1993436.1 | J13: =+I13-H13 -> 0 | K13: ZERO CHECK:
A14: Less: Remaining - Budget Hold | B14: ='Schedule B'!Q245 -> 0 | C14: ='Schedule B'!Q250 -> 0 | D14: ='Schedule B'!Q251 -> 0 | E14: 0 | F14: ='Schedule B'!Q256 -> 0 | G14: ='Schedule B'!Q261 -> 0 | H14: =SUM(B14:G14) -> 0 | I14: ='Schedule A'!O34 -> 0 | J14: =+I14-H14 -> 0 | K14: ZERO CHECK:
A16: Potential Out-Turn Costs
A17: PVO's (uncommitted) | B17: ='Level 02'!M19 -> 101675.08 | C17: ='Level 02'!M24 -> -53507 | D17: ='Level 02'!M27 -> 0 | E17: ='Level 02'!M31 -> 0 | F17: ='Level 02'!M125 -> -18178392 | G17: ='Level 02'!M140 -> 0 | H17: =SUM(B17:G17) -> -18130224 | I17: ='Schedule A'!K32 -> -18130224 | J17: =+I17-H17 -> 0 | K17: ZERO CHECK:
A18: Early Warnings | B18: ='Level 02'!P19 -> 0 | C18: ='Level 02'!P24 -> 0 | D18: ='Level 02'!P27 -> 0 | E18: ='Level 02'!P31 -> -782972 | F18: ='Level 02'!P125 -> 33674621 | G18: =+'Level 02'!P140 -> 0 | H18: =SUM(B18:G18) -> 32891649 | I18: ='Schedule A'!M32 -> 32891649 | J18: =+I18-H18 -> 0 | K18: ZERO CHECK:
A20: Balance to Procure
A21: CTC - Site | B21: ='Level 02'!N19 -> 0 | C21: ='Level 02'!N24 -> -49207 | D21: ='Level 02'!N27 -> 0 | E21: ='Level 02'!N31 -> 0 | F21: ='Level 02'!N125 -> 3205613.5 | G21: =+'Level 02'!N140 -> 429156 | H21: =SUM(B21:G21) -> 3585562.5 | I21: ='Schedule A'!L32 -> 3585562.5 | J21: =+I21-H21 -> 0 | K21: ZERO CHECK:
A22: CTC - Procurement | B22: ='Level 02'!O19 -> 0 | C22: ='Level 02'!O24 -> 0 | D22: ='Level 02'!O27 -> 0 | E22: ='Level 02'!O31 -> 0 | F22: ='Level 02'!O125 -> 0 | G22: ='Level 02'!O140 -> 0 | H22: =SUM(B22:G22) -> 0
A23: Uncommitted Packages | B23: =+'Level 02'!L19 -> 0 | C23: =+'Level 02'!L24 -> 0 | D23: =+'Level 02'!L27 -> 0 | E23: =+'Level 02'!L31 -> 0 | F23: =+'Level 02'!L125 -> 0 | G23: =+'Level 02'!L140 -> 0 | H23: =SUM(B23:G23) -> 0
A25: Anticipated Final Account | B25: =SUM(B10:B24) -> 25310505 | C25: =SUM(C10:C24) -> 14265377 | D25: =SUM(D10:D24) -> 0 | E25: =SUM(E10:E24) -> 2322302 | F25: =SUM(F10:F24) -> 4.9727899e+08 | G25: =SUM(G10:G24) -> 41435803 | H25: =SUM(H10:H24) -> 5.8061298e+08 | I25: =+'Schedule B'!Q268-'Schedule B'!Q266 -> 5.8061298e+08 | J25: =+H25-I25 -> 0 | K25: ZERO: CHECK
A27: Variance to Budget | B27: =B25-B8 -> 3254243.7 | C27: =C25-C8 -> 1226447.4 | D27: =D25-D8 -> 0 | E27: =E25-E8 -> -783481.48 | F27: =F25-F8 -> -8209582.7 | G27: =G25-G8 -> 1277799.9 | H27: =H25-H8 -> -3234573.3 | I27: =+'Level 02'!R142 -> -3234573.3 | J27: =+I27-H27 -> 0 | K27: ZERO CHECK:
A33: Last Month Anticipated Final Account | B33: 25310505 | C33: 14265377 | D33: 0 | E33: 2322302 | F33: 4.9749487e+08 | G33: 41435803 | H33: 5.8082886e+08
A35: Variance to Last Month | B35: =B25-B33 -> 0 | C35: =C25-C33 -> 0 | D35: =D25-D33 -> 0 | E35: =E25-E33 -> 0 | F35: =F25-F33 -> -215885.19 | G35: =G25-G33 -> 0 | H35: =SUM(B35:G35) -> -215885.19
A37: Reasons for Variance - from last month | B37: Al Futtaim elevator contract awarded (SAR 691,955 against RFC SAR 850,000); Alutec external doors EW cancelled (SAR 780,000); Al Fanar manpower extension PVO 012 (SAR 842,550); KAA final account saving (SAR 49,207).

Sheet Early Warnings
A2: ='Data Input'!A1&" - "&'Data Input'!B1 -> PROGRAMME: - MARINA VILLAGE (PROGRAMME 1_TRIPLE BAY)
A3: ='Data Input'!A2&" - "&'Data Input'!B2 -> PROGRAMME CODE: - 1TB01003
A4: ='Data Input'!A3&" - "&'Data Input'!B3 -> ASSET NAME: - AMAALA YACHT CLUB
A5: ='Data Input'!A6&" - "&'Data Input'!B6 -> Location: - AL WAJH SAUDI ARABIA
A6: ='Data Input'!A7&" - "&'Data Input'!B7 -> REPORT NO: - MONTHLY REPORT NO. 49
A8: Item No. | B8: Package | C8: Early Warning Description | D8: Impact | E8: Change Status | F8: Remarks
B9: PROFESSIONAL SERVICES | D9: 0
B11: MANAGEMENT SUPERVISION | D11: 0
B13: COMMERCIAL MANAGEMENT | D13: 0
B15: CONSTRUCTION WORKS | D15: =D21+D59+D64+D70+D82+D88+D95+D100 -> 32891649
B17: SOI TB Ground Improvement Works (SIC)
A18: ='Schedule C'!O166 -> EW 058 | B18: ='Schedule C'!M166 -> SOI TB Ground Improvement Works | C18: ='Schedule C'!B166 -> SIC Contract (Works not Done) | D18: ='Schedule C'!Q166 -> -500000 | E18: Awaiting confirmation from Programme 2 Commercial. | F18: ='Schedule C'!BD166 -> This will be incorporated in the SIC Final Account. Awaiting confirmation from Prog 2 Commercial.
A19: ='Schedule C'!O167 -> EW 059 | B19: ='Schedule C'!M167 -> SOI TB Ground Improvement Works (PS) | C19: ='Schedule C'!B167 -> SIC Contract (PS - Not done) | D19: ='Schedule C'!Q167 -> -282972 | E19: Awaiting confirmation from Programme 2 Commercial. | F19: ='Schedule C'!BD167 -> This will be incorporated in the SIC Final Account. Awaiting confirmation from Prog 2 Commercial.
A21: SUB-TOTAL | D21: =SUM(D18:D19) -> -782972
B23: SAB - Civil and Arch Works, MEPD & ICT/ELV (Baytur)
A24: ='Schedule C'!O67 -> EW 15 | B24: ='Schedule C'!M67 -> SAB - Civil and Arch Works, MEPD & ICT/ELV | C24: ='Schedule C'!B67 -> Omission of Surveying Equipment from SAB Contract | D24: ='Schedule C'!Q67 -> -7890 | E24: Early Warning | F24: ='Schedule C'!BD67 -> This will be dealt with in the final account reconciliation with SAB; therefore, there is no need to process a PVO/VO.
A25: ='Schedule C'!O69 -> EW 17 | B25: ='Schedule C'!M69 -> SAB - Civil and Arch Works, MEPD & ICT/ELV | C25: ='Schedule C'!B69 -> Omission of food and welfare provision to AMAALA Staff from SAB Contract. | D25: ='Schedule C'!Q69 -> -90000 | E25: Early Warning | F25: ='Schedule C'!BD69 -> This will be dealt with in the final account reconciliation with SAB; therefore, there is no need to process a PVO/VO.
A26: ='Schedule C'!O70 -> EW 17 | B26: ='Schedule C'!M70 -> SAB - Civil and Arch Works, MEPD & ICT/ELV | C26: ='Schedule C'!B70 -> Cost saving to Site Office Monthly Running Cost due to late installation of the Office Establishment by SAB. | D26: ='Schedule C'!Q70 -> -200000 | E26: Early Warning | F26: ='Schedule C'!BD70 -> This will be dealt with in the final account reconciliation with SAB; therefore, there is no need to process a PVO/VO.
A27: ='Schedule C'!O135 -> EW 029 | B27: ='Schedule C'!M135 -> SAB - Civil and Arch Works, MEPD & ICT/ELV | C27: ='Schedule C'!B135 -> Cancellation of Amphitheatre Works issued to MAS - Process not followed | D27: ='Schedule C'!Q135 -> -1108000 | E27: RFA appoved | F27: ='Schedule C'!BD135 -> This will be dealt with in the final account reconciliation with SAB; therefore, there is no need to process a PVO/VO.
A28: ='Schedule C'!O137 -> EW 031 | B28: ='Schedule C'!M137 -> SAB - Civil and Arch Works, MEPD & ICT/ELV | C28: ='Schedule C'!B137 -> Recovery of Remaining Block work, Plaster work and Paint Work to be carried out by MAS - Process not followed | D28: ='Schedule C'!Q137 -> -4004000 | E28: RFA appoved | F28: ='Schedule C'!BD137 -> This EI was drafted and issued by delivery on the 15th September 2024, Processes were not followed. No need for PVO/VO. This will be dealt with in the Final Account.
A29: ='Schedule C'!O141 -> EW 034 | B29: ='Schedule C'!M141 -> SAB - Civil and Arch Works, MEPD & ICT/ELV | C29: ='Schedule C'!B141 -> Deployment of Seven (7) Surveyors | D29: ='Schedule C'!Q141 -> 201600 | E29: EI issued | F29: ='Schedule C'!BD141 -> SAB has not been notified of submitting a variation cost for this. This will be dealt with in the final account reconciliation with SAB; therefore, there is no need to process a PVO/VO.
A30: ='Schedule C'!O144 -> EW 037 | B30: ='Schedule C'!M144 -> SAB - Civil and Arch Works, MEPD & ICT/ELV | C30: ='Schedule C'!B144 -> Scaffolding works for Secondary Steel and Façade (Design) | D30: ='Schedule C'!Q144 -> 75000 | E30: EI issued | F30: ='Schedule C'!BD144 -> SAB has not been notified of submitting a variation cost for this. This will be dealt with in the final account reconciliation with SAB; therefore, there is no need to process a PVO/VO.
A31: ='Schedule C'!O150 -> EW 043 | B31: ='Schedule C'!M150 -> SAB - Civil and Arch Works, MEPD & ICT/ELV | C31: ='Schedule C'!B150 -> Column Dry Wall Cladding and Partitions (Blockworks Omission) | D31: ='Schedule C'!Q150 -> -9180 | E31: Early Warning | F31: ='Schedule C'!BD150 -> This will be dealt with in the final account reconciliation with SAB; therefore, there is no need to process a PVO/VO.
A32: ='Schedule C'!O152 -> EW 045 | B32: ='Schedule C'!M152 -> SAB - Civil and Arch Works, MEPD & ICT/ELV | C32: ='Schedule C'!B152 -> Replace the existing FOH electrical faceplates in designated areas of the Project with upgraded units meeting specifications. (Omission from SAB) | D32: ='Schedule C'!Q152 -> -68541 | E32: Early Warning | F32: ='Schedule C'!BD152 -> This will be dealt with in the final account reconciliation with SAB; therefore, there is no need to process a PVO/VO.
A33: ='Schedule C'!O154 -> EW 047 | B33: ='Schedule C'!M154 -> SAB - Civil and Arch Works, MEPD & ICT/ELV | C33: ='Schedule C'!B154 -> LPG Works (Omission from SAB) | D33: ='Schedule C'!Q154 -> -582220 | E33: Early Warning | F33: ='Schedule C'!BD154 -> This will be dealt with in the final account reconciliation with SAB; therefore, there is no need to process a PVO/VO.
A34: ='Schedule C'!O157 -> EW 050 | B34: ='Schedule C'!M157 -> SAB - Civil and Arch Works, MEPD & ICT/ELV | C34: ='Schedule C'!B157 -> Allowance for SAB (Grankraft) works on mockup (same as advance payment amount) | D34: ='Schedule C'!Q157 -> 852173.91 | E34: Early Warning | F34: ='Schedule C'!BD157 -> Included in the approved RFA for Cost to Complete (Grankraft). This amount is being used to make direct payments to SAB's suppliers and subcontractors. This will be dealt with in the final account reconciliation with SAB; therefore, there is no need to process a PVO/VO.
A35: ='Schedule C'!O158 -> EW 051 | B35: ='Schedule C'!M158 -> SAB - Civil and Arch Works, MEPD & ICT/ELV | C35: ='Schedule C'!B158 -> Additional Costs related to Aluminium Soffits & Cladding - Alcatop | D35: ='Schedule C'!Q158 -> 1026091 | E35: Early Warning | F35: ='Schedule C'!BD158 -> Included in the approved RFA for Cost to Complete (Alcatop). This amount is being used to make direct payments to SAB's suppliers and subcontractors. This will be dealt with in the final account reconciliation with SAB; therefore, there is no need to process a PVO/VO.
A36: ='Schedule C'!O159 -> EW 052 | B36: ='Schedule C'!M159 -> SAB - Civil and Arch Works, MEPD & ICT/ELV | C36: ='Schedule C'!B159 -> Additional Costs related to Abu Dhabi Precast - GRC Cladding | D36: ='Schedule C'!Q159 -> 3761897 | E36: Early Warning | F36: ='Schedule C'!BD159 -> Included in the approved RFA for Cost to Complete (Abu Dhabi Precast). This amount is being used to make direct payments to SAB's suppliers and subcontractors. This will be dealt with in the final account reconciliation with SAB; therefore, there is no need to process a PVO/VO.
A37: ='Schedule C'!O160 -> EW 053 | B37: ='Schedule C'!M160 -> SAB - Civil and Arch Works, MEPD & ICT/ELV | C37: ='Schedule C'!B160 -> Additional Costs related to Structural Metal Work - SAMIF | D37: ='Schedule C'!Q160 -> 4647142 | E37: Early Warning | F37: ='Schedule C'!BD160 -> Included in the approved RFA for Cost to Complete (SAMIF). This amount is being used to make direct payments to SAB's suppliers and subcontractors. This will be dealt with in the final account reconciliation with SAB; therefore, there is no need to process a PVO/VO.
A38: ='Schedule C'!O163 -> EW 055 | B38: ='Schedule C'!M163 -> SAB - Civil and Arch Works, MEPD & ICT/ELV | C38: ='Schedule C'!B163 -> Dismantling and Reinstatement of Cold Rooms (Chiller 1, Chiller 2, and Chiller 3) including coordination - Backcharge | D38: ='Schedule C'!Q163 -> -22250 | E38: Early Warning | F38: ='Schedule C'!BD163 -> This will be dealt with in the final account reconciliation with SAB; therefore, there is no need to process a PVO/VO.
A39: ='Schedule C'!O170 -> EW 062 | B39: ='Schedule C'!M170 -> SAB - Civil and Arch Works, MEPD & ICT/ELV | C39: ='Schedule C'!B170 -> Omission of Limestone from SAB | D39: ='Schedule C'!Q170 -> -133949.24 | E39: RFA appoved | F39: ='Schedule C'!BD170 -> Included in the approved RFA for SAB Cost to Complete (Limestone). This will be dealt with in the final account reconciliation with SAB; therefore, there is no need to process a PVO/VO.
A40: ='Schedule C'!O171 -> EW 063 | B40: ='Schedule C'!M171 -> SAB - Civil and Arch Works, MEPD & ICT/ELV | C40: ='Schedule C'!B171 -> Cost to Complete (SAB Amount) - Including Contingencies | D40: ='Schedule C'!Q171 -> 53011625 | E40: RFA appoved | F40: ='Schedule C'!BD171 -> Included in the approved RFA for SAB Cost to Complete (SAB Cost). This amount is being used to make direct payments to SAB's suppliers and subcontractors. This will be dealt with in the final account reconciliation with SAB; therefore, there is no need to process a PVO/VO.
A41: ='Schedule C'!O174 -> EW 065 | B41: ='Schedule C'!M174 -> SAB - Civil and Arch Works, MEPD & ICT/ELV | C41: ='Schedule C'!B174 -> Back-of-House Finishes (EI 006)_SAB | D41: ='Schedule C'!Q174 -> -701856.29 | E41: EI issued | F41: ='Schedule C'!BD174 -> This will be dealt with in the final account reconciliation with SAB; therefore, there is no need to process a PVO/VO.
A42: ='Schedule C'!O188 -> EW 077 | B42: ='Schedule C'!M188 -> SAB - Civil and Arch Works, MEPD & ICT/ELV | C42: ='Schedule C'!B188 -> Omission of Interior Designer Selected Light Fittings (included in the FF&E) | D42: ='Schedule C'!Q188 -> -1173602.4 | E42: Early Warning | F42: ='Schedule C'!BD188 -> This will be dealt with in the final account reconciliation with SAB; therefore, there is no need to process a PVO/VO.
A43: ='Schedule C'!O189 -> EW 078 | B43: ='Schedule C'!M189 -> SAB - Civil and Arch Works, MEPD & ICT/ELV | C43: ='Schedule C'!B189 -> Omission of Swimming Pool Lights (supplied by Al Fanar) | D43: ='Schedule C'!Q189 -> -581464.2 | E43: Early Warning | F43: ='Schedule C'!BD189 -> This will be dealt with in the final account reconciliation with SAB; therefore, there is no need to process a PVO/VO.
A44: ='Schedule C'!O208 -> EW 095 | B44: ='Schedule C'!M208 -> SAB - Civil and Arch Works, MEPD & ICT/ELV | C44: ='Schedule C'!B208 -> Omission of Accommodation Budget from SAB (Payment for Tamimi) - to be deducted from SAB Contract Adjustment EW 063. | D44: ='Schedule C'!Q208 -> -10718725 | E44: Early Warning | F44: ='Schedule C'!BD208 -> This will be dealt with in the final account reconciliation with SAB; therefore, there is no need to process a PVO/VO.
A45: ='Schedule C'!O209 -> EW 096 | B45: ='Schedule C'!M209 -> SAB - Civil and Arch Works, MEPD & ICT/ELV | C45: ='Schedule C'!B209 -> Overrun on SAB's Accommodation Budget (Payment for Tamimi) - to be deducted from SAB Contract Adjustment EW 063. | D45: ='Schedule C'!Q209 -> -9279215.8 | E45: Early Warning | F45: ='Schedule C'!BD209 -> This will be dealt with in the final account reconciliation with SAB; therefore, there is no need to process a PVO/VO.
A46: ='Schedule C'!O212 -> EW 100 | B46: ='Schedule C'!M212 -> SAB - Civil and Arch Works, MEPD & ICT/ELV | C46: ='Schedule C'!B212 -> Direct Payments to SAB's Subcontractors and Suppliers (August 2025). | D46: ='Schedule C'!Q212 -> -5277917.8 | E46: Payment Release | F46: ='Schedule C'!BD212 -> 0
A47: ='Schedule C'!O213 -> EW 101 | B47: ='Schedule C'!M213 -> SAB - Civil and Arch Works, MEPD & ICT/ELV | C47: ='Schedule C'!B213 -> Direct Payments to SAB's Subcontractors and Suppliers (September 2025). | D47: ='Schedule C'!Q213 -> -3192741.9 | E47: Payment Release | F47: ='Schedule C'!BD213 -> 0
A48: ='Schedule C'!O214 -> EW 102 | B48: ='Schedule C'!M214 -> SAB - Civil and Arch Works, MEPD & ICT/ELV | C48: ='Schedule C'!B214 -> Direct Payments to SAB's Subcontractors and Suppliers (October 2025). | D48: ='Schedule C'!Q214 -> -3189139.9 | E48: Payment Release | F48: ='Schedule C'!BD214 -> Direct Payment
A49: ='Schedule C'!O215 -> EW 103 | B49: ='Schedule C'!M215 -> SAB - Civil and Arch Works, MEPD & ICT/ELV | C49: ='Schedule C'!B215 -> Direct Payments to SAB's Subcontractors and Suppliers (Nov and Dec 2025). | D49: ='Schedule C'!Q215 -> -4203149.6 | F49: ='Schedule C'!BD215 -> 0
A50: ='Schedule C'!O225 -> EW 112 | B50: ='Schedule C'!M225 -> SAB - Civil and Arch Works, MEPD & ICT/ELV | C50: ='Schedule C'!B225 -> Balance Works for ICT System (NESMA) | D50: ='Schedule C'!Q225 -> 2674938 | E50: EI issued | F50: ='Schedule C'!BD225 -> This will be part of the direct payments negative PVO. Therefore, there is no need to process a separate PVO/VO for this item.
A51: ='Schedule C'!O227 -> EW 114 | B51: ='Schedule C'!M227 -> SAB - Civil and Arch Works, MEPD & ICT/ELV | C51: ='Schedule C'!B227 -> Omission of Internal Windows (Kitchen Service Hatches) from SAB - Supply and install by RAQTAN | D51: ='Schedule C'!Q227 -> -8078.16 | E51: RFA appoved | F51: ='Schedule C'!BD227 -> This will be dealt with in the final account reconciliation with SAB; therefore, there is no need to process a PVO/VO.
A52: ='Schedule C'!O236 -> EW 123 | B52: ='Schedule C'!M236 -> SAB - Civil and Arch Works, MEPD & ICT/ELV | C52: ='Schedule C'!B236 -> EI-18 : Amendment of Secondary Steel Structure vs Honeycomb Limestone Cladding | D52: ='Schedule C'!Q236 -> 54000 | E52: Early Warning | F52: ='Schedule C'!BD236 -> PVO to prepare
A53: ='Schedule C'!O254 -> EW 137 | B53: ='Schedule C'!M254 -> SAB - Civil and Arch Works, MEPD & ICT/ELV | C53: ='Schedule C'!B254 -> Employer's Instruction No. 020 – Replacement of the Aluminium Ceiling Panels | D53: ='Schedule C'!Q254 -> 282122.46 | E53: EI issued | F53: ='Schedule C'!BD254 -> PVO to prepare
A54: ='Schedule C'!O257 -> EW 139 | B54: ='Schedule C'!M257 -> SAB - Civil and Arch Works, MEPD & ICT/ELV | C54: ='Schedule C'!B257 -> Backcharge Notification: Marvel System for Ecology Unit provided by Raqtan on behalf of SAB | D54: ='Schedule C'!Q257 -> -233351.85 | E54: EI issued | F54: ='Schedule C'!BD257 -> PVO to prepare
A55: ='Schedule C'!O259 -> EW 141 | B55: ='Schedule C'!M259 -> SAB - Civil and Arch Works, MEPD & ICT/ELV | C55: ='Schedule C'!B259 -> Employer’s Instruction No. 025 – Aluminum Cladding Panel Replacement at Various Locations (Discrepancy between the model and actual site conditions (construction tolerances).) | D55: ='Schedule C'!Q259 -> 269447.1 | E55: BC issued | F55: ='Schedule C'!BD259 -> PVO to prepare
A56: ='Schedule C'!O276 -> EW 151 | B56: ='Schedule C'!M276 -> SAB - Civil and Arch Works, MEPD & ICT/ELV | C56: ='Schedule C'!B276 -> EVO No. 005 - Supply of Alutec Manpower to Install the External Glass Balustrade on Behalf of Alcatop (BC to Alcatop) | D56: ='Schedule C'!Q276 -> -332640 | E56: EI issued | F56: ='Schedule C'!BD276 -> 0
A57: ='Schedule C'!O281 -> EW 156 | B57: ='Schedule C'!M281 -> SAB - Civil and Arch Works, MEPD & ICT/ELV | C57: ='Schedule C'!B281 -> EVO 29 Rectification of damaged waterproofing at Water Features | D57: ='Schedule C'!Q281 -> 60000 | F57: ='Schedule C'!BD281 -> PVO to prepare
A59: SUB-TOTAL | D59: =SUM(D24:D57) -> 21798123
B61: ESCCO - Vertical Transport
A62: ='Schedule C'!O191 -> EW 080 | B62: ='Schedule C'!M191 -> ESCCO - Vertical Transport | C62: ='Schedule C'!B191 -> Clause 11.11 (Backcharging by Employer) - Supply of Electricians by Al Fanar for ESCCO’s Vertical Transportation Installations | D62: ='Schedule C'!Q191 -> -15675 | E62: BC issued | F62: ='Schedule C'!BD191 -> This will be dealt with in the final account reconciliation with RAQTAN; therefore, there is no need to process a PVO/VO.
A64: SUB-TOTAL | D64: =SUM(D62:D62) -> -15675
B66: Special Kitchen (Al Raqtan)
A67: ='Schedule C'!O162 -> EW 054 | B67: ='Schedule C'!M162 -> Special Kitchen | C67: ='Schedule C'!B162 -> Dismantling and Reinstatement of Cold Rooms (Chiller 1, Chiller 2, and Chiller 3) including coordination | D67: ='Schedule C'!Q162 -> 22250 | E67: Early Warning | F67: ='Schedule C'!BD162 -> Works completed. RAQTAN has not been notified of submitting a variation cost for this. This will be dealt with in the final account reconciliation with RAQTAN; therefore, there is no need to process a PVO/VO.
A68: ='Schedule C'!O258 -> EW 140 | B68: ='Schedule C'!M258 -> Special Kitchen | C68: ='Schedule C'!B258 -> Marvel System for Ecology Unit provided by Raqtan on behalf of SAB | D68: ='Schedule C'!Q258 -> 233351.85 | E68: Completed at Site | F68: ='Schedule C'!BD258 -> PVO to prepare
A70: SUB-TOTAL | D70: =SUM(D67:D68) -> 255601.85
B72: DEPA Interior Fitout
A73: ='Schedule C'!O138 -> EW 032 | B73: ='Schedule C'!M138 -> DEPA Interior Fitout | C73: ='Schedule C'!B138 -> Alteration to finishes due to Façade Layout Changes - Process not Followed | D73: ='Schedule C'!Q138 -> 69000 | E73: Ei Issued | F73: ='Schedule C'!BD138 -> Works completed. DEPA has not been notified of submitting a variation cost for this. This will be dealt with in the final account reconciliation with DEPA; therefore, there is no need to process a PVO/VO.
A74: ='Schedule C'!O168 -> EW 060 | B74: ='Schedule C'!M168 -> DEPA Interior Fitout | C74: ='Schedule C'!B168 -> DEPA EOT 01 Prolongation Cost (Estimated) | D74: ='Schedule C'!Q168 -> 8100000 | E74: Time assessment issued. Awaiting DEPA's submission of prolongation cost. | F74: ='Schedule C'!BD168 -> DEPA to submit the actual cost upon agreement of the time imact for EOT 001.
A75: ='Schedule C'!O228 -> EW 115 | B75: ='Schedule C'!M228 -> DEPA Interior Fitout | C75: ='Schedule C'!B228 -> EI-17: Road Markings Paint Application | D75: ='Schedule C'!Q228 -> 8000 | E75: EI issued | F75: ='Schedule C'!BD228 -> 0
A76: ='Schedule C'!O234 -> EW 121 | B76: ='Schedule C'!M234 -> DEPA Interior Fitout | C76: ='Schedule C'!B234 -> EI-20: Rectification of the Damaged Ceilings Based on the Various Damage Reports | D76: ='Schedule C'!Q234 -> 100000 | E76: EI issued | F76: ='Schedule C'!BD234 -> 0
A77: ='Schedule C'!O240 -> EW 127 | B77: ='Schedule C'!M240 -> DEPA Interior Fitout | C77: ='Schedule C'!B240 -> Adjustment for DEPA PVO 008, PVO 015 and PVO 013 (expected DVOs to be agreed) | D77: ='Schedule C'!Q240 -> 1936178.3 | E77: Anticipated adjustment for DVOs value to be agreed. | F77: ='Schedule C'!BD240 -> 0
A78: ='Schedule C'!O242 -> EW 128 | B78: ='Schedule C'!M242 -> DEPA Interior Fitout | C78: ='Schedule C'!B242 -> Allow for rectification of damaged ceiling and other finishes. | D78: ='Schedule C'!Q242 -> 900000 | E78: PVO to prepare upon receipt of Final Cost | F78: ='Schedule C'!BD242 -> PVO to prepare
A79: ='Schedule C'!O266 -> EW 144 | B79: ='Schedule C'!M266 -> DEPA Interior Fitout | C79: ='Schedule C'!B266 -> Employer’s Instruction No. 030 – Changes in the Aluminum Panels Design (Accommodation of Actual Site Conditions: Adjustments are required to align with on-site realities resulting from changes within adjacent or interfacing work packages. • Aesthetic Enhancements: Revisions have been introduced to improve the visual outcome of the façade elements.) | D79: ='Schedule C'!Q266 -> 131987.45 | E79: EI issued | F79: ='Schedule C'!BD266 -> PVO to prepare. This is SAB
A80: ='Schedule C'!O282 -> EW 157 | B80: ='Schedule C'!M282 -> DEPA Interior Fitout | C80: ='Schedule C'!B282 -> EVO 29 Rectification of damaged waterproofing at Water Features (BC) | D80: ='Schedule C'!Q282 -> -60000 | E80: BC issued | F80: ='Schedule C'!BD282 -> PVO to prepare
A82: SUB-TOTAL | D82: =SUM(D73:D80) -> 11185166
B84: Façade & Glazing Works (Alutec)
A85: ='Schedule C'!O239 -> EW 126 | B85: ='Schedule C'!M239 -> Façade & Glazing Works | C85: ='Schedule C'!B239 -> Replacement of External Doors - requested by the Operator (Cluster Manager - Back of House) | D85: ='Schedule C'!Q239 -> 0 | E85: RFC to prepare | F85: ='Schedule C'!BD239 -> No action has been taken in 5 months, hence cancelled
A86: ='Schedule C'!O275 -> EW 150 | B86: ='Schedule C'!M275 -> Façade & Glazing Works | C86: ='Schedule C'!B275 -> EVO No. 005 - Supply of Alutec Manpower to Install the External Glass Balustrade on Behalf of Alcatop | D86: ='Schedule C'!Q275 -> 332640 | E86: EVO issued | F86: ='Schedule C'!BD275 -> Emergency Variation order was issued on the 18th Feb 2026. PVO, DVO to be processed
A88: SUB-TOTAL | D88: =SUM(D85:D86) -> 332640
B90: Al Fanar - MEP Labour Supply
A91: ='Schedule C'!O184 -> EW 073 | B91: ='Schedule C'!M184 -> Al Fanar - MEP Labour Supply | C91: ='Schedule C'!B184 -> Employer’s Instruction for Variation – Panic Alarm System for ADA toilets | D91: ='Schedule C'!Q184 -> 87285 | E91: EI issued | F91: ='Schedule C'!BD184 -> This will be included in the material supply DVO with Al Fanar; therefore, there is no need to process a PVO/VO.
A92: ='Schedule C'!O202 -> EW 089 | B92: ='Schedule C'!M202 -> Al Fanar - MEP Labour Supply | C92: ='Schedule C'!B202 -> Powder coating of wiring accessories (to suit ID requirements) | D92: ='Schedule C'!Q202 -> 20000 | E92: EI issued | F92: ='Schedule C'!BD202 -> This will be included in the material supply DVO with Al Fanar; therefore, there is no need to process a PVO/VO.
A93: ='Schedule C'!O217 -> EW 105 | B93: ='Schedule C'!M217 -> Al Fanar - MEP Labour Supply | C93: ='Schedule C'!B217 -> EI 05: Powder coating of ID light fittings (to suit ID requirements) | D93: ='Schedule C'!Q217 -> 21000 | E93: EI issued | F93: ='Schedule C'!BD217 -> This will be included in the material supply DVO with Al Fanar; therefore, there is no need to process a PVO/VO.
A95: SUB-TOTAL | D95: =SUM(D91:D93) -> 128285
B97: MAS - Amphitheatre & Labour Supply Works
A98: ='Schedule C'!O333 -> EW 01 - MAS | B98: ='Schedule C'!M333 -> MAS - Amphitheatre | C98: ='Schedule C'!B333 -> Amphitheatre Construction Works - Final Account | D98: ='Schedule C'!Q333 -> -9520 | E98: ='Schedule C'!G333 -> 0 | F98: ='Schedule C'!BD333 -> P Donaghy: Please confirm if they owe us accommodation charges P Donaghy: So is there outstanding accommodation on the other contract? Yes or No?
A100: SUB-TOTAL | D100: =SUM(D98:D98) -> -9520
B102: FF&E AND OS&E | D102: 0
A105: EARLY WARNING TOTAL | D105: =D9+D11+D13+D15+D102 -> 32891649
C107: Check EW (from Schedule A) | D107: ='Schedule A'!M32 -> 32891649
C108: Should Be Zero | D108: =D105-D107 -> 0

Sheet Early Warning (2)
A2: ='Data Input'!A1&" - "&'Data Input'!B1 -> PROGRAMME: - MARINA VILLAGE (PROGRAMME 1_TRIPLE BAY)
A3: ='Data Input'!A2&" - "&'Data Input'!B2 -> PROGRAMME CODE: - 1TB01003
A4: ='Data Input'!A3&" - "&'Data Input'!B3 -> ASSET NAME: - AMAALA YACHT CLUB
A5: ='Data Input'!A6&" - "&'Data Input'!B6 -> Location: - AL WAJH SAUDI ARABIA
A6: ='Data Input'!A7&" - "&'Data Input'!B7 -> REPORT NO: - MONTHLY REPORT NO. 49
A8: Item No. | B8: Package | C8: Early Warning Description | D8: Impact | E8: Change Status | F8: Remarks
B10: Professional Services | D10: 0
B12: Management Supervision | D12: =SUM(D13:D13) -> 0
B14: Commercial Management | D14: =SUM(D15:D15) -> 0
B16: =+'Stakeholder Executive Review'!A35 -> Construction | D16: =SUM(D18:D46) -> -22201579
A18: RFC 26 | B18: =+'Schedule C'!M90 -> SAB - Civil and Arch Works, MEPD & ICT/ELV | C18: =+'Schedule C'!B90 -> AYC | Grand Stair Structure Backfill | D18: =+'Schedule C'!Y90 -> 166610 | E18: PVO rejected | F18: To be discussed if this still be pursued. SAB currently not put forward a variation cost submission for this.
A19: =+'Schedule C'!R133 -> 48 | B19: =+'Schedule C'!M133 -> SAB - Civil and Arch Works, MEPD & ICT/ELV | C19: =+'Schedule C'!B133 -> Additional Primary side CHW Valve Arrangement, Flushing Bypass and BTU Meter | D19: =+'Schedule C'!AG133 -> 223236 | G19: Not yet in ACC | J19: 49699225
A20: =+'Schedule C'!R107 -> 39 | B20: =+'Schedule C'!M107 -> SAB - Civil and Arch Works, MEPD & ICT/ELV | C20: =+'Schedule C'!B107 -> Provision of New IBS Infra. Requirements for Indoor GSM | D20: =+'Schedule C'!AG107 -> 1017433 | G20: Not yet in ACC
A21: RFC 32 | B21: =+'Schedule C'!M111 -> Special Kitchen | C21: =+'Schedule C'!B111 -> Relocation Marina Offices and Regeneration Kitchen (Kitchen) | D21: =+'Schedule C'!Y111 -> 1109644.6 | E21: Approved RFC | F21: PVO will be submitted upon receipt of completed IFC drawings from Dewan. | J21: =+D18+D19+D22+D25+D26+D30+D31+D32+D33+D34+D35+D39+D42+D44+D20 -> -24440698 | K21: SAB
A22: RFC 32 | B22: =+'Schedule C'!M112 -> SAB - Civil and Arch Works, MEPD & ICT/ELV | C22: =+'Schedule C'!B112 -> Relocation Marina Offices and Regeneration Kitchen (Construction plus abortive Works) | D22: =+'Schedule C'!Y112 -> 2230143 | E22: Approved RFC | F22: PVO will be submitted upon receipt of completed IFC drawings from Dewan. | J22: =+J19-J21 -> 74139923
A23: RFC 41 | B23: =+'Schedule C'!M114 -> DEPA Interior Fitout | C23: =+'Schedule C'!B114 -> AYC Guest Lobby Staircase Geometry & Finish Revisions (Construction) | D23: =+'Schedule C'!Y114 -> 0 | E23: Approved RFC | F23: PVO will be submitted upon receipt of completed IFC drawings from Dewan.
A24: RFC 43 | B24: =+'Schedule C'!M118 -> DEPA Interior Fitout | C24: =+'Schedule C'!B118 -> Changes to Members Lobby and Guest Lobby Staircase Ballustrades | D24: =+'Schedule C'!Y118 -> 27201.54 | E24: Approved RFC | F24: PVO will be submitted upon receipt of completed IFC drawings from Dewan.
A25: RFC 44 | B25: =+'Schedule C'!M120 -> SAB - Civil and Arch Works, MEPD & ICT/ELV | C25: =+'Schedule C'!B120 -> Grand Stair Balustrade Revision to Avoid Fall Hazard (Construction) | D25: =+'Schedule C'!Y120 -> 180170 | E25: Approved RFC | F25: PVO will be submitted upon receipt of completed IFC drawings from Dewan.
A26: RFA | B26: =+'Schedule C'!M140 -> SAB - Civil and Arch Works, MEPD & ICT/ELV | C26: =+'Schedule C'!B140 -> MEP Manpower Supply to AYC Project on behalf of SAB. | D26: =+'Schedule C'!Y140 -> -23125000 | E26: Approved RFA | F26: PVO 026 in WF for Approval
C27: Adjustment to PVO 005 per Approved DVO 005 - DEPA | D27: -52635
C28: Adjustment to PVO 006 per Approved DVO 006 - DEPA | D28: -198642.89
A30: EW 15 | B30: =+'Schedule C'!M67 -> SAB - Civil and Arch Works, MEPD & ICT/ELV | C30: =+'Schedule C'!B67 -> Omission of Surveying Equipment from SAB Contract | D30: =+'Schedule C'!Q67 -> -7890 | E30: Early Warning | F30: RFC to be initiated upon receipt of submission from SAB.
A31: EW 17 | B31: =+'Schedule C'!M69 -> SAB - Civil and Arch Works, MEPD & ICT/ELV | C31: =+'Schedule C'!B69 -> Omission of food and welfare provision to AMAALA Staff from SAB Contract. | D31: =+'Schedule C'!Q69 -> -90000 | E31: Early Warning | F31: RFC to be initiated upon receipt of submission from SAB.
A32: EW 17 | B32: =+'Schedule C'!M70 -> SAB - Civil and Arch Works, MEPD & ICT/ELV | C32: =+'Schedule C'!B70 -> Cost saving to Site Office Monthly Running Cost due to late installation of the Office Establishment by SAB. | D32: =+'Schedule C'!Q70 -> -200000 | E32: Early Warning | F32: RFC to be initiated upon receipt of submission from SAB.
A33: EW 26 | B33: =+'Schedule C'!M128 -> SAB - Civil and Arch Works, MEPD & ICT/ELV | C33: =+'Schedule C'!B128 -> Potential Contract Cost Adjustment | D33: =+'Schedule C'!Q128 -> 0 | E33: Early Warning | F33: Under review - Awaiting SAB Submission of Supporting Documents
A34: EW 29 | B34: =+'Schedule C'!M135 -> SAB - Civil and Arch Works, MEPD & ICT/ELV | C34: =+'Schedule C'!B135 -> Cancellation of Amphitheatre Works issued to MAS - Process not followed | D34: =+'Schedule C'!Q135 -> -1108000 | E34: RFA appoved | F34: PVO to be processed.
A35: EW 31 | B35: =+'Schedule C'!M137 -> SAB - Civil and Arch Works, MEPD & ICT/ELV | C35: =+'Schedule C'!B137 -> Recovery of Remaining Block work, Plaster work and Paint Work to be carried out by MAS - Process not followed | D35: =+'Schedule C'!Q137 -> -4004000 | E35: RFA appoved | F35: PVO to be processed.
A36: EW 32 | B36: =+'Schedule C'!M138 -> DEPA Interior Fitout | C36: =+'Schedule C'!B138 -> Alteration to finishes due to Façade Layout Changes - Process not Followed | D36: =+'Schedule C'!Q138 -> 69000 | E36: EI issued to DEPA | F36: EI issued and awaiting DEPA to submit the cost proposal before we initiate the PVO.
C37: MAS Amphitheatre Works | D37: =+'Schedule B'!K154 -> 1284550.4 | F37: Pending Downstream Contracts - Not yet approved in ACC.
A38: EW 33 | B38: =+'Schedule C'!M139 -> MAS - Amphitheatre | C38: =+'Schedule C'!B139 -> Additional Porte Cochere Works to be carried out by MAS | D38: =+'Schedule C'!Q139 -> 0 | E38: EI issued to MAS | F38: EI issued to MAS. PVO and VO will be prepared.
A39: EW 34 | B39: =+'Schedule C'!M141 -> SAB - Civil and Arch Works, MEPD & ICT/ELV | C39: =+'Schedule C'!B141 -> Deployment of Seven (7) Surveyors | D39: =+'Schedule C'!Q141 -> 201600 | E39: EI issued to SAB | F39: EI issued to SAB. PVO and VO will be prepared.
A40: EW 35 | B40: =+'Schedule C'!M142 -> DEPA Interior Fitout | C40: =+'Schedule C'!B142 -> Employer’s instruction for ID Finishes on Vertical Transportation Fixture Elements | D40: =+'Schedule C'!Q142 -> 0 | E40: EI to DEPA drafted | F40: EI to DEPA drafted. Awaiting approval before issue to DEPA.
A41: EW 36 | B41: =+'Schedule C'!M143 -> ESCCO - Vertical Transport | C41: =+'Schedule C'!B143 -> AYC – Disassembly and Reassembly of electronic items from VT fixtures | D41: =+'Schedule C'!Q143 -> 0 | E41: EI to ESCCO drafted | F41: EI to ESCCO drafted. Awaiting approval before issue to ESCCO.
A42: EW 37 | B42: =+'Schedule C'!M144 -> SAB - Civil and Arch Works, MEPD & ICT/ELV | C42: =+'Schedule C'!B144 -> Scaffolding works for Secondary Steel and Façade (Design) | D42: =+'Schedule C'!Q144 -> 75000 | E42: EI issued to SAB | F42: EI issued to SAB. PVO and VO will be prepared.
A43: EW 38 | B43: =+'Schedule C'!M145 -> ARMETAL - Reflective ceiling | C43: =+'Schedule C'!B145 -> Reflective Ceiling (Award to Armetal) | D43: =+'Schedule C'!Q145 -> 0 | E43: RFA under Approval | F43: RFA to award the reflective ceiling to ARMETAL in WF for approval.
A44: EW 39 | B44: =+'Schedule C'!M146 -> SAB - Civil and Arch Works, MEPD & ICT/ELV | C44: =+'Schedule C'!B146 -> Reflective Ceiling (Omission from SAB) | D44: =+'Schedule C'!Q146 -> 0 | E44: RFA under Approval | F44: PVO and VO will be prepared.
A45: EW 40 | B45: =+'Schedule C'!B147 -> Al Fanar MEP Manpower Supply to AYC Project on behalf of SAB. | C45: =+'Schedule C'!B147 -> Al Fanar MEP Manpower Supply to AYC Project on behalf of SAB. | D45: =+'Schedule C'!Q147 -> 0 | E45: Approved RFA | F45: Contract for Al Fanar under process.
B47: FF&E | D47: =SUM(D48:D48) -> 429156
A48: RFC 45 | B48: =+'Schedule C'!M125 -> OS&E Items | C48: =+'Schedule C'!B125 -> Addition of Accessories to Existing Artwork Proposal - Change Decision Pack_Artwork Package | D48: =+'Schedule C'!Y125 -> 429156 | F48: PVO will be submitted upon receipt of completed details from Dewan/Art Consultant.
A50: EARLY WARNING TOTAL | D50: =+D47+D16+D14+D12+D10 -> -21772423
D53: =+'Schedule B'!N240 -> 3585562.5 | E53: =+D18+D21+D22+D23+D24+D25+D48+D26 -> -18982075 | F53: =+E53-D53 -> -22567637
D54: =+'Schedule B'!O240 -> 32891649 | E54: =+D30+D31+D32+D33+D34+D35+D36+D38+D43+D44+D39+D40+D41+D42+D45 -> -5064290 | F54: =+E54-D54 -> -37955939
D55: =+D54+D53 -> 36477211
D56: =+D55-D50 -> 58249635
D58: =+'Schedule B'!N240 -> 3585562.5
D59: =+'Schedule B'!O240 -> 32891649
D60: =+D59+D58 -> 36477211

Sheet ACC
A2: ='Data Input'!A1&" - "&'Data Input'!B1 -> PROGRAMME: - MARINA VILLAGE (PROGRAMME 1_TRIPLE BAY)
A3: ='Data Input'!A2&" - "&'Data Input'!B2 -> PROGRAMME CODE: - 1TB01003
A4: ='Data Input'!A5&" - "&'Data Input'!B5 -> Client: - AMAALA
A5: ='Data Input'!A6&" - "&'Data Input'!B6 -> Location: - AL WAJH SAUDI ARABIA
A6: ='Data Input'!A7&" - "&'Data Input'!B7 -> REPORT NO: - MONTHLY REPORT NO. 49

Sheet Movement
F62: October 2025 - Report
C63: October 2025 Cost Report
C65: Al Fanar Manpower from Jul to Oct25 | D65: 14.56 | E65: 14557384 | F65: =+E65/1000000 -> 14.557384
C66: Direct Payment for NESMA for ICT System | D66: 2.67 | E66: 2674938 | F66: =+E66/1000000 -> 2.674938 | J66: Al Fanar Mapower Services to Dec 2025, & DLP (Jan to Mar25). | K66: 8136064 | L66: =+ROUND(K66/1000000,2) -> 8.14
C67: Al Fanar Mapower Services to Dec 2025, & DLP (Jan to Mar25). | D67: 8.14 | E67: 8136064 | F67: =+E67/1000000 -> 8.136064 | J67: Al Fanar further MEP Matls. (excluded in DVO 002) | K67: 4300000 | L67: =+ROUND(K67/1000000,2) -> 4.3 | O67: RFA for October 2025 Direct Payment:
C68: MAS Manpower Services (Nov to Dec 25) | D68: 3.05 | E68: 3050936 | F68: =+E68/1000000 -> 3.050936 | J68: MAS Manpower Services (Nov to Dec 25) | K68: 3050936 | L68: =+ROUND(K68/1000000,2) -> 3.05 | O68: SAB Position:
C69: Contract Award for GST (Sustainability) | D69: 0.13 | E69: 133000 | F69: =+E69/1000000 -> 0.133 | J69: Contract Award for GST (Sustainability) | K69: 133000 | L69: =+ROUND(K69/1000000,2) -> 0.13 | O69: Payment Made to Date | P69: =+'Schedule H SAB'!AD33 -> 2.0824904e+08 | Q69: 2.0824904e+08 | R69: copied value
C70: Contract Award for Enviro (Deep Cleaning) | D70: 0.8 | E70: 799625.31 | F70: =+E70/1000000 -> 0.79962531 | J70: Contract Award for Enviro (Deep Cleaning) | K70: 799625.31 | L70: =+ROUND(K70/1000000,2) -> 0.8 | O70: AP and PB Recovery | P70: =+'Schedule H SAB'!AD40+'Schedule H SAB'!AD41 -> -37656960
C71: Al Fanar further MEP Matls. (excluded in DVO 002) | D71: 4.3 | E71: 4300000 | F71: =+E71/1000000 -> 4.3 | J71: Replacement of External Doors - requested by the Operator | K71: 780000 | L71: =+ROUND(K71/1000000,2) -> 0.78 | P71: =+P70+P69 -> 1.7059208e+08
C72: Replacement of External Doors - requested by the Operator | D72: 0.78 | J72: Various EIs | K72: 402710.72 | L72: =+ROUND(K72/1000000,2) -> 0.4
J73: Omission Kitchen Service Hatches from SAB | K73: -8078.16 | L73: =+ROUND(K73/1000000,2) -> -0.01 | O73: SAB FFA, Oct 25 Cost Report | P73: =+'Schedule B'!Q79 -> 1.7098942e+08 | Q73: 2.2836252e+08 | R73: copied value
D74: =SUM(D65:D72) -> 34.43 | J74: Adj. to SAB's EW cost to cover the various EIs | K74: -402710.72 | L74: =+ROUND(K74/1000000,2) -> -0.4 | O74: August 2025 Direct Payment | P74: 4790313.1 | Q74: 4790313.1 | R74: copied value
J75: Adj. to SAB's EW cost to cover the previous Alcatop VOs and SAMIF's VOs. | K75: -1168628.1 | L75: =+ROUND(K75/1000000,2) -> -1.17 | O75: September 2025 Direct Payment | P75: 3198424.2 | Q75: 3198424.2 | R75: copied value
J76: Adj. due to the approved DVOs value vs PVOs | K76: -52726 | L76: =+ROUND(K76/1000000,2) -> -0.05 | P76: =+P73-P74-P75 -> 1.6300068e+08
K77: =SUM(K66:K76) -> 15970193 | L77: =SUM(L66:L76) -> 15.97 | O77: Remaining for October 2025 Report | P77: =+P76-P69 -> -45248364
O78: This is based on SAB approved EAC.
P81: 2.0526498e+08
P82: 222783157
P83: =+P82/1.15 -> 1.9372448e+08
P84: =+P82-P81 -> 17518174
P87: 2.2278316e+08
P88: 14534123
P89: =+P87-P88 -> 2.0824903e+08
C91: DVO High Level Overview | G91: 238213
C92: Item No. - 112 - Employer’s Instruction No.01 - Supply of additional Kitchen Shelf Opening Hatch (Servery Hatches) | G92: 10143 | H92: =+G92+G101 -> -5796 | J92: Adjustment due to the approved DVO value vs PVO | K92: =+H92+H93 -> -52726 | O92: Al Fanar Manpower from July to October 2025 (per the approved DVO 003) | P92: 14557384
C93: Item No. - 111 - Metal Mesh Grating as per CML requirements in MEP shafts | G93: 228070 | H93: =+G93+G102 -> -46930 | P93: =+P77-P92 -> -59805749
O94: Remaining budget for SAB, based on approved EAC | P94: =+P77 -> -45248364
O95: Alfanar DVO 003 (Jul to Oct25), no BTR yet | P95: -14557384
O96: NET Budget Hold | P96: =+P95+P94 -> -59805749
C100: PVO High Level Overview | G100: -290939
C101: Item No. - 112 - Employer’s Instruction No.01 - Supply of additional Kitchen Shelf Opening Hatch (Servery Hatches) | G101: -15939
C102: Item No. - 111 - Metal Mesh Grating as per CML requirements in MEP shafts | G102: -275000
C113: RFC High Level Overview | G113: 0
C122: Early Warnings | G122: 16022919
C123: Item No. - 161 - Omission of Internal Windows (Kitchen Service Hatches) from SAB - Supply and install by RAQTAN | F123: EW 114 | G123: -8078.16 | J123: Omission Kitchen Service Hatches from SAB | K123: =+G123 -> -8078.16
C124: Item No. - 162 - EI-17: Road Markings Paint Application | F124: EW 115 | G124: 8000 | J124: Various EIs | K124: =+G124+G127+G128+G129+G130+G131+G133+G134 -> 402710.72
C125: Item No. - 163 - Extension of Al Fanar Mapower Services to AMAALA Yacht Club Project through to December 2025, and DLP Contingency (January to March 2025). | F125: EW 116 | G125: 8136064 | J125: Al Fanar Mapower Services to Dec 2025, & DLP (Jan to Mar25). | K125: =+G125 -> 8136064
C126: Item No. - 164 - Extension of MAS Manpower Services (Nov to Dec 2025) - TB01003-003C31-AMA-RFA-CM-0002 | F126: EW 117 | G126: 3050936 | J126: MAS Manpower Services (Nov to Dec 25) | K126: =+G126 -> 3050936
C127: Item No. - 158 - EI 16: Change in Aged Mirror finish to members' bar & Signature Restaurant | F127: EW 111 | G127: -204382
C128: Item No. - 160 - EI-15: Removing and replace tiling around faulty Urinal Sensors | F128: EW 113 | G128: 72092.72
C129: Item No. - 166 - EI-18: Consolidated Fit-Out Instructions (Ceiling, LPG, Capping, Beech Ovens & Hood Cladding) | F129: EW 119 | G129: 232000
C130: Item No. - 167 - EI-19: Replacement of Vanity Top Soap Dispensers and Rectification of Existing Vanity Units | F130: EW 120 | G130: 90000
C131: Item No. - 168 - EI-20: Rectification of the Damaged Ceilings Based on the Various Damage Reports | F131: EW 121 | G131: 100000
C132: Item No. - 169 - EI-03: Cooled Glass Display Case at Café (CPD10). | F132: EW 122 | G132: 0
C133: Item No. - 170 - EI-18 : Amendment of Secondary Steel Structure vs Honeycomb Limestone Cladding | F133: EW 123 | G133: 54000
C134: Item No. - 171 - EI-03: External Glass Door Application at Chart Model Room Staircase | F134: EW 124 | G134: 51000
C136: Item No. - 102 - Cost to Complete (SAB Amount) - Including Contingencies | F136: EW 063 - Adjustment | G136: -402710.72 | J136: Adjustment to SAB's EW cost to cover the various EIs | K136: =+G136 -> -402710.72
C137: Contract Award to GST for Sustainability Accreditations Services | G137: 133000 | J137: Contract Award for GST (Sustainability) | K137: =+G137 -> 133000
C138: Contract Award to Enviro Facility Management for Deep Cleaning | G138: 799625.31 | J138: Contract Award for Enviro (Deep Cleaning) | K138: =+G138 -> 799625.31
C139: SAB - Metal Mesh Grating as per CML requirements in MEP shafts - deducted from SAB's Cost to Complete Early Warning Cost | G139: -228070 | J139: Adjustment to SAB's EW cost to cover the Alcatop VOs on handrail changes and SAMIF's VO Metal Mesh Gratings | K139: =+G139+G140+G141 -> -1168628.1
C140: SAB - Employer's Instruction No. 017 - Grand Stair Handrail (Alcatop) - deducted from SAB's Cost to Complete Early Warning Cost | G140: -677313.67
C141: Item No. - 102 - Cost to Complete (SAB Amount) - Including Contingencies | F141: Further adjustment to align with the requested additional budget | G141: -263244.46
C142: Item No. - 172 - Further MEP Material Supply by Al Fanar (excluded in the previous DVO) - Al Fanar letter 1TB01003-003C34-ACY-LTR-0057 | G142: 4300000 | J142: Al Fanar further MEP Matls. (excluded in DVO 002) | K142: =+G142 -> 4300000
C143: Item No. - 173 - Replacement of External Doors - requested by the Operator (Cluster Manager - Back of House) | G143: 780000 | J143: Replacement of External Doors - requested by the Operator | K143: =+G143 -> 780000
K144: =SUM(K92:K143) -> 15970193
C150: BUDGET HOLD Movement | G150: 0
G156: 15970193
B160: 13.28 | C160: a) 13.28M – approved PVO for Al Fanar Manpower Extension up to 31 Oct 25.
B161: 1.28 | C161: b) 1.28M – adjustment due to variance in PVO and DVO approval regarding Al Fanar Manpower Extension up to 31 Oct 25.
B162: 1.02 | C162: c) 1.02M – adjustment due to the variance in Early Warning and PVO approval regarding the direct payment to SAB’s subcontractors and suppliers for April and May 2025 Invoices.
B163: 2.67 | C163: d) 2.67M – ICT system by NESMA.
B164: 0.25 | C164: e) 0.21M – adjustments due to various approved DVOs values compared to PVOs.
B165: =SUM(B160:B164) -> 18.5
B166: 12.06 | F166: =+B164*1000000 -> 250000
B167: 30.511922
F168: =+G168/1000000 -> -0.052726 | G168: =-5796-46930 -> -52726 | H168: Adjustment due to approved DVO value compared to PVO.
B169: -0.05 | C169: a) -0.05M - Adj due to variance in PVO and DVO 001 of RAQTAN and PVO and DVO 018 of SAB
B170: 0.3 | C170: f) 0.30M - EI-15, EI-16, EI-17, EI-18, EI-19 and EI-20 to DEPA
B171: 0.05 | C171: g) 0.50M - EI-18 to SAB/SAMIF
B172: 0.05 | C172: h) 0.05M - EI-09 to Alutec
B173: 3.05 | C173: i) 3.05M - RFA - MAS labour up to Dec-25 | F173: =+G173/1000000 -> -0.00807816 | G173: -8078.16 | H173: Item No. - 161 - Omission of Internal Windows (Kitchen Service Hatches) from SAB - Supply and install by RAQTAN | K173: EW 114 | L173: -8078.16
B174: 5.54 | C174: j) 5.54M - RFA - Al Fanar labour up to Dec-25 | F174: =+G174/1000000 -> 0.008 | G174: 8000 | H174: Item No. - 162 - EI-17: Road Markings Paint Application | K174: EW 115 | L174: 8000
B175: 3.49 | C175: k) 3.49M - RFA - Al Fanar labour DLP/contingency | F175: =+G175/1000000 -> 5.5360636 | G175: 5536063.6 | H175: Item No. - 163 - Extension of Al Fanar Manpower Services (Nov to Dec 2025) | K175: EW 116 | L175: 5536063.6
B176: -0.4 | C176: l) -0.40M - Adjustment to SAB's Contract Adjustment allowance (covering all EIs issued to DEPA, Alutec and SAB/SAMIF) | F176: =+G176/1000000 -> 3.050936 | G176: 3050936 | H176: Item No. - 164 - Extension of MAS Manpower Services (Nov to Dec 2025) - TB01003-003C31-AMA-RFA-CM-0002 | K176: EW 117 | L176: 3050936
B177: -0.01 | C177: m) -0.01M - Omission of Service Hatches from SAB (install by RAQTAN) | F177: =+G177/1000000 -> -0.204382 | G177: -204382 | H177: Item No. - 158 - EI 16: Change in Aged Mirror finish to members' bar & Signature Restaurant | K177: EW 111 | L177: -204382
F178: =+G178/1000000 -> 0.07209272 | G178: 72092.72 | H178: Item No. - 160 - EI-15: Removing and replace tiling around faulty Urinal Sensors | K178: EW 113 | L178: 72092.72
B179: =SUM(B169:B178) -> 12.02 | F179: =+G179/1000000 -> 0.232 | G179: 232000 | H179: Item No. - 166 - EI-18: Consolidated Fit-Out Instructions (Ceiling, LPG, Capping, Beech Ovens & Hood Cladding) | K179: EW 119 | L179: 232000
B180: =B165+B179 -> 30.52 | F180: =+G180/1000000 -> 0.09 | G180: 90000 | H180: Item No. - 167 - EI-19: Replacement of Vanity Top Soap Dispensers and Rectification of Existing Vanity Units | K180: EW 120 | L180: 90000
B181: =B180-B169 -> 30.57 | F181: =+G181/1000000 -> 0.1 | G181: 100000 | H181: Item No. - 168 - EI-20: Rectification of the Damaged Ceilings Based on the Various Damage Reports | K181: EW 121 | L181: 100000
B182: 30.61 | F182: =+G182/1000000 -> 0 | G182: 0 | H182: Item No. - 169 - EI-03: Cooled Glass Display Case at Café (CPD10). | K182: EW 122 | L182: 0
B183: =B182-B181 -> 0.04 | F183: =+G183/1000000 -> 0.054 | G183: 54000 | H183: Item No. - 170 - EI-18 : Amendment of Secondary Steel Structure vs Honeycomb Limestone Cladding | K183: EW 123 | L183: 54000
F184: =+G184/1000000 -> 0.051 | G184: 51000 | H184: Item No. - 171 - EI-03: External Glass Door Application at Chart Model Room Staircase | K184: EW 124 | L184: 51000
F185: =+G185/1000000 -> 3.4928252 | G185: 3492825.2 | H185: Item No. - 172 - Additional Budget Approval for Al Fanar Manpower Services (Dec 2025 Completion and DLP Contingency) - 1TB01003-003C34-AMA-RFA-CM-0003 | K185: EW 125 | L185: 3492825.2
F186: =+G186/1000000 -> -0.40271072 | G186: -402710.72 | H186: Item No. - 102 - Cost to Complete (SAB Amount) - Including Contingencies | K186: EW 063 - Adjustment | L186: -402710.72
G188: =+G174+G177+G178+G179+G180+G181 -> 297710.72
F189: =SUM(F173:F188) -> 12.071747 | G189: =+G188+G184+G183 -> 402710.72
B191: 14.56 | C191: a) 14.56M – DVO for Al Fanar Manpower up to 31 Oct 25. | G191: =SUM(G173:G186) -> 12071747
B192: 1.02 | C192: b) 1.02M – adj due to the variance in EW and PVO regarding SAB's direct payment (Apr & May 25). | G192: =+G191+G168 -> 12019021
B193: 2.67 | C193: c) 2.67M – direct payment for the ICT system by NESMA.
B194: 0.29 | C194: d) 0.25M – adj due to various approved DVOs compared to PVOs.
B195: 0.3 | C195: e) 0.30M - EI-15, EI-16, EI-17, EI-18, EI-19 and EI-20 to DEPA
B196: 0.05 | C196: f) 0.05M - EI-18 to SAB/SAMIF
B197: 0.05 | C197: g) 0.05M - EI-09 to Alutec
B198: 3.05 | C198: h) 3.05M - RFA - MAS labour up to Dec-25
B199: 5.54 | C199: i) 5.54M - RFA - Al Fanar labour up to Dec-25
B200: 3.49 | C200: j) 3.49M - RFA - Al Fanar labour DLP/contingency
B201: -0.4 | C201: k) -0.40M - reduction of SAB's CP Adjustment allowance (cost of all EIs issued to DEPA, Alutec and SAB/SAMIF).
B202: -0.01 | C202: l) -0.01M - Omission of Service Hatches from SAB.
B203: =SUM(B191:B202) -> 30.61
B204: =B182-B203 -> 0

Sheet 75.7M SAB EW
A1: =75,660,633.83-(13,737,620)-(760,869.57+612,731.57)-4,055,764.55-(1,655,399.8-569838*0)-82,2640.54-519,230.25-(158,817.97)-(104,000)+666,280-(21,000)-(115,000)-(50,000)
A2: =75660633.83-(13737620)-(760869.57+612731.57)-4055764.55-(1655399.8-569838*0)-822640.54-519230.25-(158817.97)-(104000)+666280-(21000)-(115000)-(50000) -> 53713840
B4: Early Warning | C4: Cost to Complete (SAB Amount) - Including Contingencies | D4: 75723857
M5: Adjustment for DEPA
B6: 45566 | C6: No change | D6: 0 | M6: Employer’s instruction for ID Finishes on Vertical Transportation Fixture Elements | N6: 684836.5 | O6: =+N6-'Schedule C'!AG142 -> 313961.5 | P6: =+N6-O6 -> 370875
B7: 45597 | C7: No change | D7: 0 | M7: Back-of-House Finishes (EI 006)_DEPA | N7: 3351000 | O7: =+'Schedule C'!AG172 -> 2521135.5 | P7: =+N7-O7 -> 829864.48
B8: 45627 | C8: Removed | D8: 0 | M8: Employers Instruction No. 07 – Supply and Installation of Millworks to Show Kitchens | P8: =+N8-O8 -> 0
B9: 45658 | C9: Owner Controlled Insurance Program | D9: -63223 | M9: Employers Instruction No. 09 – Honeycomb Limestone System and External Doors | N9: 1585809.4 | O9: =+'Schedule C'!AG181 -> 850370.6 | P9: =+N9-O9 -> 735438.85
B10: 45689 | C10: MAS Manpower and Supervision PVO | D10: -13737620 | M10: Employer's Instruction No. 10 - Changes In the Balustrade Materials at the Member's Lobby and Guest Foyer
B11: 45689 | C11: Scaffolding Material in CTC | D11: -760869.57 | E11: The Scaffolding Contract Awarded to HAS at | I11: SAR 3,096,124.9 | M11: Descope FF12.04 Millwork & Procure Globe via Depa
B12: 45689 | C12: ??? | D12: -612731.57 | M12: Total | P12: =SUM(P6:P11) -> 1936178.3
B13: 45719 | C13: No change
B14: 45750 | C14: No change
B15: 45778 | C15: Negative adjustment to maintain the SAR 584.59M EAC | D15: -4055764.5
B16: 45811 | C16: No change | E16: =-(1655399.8-569838*0)-822640.54-519230.25-(158817.97)
B17: 45841 | C17: K&A Extension | D17: -1655399.8 | E17: =-(1655399.8-569838*0)-822640.54-519230.25-(158817.97) | J17: =-(1655399.8-569838*0)-822640.54-519230.25-(158817.97) -> -3156088.6
B18: 45841 | C18: CML Extension | D18: -822640.54
B19: 45841 | C19: Areen's Extension | D19: -519230.25 | G19: -158817.97
B20: 45841 | C20: Negative adjustment to maintain the previous EAC Report in Jul 2025 of SAR 594.03M (however, this is deducted with SAB's PB and APB amount of SAR 37.66 = SAR 556.37M EAC in Jul 2025). | D20: -158817.97 | G20: 106917.56 | I20: 0 | J20: 0
B21: 45872 | C21: Modification to Members Lobby & Guest Foyer Staircase Finishes | D21: -104000 | G21: =+G20+G19 -> -51900.41 | I21: 0 | J21: 0
C22: Powder coating of ID light fittings (to suit ID requirements) | D22: -21000 | I22: =+I21+I20+G19 -> -158817.97
C23: Installation of Decorative Lights | D23: -115000
C24: Supply and Install Access Doors | D24: -50000
C25: ??? | D25: 666280
B26: 45925 | C26: No change
B27: 45933 | C27: Item No. - 162 - EI-17: Road Markings Paint Application | D27: -8000 | J27: 8000
C28: Item No. - 158 - EI 16: Change in Aged Mirror finish to members' bar & Signature Restaurant | D28: 204382
C29: Item No. - 160 - EI-15: Removing and replace tiling around faulty Urinal Sensors | D29: -72092.72
C30: Item No. - 166 - EI-18: Consolidated Fit-Out Instructions (Ceiling, LPG, Capping, Beech Ovens & Hood Cladding) | D30: -232000
C31: Item No. - 167 - EI-19: Replacement of Vanity Top Soap Dispensers and Rectification of Existing Vanity Units | D31: -90000
C32: Item No. - 168 - EI-20: Rectification of the Damaged Ceilings Based on the Various Damage Reports | D32: -100000
C33: Item No. - 169 - EI-03: Cooled Glass Display Case at Café (CPD10). | D33: 0
C34: Item No. - 170 - EI-18 : Amendment of Secondary Steel Structure vs Honeycomb Limestone Cladding | D34: -54000
C35: Item No. - 171 - EI-03: External Glass Door Application at Chart Model Room Staircase | D35: -51000 | E35: =SUM(D27:D35) -> -402710.72
C36: Metal Mesh Grating as per CML requirements in MEP shafts | D36: -228070
C37: Employer's Instruction No. 017 - Grand Stair Handrail (Alcatop) | D37: -677313.67
C38: Further adjustment (for balancing of requested budget) | D38: -263244.46
B39: 45986 | C39: Adjustment due to DEPA PVO 019 increased by 10K from EW | D39: -10000
C40: Adjustment due variance in EW and PVO 033 (Jun and Jul 25 Direct Payment) | D40: 838114.1
C41: Adjustment due to variance in PVO and DVO (SAB Road Studs from Railing) | D41: 41010
C42: TOTAL | D42: =SUM(D4:D41) -> 53011625 | G42: 0 | H42: 0
D43: =+D42-A2 -> -702214.75 | G43: 0 | H43: 0
G44: =SUM(G42:G43) -> 0
G46: -569838.42
D47: =+D25+D12 -> 53548.43 | G47: 1655399.8
G48: =+G47+G46 -> 1085561.4
C49: Direct Payments
C50: Direct Payment - Jan to Mar 25 | D50: -8870230.3
C51: Direct Payment - Apr to May 25 | D51: -7235632.8
C52: Direct Payment - Jun to Jul 25 | D52: -8703634.6
D53: =SUM(D50:D52) -> -24809498
D54: =+D53+D42 -> 28202127
C55: Contigencies | D55: 0
D56: =+D55+D54 -> 28202127 | G56: 45441
G57: 45475
G58: =+G57-G56 -> 34
D59: 0.29
D60: 0.25

Sheet Level 02
A1: Triple Bay Portfolio
A2: Cost Report Executive Summary
A3: Programme 1 - Amaala Yacht Club
A4: =+Current_date -> OCTOBER 2026
A6: Program | B6: Asset | C6: Sub-category | D6: Name | E6: Previous Approved Budget | F6: Approved Budget Transfers | G6: Currently Approved Budget | H6: Contracts | I6: DVO's | J6: Committed PVOs | K6: Committed | L6: Uncommitted | M6: PVO's | N6: CTC - Site | O6: CTC - Procurement | P6: Early Warnings | Q6: Final Account | R6: Variance
A7: Program 1 - AYC | B7: =B$19 -> Professional Services | C7: Professional Services | D7: ='Schedule B'!C17 -> Dewan Architects & Engineers 2200445 | E7: ='Schedule B'!E17 -> 5973808 | F7: ='Schedule B'!F17 -> 0 | G7: =F7+E7 -> 5973808 | H7: ='Schedule B'!H17 -> 5973808 | I7: ='Schedule B'!I17 -> 3316718.1 | J7: =+'Schedule B'!J17 -> 0 | K7: =SUM(H7:J7) -> 9290526.1 | M7: ='Schedule B'!M17 -> 0 | N7: ='Schedule B'!N17 -> 0 | P7: ='Schedule B'!O17 -> 0 | Q7: =SUM(K7:P7) -> 9290526.1 | R7: =Q7-G7 -> 3316718.1
A8: Program 1-AYC | B8: =B$19 -> Professional Services | C8: Professional Services | D8: ='Schedule B'!C18 -> HKS Architects Ltd - Design Competition Fees 2200010 | E8: ='Schedule B'!E18 -> 555960.36 | F8: ='Schedule B'!F18 -> 0 | G8: =F8+E8 -> 555960.36 | H8: ='Schedule B'!H18 -> 555960.36 | I8: ='Schedule B'!I18 -> 0 | J8: =+'Schedule B'!J18 -> 0 | K8: =SUM(H8:J8) -> 555960.36 | M8: ='Schedule B'!M18 -> 0 | N8: ='Schedule B'!N18 -> 0 | P8: ='Schedule B'!O18 -> 0 | Q8: =SUM(K8:P8) -> 555960.36 | R8: =Q8-G8 -> 0
A9: Program 1-AYC | B9: =B$19 -> Professional Services | C9: Professional Services | D9: ='Schedule B'!C19 -> HKS Architects Ltd - Design Architect Fees 2200375 | E9: ='Schedule B'!E19 -> 10891204 | F9: ='Schedule B'!F19 -> 0 | G9: =F9+E9 -> 10891204 | H9: ='Schedule B'!H19 -> 10891204 | I9: ='Schedule B'!I19 -> -89775 | J9: =+'Schedule B'!J19 -> 0 | K9: =SUM(H9:J9) -> 10801429 | M9: ='Schedule B'!M19 -> 0 | N9: ='Schedule B'!N19 -> 0 | P9: ='Schedule B'!O19 -> 0 | Q9: =SUM(K9:P9) -> 10801429 | R9: =Q9-G9 -> -89775
A10: Program 1-AYC | B10: =B$19 -> Professional Services | C10: Professional Services | D10: ='Schedule B'!C20 -> Applied Technology and Management Inc (Dubai BR)s 2210167 | E10: ='Schedule B'!E20 -> 93750 | F10: ='Schedule B'!F20 -> 0 | G10: =F10+E10 -> 93750 | H10: ='Schedule B'!H20 -> 93750 | I10: ='Schedule B'!I20 -> 0 | J10: =+'Schedule B'!J20 -> 0 | K10: =SUM(H10:J10) -> 93750 | M10: ='Schedule B'!M20 -> 0 | N10: ='Schedule B'!N20 -> 0 | P10: ='Schedule B'!O20 -> 0 | Q10: =SUM(K10:P10) -> 93750 | R10: =Q10-G10 -> 0
A11: Program 1-AYC | B11: =B$19 -> Professional Services | C11: Professional Services | D11: ='Schedule B'!C21 -> Langan International UK Limited 2230042 | E11: ='Schedule B'!E21 -> 0 | F11: ='Schedule B'!F21 -> 172368.42 | G11: =F11+E11 -> 172368.42 | H11: ='Schedule B'!H21 -> 172368.42 | I11: ='Schedule B'!I21 -> -1898.52 | J11: =+'Schedule B'!J21 -> 0 | K11: =SUM(H11:J11) -> 170469.9 | M11: ='Schedule B'!M21 -> 0 | N11: ='Schedule B'!N21 -> 0 | P11: ='Schedule B'!O21 -> 0 | Q11: =SUM(K11:P11) -> 170469.9 | R11: =Q11-G11 -> -1898.52
A12: Program 1-AYC | B12: =B$19 -> Professional Services | C12: Professional Services | D12: ='Schedule B'!C22 -> Zuhair Fayez and Partners 2230041 | E12: ='Schedule B'!E22 -> 0 | F12: ='Schedule B'!F22 -> 106231.5 | G12: =F12+E12 -> 106231.5 | H12: ='Schedule B'!H22 -> 106231.5 | I12: ='Schedule B'!I22 -> 0 | J12: =+'Schedule B'!J22 -> 0 | K12: =SUM(H12:J12) -> 106231.5 | M12: ='Schedule B'!M22 -> 0 | N12: ='Schedule B'!N22 -> 0 | P12: ='Schedule B'!O22 -> 0 | Q12: =SUM(K12:P12) -> 106231.5 | R12: =Q12-G12 -> 0
A13: Program 1-AYC | B13: =B$19 -> Professional Services | C13: Professional Services | D13: ='Schedule B'!C23 -> Ministry of Municipality and Rural Affairs (Tabuk) | E13: ='Schedule B'!E23 -> 0 | F13: ='Schedule B'!F23 -> 45677.6 | G13: =F13+E13 -> 45677.6 | H13: ='Schedule B'!H23 -> 45677.6 | I13: ='Schedule B'!I23 -> 0 | J13: =+'Schedule B'!J23 -> 0 | K13: =SUM(H13:J13) -> 45677.6 | M13: ='Schedule B'!M23 -> 0 | N13: ='Schedule B'!N23 -> 0 | P13: ='Schedule B'!O23 -> 0 | Q13: =SUM(K13:P13) -> 45677.6 | R13: =Q13-G13 -> 0
A14: Program 1-AYC | B14: =B$19 -> Professional Services | C14: Professional Services | D14: ='Schedule B'!C24 -> Jensen Hughes Saudi Arabia Co 2230180 | E14: ='Schedule B'!E24 -> 0 | F14: ='Schedule B'!F24 -> 127291.9 | G14: =F14+E14 -> 127291.9 | H14: ='Schedule B'!H24 -> 127291.9 | I14: ='Schedule B'!I24 -> -56700 | J14: =+'Schedule B'!J24 -> 0 | K14: =SUM(H14:J14) -> 70591.9 | M14: ='Schedule B'!M24 -> 0 | N14: ='Schedule B'!N24 -> 0 | P14: ='Schedule B'!O24 -> 0 | Q14: =SUM(K14:P14) -> 70591.9 | R14: =Q14-G14 -> -56700
