Workbook

Sheet Required actions
A2: Overall Status | C2: Program_01 | D2: Program_02 | E2: Program_03 | F2: Program_04 | G2: Program_05 | H2: Program_06 | I2: Program_07 | J2: Program_08 | K2: Program_09 | L2: Program_10 | M2: Program_11 | N2: Program_12 | O2: Program_16 | P2: Program_17 | Q2: Program_18 | R2: Program_90 | S2: Program_96 | T2: Program_99 | U2: Total
A3: Open | C3: =COUNTIFS(Summary!$A:$A,C$2,Summary!$AV:$AV,$A$3)+COUNTIFS(Summary!$A:$A,C$2,Summary!$AW:$AW,$A$3) -> 83 | D3: =COUNTIFS(Summary!$A:$A,D$2,Summary!$AV:$AV,$A$3)+COUNTIFS(Summary!$A:$A,D$2,Summary!$AW:$AW,$A$3) -> 0 | E3: =COUNTIFS(Summary!$A:$A,E$2,Summary!$AV:$AV,$A$3)+COUNTIFS(Summary!$A:$A,E$2,Summary!$AW:$AW,$A$3) -> 0 | F3: =COUNTIFS(Summary!$A:$A,F$2,Summary!$AV:$AV,$A$3)+COUNTIFS(Summary!$A:$A,F$2,Summary!$AW:$AW,$A$3) -> 0 | G3: =COUNTIFS(Summary!$A:$A,G$2,Summary!$AV:$AV,$A$3)+COUNTIFS(Summary!$A:$A,G$2,Summary!$AW:$AW,$A$3) -> 0 | H3: =COUNTIFS(Summary!$A:$A,H$2,Summary!$AV:$AV,$A$3)+COUNTIFS(Summary!$A:$A,H$2,Summary!$AW:$AW,$A$3) -> 0 | I3: =COUNTIFS(Summary!$A:$A,I$2,Summary!$AV:$AV,$A$3)+COUNTIFS(Summary!$A:$A,I$2,Summary!$AW:$AW,$A$3) -> 0 | J3: =COUNTIFS(Summary!$A:$A,J$2,Summary!$AV:$AV,$A$3)+COUNTIFS(Summary!$A:$A,J$2,Summary!$AW:$AW,$A$3) -> 0 | ... T3: =COUNTIFS(Summary!$A:$A,T$2,Summary!$AV:$AV,$A$3)+COUNTIFS(Summary!$A:$A,T$2,Summary!$AW:$AW,$A$3) -> 0 | U3: =SUM(C3:T3) -> 83
A4: Closed | C4: =COUNTIFS(Summary!$A:$A,C$2,Summary!$AV:$AV,$A$4)+COUNTIFS(Summary!$A:$A,C$2,Summary!$AW:$AW,$A$4) -> 79 | D4: =COUNTIFS(Summary!$A:$A,D$2,Summary!$AV:$AV,$A$4)+COUNTIFS(Summary!$A:$A,D$2,Summary!$AW:$AW,$A$4) -> 0 | E4: =COUNTIFS(Summary!$A:$A,E$2,Summary!$AV:$AV,$A$4)+COUNTIFS(Summary!$A:$A,E$2,Summary!$AW:$AW,$A$4) -> 0 | F4: =COUNTIFS(Summary!$A:$A,F$2,Summary!$AV:$AV,$A$4)+COUNTIFS(Summary!$A:$A,F$2,Summary!$AW:$AW,$A$4) -> 0 | G4: =COUNTIFS(Summary!$A:$A,G$2,Summary!$AV:$AV,$A$4)+COUNTIFS(Summary!$A:$A,G$2,Summary!$AW:$AW,$A$4) -> 0 | H4: =COUNTIFS(Summary!$A:$A,H$2,Summary!$AV:$AV,$A$4)+COUNTIFS(Summary!$A:$A,H$2,Summary!$AW:$AW,$A$4) -> 0 | I4: =COUNTIFS(Summary!$A:$A,I$2,Summary!$AV:$AV,$A$4)+COUNTIFS(Summary!$A:$A,I$2,Summary!$AW:$AW,$A$4) -> 0 | J4: =COUNTIFS(Summary!$A:$A,J$2,Summary!$AV:$AV,$A$4)+COUNTIFS(Summary!$A:$A,J$2,Summary!$AW:$AW,$A$4) -> 0 | ... T4: =COUNTIFS(Summary!$A:$A,T$2,Summary!$AV:$AV,$A$4)+COUNTIFS(Summary!$A:$A,T$2,Summary!$AW:$AW,$A$4) -> 0 | U4: =SUM(C4:T4) -> 79
A5: Total | C5: =SUM(C3:C4) -> 162 | D5: =SUM(D3:D4) -> 0 | E5: =SUM(E3:E4) -> 0 | F5: =SUM(F3:F4) -> 0 | G5: =SUM(G3:G4) -> 0 | H5: =SUM(H3:H4) -> 0 | I5: =SUM(I3:I4) -> 0 | J5: =SUM(J3:J4) -> 0 | ... T5: =SUM(T3:T4) -> 0 | U5: =SUM(C5:T5) -> 162
A7: A | B7: Claims Requiring Response Letter (within 21 days from Claim submission date)
A8: From receipt of Claim | C8: Program_01 | D8: Program_02 | E8: Program_03 | F8: Program_04 | G8: Program_05 | H8: Program_06 | I8: Program_07 | J8: Program_08 | K8: Program_09 | L8: Program_10 | M8: Program_11 | N8: Program_12 | O8: Program_16 | P8: Program_17 | Q8: Program_18 | R8: Program_90 | S8: Program_96 | T8: Program_99 | U8: Total
A9: A1 | B9: 1 to 7 days | C9: =COUNTIFS(Summary!$A:$A,C$8,Summary!$V:$V,0,Summary!$W:$W,">=1",Summary!$W:$W,"<=7") -> 0 | D9: =COUNTIFS(Summary!$A:$A,D$8,Summary!$V:$V,0,Summary!$W:$W,">=1",Summary!$W:$W,"<=7") -> 0 | E9: =COUNTIFS(Summary!$A:$A,E$8,Summary!$V:$V,0,Summary!$W:$W,">=1",Summary!$W:$W,"<=7") -> 0 | F9: =COUNTIFS(Summary!$A:$A,F$8,Summary!$V:$V,0,Summary!$W:$W,">=1",Summary!$W:$W,"<=7") -> 0 | G9: =COUNTIFS(Summary!$A:$A,G$8,Summary!$V:$V,0,Summary!$W:$W,">=1",Summary!$W:$W,"<=7") -> 0 | H9: =COUNTIFS(Summary!$A:$A,H$8,Summary!$V:$V,0,Summary!$W:$W,">=1",Summary!$W:$W,"<=7") -> 0 | I9: =COUNTIFS(Summary!$A:$A,I$8,Summary!$V:$V,0,Summary!$W:$W,">=1",Summary!$W:$W,"<=7") -> 0 | J9: =COUNTIFS(Summary!$A:$A,J$8,Summary!$V:$V,0,Summary!$W:$W,">=1",Summary!$W:$W,"<=7") -> 0 | ... T9: =COUNTIFS(Summary!$A:$A,T$8,Summary!$V:$V,0,Summary!$W:$W,">=1",Summary!$W:$W,"<=7") -> 0 | U9: =SUM(C9:T9) -> 0
A10: A2 | B10: 8 to 14 days | C10: =COUNTIFS(Summary!$A:$A,C$8,Summary!$V:$V,0,Summary!$W:$W,">=8",Summary!$W:$W,"<=14") -> 1 | D10: =COUNTIFS(Summary!$A:$A,D$8,Summary!$V:$V,0,Summary!$W:$W,">=8",Summary!$W:$W,"<=14") -> 0 | E10: =COUNTIFS(Summary!$A:$A,E$8,Summary!$V:$V,0,Summary!$W:$W,">=8",Summary!$W:$W,"<=14") -> 0 | F10: =COUNTIFS(Summary!$A:$A,F$8,Summary!$V:$V,0,Summary!$W:$W,">=8",Summary!$W:$W,"<=14") -> 0 | G10: =COUNTIFS(Summary!$A:$A,G$8,Summary!$V:$V,0,Summary!$W:$W,">=8",Summary!$W:$W,"<=14") -> 0 | H10: =COUNTIFS(Summary!$A:$A,H$8,Summary!$V:$V,0,Summary!$W:$W,">=8",Summary!$W:$W,"<=14") -> 0 | I10: =COUNTIFS(Summary!$A:$A,I$8,Summary!$V:$V,0,Summary!$W:$W,">=8",Summary!$W:$W,"<=14") -> 0 | J10: =COUNTIFS(Summary!$A:$A,J$8,Summary!$V:$V,0,Summary!$W:$W,">=8",Summary!$W:$W,"<=14") -> 0 | ... T10: =COUNTIFS(Summary!$A:$A,T$8,Summary!$V:$V,0,Summary!$W:$W,">=8",Summary!$W:$W,"<=14") -> 0 | U10: =SUM(C10:T10) -> 1
A11: A3 | B11: 15 to 21 days | C11: =COUNTIFS(Summary!$A:$A,C$8,Summary!$V:$V,0,Summary!$W:$W,">=15",Summary!$W:$W,"<=21") -> 1 | D11: =COUNTIFS(Summary!$A:$A,D$8,Summary!$V:$V,0,Summary!$W:$W,">=15",Summary!$W:$W,"<=21") -> 0 | E11: =COUNTIFS(Summary!$A:$A,E$8,Summary!$V:$V,0,Summary!$W:$W,">=15",Summary!$W:$W,"<=21") -> 0 | F11: =COUNTIFS(Summary!$A:$A,F$8,Summary!$V:$V,0,Summary!$W:$W,">=15",Summary!$W:$W,"<=21") -> 0 | G11: =COUNTIFS(Summary!$A:$A,G$8,Summary!$V:$V,0,Summary!$W:$W,">=15",Summary!$W:$W,"<=21") -> 0 | H11: =COUNTIFS(Summary!$A:$A,H$8,Summary!$V:$V,0,Summary!$W:$W,">=15",Summary!$W:$W,"<=21") -> 0 | I11: =COUNTIFS(Summary!$A:$A,I$8,Summary!$V:$V,0,Summary!$W:$W,">=15",Summary!$W:$W,"<=21") -> 0 | J11: =COUNTIFS(Summary!$A:$A,J$8,Summary!$V:$V,0,Summary!$W:$W,">=15",Summary!$W:$W,"<=21") -> 0 | ... T11: =COUNTIFS(Summary!$A:$A,T$8,Summary!$V:$V,0,Summary!$W:$W,">=15",Summary!$W:$W,"<=21") -> 0 | U11: =SUM(C11:T11) -> 1
A12: A4 | B12: Exceeding 21 days | C12: =COUNTIFS(Summary!$A:$A,C$8,Summary!$V:$V,0,Summary!$W:$W,">21") -> 21 | D12: =COUNTIFS(Summary!$A:$A,D$8,Summary!$V:$V,0,Summary!$W:$W,">21") -> 0 | E12: =COUNTIFS(Summary!$A:$A,E$8,Summary!$V:$V,0,Summary!$W:$W,">21") -> 0 | F12: =COUNTIFS(Summary!$A:$A,F$8,Summary!$V:$V,0,Summary!$W:$W,">21") -> 0 | G12: =COUNTIFS(Summary!$A:$A,G$8,Summary!$V:$V,0,Summary!$W:$W,">21") -> 0 | H12: =COUNTIFS(Summary!$A:$A,H$8,Summary!$V:$V,0,Summary!$W:$W,">21") -> 0 | I12: =COUNTIFS(Summary!$A:$A,I$8,Summary!$V:$V,0,Summary!$W:$W,">21") -> 0 | J12: =COUNTIFS(Summary!$A:$A,J$8,Summary!$V:$V,0,Summary!$W:$W,">21") -> 0 | ... T12: =COUNTIFS(Summary!$A:$A,T$8,Summary!$V:$V,0,Summary!$W:$W,">21") -> 0 | U12: =SUM(C12:T12) -> 21
B13: Total | C13: =SUM(C9:C12) -> 23 | D13: =SUM(D9:D12) -> 0 | E13: =SUM(E9:E12) -> 0 | F13: =SUM(F9:F12) -> 0 | G13: =SUM(G9:G12) -> 0 | H13: =SUM(H9:H12) -> 0 | I13: =SUM(I9:I12) -> 0 | J13: =SUM(J9:J12) -> 0 | ... T13: =SUM(T9:T12) -> 0 | U13: =SUM(C13:T13) -> 23
A15: B | B15: Pending Issuance of EoT or Cost Assessment Report
A16: Action With | C16: Program_01 | D16: Program_02 | E16: Program_03 | F16: Program_04 | G16: Program_05 | H16: Program_06 | I16: Program_07 | J16: Program_08 | K16: Program_09 | L16: Program_10 | M16: Program_11 | N16: Program_12 | O16: Program_16 | P16: Program_17 | Q16: Program_18 | R16: Program_90 | S16: Program_96 | T16: Program_99 | U16: Total
A17: B1 | B17: Contractor | C17: =COUNTIFS(Summary!$A:$A,C$16,Summary!$AR:$AR,"Pending",Summary!$AT:$AT,$B17) -> 18 | D17: =COUNTIFS(Summary!$A:$A,D$16,Summary!$AR:$AR,"Pending",Summary!$AT:$AT,$B17) -> 0 | E17: =COUNTIFS(Summary!$A:$A,E$16,Summary!$AR:$AR,"Pending",Summary!$AT:$AT,$B17) -> 0 | F17: =COUNTIFS(Summary!$A:$A,F$16,Summary!$AR:$AR,"Pending",Summary!$AT:$AT,$B17) -> 0 | G17: =COUNTIFS(Summary!$A:$A,G$16,Summary!$AR:$AR,"Pending",Summary!$AT:$AT,$B17) -> 0 | H17: =COUNTIFS(Summary!$A:$A,H$16,Summary!$AR:$AR,"Pending",Summary!$AT:$AT,$B17) -> 0 | I17: =COUNTIFS(Summary!$A:$A,I$16,Summary!$AR:$AR,"Pending",Summary!$AT:$AT,$B17) -> 0 | J17: =COUNTIFS(Summary!$A:$A,J$16,Summary!$AR:$AR,"Pending",Summary!$AT:$AT,$B17) -> 0 | ... T17: =COUNTIFS(Summary!$A:$A,T$16,Summary!$AR:$AR,"Pending",Summary!$AT:$AT,$B17) -> 0 | U17: =SUM(C17:T17) -> 18
A18: B2 | B18: Engineer | C18: =COUNTIFS(Summary!$A:$A,C$16,Summary!$AR:$AR,"Pending",Summary!$AT:$AT,$B18) -> 0 | D18: =COUNTIFS(Summary!$A:$A,D$16,Summary!$AR:$AR,"Pending",Summary!$AT:$AT,$B18) -> 0 | E18: =COUNTIFS(Summary!$A:$A,E$16,Summary!$AR:$AR,"Pending",Summary!$AT:$AT,$B18) -> 0 | F18: =COUNTIFS(Summary!$A:$A,F$16,Summary!$AR:$AR,"Pending",Summary!$AT:$AT,$B18) -> 0 | G18: =COUNTIFS(Summary!$A:$A,G$16,Summary!$AR:$AR,"Pending",Summary!$AT:$AT,$B18) -> 0 | H18: =COUNTIFS(Summary!$A:$A,H$16,Summary!$AR:$AR,"Pending",Summary!$AT:$AT,$B18) -> 0 | I18: =COUNTIFS(Summary!$A:$A,I$16,Summary!$AR:$AR,"Pending",Summary!$AT:$AT,$B18) -> 0 | J18: =COUNTIFS(Summary!$A:$A,J$16,Summary!$AR:$AR,"Pending",Summary!$AT:$AT,$B18) -> 0 | ... T18: =COUNTIFS(Summary!$A:$A,T$16,Summary!$AR:$AR,"Pending",Summary!$AT:$AT,$B18) -> 0 | U18: =SUM(C18:T18) -> 0
A19: B3 | B19: Awaiting conclusion of EoT | C19: =COUNTIFS(Summary!$A:$A,C$16,Summary!$AR:$AR,"Pending",Summary!$AT:$AT,$B19) -> 8 | D19: =COUNTIFS(Summary!$A:$A,D$16,Summary!$AR:$AR,"Pending",Summary!$AT:$AT,$B19) -> 0 | E19: =COUNTIFS(Summary!$A:$A,E$16,Summary!$AR:$AR,"Pending",Summary!$AT:$AT,$B19) -> 0 | F19: =COUNTIFS(Summary!$A:$A,F$16,Summary!$AR:$AR,"Pending",Summary!$AT:$AT,$B19) -> 0 | G19: =COUNTIFS(Summary!$A:$A,G$16,Summary!$AR:$AR,"Pending",Summary!$AT:$AT,$B19) -> 0 | H19: =COUNTIFS(Summary!$A:$A,H$16,Summary!$AR:$AR,"Pending",Summary!$AT:$AT,$B19) -> 0 | I19: =COUNTIFS(Summary!$A:$A,I$16,Summary!$AR:$AR,"Pending",Summary!$AT:$AT,$B19) -> 0 | J19: =COUNTIFS(Summary!$A:$A,J$16,Summary!$AR:$AR,"Pending",Summary!$AT:$AT,$B19) -> 0 | ... T19: =COUNTIFS(Summary!$A:$A,T$16,Summary!$AR:$AR,"Pending",Summary!$AT:$AT,$B19) -> 0 | U19: =SUM(C19:T19) -> 8
A20: B4 | B20: Commercial Team | C20: =COUNTIFS(Summary!$A:$A,C$16,Summary!$AR:$AR,"Pending",Summary!$AT:$AT,$B20) -> 30 | D20: =COUNTIFS(Summary!$A:$A,D$16,Summary!$AR:$AR,"Pending",Summary!$AT:$AT,$B20) -> 0 | E20: =COUNTIFS(Summary!$A:$A,E$16,Summary!$AR:$AR,"Pending",Summary!$AT:$AT,$B20) -> 0 | F20: =COUNTIFS(Summary!$A:$A,F$16,Summary!$AR:$AR,"Pending",Summary!$AT:$AT,$B20) -> 0 | G20: =COUNTIFS(Summary!$A:$A,G$16,Summary!$AR:$AR,"Pending",Summary!$AT:$AT,$B20) -> 0 | H20: =COUNTIFS(Summary!$A:$A,H$16,Summary!$AR:$AR,"Pending",Summary!$AT:$AT,$B20) -> 0 | I20: =COUNTIFS(Summary!$A:$A,I$16,Summary!$AR:$AR,"Pending",Summary!$AT:$AT,$B20) -> 0 | J20: =COUNTIFS(Summary!$A:$A,J$16,Summary!$AR:$AR,"Pending",Summary!$AT:$AT,$B20) -> 0 | ... T20: =COUNTIFS(Summary!$A:$A,T$16,Summary!$AR:$AR,"Pending",Summary!$AT:$AT,$B20) -> 0 | U20: =SUM(C20:T20) -> 30
A21: B5 | B21: Planning Team | C21: =COUNTIFS(Summary!$A:$A,C$16,Summary!$AR:$AR,"Pending",Summary!$AT:$AT,$B21) -> 8 | D21: =COUNTIFS(Summary!$A:$A,D$16,Summary!$AR:$AR,"Pending",Summary!$AT:$AT,$B21) -> 0 | E21: =COUNTIFS(Summary!$A:$A,E$16,Summary!$AR:$AR,"Pending",Summary!$AT:$AT,$B21) -> 0 | F21: =COUNTIFS(Summary!$A:$A,F$16,Summary!$AR:$AR,"Pending",Summary!$AT:$AT,$B21) -> 0 | G21: =COUNTIFS(Summary!$A:$A,G$16,Summary!$AR:$AR,"Pending",Summary!$AT:$AT,$B21) -> 0 | H21: =COUNTIFS(Summary!$A:$A,H$16,Summary!$AR:$AR,"Pending",Summary!$AT:$AT,$B21) -> 0 | I21: =COUNTIFS(Summary!$A:$A,I$16,Summary!$AR:$AR,"Pending",Summary!$AT:$AT,$B21) -> 0 | J21: =COUNTIFS(Summary!$A:$A,J$16,Summary!$AR:$AR,"Pending",Summary!$AT:$AT,$B21) -> 0 | ... T21: =COUNTIFS(Summary!$A:$A,T$16,Summary!$AR:$AR,"Pending",Summary!$AT:$AT,$B21) -> 0 | U21: =SUM(C21:T21) -> 8
A22: B6 | B22: Claims Team | C22: =COUNTIFS(Summary!$A:$A,C$16,Summary!$AR:$AR,"Pending",Summary!$AT:$AT,$B22) -> 4 | D22: =COUNTIFS(Summary!$A:$A,D$16,Summary!$AR:$AR,"Pending",Summary!$AT:$AT,$B22) -> 0 | E22: =COUNTIFS(Summary!$A:$A,E$16,Summary!$AR:$AR,"Pending",Summary!$AT:$AT,$B22) -> 0 | F22: =COUNTIFS(Summary!$A:$A,F$16,Summary!$AR:$AR,"Pending",Summary!$AT:$AT,$B22) -> 0 | G22: =COUNTIFS(Summary!$A:$A,G$16,Summary!$AR:$AR,"Pending",Summary!$AT:$AT,$B22) -> 0 | H22: =COUNTIFS(Summary!$A:$A,H$16,Summary!$AR:$AR,"Pending",Summary!$AT:$AT,$B22) -> 0 | I22: =COUNTIFS(Summary!$A:$A,I$16,Summary!$AR:$AR,"Pending",Summary!$AT:$AT,$B22) -> 0 | J22: =COUNTIFS(Summary!$A:$A,J$16,Summary!$AR:$AR,"Pending",Summary!$AT:$AT,$B22) -> 0 | ... T22: =COUNTIFS(Summary!$A:$A,T$16,Summary!$AR:$AR,"Pending",Summary!$AT:$AT,$B22) -> 0 | U22: =SUM(C22:T22) -> 4
A23: B7 | B23: Legal Team | C23: =COUNTIFS(Summary!$A:$A,C$16,Summary!$AR:$AR,"Pending",Summary!$AT:$AT,$B23) -> 0 | D23: =COUNTIFS(Summary!$A:$A,D$16,Summary!$AR:$AR,"Pending",Summary!$AT:$AT,$B23) -> 0 | E23: =COUNTIFS(Summary!$A:$A,E$16,Summary!$AR:$AR,"Pending",Summary!$AT:$AT,$B23) -> 0 | F23: =COUNTIFS(Summary!$A:$A,F$16,Summary!$AR:$AR,"Pending",Summary!$AT:$AT,$B23) -> 0 | G23: =COUNTIFS(Summary!$A:$A,G$16,Summary!$AR:$AR,"Pending",Summary!$AT:$AT,$B23) -> 0 | H23: =COUNTIFS(Summary!$A:$A,H$16,Summary!$AR:$AR,"Pending",Summary!$AT:$AT,$B23) -> 0 | I23: =COUNTIFS(Summary!$A:$A,I$16,Summary!$AR:$AR,"Pending",Summary!$AT:$AT,$B23) -> 0 | J23: =COUNTIFS(Summary!$A:$A,J$16,Summary!$AR:$AR,"Pending",Summary!$AT:$AT,$B23) -> 0 | ... T23: =COUNTIFS(Summary!$A:$A,T$16,Summary!$AR:$AR,"Pending",Summary!$AT:$AT,$B23) -> 0 | U23: =SUM(C23:T23) -> 0
A24: B8 | B24: For Presentation to Management | C24: =COUNTIFS(Summary!$A:$A,C$16,Summary!$AR:$AR,"Pending",Summary!$AT:$AT,$B24) -> 0 | D24: =COUNTIFS(Summary!$A:$A,D$16,Summary!$AR:$AR,"Pending",Summary!$AT:$AT,$B24) -> 0 | E24: =COUNTIFS(Summary!$A:$A,E$16,Summary!$AR:$AR,"Pending",Summary!$AT:$AT,$B24) -> 0 | F24: =COUNTIFS(Summary!$A:$A,F$16,Summary!$AR:$AR,"Pending",Summary!$AT:$AT,$B24) -> 0 | G24: =COUNTIFS(Summary!$A:$A,G$16,Summary!$AR:$AR,"Pending",Summary!$AT:$AT,$B24) -> 0 | H24: =COUNTIFS(Summary!$A:$A,H$16,Summary!$AR:$AR,"Pending",Summary!$AT:$AT,$B24) -> 0 | I24: =COUNTIFS(Summary!$A:$A,I$16,Summary!$AR:$AR,"Pending",Summary!$AT:$AT,$B24) -> 0 | J24: =COUNTIFS(Summary!$A:$A,J$16,Summary!$AR:$AR,"Pending",Summary!$AT:$AT,$B24) -> 0 | ... T24: =COUNTIFS(Summary!$A:$A,T$16,Summary!$AR:$AR,"Pending",Summary!$AT:$AT,$B24) -> 0 | U24: =SUM(C24:T24) -> 0
A25: B9 | B25: Assessment in WF | C25: =COUNTIFS(Summary!$A:$A,C$16,Summary!$AR:$AR,"Pending",Summary!$AT:$AT,$B25) -> 0 | D25: =COUNTIFS(Summary!$A:$A,D$16,Summary!$AR:$AR,"Pending",Summary!$AT:$AT,$B25) -> 0 | E25: =COUNTIFS(Summary!$A:$A,E$16,Summary!$AR:$AR,"Pending",Summary!$AT:$AT,$B25) -> 0 | F25: =COUNTIFS(Summary!$A:$A,F$16,Summary!$AR:$AR,"Pending",Summary!$AT:$AT,$B25) -> 0 | G25: =COUNTIFS(Summary!$A:$A,G$16,Summary!$AR:$AR,"Pending",Summary!$AT:$AT,$B25) -> 0 | H25: =COUNTIFS(Summary!$A:$A,H$16,Summary!$AR:$AR,"Pending",Summary!$AT:$AT,$B25) -> 0 | I25: =COUNTIFS(Summary!$A:$A,I$16,Summary!$AR:$AR,"Pending",Summary!$AT:$AT,$B25) -> 0 | J25: =COUNTIFS(Summary!$A:$A,J$16,Summary!$AR:$AR,"Pending",Summary!$AT:$AT,$B25) -> 0 | ... T25: =COUNTIFS(Summary!$A:$A,T$16,Summary!$AR:$AR,"Pending",Summary!$AT:$AT,$B25) -> 0 | U25: =SUM(C25:T25) -> 0
A26: Total | C26: =SUM(C17:C25) -> 68 | D26: =SUM(D17:D25) -> 0 | E26: =SUM(E17:E25) -> 0 | F26: =SUM(F17:F25) -> 0 | G26: =SUM(G17:G25) -> 0 | H26: =SUM(H17:H25) -> 0 | I26: =SUM(I17:I25) -> 0 | J26: =SUM(J17:J25) -> 0 | ... T26: =SUM(T17:T25) -> 0 | U26: =SUM(C26:T26) -> 68
A28: C | B28: Pending Issuance of DVO/VO/CA
A29: Action With | C29: Program_01 | D29: Program_02 | E29: Program_03 | F29: Program_04 | G29: Program_05 | H29: Program_06 | I29: Program_07 | J29: Program_08 | K29: Program_09 | L29: Program_10 | M29: Program_11 | N29: Program_12 | O29: Program_16 | P29: Program_17 | Q29: Program_18 | R29: Program_90 | S29: Program_96 | T29: Program_99 | U29: Total
A30: C1 | B30: Contractor | C30: =COUNTIFS(Summary!$A:$A,C$29,Summary!$AR:$AR,"Assessment Report Issued",Summary!$AS:$AS,"Open",Summary!$AT:$AT,$B30) -> 5 | D30: =COUNTIFS(Summary!$A:$A,D$29,Summary!$AR:$AR,"Assessment Report Issued",Summary!$AS:$AS,"Open",Summary!$AT:$AT,$B30) -> 0 | E30: =COUNTIFS(Summary!$A:$A,E$29,Summary!$AR:$AR,"Assessment Report Issued",Summary!$AS:$AS,"Open",Summary!$AT:$AT,$B30) -> 0 | F30: =COUNTIFS(Summary!$A:$A,F$29,Summary!$AR:$AR,"Assessment Report Issued",Summary!$AS:$AS,"Open",Summary!$AT:$AT,$B30) -> 0 | G30: =COUNTIFS(Summary!$A:$A,G$29,Summary!$AR:$AR,"Assessment Report Issued",Summary!$AS:$AS,"Open",Summary!$AT:$AT,$B30) -> 0 | H30: =COUNTIFS(Summary!$A:$A,H$29,Summary!$AR:$AR,"Assessment Report Issued",Summary!$AS:$AS,"Open",Summary!$AT:$AT,$B30) -> 0 | I30: =COUNTIFS(Summary!$A:$A,I$29,Summary!$AR:$AR,"Assessment Report Issued",Summary!$AS:$AS,"Open",Summary!$AT:$AT,$B30) -> 0 | J30: =COUNTIFS(Summary!$A:$A,J$29,Summary!$AR:$AR,"Assessment Report Issued",Summary!$AS:$AS,"Open",Summary!$AT:$AT,$B30) -> 0 | ... T30: =COUNTIFS(Summary!$A:$A,T$29,Summary!$AR:$AR,"Assessment Report Issued",Summary!$AS:$AS,"Open",Summary!$AT:$AT,$B30) -> 0 | U30: =SUM(C30:T30) -> 5
A31: C2 | B31: Engineer | C31: =COUNTIFS(Summary!$A:$A,C$29,Summary!$AR:$AR,"Assessment Report Issued",Summary!$AS:$AS,"Open",Summary!$AT:$AT,$B31) -> 0 | D31: =COUNTIFS(Summary!$A:$A,D$29,Summary!$AR:$AR,"Assessment Report Issued",Summary!$AS:$AS,"Open",Summary!$AT:$AT,$B31) -> 0 | E31: =COUNTIFS(Summary!$A:$A,E$29,Summary!$AR:$AR,"Assessment Report Issued",Summary!$AS:$AS,"Open",Summary!$AT:$AT,$B31) -> 0 | F31: =COUNTIFS(Summary!$A:$A,F$29,Summary!$AR:$AR,"Assessment Report Issued",Summary!$AS:$AS,"Open",Summary!$AT:$AT,$B31) -> 0 | G31: =COUNTIFS(Summary!$A:$A,G$29,Summary!$AR:$AR,"Assessment Report Issued",Summary!$AS:$AS,"Open",Summary!$AT:$AT,$B31) -> 0 | H31: =COUNTIFS(Summary!$A:$A,H$29,Summary!$AR:$AR,"Assessment Report Issued",Summary!$AS:$AS,"Open",Summary!$AT:$AT,$B31) -> 0 | I31: =COUNTIFS(Summary!$A:$A,I$29,Summary!$AR:$AR,"Assessment Report Issued",Summary!$AS:$AS,"Open",Summary!$AT:$AT,$B31) -> 0 | J31: =COUNTIFS(Summary!$A:$A,J$29,Summary!$AR:$AR,"Assessment Report Issued",Summary!$AS:$AS,"Open",Summary!$AT:$AT,$B31) -> 0 | ... T31: =COUNTIFS(Summary!$A:$A,T$29,Summary!$AR:$AR,"Assessment Report Issued",Summary!$AS:$AS,"Open",Summary!$AT:$AT,$B31) -> 0 | U31: =SUM(C31:T31) -> 0
A32: C3 | B32: Commercial Team | C32: =COUNTIFS(Summary!$A:$A,C$29,Summary!$AR:$AR,"Assessment Report Issued",Summary!$AS:$AS,"Open",Summary!$AT:$AT,$B32) -> 3 | D32: =COUNTIFS(Summary!$A:$A,D$29,Summary!$AR:$AR,"Assessment Report Issued",Summary!$AS:$AS,"Open",Summary!$AT:$AT,$B32) -> 0 | E32: =COUNTIFS(Summary!$A:$A,E$29,Summary!$AR:$AR,"Assessment Report Issued",Summary!$AS:$AS,"Open",Summary!$AT:$AT,$B32) -> 0 | F32: =COUNTIFS(Summary!$A:$A,F$29,Summary!$AR:$AR,"Assessment Report Issued",Summary!$AS:$AS,"Open",Summary!$AT:$AT,$B32) -> 0 | G32: =COUNTIFS(Summary!$A:$A,G$29,Summary!$AR:$AR,"Assessment Report Issued",Summary!$AS:$AS,"Open",Summary!$AT:$AT,$B32) -> 0 | H32: =COUNTIFS(Summary!$A:$A,H$29,Summary!$AR:$AR,"Assessment Report Issued",Summary!$AS:$AS,"Open",Summary!$AT:$AT,$B32) -> 0 | I32: =COUNTIFS(Summary!$A:$A,I$29,Summary!$AR:$AR,"Assessment Report Issued",Summary!$AS:$AS,"Open",Summary!$AT:$AT,$B32) -> 0 | J32: =COUNTIFS(Summary!$A:$A,J$29,Summary!$AR:$AR,"Assessment Report Issued",Summary!$AS:$AS,"Open",Summary!$AT:$AT,$B32) -> 0 | ... T32: =COUNTIFS(Summary!$A:$A,T$29,Summary!$AR:$AR,"Assessment Report Issued",Summary!$AS:$AS,"Open",Summary!$AT:$AT,$B32) -> 0 | U32: =SUM(C32:T32) -> 3 | W32: Open Claims | Y32: Total
A33: C5 | B33: Planning Team | C33: =COUNTIFS(Summary!$A:$A,C$29,Summary!$AR:$AR,"Assessment Report Issued",Summary!$AS:$AS,"Open",Summary!$AT:$AT,$B33) -> 1 | D33: =COUNTIFS(Summary!$A:$A,D$29,Summary!$AR:$AR,"Assessment Report Issued",Summary!$AS:$AS,"Open",Summary!$AT:$AT,$B33) -> 0 | E33: =COUNTIFS(Summary!$A:$A,E$29,Summary!$AR:$AR,"Assessment Report Issued",Summary!$AS:$AS,"Open",Summary!$AT:$AT,$B33) -> 0 | F33: =COUNTIFS(Summary!$A:$A,F$29,Summary!$AR:$AR,"Assessment Report Issued",Summary!$AS:$AS,"Open",Summary!$AT:$AT,$B33) -> 0 | G33: =COUNTIFS(Summary!$A:$A,G$29,Summary!$AR:$AR,"Assessment Report Issued",Summary!$AS:$AS,"Open",Summary!$AT:$AT,$B33) -> 0 | H33: =COUNTIFS(Summary!$A:$A,H$29,Summary!$AR:$AR,"Assessment Report Issued",Summary!$AS:$AS,"Open",Summary!$AT:$AT,$B33) -> 0 | I33: =COUNTIFS(Summary!$A:$A,I$29,Summary!$AR:$AR,"Assessment Report Issued",Summary!$AS:$AS,"Open",Summary!$AT:$AT,$B33) -> 0 | J33: =COUNTIFS(Summary!$A:$A,J$29,Summary!$AR:$AR,"Assessment Report Issued",Summary!$AS:$AS,"Open",Summary!$AT:$AT,$B33) -> 0 | ... T33: =COUNTIFS(Summary!$A:$A,T$29,Summary!$AR:$AR,"Assessment Report Issued",Summary!$AS:$AS,"Open",Summary!$AT:$AT,$B33) -> 0 | U33: =SUM(C33:T33) -> 1 | W33: B + C + D | Y33: =U26+U36+U45 -> 77
A34: C6 | B34: Claims Team | C34: =COUNTIFS(Summary!$A:$A,C$29,Summary!$AR:$AR,"Assessment Report Issued",Summary!$AS:$AS,"Open",Summary!$AT:$AT,$B34) -> 0 | D34: =COUNTIFS(Summary!$A:$A,D$29,Summary!$AR:$AR,"Assessment Report Issued",Summary!$AS:$AS,"Open",Summary!$AT:$AT,$B34) -> 0 | E34: =COUNTIFS(Summary!$A:$A,E$29,Summary!$AR:$AR,"Assessment Report Issued",Summary!$AS:$AS,"Open",Summary!$AT:$AT,$B34) -> 0 | F34: =COUNTIFS(Summary!$A:$A,F$29,Summary!$AR:$AR,"Assessment Report Issued",Summary!$AS:$AS,"Open",Summary!$AT:$AT,$B34) -> 0 | G34: =COUNTIFS(Summary!$A:$A,G$29,Summary!$AR:$AR,"Assessment Report Issued",Summary!$AS:$AS,"Open",Summary!$AT:$AT,$B34) -> 0 | H34: =COUNTIFS(Summary!$A:$A,H$29,Summary!$AR:$AR,"Assessment Report Issued",Summary!$AS:$AS,"Open",Summary!$AT:$AT,$B34) -> 0 | I34: =COUNTIFS(Summary!$A:$A,I$29,Summary!$AR:$AR,"Assessment Report Issued",Summary!$AS:$AS,"Open",Summary!$AT:$AT,$B34) -> 0 | J34: =COUNTIFS(Summary!$A:$A,J$29,Summary!$AR:$AR,"Assessment Report Issued",Summary!$AS:$AS,"Open",Summary!$AT:$AT,$B34) -> 0 | ... T34: =COUNTIFS(Summary!$A:$A,T$29,Summary!$AR:$AR,"Assessment Report Issued",Summary!$AS:$AS,"Open",Summary!$AT:$AT,$B34) -> 0 | U34: =SUM(C34:T34) -> 0
A35: C7 | B35: DVO/VO in WF | C35: =COUNTIFS(Summary!$A:$A,C$29,Summary!$AR:$AR,"Assessment Report Issued",Summary!$AS:$AS,"Open",Summary!$AT:$AT,$B35) -> 0 | D35: =COUNTIFS(Summary!$A:$A,D$29,Summary!$AR:$AR,"Assessment Report Issued",Summary!$AS:$AS,"Open",Summary!$AT:$AT,$B35) -> 0 | E35: =COUNTIFS(Summary!$A:$A,E$29,Summary!$AR:$AR,"Assessment Report Issued",Summary!$AS:$AS,"Open",Summary!$AT:$AT,$B35) -> 0 | F35: =COUNTIFS(Summary!$A:$A,F$29,Summary!$AR:$AR,"Assessment Report Issued",Summary!$AS:$AS,"Open",Summary!$AT:$AT,$B35) -> 0 | G35: =COUNTIFS(Summary!$A:$A,G$29,Summary!$AR:$AR,"Assessment Report Issued",Summary!$AS:$AS,"Open",Summary!$AT:$AT,$B35) -> 0 | H35: =COUNTIFS(Summary!$A:$A,H$29,Summary!$AR:$AR,"Assessment Report Issued",Summary!$AS:$AS,"Open",Summary!$AT:$AT,$B35) -> 0 | I35: =COUNTIFS(Summary!$A:$A,I$29,Summary!$AR:$AR,"Assessment Report Issued",Summary!$AS:$AS,"Open",Summary!$AT:$AT,$B35) -> 0 | J35: =COUNTIFS(Summary!$A:$A,J$29,Summary!$AR:$AR,"Assessment Report Issued",Summary!$AS:$AS,"Open",Summary!$AT:$AT,$B35) -> 0 | ... T35: =COUNTIFS(Summary!$A:$A,T$29,Summary!$AR:$AR,"Assessment Report Issued",Summary!$AS:$AS,"Open",Summary!$AT:$AT,$B35) -> 0 | U35: =SUM(C35:T35) -> 0
A36: Total | C36: =SUM(C30:C35) -> 9 | D36: =SUM(D30:D35) -> 0 | E36: =SUM(E30:E35) -> 0 | F36: =SUM(F30:F35) -> 0 | G36: =SUM(G30:G35) -> 0 | H36: =SUM(H30:H35) -> 0 | I36: =SUM(I30:I35) -> 0 | J36: =SUM(J30:J35) -> 0 | ... T36: =SUM(T30:T35) -> 0 | U36: =SUM(C36:T36) -> 9
A38: D | B38: Pending Full Closure of Claim (Assessment Report & DVO/VO/CA Issued)
A39: Action With | C39: Program_01 | D39: Program_02 | E39: Program_03 | F39: Program_04 | G39: Program_05 | H39: Program_06 | I39: Program_07 | J39: Program_08 | K39: Program_09 | L39: Program_10 | M39: Program_11 | N39: Program_12 | O39: Program_16 | P39: Program_17 | Q39: Program_18 | R39: Program_90 | S39: Program_96 | T39: Program_99 | U39: Total
A40: D1 | B40: Contractor | C40: =COUNTIFS(Summary!$A:$A,C$39,Summary!$AR:$AR,"<>Pending",Summary!$AS:$AS,"<>Open",Summary!$AT:$AT,$B40) -> 0 | D40: =COUNTIFS(Summary!$A:$A,D$39,Summary!$AR:$AR,"<>Pending",Summary!$AS:$AS,"<>Open",Summary!$AT:$AT,$B40) -> 0 | E40: =COUNTIFS(Summary!$A:$A,E$39,Summary!$AR:$AR,"<>Pending",Summary!$AS:$AS,"<>Open",Summary!$AT:$AT,$B40) -> 0 | F40: =COUNTIFS(Summary!$A:$A,F$39,Summary!$AR:$AR,"<>Pending",Summary!$AS:$AS,"<>Open",Summary!$AT:$AT,$B40) -> 0 | G40: =COUNTIFS(Summary!$A:$A,G$39,Summary!$AR:$AR,"<>Pending",Summary!$AS:$AS,"<>Open",Summary!$AT:$AT,$B40) -> 0 | H40: =COUNTIFS(Summary!$A:$A,H$39,Summary!$AR:$AR,"<>Pending",Summary!$AS:$AS,"<>Open",Summary!$AT:$AT,$B40) -> 0 | I40: =COUNTIFS(Summary!$A:$A,I$39,Summary!$AR:$AR,"<>Pending",Summary!$AS:$AS,"<>Open",Summary!$AT:$AT,$B40) -> 0 | J40: =COUNTIFS(Summary!$A:$A,J$39,Summary!$AR:$AR,"<>Pending",Summary!$AS:$AS,"<>Open",Summary!$AT:$AT,$B40) -> 0 | ... T40: =COUNTIFS(Summary!$A:$A,T$39,Summary!$AR:$AR,"<>Pending",Summary!$AS:$AS,"<>Open",Summary!$AT:$AT,$B40) -> 0 | U40: =SUM(C40:T40) -> 0
A41: D2 | B41: Commercial Team | C41: =COUNTIFS(Summary!$A:$A,C$39,Summary!$AR:$AR,"<>Pending",Summary!$AS:$AS,"<>Open",Summary!$AT:$AT,$B41) -> 0 | D41: =COUNTIFS(Summary!$A:$A,D$39,Summary!$AR:$AR,"<>Pending",Summary!$AS:$AS,"<>Open",Summary!$AT:$AT,$B41) -> 0 | E41: =COUNTIFS(Summary!$A:$A,E$39,Summary!$AR:$AR,"<>Pending",Summary!$AS:$AS,"<>Open",Summary!$AT:$AT,$B41) -> 0 | F41: =COUNTIFS(Summary!$A:$A,F$39,Summary!$AR:$AR,"<>Pending",Summary!$AS:$AS,"<>Open",Summary!$AT:$AT,$B41) -> 0 | G41: =COUNTIFS(Summary!$A:$A,G$39,Summary!$AR:$AR,"<>Pending",Summary!$AS:$AS,"<>Open",Summary!$AT:$AT,$B41) -> 0 | H41: =COUNTIFS(Summary!$A:$A,H$39,Summary!$AR:$AR,"<>Pending",Summary!$AS:$AS,"<>Open",Summary!$AT:$AT,$B41) -> 0 | I41: =COUNTIFS(Summary!$A:$A,I$39,Summary!$AR:$AR,"<>Pending",Summary!$AS:$AS,"<>Open",Summary!$AT:$AT,$B41) -> 0 | J41: =COUNTIFS(Summary!$A:$A,J$39,Summary!$AR:$AR,"<>Pending",Summary!$AS:$AS,"<>Open",Summary!$AT:$AT,$B41) -> 0 | ... T41: =COUNTIFS(Summary!$A:$A,T$39,Summary!$AR:$AR,"<>Pending",Summary!$AS:$AS,"<>Open",Summary!$AT:$AT,$B41) -> 0 | U41: =SUM(C41:T41) -> 0
A42: D3 | B42: Planning Team | C42: =COUNTIFS(Summary!$A:$A,C$39,Summary!$AR:$AR,"<>Pending",Summary!$AS:$AS,"<>Open",Summary!$AT:$AT,$B42) -> 0 | D42: =COUNTIFS(Summary!$A:$A,D$39,Summary!$AR:$AR,"<>Pending",Summary!$AS:$AS,"<>Open",Summary!$AT:$AT,$B42) -> 0 | E42: =COUNTIFS(Summary!$A:$A,E$39,Summary!$AR:$AR,"<>Pending",Summary!$AS:$AS,"<>Open",Summary!$AT:$AT,$B42) -> 0 | F42: =COUNTIFS(Summary!$A:$A,F$39,Summary!$AR:$AR,"<>Pending",Summary!$AS:$AS,"<>Open",Summary!$AT:$AT,$B42) -> 0 | G42: =COUNTIFS(Summary!$A:$A,G$39,Summary!$AR:$AR,"<>Pending",Summary!$AS:$AS,"<>Open",Summary!$AT:$AT,$B42) -> 0 | H42: =COUNTIFS(Summary!$A:$A,H$39,Summary!$AR:$AR,"<>Pending",Summary!$AS:$AS,"<>Open",Summary!$AT:$AT,$B42) -> 0 | I42: =COUNTIFS(Summary!$A:$A,I$39,Summary!$AR:$AR,"<>Pending",Summary!$AS:$AS,"<>Open",Summary!$AT:$AT,$B42) -> 0 | J42: =COUNTIFS(Summary!$A:$A,J$39,Summary!$AR:$AR,"<>Pending",Summary!$AS:$AS,"<>Open",Summary!$AT:$AT,$B42) -> 0 | ... T42: =COUNTIFS(Summary!$A:$A,T$39,Summary!$AR:$AR,"<>Pending",Summary!$AS:$AS,"<>Open",Summary!$AT:$AT,$B42) -> 0 | U42: =SUM(C42:T42) -> 0
A43: D4 | B43: Claims Team | C43: =COUNTIFS(Summary!$A:$A,C$39,Summary!$AR:$AR,"<>Pending",Summary!$AS:$AS,"<>Open",Summary!$AT:$AT,$B43) -> 0 | D43: =COUNTIFS(Summary!$A:$A,D$39,Summary!$AR:$AR,"<>Pending",Summary!$AS:$AS,"<>Open",Summary!$AT:$AT,$B43) -> 0 | E43: =COUNTIFS(Summary!$A:$A,E$39,Summary!$AR:$AR,"<>Pending",Summary!$AS:$AS,"<>Open",Summary!$AT:$AT,$B43) -> 0 | F43: =COUNTIFS(Summary!$A:$A,F$39,Summary!$AR:$AR,"<>Pending",Summary!$AS:$AS,"<>Open",Summary!$AT:$AT,$B43) -> 0 | G43: =COUNTIFS(Summary!$A:$A,G$39,Summary!$AR:$AR,"<>Pending",Summary!$AS:$AS,"<>Open",Summary!$AT:$AT,$B43) -> 0 | H43: =COUNTIFS(Summary!$A:$A,H$39,Summary!$AR:$AR,"<>Pending",Summary!$AS:$AS,"<>Open",Summary!$AT:$AT,$B43) -> 0 | I43: =COUNTIFS(Summary!$A:$A,I$39,Summary!$AR:$AR,"<>Pending",Summary!$AS:$AS,"<>Open",Summary!$AT:$AT,$B43) -> 0 | J43: =COUNTIFS(Summary!$A:$A,J$39,Summary!$AR:$AR,"<>Pending",Summary!$AS:$AS,"<>Open",Summary!$AT:$AT,$B43) -> 0 | ... T43: =COUNTIFS(Summary!$A:$A,T$39,Summary!$AR:$AR,"<>Pending",Summary!$AS:$AS,"<>Open",Summary!$AT:$AT,$B43) -> 0 | U43: =SUM(C43:T43) -> 0
A44: D5 | B44: Legal Team | C44: =COUNTIFS(Summary!$A:$A,C$39,Summary!$AR:$AR,"<>Pending",Summary!$AS:$AS,"<>Open",Summary!$AT:$AT,$B44) -> 0 | D44: =COUNTIFS(Summary!$A:$A,D$39,Summary!$AR:$AR,"<>Pending",Summary!$AS:$AS,"<>Open",Summary!$AT:$AT,$B44) -> 0 | E44: =COUNTIFS(Summary!$A:$A,E$39,Summary!$AR:$AR,"<>Pending",Summary!$AS:$AS,"<>Open",Summary!$AT:$AT,$B44) -> 0 | F44: =COUNTIFS(Summary!$A:$A,F$39,Summary!$AR:$AR,"<>Pending",Summary!$AS:$AS,"<>Open",Summary!$AT:$AT,$B44) -> 0 | G44: =COUNTIFS(Summary!$A:$A,G$39,Summary!$AR:$AR,"<>Pending",Summary!$AS:$AS,"<>Open",Summary!$AT:$AT,$B44) -> 0 | H44: =COUNTIFS(Summary!$A:$A,H$39,Summary!$AR:$AR,"<>Pending",Summary!$AS:$AS,"<>Open",Summary!$AT:$AT,$B44) -> 0 | I44: =COUNTIFS(Summary!$A:$A,I$39,Summary!$AR:$AR,"<>Pending",Summary!$AS:$AS,"<>Open",Summary!$AT:$AT,$B44) -> 0 | J44: =COUNTIFS(Summary!$A:$A,J$39,Summary!$AR:$AR,"<>Pending",Summary!$AS:$AS,"<>Open",Summary!$AT:$AT,$B44) -> 0 | ... T44: =COUNTIFS(Summary!$A:$A,T$39,Summary!$AR:$AR,"<>Pending",Summary!$AS:$AS,"<>Open",Summary!$AT:$AT,$B44) -> 0 | U44: =SUM(C44:T44) -> 0
A45: Total | C45: =SUM(C40:C44) -> 0 | D45: =SUM(D40:D44) -> 0 | E45: =SUM(E40:E44) -> 0 | F45: =SUM(F40:F44) -> 0 | G45: =SUM(G40:G44) -> 0 | H45: =SUM(H40:H44) -> 0 | I45: =SUM(I40:I44) -> 0 | J45: =SUM(J40:J44) -> 0 | ... T45: =SUM(T40:T44) -> 0 | U45: =SUM(C45:T45) -> 0
A47: E | B47: Pending EoT Assessment Report (140 days from Fully Detailed Claim submission date)
A48: From receipt of Fully Detailed Claim | C48: Program_01 | D48: Program_02 | E48: Program_03 | F48: Program_04 | G48: Program_05 | H48: Program_06 | I48: Program_07 | J48: Program_08 | K48: Program_09 | L48: Program_10 | M48: Program_11 | N48: Program_12 | O48: Program_16 | P48: Program_17 | Q48: Program_18 | R48: Program_90 | S48: Program_96 | T48: Program_99 | U48: Total
A49: E1 | B49: With Contractor to submit FDC | C49: =COUNTIFS(Summary!$A:$A,C$48,Summary!$I:$I,"=EOT",Summary!$AR:$AR,"Pending",Summary!$AT:$AT,"=Contractor") -> 13 | D49: =COUNTIFS(Summary!$A:$A,D$48,Summary!$I:$I,"=EOT",Summary!$AR:$AR,"Pending",Summary!$AT:$AT,"=Contractor") -> 0 | E49: =COUNTIFS(Summary!$A:$A,E$48,Summary!$I:$I,"=EOT",Summary!$AR:$AR,"Pending",Summary!$AT:$AT,"=Contractor") -> 0 | F49: =COUNTIFS(Summary!$A:$A,F$48,Summary!$I:$I,"=EOT",Summary!$AR:$AR,"Pending",Summary!$AT:$AT,"=Contractor") -> 0 | G49: =COUNTIFS(Summary!$A:$A,G$48,Summary!$I:$I,"=EOT",Summary!$AR:$AR,"Pending",Summary!$AT:$AT,"=Contractor") -> 0 | H49: =COUNTIFS(Summary!$A:$A,H$48,Summary!$I:$I,"=EOT",Summary!$AR:$AR,"Pending",Summary!$AT:$AT,"=Contractor") -> 0 | I49: =COUNTIFS(Summary!$A:$A,I$48,Summary!$I:$I,"=EOT",Summary!$AR:$AR,"Pending",Summary!$AT:$AT,"=Contractor") -> 0 | J49: =COUNTIFS(Summary!$A:$A,J$48,Summary!$I:$I,"=EOT",Summary!$AR:$AR,"Pending",Summary!$AT:$AT,"=Contractor") -> 0 | ... T49: =COUNTIFS(Summary!$A:$A,T$48,Summary!$I:$I,"=EOT",Summary!$AR:$AR,"Pending",Summary!$AT:$AT,"=Contractor") -> 0 | U49: =SUM(C49:T49) -> 13
A50: E2 | B50: 1 to 45 days | C50: =COUNTIFS(Summary!$A:$A,C$57,Summary!$I:$I,"=EOT",Summary!$AR:$AR,"Pending",Summary!$BN:$BN,">=1",Summary!$BN:$BN,"<=45") -> 9 | D50: =COUNTIFS(Summary!$A:$A,D$57,Summary!$I:$I,"=EOT",Summary!$AR:$AR,"Pending",Summary!$BN:$BN,">=1",Summary!$BN:$BN,"<=45") -> 0 | E50: =COUNTIFS(Summary!$A:$A,E$57,Summary!$I:$I,"=EOT",Summary!$AR:$AR,"Pending",Summary!$BN:$BN,">=1",Summary!$BN:$BN,"<=45") -> 0 | F50: =COUNTIFS(Summary!$A:$A,F$57,Summary!$I:$I,"=EOT",Summary!$AR:$AR,"Pending",Summary!$BN:$BN,">=1",Summary!$BN:$BN,"<=45") -> 0 | G50: =COUNTIFS(Summary!$A:$A,G$57,Summary!$I:$I,"=EOT",Summary!$AR:$AR,"Pending",Summary!$BN:$BN,">=1",Summary!$BN:$BN,"<=45") -> 0 | H50: =COUNTIFS(Summary!$A:$A,H$57,Summary!$I:$I,"=EOT",Summary!$AR:$AR,"Pending",Summary!$BN:$BN,">=1",Summary!$BN:$BN,"<=45") -> 0 | I50: =COUNTIFS(Summary!$A:$A,I$57,Summary!$I:$I,"=EOT",Summary!$AR:$AR,"Pending",Summary!$BN:$BN,">=1",Summary!$BN:$BN,"<=45") -> 0 | J50: =COUNTIFS(Summary!$A:$A,J$57,Summary!$I:$I,"=EOT",Summary!$AR:$AR,"Pending",Summary!$BN:$BN,">=1",Summary!$BN:$BN,"<=45") -> 0 | ... T50: =COUNTIFS(Summary!$A:$A,T$57,Summary!$I:$I,"=EOT",Summary!$AR:$AR,"Pending",Summary!$BN:$BN,">=1",Summary!$BN:$BN,"<=45") -> 0 | U50: =SUM(C50:T50) -> 9
A51: E3 | B51: 46 to 90 days | C51: =COUNTIFS(Summary!$A:$A,C$57,Summary!$I:$I,"=EOT",Summary!$AR:$AR,"Pending",Summary!$BN:$BN,">=46",Summary!$BN:$BN,"<=90") -> 16 | D51: =COUNTIFS(Summary!$A:$A,D$57,Summary!$I:$I,"=EOT",Summary!$AR:$AR,"Pending",Summary!$BN:$BN,">=46",Summary!$BN:$BN,"<=90") -> 0 | E51: =COUNTIFS(Summary!$A:$A,E$57,Summary!$I:$I,"=EOT",Summary!$AR:$AR,"Pending",Summary!$BN:$BN,">=46",Summary!$BN:$BN,"<=90") -> 0 | F51: =COUNTIFS(Summary!$A:$A,F$57,Summary!$I:$I,"=EOT",Summary!$AR:$AR,"Pending",Summary!$BN:$BN,">=46",Summary!$BN:$BN,"<=90") -> 0 | G51: =COUNTIFS(Summary!$A:$A,G$57,Summary!$I:$I,"=EOT",Summary!$AR:$AR,"Pending",Summary!$BN:$BN,">=46",Summary!$BN:$BN,"<=90") -> 0 | H51: =COUNTIFS(Summary!$A:$A,H$57,Summary!$I:$I,"=EOT",Summary!$AR:$AR,"Pending",Summary!$BN:$BN,">=46",Summary!$BN:$BN,"<=90") -> 0 | I51: =COUNTIFS(Summary!$A:$A,I$57,Summary!$I:$I,"=EOT",Summary!$AR:$AR,"Pending",Summary!$BN:$BN,">=46",Summary!$BN:$BN,"<=90") -> 0 | J51: =COUNTIFS(Summary!$A:$A,J$57,Summary!$I:$I,"=EOT",Summary!$AR:$AR,"Pending",Summary!$BN:$BN,">=46",Summary!$BN:$BN,"<=90") -> 0 | ... T51: =COUNTIFS(Summary!$A:$A,T$57,Summary!$I:$I,"=EOT",Summary!$AR:$AR,"Pending",Summary!$BN:$BN,">=46",Summary!$BN:$BN,"<=90") -> 0 | U51: =SUM(C51:T51) -> 16
A52: E4 | B52: 91 to 140 days | C52: =COUNTIFS(Summary!$A:$A,C$57,Summary!$I:$I,"=EOT",Summary!$AR:$AR,"Pending",Summary!$BN:$BN,">=91",Summary!$BN:$BN,"<=140") -> 5 | D52: =COUNTIFS(Summary!$A:$A,D$57,Summary!$I:$I,"=EOT",Summary!$AR:$AR,"Pending",Summary!$BN:$BN,">=91",Summary!$BN:$BN,"<=140") -> 0 | E52: =COUNTIFS(Summary!$A:$A,E$57,Summary!$I:$I,"=EOT",Summary!$AR:$AR,"Pending",Summary!$BN:$BN,">=91",Summary!$BN:$BN,"<=140") -> 0 | F52: =COUNTIFS(Summary!$A:$A,F$57,Summary!$I:$I,"=EOT",Summary!$AR:$AR,"Pending",Summary!$BN:$BN,">=91",Summary!$BN:$BN,"<=140") -> 0 | G52: =COUNTIFS(Summary!$A:$A,G$57,Summary!$I:$I,"=EOT",Summary!$AR:$AR,"Pending",Summary!$BN:$BN,">=91",Summary!$BN:$BN,"<=140") -> 0 | H52: =COUNTIFS(Summary!$A:$A,H$57,Summary!$I:$I,"=EOT",Summary!$AR:$AR,"Pending",Summary!$BN:$BN,">=91",Summary!$BN:$BN,"<=140") -> 0 | I52: =COUNTIFS(Summary!$A:$A,I$57,Summary!$I:$I,"=EOT",Summary!$AR:$AR,"Pending",Summary!$BN:$BN,">=91",Summary!$BN:$BN,"<=140") -> 0 | J52: =COUNTIFS(Summary!$A:$A,J$57,Summary!$I:$I,"=EOT",Summary!$AR:$AR,"Pending",Summary!$BN:$BN,">=91",Summary!$BN:$BN,"<=140") -> 0 | ... T52: =COUNTIFS(Summary!$A:$A,T$57,Summary!$I:$I,"=EOT",Summary!$AR:$AR,"Pending",Summary!$BN:$BN,">=91",Summary!$BN:$BN,"<=140") -> 0 | U52: =SUM(C52:T52) -> 5
A53: E5 | B53: exceeding 140 days | C53: =COUNTIFS(Summary!$A:$A,C$57,Summary!$I:$I,"=EOT",Summary!$AR:$AR,"Pending",Summary!$BN:$BN,">=141") -> 7 | D53: =COUNTIFS(Summary!$A:$A,D$57,Summary!$I:$I,"=EOT",Summary!$AR:$AR,"Pending",Summary!$BN:$BN,">=141") -> 0 | E53: =COUNTIFS(Summary!$A:$A,E$57,Summary!$I:$I,"=EOT",Summary!$AR:$AR,"Pending",Summary!$BN:$BN,">=141") -> 0 | F53: =COUNTIFS(Summary!$A:$A,F$57,Summary!$I:$I,"=EOT",Summary!$AR:$AR,"Pending",Summary!$BN:$BN,">=141") -> 0 | G53: =COUNTIFS(Summary!$A:$A,G$57,Summary!$I:$I,"=EOT",Summary!$AR:$AR,"Pending",Summary!$BN:$BN,">=141") -> 0 | H53: =COUNTIFS(Summary!$A:$A,H$57,Summary!$I:$I,"=EOT",Summary!$AR:$AR,"Pending",Summary!$BN:$BN,">=141") -> 0 | I53: =COUNTIFS(Summary!$A:$A,I$57,Summary!$I:$I,"=EOT",Summary!$AR:$AR,"Pending",Summary!$BN:$BN,">=141") -> 0 | J53: =COUNTIFS(Summary!$A:$A,J$57,Summary!$I:$I,"=EOT",Summary!$AR:$AR,"Pending",Summary!$BN:$BN,">=141") -> 0 | ... T53: =COUNTIFS(Summary!$A:$A,T$57,Summary!$I:$I,"=EOT",Summary!$AR:$AR,"Pending",Summary!$BN:$BN,">=141") -> 0 | U53: =SUM(C53:T53) -> 7
A54: Total | C54: =SUM(C49:C53) -> 50 | D54: =SUM(D49:D53) -> 0 | E54: =SUM(E49:E53) -> 0 | F54: =SUM(F49:F53) -> 0 | G54: =SUM(G49:G53) -> 0 | H54: =SUM(H49:H53) -> 0 | I54: =SUM(I49:I53) -> 0 | J54: =SUM(J49:J53) -> 0 | ... T54: =SUM(T49:T53) -> 0 | U54: =SUM(C54:T54) -> 50
A56: F | B56: Pending Assessment of Cost Claims (140 days from Fully Detailed Claim submission date)
A57: From receipt of Fully Detailed Claim | C57: Program_01 | D57: Program_02 | E57: Program_03 | F57: Program_04 | G57: Program_05 | H57: Program_06 | I57: Program_07 | J57: Program_08 | K57: Program_09 | L57: Program_10 | M57: Program_11 | N57: Program_12 | O57: Program_16 | P57: Program_17 | Q57: Program_18 | R57: Program_90 | S57: Program_96 | T57: Program_99 | U57: Total
A58: F1 | B58: With Contractor to submit FDC | C58: =COUNTIFS(Summary!$A:$A,C$57,Summary!$I:$I,"<>EOT",Summary!$AR:$AR,"Pending",Summary!$AT:$AT,"=Contractor") -> 5 | D58: =COUNTIFS(Summary!$A:$A,D$57,Summary!$I:$I,"<>EOT",Summary!$AR:$AR,"Pending",Summary!$AT:$AT,"=Contractor") -> 0 | E58: =COUNTIFS(Summary!$A:$A,E$57,Summary!$I:$I,"<>EOT",Summary!$AR:$AR,"Pending",Summary!$AT:$AT,"=Contractor") -> 0 | F58: =COUNTIFS(Summary!$A:$A,F$57,Summary!$I:$I,"<>EOT",Summary!$AR:$AR,"Pending",Summary!$AT:$AT,"=Contractor") -> 0 | G58: =COUNTIFS(Summary!$A:$A,G$57,Summary!$I:$I,"<>EOT",Summary!$AR:$AR,"Pending",Summary!$AT:$AT,"=Contractor") -> 0 | H58: =COUNTIFS(Summary!$A:$A,H$57,Summary!$I:$I,"<>EOT",Summary!$AR:$AR,"Pending",Summary!$AT:$AT,"=Contractor") -> 0 | I58: =COUNTIFS(Summary!$A:$A,I$57,Summary!$I:$I,"<>EOT",Summary!$AR:$AR,"Pending",Summary!$AT:$AT,"=Contractor") -> 0 | J58: =COUNTIFS(Summary!$A:$A,J$57,Summary!$I:$I,"<>EOT",Summary!$AR:$AR,"Pending",Summary!$AT:$AT,"=Contractor") -> 0 | ... T58: =COUNTIFS(Summary!$A:$A,T$57,Summary!$I:$I,"<>EOT",Summary!$AR:$AR,"Pending",Summary!$AT:$AT,"=Contractor") -> 0 | U58: =SUM(C58:T58) -> 5
A59: F2 | B59: Awaiting conclusion of EoT | C59: =COUNTIFS(Summary!$A:$A,C$57,Summary!$I:$I,"<>EOT",Summary!$AR:$AR,"Pending",Summary!$AT:$AT,"=Awaiting conclusion of EoT") -> 8 | D59: =COUNTIFS(Summary!$A:$A,D$57,Summary!$I:$I,"<>EOT",Summary!$AR:$AR,"Pending",Summary!$AT:$AT,"=Awaiting conclusion of EoT") -> 0 | E59: =COUNTIFS(Summary!$A:$A,E$57,Summary!$I:$I,"<>EOT",Summary!$AR:$AR,"Pending",Summary!$AT:$AT,"=Awaiting conclusion of EoT") -> 0 | F59: =COUNTIFS(Summary!$A:$A,F$57,Summary!$I:$I,"<>EOT",Summary!$AR:$AR,"Pending",Summary!$AT:$AT,"=Awaiting conclusion of EoT") -> 0 | G59: =COUNTIFS(Summary!$A:$A,G$57,Summary!$I:$I,"<>EOT",Summary!$AR:$AR,"Pending",Summary!$AT:$AT,"=Awaiting conclusion of EoT") -> 0 | H59: =COUNTIFS(Summary!$A:$A,H$57,Summary!$I:$I,"<>EOT",Summary!$AR:$AR,"Pending",Summary!$AT:$AT,"=Awaiting conclusion of EoT") -> 0 | I59: =COUNTIFS(Summary!$A:$A,I$57,Summary!$I:$I,"<>EOT",Summary!$AR:$AR,"Pending",Summary!$AT:$AT,"=Awaiting conclusion of EoT") -> 0 | J59: =COUNTIFS(Summary!$A:$A,J$57,Summary!$I:$I,"<>EOT",Summary!$AR:$AR,"Pending",Summary!$AT:$AT,"=Awaiting conclusion of EoT") -> 0 | ... T59: =COUNTIFS(Summary!$A:$A,T$57,Summary!$I:$I,"<>EOT",Summary!$AR:$AR,"Pending",Summary!$AT:$AT,"=Awaiting conclusion of EoT") -> 0 | U59: =SUM(C59:T59) -> 8
A60: F3 | B60: 1 to 45 days | C60: =COUNTIFS(Summary!$A:$A,C$57,Summary!$I:$I,"<>EOT",Summary!$AR:$AR,"Pending",Summary!$BN:$BN,">=1",Summary!$BN:$BN,"<=45") -> 2 | D60: =COUNTIFS(Summary!$A:$A,D$57,Summary!$I:$I,"<>EOT",Summary!$AR:$AR,"Pending",Summary!$BN:$BN,">=1",Summary!$BN:$BN,"<=45") -> 0 | E60: =COUNTIFS(Summary!$A:$A,E$57,Summary!$I:$I,"<>EOT",Summary!$AR:$AR,"Pending",Summary!$BN:$BN,">=1",Summary!$BN:$BN,"<=45") -> 0 | F60: =COUNTIFS(Summary!$A:$A,F$57,Summary!$I:$I,"<>EOT",Summary!$AR:$AR,"Pending",Summary!$BN:$BN,">=1",Summary!$BN:$BN,"<=45") -> 0 | G60: =COUNTIFS(Summary!$A:$A,G$57,Summary!$I:$I,"<>EOT",Summary!$AR:$AR,"Pending",Summary!$BN:$BN,">=1",Summary!$BN:$BN,"<=45") -> 0 | H60: =COUNTIFS(Summary!$A:$A,H$57,Summary!$I:$I,"<>EOT",Summary!$AR:$AR,"Pending",Summary!$BN:$BN,">=1",Summary!$BN:$BN,"<=45") -> 0 | I60: =COUNTIFS(Summary!$A:$A,I$57,Summary!$I:$I,"<>EOT",Summary!$AR:$AR,"Pending",Summary!$BN:$BN,">=1",Summary!$BN:$BN,"<=45") -> 0 | J60: =COUNTIFS(Summary!$A:$A,J$57,Summary!$I:$I,"<>EOT",Summary!$AR:$AR,"Pending",Summary!$BN:$BN,">=1",Summary!$BN:$BN,"<=45") -> 0 | ... T60: =COUNTIFS(Summary!$A:$A,T$57,Summary!$I:$I,"<>EOT",Summary!$AR:$AR,"Pending",Summary!$BN:$BN,">=1",Summary!$BN:$BN,"<=45") -> 0 | U60: =SUM(C60:T60) -> 2
A61: F4 | B61: 46 to 90 days | C61: =COUNTIFS(Summary!$A:$A,C$57,Summary!$I:$I,"<>EOT",Summary!$AR:$AR,"Pending",Summary!$BN:$BN,">=46",Summary!$BN:$BN,"<=90") -> 0 | D61: =COUNTIFS(Summary!$A:$A,D$57,Summary!$I:$I,"<>EOT",Summary!$AR:$AR,"Pending",Summary!$BN:$BN,">=46",Summary!$BN:$BN,"<=90") -> 0 | E61: =COUNTIFS(Summary!$A:$A,E$57,Summary!$I:$I,"<>EOT",Summary!$AR:$AR,"Pending",Summary!$BN:$BN,">=46",Summary!$BN:$BN,"<=90") -> 0 | F61: =COUNTIFS(Summary!$A:$A,F$57,Summary!$I:$I,"<>EOT",Summary!$AR:$AR,"Pending",Summary!$BN:$BN,">=46",Summary!$BN:$BN,"<=90") -> 0 | G61: =COUNTIFS(Summary!$A:$A,G$57,Summary!$I:$I,"<>EOT",Summary!$AR:$AR,"Pending",Summary!$BN:$BN,">=46",Summary!$BN:$BN,"<=90") -> 0 | H61: =COUNTIFS(Summary!$A:$A,H$57,Summary!$I:$I,"<>EOT",Summary!$AR:$AR,"Pending",Summary!$BN:$BN,">=46",Summary!$BN:$BN,"<=90") -> 0 | I61: =COUNTIFS(Summary!$A:$A,I$57,Summary!$I:$I,"<>EOT",Summary!$AR:$AR,"Pending",Summary!$BN:$BN,">=46",Summary!$BN:$BN,"<=90") -> 0 | J61: =COUNTIFS(Summary!$A:$A,J$57,Summary!$I:$I,"<>EOT",Summary!$AR:$AR,"Pending",Summary!$BN:$BN,">=46",Summary!$BN:$BN,"<=90") -> 0 | ... T61: =COUNTIFS(Summary!$A:$A,T$57,Summary!$I:$I,"<>EOT",Summary!$AR:$AR,"Pending",Summary!$BN:$BN,">=46",Summary!$BN:$BN,"<=90") -> 0 | U61: =SUM(C61:T61) -> 0
A62: F5 | B62: 91 to 140 days | C62: =COUNTIFS(Summary!$A:$A,C$57,Summary!$I:$I,"<>EOT",Summary!$AR:$AR,"Pending",Summary!$BN:$BN,">=91",Summary!$BN:$BN,"<=140") -> 1 | D62: =COUNTIFS(Summary!$A:$A,D$57,Summary!$I:$I,"<>EOT",Summary!$AR:$AR,"Pending",Summary!$BN:$BN,">=91",Summary!$BN:$BN,"<=140") -> 0 | E62: =COUNTIFS(Summary!$A:$A,E$57,Summary!$I:$I,"<>EOT",Summary!$AR:$AR,"Pending",Summary!$BN:$BN,">=91",Summary!$BN:$BN,"<=140") -> 0 | F62: =COUNTIFS(Summary!$A:$A,F$57,Summary!$I:$I,"<>EOT",Summary!$AR:$AR,"Pending",Summary!$BN:$BN,">=91",Summary!$BN:$BN,"<=140") -> 0 | G62: =COUNTIFS(Summary!$A:$A,G$57,Summary!$I:$I,"<>EOT",Summary!$AR:$AR,"Pending",Summary!$BN:$BN,">=91",Summary!$BN:$BN,"<=140") -> 0 | H62: =COUNTIFS(Summary!$A:$A,H$57,Summary!$I:$I,"<>EOT",Summary!$AR:$AR,"Pending",Summary!$BN:$BN,">=91",Summary!$BN:$BN,"<=140") -> 0 | I62: =COUNTIFS(Summary!$A:$A,I$57,Summary!$I:$I,"<>EOT",Summary!$AR:$AR,"Pending",Summary!$BN:$BN,">=91",Summary!$BN:$BN,"<=140") -> 0 | J62: =COUNTIFS(Summary!$A:$A,J$57,Summary!$I:$I,"<>EOT",Summary!$AR:$AR,"Pending",Summary!$BN:$BN,">=91",Summary!$BN:$BN,"<=140") -> 0 | ... T62: =COUNTIFS(Summary!$A:$A,T$57,Summary!$I:$I,"<>EOT",Summary!$AR:$AR,"Pending",Summary!$BN:$BN,">=91",Summary!$BN:$BN,"<=140") -> 0 | U62: =SUM(C62:T62) -> 1
A63: F6 | B63: exceeding 140 days | C63: =COUNTIFS(Summary!$A:$A,C$57,Summary!$I:$I,"<>EOT",Summary!$AR:$AR,"Pending",Summary!$BN:$BN,">140") -> 0 | D63: =COUNTIFS(Summary!$A:$A,D$57,Summary!$I:$I,"<>EOT",Summary!$AR:$AR,"Pending",Summary!$BN:$BN,">140") -> 0 | E63: =COUNTIFS(Summary!$A:$A,E$57,Summary!$I:$I,"<>EOT",Summary!$AR:$AR,"Pending",Summary!$BN:$BN,">140") -> 0 | F63: =COUNTIFS(Summary!$A:$A,F$57,Summary!$I:$I,"<>EOT",Summary!$AR:$AR,"Pending",Summary!$BN:$BN,">140") -> 0 | G63: =COUNTIFS(Summary!$A:$A,G$57,Summary!$I:$I,"<>EOT",Summary!$AR:$AR,"Pending",Summary!$BN:$BN,">140") -> 0 | H63: =COUNTIFS(Summary!$A:$A,H$57,Summary!$I:$I,"<>EOT",Summary!$AR:$AR,"Pending",Summary!$BN:$BN,">140") -> 0 | I63: =COUNTIFS(Summary!$A:$A,I$57,Summary!$I:$I,"<>EOT",Summary!$AR:$AR,"Pending",Summary!$BN:$BN,">140") -> 0 | J63: =COUNTIFS(Summary!$A:$A,J$57,Summary!$I:$I,"<>EOT",Summary!$AR:$AR,"Pending",Summary!$BN:$BN,">140") -> 0 | ... T63: =COUNTIFS(Summary!$A:$A,T$57,Summary!$I:$I,"<>EOT",Summary!$AR:$AR,"Pending",Summary!$BN:$BN,">140") -> 0 | U63: =SUM(C63:T63) -> 0
A64: Total | C64: =SUM(C60:C63) -> 3 | D64: =SUM(D58:D63) -> 0 | E64: =SUM(E58:E63) -> 0 | F64: =SUM(F58:F63) -> 0 | G64: =SUM(G58:G63) -> 0 | H64: =SUM(H58:H63) -> 0 | I64: =SUM(I58:I63) -> 0 | J64: =SUM(J58:J63) -> 0 | K64: =SUM(K58:K63) -> 0 | ... T64: =SUM(T58:T63) -> 0 | U64: =SUM(C64:T64) -> 3
A66: G | B66: Claims Requiring DVO/VO/CA (90 days from Cost Assessment or EoT Assessment Report issued date)
A67: From issued date of Assessment Report | C67: Program_01 | D67: Program_02 | E67: Program_03 | F67: Program_04 | G67: Program_05 | H67: Program_06 | I67: Program_07 | J67: Program_08 | K67: Program_09 | L67: Program_10 | M67: Program_11 | N67: Program_12 | O67: Program_16 | P67: Program_17 | Q67: Program_18 | R67: Program_90 | S67: Program_96 | T67: Program_99 | U67: Total
A68: E1 | B68: 1 to 30 days | C68: =COUNTIFS(Summary!$A:$A,C$67,Summary!$AS:$AS,"Open",Summary!$AV:$AV,"Open",Summary!$BU:$BU,">=1",Summary!$BU:$BU,"<=30")+COUNTIFS(Summary!$A:$A,C$67,Summary!$AS:$AS,"Open",Summary!$AV:$AV,"Closed",Summary!$BU:$BU,">=1",Summary!$BU:$BU,"<=30") -> 0 | D68: =COUNTIFS(Summary!$A:$A,D$67,Summary!$AS:$AS,"Open",Summary!$AV:$AV,"Open",Summary!$BU:$BU,">=1",Summary!$BU:$BU,"<=30")+COUNTIFS(Summary!$A:$A,D$67,Summary!$AS:$AS,"Open",Summary!$AV:$AV,"Closed",Summary!$BU:$BU,">=1",Summary!$BU:$BU,"<=30") -> 0 | E68: =COUNTIFS(Summary!$A:$A,E$67,Summary!$AS:$AS,"Open",Summary!$AV:$AV,"Open",Summary!$BU:$BU,">=1",Summary!$BU:$BU,"<=30")+COUNTIFS(Summary!$A:$A,E$67,Summary!$AS:$AS,"Open",Summary!$AV:$AV,"Closed",Summary!$BU:$BU,">=1",Summary!$BU:$BU,"<=30") -> 0 | F68: =COUNTIFS(Summary!$A:$A,F$67,Summary!$AS:$AS,"Open",Summary!$AV:$AV,"Open",Summary!$BU:$BU,">=1",Summary!$BU:$BU,"<=30")+COUNTIFS(Summary!$A:$A,F$67,Summary!$AS:$AS,"Open",Summary!$AV:$AV,"Closed",Summary!$BU:$BU,">=1",Summary!$BU:$BU,"<=30") -> 0 | G68: =COUNTIFS(Summary!$A:$A,G$67,Summary!$AS:$AS,"Open",Summary!$AV:$AV,"Open",Summary!$BU:$BU,">=1",Summary!$BU:$BU,"<=30")+COUNTIFS(Summary!$A:$A,G$67,Summary!$AS:$AS,"Open",Summary!$AV:$AV,"Closed",Summary!$BU:$BU,">=1",Summary!$BU:$BU,"<=30") -> 0 | H68: =COUNTIFS(Summary!$A:$A,H$67,Summary!$AS:$AS,"Open",Summary!$AV:$AV,"Open",Summary!$BU:$BU,">=1",Summary!$BU:$BU,"<=30")+COUNTIFS(Summary!$A:$A,H$67,Summary!$AS:$AS,"Open",Summary!$AV:$AV,"Closed",Summary!$BU:$BU,">=1",Summary!$BU:$BU,"<=30") -> 0 | I68: =COUNTIFS(Summary!$A:$A,I$67,Summary!$AS:$AS,"Open",Summary!$AV:$AV,"Open",Summary!$BU:$BU,">=1",Summary!$BU:$BU,"<=30")+COUNTIFS(Summary!$A:$A,I$67,Summary!$AS:$AS,"Open",Summary!$AV:$AV,"Closed",Summary!$BU:$BU,">=1",Summary!$BU:$BU,"<=30") -> 0 | J68: =COUNTIFS(Summary!$A:$A,J$67,Summary!$AS:$AS,"Open",Summary!$AV:$AV,"Open",Summary!$BU:$BU,">=1",Summary!$BU:$BU,"<=30")+COUNTIFS(Summary!$A:$A,J$67,Summary!$AS:$AS,"Open",Summary!$AV:$AV,"Closed",Summary!$BU:$BU,">=1",Summary!$BU:$BU,"<=30") -> 0 | ... T68: =COUNTIFS(Summary!$A:$A,T$67,Summary!$AS:$AS,"Open",Summary!$AV:$AV,"Open",Summary!$BU:$BU,">=1",Summary!$BU:$BU,"<=30")+COUNTIFS(Summary!$A:$A,T$67,Summary!$AS:$AS,"Open",Summary!$AV:$AV,"Closed",Summary!$BU:$BU,">=1",Summary!$BU:$BU,"<=30") -> 0 | U68: =SUM(C68:T68) -> 0
A69: E2 | B69: 31 to 60 days | C69: =COUNTIFS(Summary!$A:$A,C$67,Summary!$AS:$AS,"Open",Summary!$AV:$AV,"Open",Summary!$BU:$BU,">30",Summary!$BU:$BU,"<=60")+COUNTIFS(Summary!$A:$A,C$67,Summary!$AS:$AS,"Open",Summary!$AV:$AV,"Closed",Summary!$BU:$BU,">30",Summary!$BU:$BU,"<=60") -> 0 | D69: =COUNTIFS(Summary!$A:$A,D$67,Summary!$AS:$AS,"Open",Summary!$AV:$AV,"Open",Summary!$BU:$BU,">30",Summary!$BU:$BU,"<=60")+COUNTIFS(Summary!$A:$A,D$67,Summary!$AS:$AS,"Open",Summary!$AV:$AV,"Closed",Summary!$BU:$BU,">30",Summary!$BU:$BU,"<=60") -> 0 | E69: =COUNTIFS(Summary!$A:$A,E$67,Summary!$AS:$AS,"Open",Summary!$AV:$AV,"Open",Summary!$BU:$BU,">30",Summary!$BU:$BU,"<=60")+COUNTIFS(Summary!$A:$A,E$67,Summary!$AS:$AS,"Open",Summary!$AV:$AV,"Closed",Summary!$BU:$BU,">30",Summary!$BU:$BU,"<=60") -> 0 | F69: =COUNTIFS(Summary!$A:$A,F$67,Summary!$AS:$AS,"Open",Summary!$AV:$AV,"Open",Summary!$BU:$BU,">30",Summary!$BU:$BU,"<=60")+COUNTIFS(Summary!$A:$A,F$67,Summary!$AS:$AS,"Open",Summary!$AV:$AV,"Closed",Summary!$BU:$BU,">30",Summary!$BU:$BU,"<=60") -> 0 | G69: =COUNTIFS(Summary!$A:$A,G$67,Summary!$AS:$AS,"Open",Summary!$AV:$AV,"Open",Summary!$BU:$BU,">30",Summary!$BU:$BU,"<=60")+COUNTIFS(Summary!$A:$A,G$67,Summary!$AS:$AS,"Open",Summary!$AV:$AV,"Closed",Summary!$BU:$BU,">30",Summary!$BU:$BU,"<=60") -> 0 | H69: =COUNTIFS(Summary!$A:$A,H$67,Summary!$AS:$AS,"Open",Summary!$AV:$AV,"Open",Summary!$BU:$BU,">30",Summary!$BU:$BU,"<=60")+COUNTIFS(Summary!$A:$A,H$67,Summary!$AS:$AS,"Open",Summary!$AV:$AV,"Closed",Summary!$BU:$BU,">30",Summary!$BU:$BU,"<=60") -> 0 | I69: =COUNTIFS(Summary!$A:$A,I$67,Summary!$AS:$AS,"Open",Summary!$AV:$AV,"Open",Summary!$BU:$BU,">30",Summary!$BU:$BU,"<=60")+COUNTIFS(Summary!$A:$A,I$67,Summary!$AS:$AS,"Open",Summary!$AV:$AV,"Closed",Summary!$BU:$BU,">30",Summary!$BU:$BU,"<=60") -> 0 | J69: =COUNTIFS(Summary!$A:$A,J$67,Summary!$AS:$AS,"Open",Summary!$AV:$AV,"Open",Summary!$BU:$BU,">30",Summary!$BU:$BU,"<=60")+COUNTIFS(Summary!$A:$A,J$67,Summary!$AS:$AS,"Open",Summary!$AV:$AV,"Closed",Summary!$BU:$BU,">30",Summary!$BU:$BU,"<=60") -> 0 | ... T69: =COUNTIFS(Summary!$A:$A,T$67,Summary!$AS:$AS,"Open",Summary!$AV:$AV,"Open",Summary!$BU:$BU,">30",Summary!$BU:$BU,"<=60")+COUNTIFS(Summary!$A:$A,T$67,Summary!$AS:$AS,"Open",Summary!$AV:$AV,"Closed",Summary!$BU:$BU,">30",Summary!$BU:$BU,"<=60") -> 0 | U69: =SUM(C69:T69) -> 0
A70: E3 | B70: 61 to 90 days | C70: =COUNTIFS(Summary!$A:$A,C$67,Summary!$AS:$AS,"Open",Summary!$AV:$AV,"Open",Summary!$AS:$AS,"Open",Summary!$BU:$BU,">60",Summary!$BU:$BU,"<=90")+COUNTIFS(Summary!$A:$A,C$67,Summary!$AS:$AS,"Open",Summary!$AV:$AV,"Closed",Summary!$AS:$AS,"Open",Summary!$BU:$BU,">60",Summary!$BU:$BU,"<=90") -> 0 | D70: =COUNTIFS(Summary!$A:$A,D$67,Summary!$AS:$AS,"Open",Summary!$AV:$AV,"Open",Summary!$AS:$AS,"Open",Summary!$BU:$BU,">60",Summary!$BU:$BU,"<=90")+COUNTIFS(Summary!$A:$A,D$67,Summary!$AS:$AS,"Open",Summary!$AV:$AV,"Closed",Summary!$AS:$AS,"Open",Summary!$BU:$BU,">60",Summary!$BU:$BU,"<=90") -> 0 | E70: =COUNTIFS(Summary!$A:$A,E$67,Summary!$AS:$AS,"Open",Summary!$AV:$AV,"Open",Summary!$AS:$AS,"Open",Summary!$BU:$BU,">60",Summary!$BU:$BU,"<=90")+COUNTIFS(Summary!$A:$A,E$67,Summary!$AS:$AS,"Open",Summary!$AV:$AV,"Closed",Summary!$AS:$AS,"Open",Summary!$BU:$BU,">60",Summary!$BU:$BU,"<=90") -> 0 | F70: =COUNTIFS(Summary!$A:$A,F$67,Summary!$AS:$AS,"Open",Summary!$AV:$AV,"Open",Summary!$AS:$AS,"Open",Summary!$BU:$BU,">60",Summary!$BU:$BU,"<=90")+COUNTIFS(Summary!$A:$A,F$67,Summary!$AS:$AS,"Open",Summary!$AV:$AV,"Closed",Summary!$AS:$AS,"Open",Summary!$BU:$BU,">60",Summary!$BU:$BU,"<=90") -> 0 | G70: =COUNTIFS(Summary!$A:$A,G$67,Summary!$AS:$AS,"Open",Summary!$AV:$AV,"Open",Summary!$AS:$AS,"Open",Summary!$BU:$BU,">60",Summary!$BU:$BU,"<=90")+COUNTIFS(Summary!$A:$A,G$67,Summary!$AS:$AS,"Open",Summary!$AV:$AV,"Closed",Summary!$AS:$AS,"Open",Summary!$BU:$BU,">60",Summary!$BU:$BU,"<=90") -> 0 | H70: =COUNTIFS(Summary!$A:$A,H$67,Summary!$AS:$AS,"Open",Summary!$AV:$AV,"Open",Summary!$AS:$AS,"Open",Summary!$BU:$BU,">60",Summary!$BU:$BU,"<=90")+COUNTIFS(Summary!$A:$A,H$67,Summary!$AS:$AS,"Open",Summary!$AV:$AV,"Closed",Summary!$AS:$AS,"Open",Summary!$BU:$BU,">60",Summary!$BU:$BU,"<=90") -> 0 | I70: =COUNTIFS(Summary!$A:$A,I$67,Summary!$AS:$AS,"Open",Summary!$AV:$AV,"Open",Summary!$AS:$AS,"Open",Summary!$BU:$BU,">60",Summary!$BU:$BU,"<=90")+COUNTIFS(Summary!$A:$A,I$67,Summary!$AS:$AS,"Open",Summary!$AV:$AV,"Closed",Summary!$AS:$AS,"Open",Summary!$BU:$BU,">60",Summary!$BU:$BU,"<=90") -> 0 | J70: =COUNTIFS(Summary!$A:$A,J$67,Summary!$AS:$AS,"Open",Summary!$AV:$AV,"Open",Summary!$AS:$AS,"Open",Summary!$BU:$BU,">60",Summary!$BU:$BU,"<=90")+COUNTIFS(Summary!$A:$A,J$67,Summary!$AS:$AS,"Open",Summary!$AV:$AV,"Closed",Summary!$AS:$AS,"Open",Summary!$BU:$BU,">60",Summary!$BU:$BU,"<=90") -> 0 | ... T70: =COUNTIFS(Summary!$A:$A,T$67,Summary!$AS:$AS,"Open",Summary!$AV:$AV,"Open",Summary!$AS:$AS,"Open",Summary!$BU:$BU,">60",Summary!$BU:$BU,"<=90")+COUNTIFS(Summary!$A:$A,T$67,Summary!$AS:$AS,"Open",Summary!$AV:$AV,"Closed",Summary!$AS:$AS,"Open",Summary!$BU:$BU,">60",Summary!$BU:$BU,"<=90") -> 0 | U70: =SUM(C70:T70) -> 0
A71: E4 | B71: Exceeding 90 days | C71: =COUNTIFS(Summary!$A:$A,C$67,Summary!$AS:$AS,"Open",Summary!$AV:$AV,"Open",Summary!$AS:$AS,"Open",Summary!$BU:$BU,">90")+COUNTIFS(Summary!$A:$A,C$67,Summary!$AS:$AS,"Open",Summary!$AV:$AV,"Closed",Summary!$AS:$AS,"Open",Summary!$BU:$BU,">60") -> 0 | D71: =COUNTIFS(Summary!$A:$A,D$67,Summary!$AS:$AS,"Open",Summary!$AV:$AV,"Open",Summary!$AS:$AS,"Open",Summary!$BU:$BU,">90")+COUNTIFS(Summary!$A:$A,D$67,Summary!$AS:$AS,"Open",Summary!$AV:$AV,"Closed",Summary!$AS:$AS,"Open",Summary!$BU:$BU,">60") -> 0 | E71: =COUNTIFS(Summary!$A:$A,E$67,Summary!$AS:$AS,"Open",Summary!$AV:$AV,"Open",Summary!$AS:$AS,"Open",Summary!$BU:$BU,">90")+COUNTIFS(Summary!$A:$A,E$67,Summary!$AS:$AS,"Open",Summary!$AV:$AV,"Closed",Summary!$AS:$AS,"Open",Summary!$BU:$BU,">60") -> 0 | F71: =COUNTIFS(Summary!$A:$A,F$67,Summary!$AS:$AS,"Open",Summary!$AV:$AV,"Open",Summary!$AS:$AS,"Open",Summary!$BU:$BU,">90")+COUNTIFS(Summary!$A:$A,F$67,Summary!$AS:$AS,"Open",Summary!$AV:$AV,"Closed",Summary!$AS:$AS,"Open",Summary!$BU:$BU,">60") -> 0 | G71: =COUNTIFS(Summary!$A:$A,G$67,Summary!$AS:$AS,"Open",Summary!$AV:$AV,"Open",Summary!$AS:$AS,"Open",Summary!$BU:$BU,">90")+COUNTIFS(Summary!$A:$A,G$67,Summary!$AS:$AS,"Open",Summary!$AV:$AV,"Closed",Summary!$AS:$AS,"Open",Summary!$BU:$BU,">60") -> 0 | H71: =COUNTIFS(Summary!$A:$A,H$67,Summary!$AS:$AS,"Open",Summary!$AV:$AV,"Open",Summary!$AS:$AS,"Open",Summary!$BU:$BU,">90")+COUNTIFS(Summary!$A:$A,H$67,Summary!$AS:$AS,"Open",Summary!$AV:$AV,"Closed",Summary!$AS:$AS,"Open",Summary!$BU:$BU,">60") -> 0 | I71: =COUNTIFS(Summary!$A:$A,I$67,Summary!$AS:$AS,"Open",Summary!$AV:$AV,"Open",Summary!$AS:$AS,"Open",Summary!$BU:$BU,">90")+COUNTIFS(Summary!$A:$A,I$67,Summary!$AS:$AS,"Open",Summary!$AV:$AV,"Closed",Summary!$AS:$AS,"Open",Summary!$BU:$BU,">60") -> 0 | J71: =COUNTIFS(Summary!$A:$A,J$67,Summary!$AS:$AS,"Open",Summary!$AV:$AV,"Open",Summary!$AS:$AS,"Open",Summary!$BU:$BU,">90")+COUNTIFS(Summary!$A:$A,J$67,Summary!$AS:$AS,"Open",Summary!$AV:$AV,"Closed",Summary!$AS:$AS,"Open",Summary!$BU:$BU,">60") -> 0 | ... T71: =COUNTIFS(Summary!$A:$A,T$67,Summary!$AS:$AS,"Open",Summary!$AV:$AV,"Open",Summary!$AS:$AS,"Open",Summary!$BU:$BU,">90")+COUNTIFS(Summary!$A:$A,T$67,Summary!$AS:$AS,"Open",Summary!$AV:$AV,"Closed",Summary!$AS:$AS,"Open",Summary!$BU:$BU,">60") -> 0 | U71: =SUM(C71:T71) -> 0
A72: Total | C72: =SUM(C68:C71) -> 0 | D72: =SUM(D68:D71) -> 0 | E72: =SUM(E68:E71) -> 0 | F72: =SUM(F68:F71) -> 0 | G72: =SUM(G68:G71) -> 0 | H72: =SUM(H68:H71) -> 0 | I72: =SUM(I68:I71) -> 0 | J72: =SUM(J68:J71) -> 0 | ... T72: =SUM(T68:T71) -> 0 | U72: =SUM(C72:T72) -> 0

Sheet Summary
A2: Claims Tracker (Contractor's Claims) | BE2: Pre-TIA Report (CM / Claims Team) | BI2: TIA Assessment (Planning Team)
A3: RSG-CM-FRM-0018 | AS3: Pending Action with: | BF3: - 1 to 25 days | BJ3: - 1 to 7 days
AS4: Contractor | AT4: {=SUMPRODUCT(SUBTOTAL(3,OFFSET($AT$16:$AT$194,ROW($AT$16:$AT$194)-ROW($AT$16),0,1)),--($AT$16:$AT$194=$AS4))} -> 24 | BF4: - 26 to 50 days | BJ4: - 8 to 14 days
B5: Program No.: | C5: Programs 1 - 16 | E5: Programs 1 - 16 | AS5: Engineer | AT5: {=SUMPRODUCT(SUBTOTAL(3,OFFSET($AT$16:$AT$194,ROW($AT$16:$AT$194)-ROW($AT$16),0,1)),--($AT$16:$AT$194=$AS5))} -> 0 | BF5: - 51 to 70 days | BJ5: - 15 to 21 days
B6: Program Name: | C6: AMAALA | E6: AMAALA | G6: =IF(Program_01!F6="Insert Entry Date for Newly Added Claims","Insert Entry Date for Newly Added Claims in Prog 01",IF([1]Program_02!F6="Insert Entry Date for Newly Added Claims","Insert Entry Date for Newly Added Claims in Prog 02",IF([1]Program_03!F6="Insert Entry Date for Newly Added Claims,","Insert Entry Date for Newly Added Claims in Prog 03",IF([1]Program_04!F6="Insert Entry Date for Newly Added Claims","Insert Entry Date for Newly Added Claims in Prog 04",IF([1]Program_05!F6="Insert Entry Date for Newly Added Claims","Insert Entry Date for Newly Added Claims in Prog 05",IF([1]Program_06!F6="Insert Entry Date for Newly Added Claims","Insert Entry Date for Newly Added Claims in Prog 06",IF([1]Program_07!F6="Insert Entry Date for Newly Added Claims","Insert Entry Date for Newly Added Claims in Prog 07",IF([1]Program_08!F6="Insert Entry Date for Newly Added Claims","Insert Entry Date for Newly Added Claims in Prog 08",IF([1]Program_09!F6="Insert Entry Date for Newly Added Claims","Insert Entry Date for Newly Added Claims in Prog 09",IF([1]Program_10!F6="Insert Entry Date for Newly Added Claims","Insert Entry Date for Newly Added Claims in Prog 10",IF([1]Program_11!F6="Insert Entry Date for Newly Added Claims","Insert Entry Date for Newly Added Claims in Prog 11",IF([1]Program_12!F6="Insert Entry Date for Newly Added Claims","Insert Entry Date for Newly Added Claims in Prog 12",IF([1]Program_16!F6="Insert Entry Date for Newly Added Claims","Insert Entry Date for Newly Added Claims in Prog 16",""))))))))))))) | AS6: Commercial Team | AT6: {=SUMPRODUCT(SUBTOTAL(3,OFFSET($AT$16:$AT$194,ROW($AT$16:$AT$194)-ROW($AT$16),0,1)),--($AT$16:$AT$194=$AS6))} -> 33 | BF6: - exceeding 70 days | BJ6: - exceeding 21 days
B7: Claims Tracker as of: | C7: 46162 | E7: 45904 | W7: Claim Initial Response Letter: | AS7: Planning Team | AT7: {=SUMPRODUCT(SUBTOTAL(3,OFFSET($AT$16:$AT$194,ROW($AT$16:$AT$194)-ROW($AT$16),0,1)),--($AT$16:$AT$194=$AS7))} -> 9 | BM7: Assessment Report: | BP7: HLEAR Assessment Report: | BU7: DVO/VO/CA:
Y8: - 1 to 7 days | AS8: Claims Team | AT8: {=SUMPRODUCT(SUBTOTAL(3,OFFSET($AT$16:$AT$194,ROW($AT$16:$AT$194)-ROW($AT$16),0,1)),--($AT$16:$AT$194=$AS8))} -> 4 | BE8: Finalization of Report (CM / Claims Team) | BN8: - 1 to 45 days | BQ8: - 1 to 25 days | BV8: - 1 to 30 days
Y9: - 8 to 14 days | AS9: Legal Team | AT9: {=SUMPRODUCT(SUBTOTAL(3,OFFSET($AT$16:$AT$194,ROW($AT$16:$AT$194)-ROW($AT$16),0,1)),--($AT$16:$AT$194=$AS9))} -> 0 | BF9: - 1 to 3 days | BN9: - 46 to 90 days | BQ9: - 26 to 50 days | BV9: - 31 to 60 days
Y10: - 15 to 21 days | AS10: For Presentation to Management | AT10: {=SUMPRODUCT(SUBTOTAL(3,OFFSET($AT$16:$AT$194,ROW($AT$16:$AT$194)-ROW($AT$16),0,1)),--($AT$16:$AT$194=$AS10))} -> 0 | AV10: OPEN | AW10: OPEN | BF10: - 4 to 6 days | BN10: - 91 to 140 days | BQ10: - 51 to 75 days | BV10: - 61 to 90 days
Y11: - exceeding 21 days | AS11: Cost claim awaiting conclusion of EoT | AT11: {=SUMPRODUCT(SUBTOTAL(3,OFFSET($AT$16:$AT$194,ROW($AT$16:$AT$194)-ROW($AT$16),0,1)),--($AT$16:$AT$194=$AS11))} -> 0 | AV11: {=SUMPRODUCT(SUBTOTAL(3,OFFSET($AV$17:$AV$194,ROW($AV$17:$AV$194)-ROW($AV$17),0,1)),--($AV$17:$AV$194=$AV10))} -> 0 | AW11: {=SUMPRODUCT(SUBTOTAL(3,OFFSET($AW$17:$AW$194,ROW($AW$17:$AW$194)-ROW($AW$17),0,1)),--($AW$17:$AW$194=$AW10))} -> 83 | BF11: - 7 to 10 days | BN11: - exceeding 140 days | BQ11: - exceeding 75 days | BV11: - exceeding 90 days
AM12: Notice of Dissatisfaction | AO12: {=SUMPRODUCT(SUBTOTAL(3,OFFSET($AN$17:$AN$194,ROW($AN$17:$AN$194)-ROW($AN$17),0,1)),--($AN$17:$AN$194="Yes"))} -> 7 | AS12: Assessment in WF | AT12: {=SUMPRODUCT(SUBTOTAL(3,OFFSET($AT$16:$AT$194,ROW($AT$16:$AT$194)-ROW($AT$16),0,1)),--($AT$16:$AT$194=$AS12))} -> 3 | AV12: CLOSED | AW12: CLOSED | BF12: - exceeding 10 days
AM13: Notice of Dispute | AO13: {=SUMPRODUCT(SUBTOTAL(3,OFFSET($AO$17:$AO$194,ROW($AO$17:$AO$194)-ROW($AO$17),0,1)),--($AO$17:$AO$194="Yes"))} -> 4 | AS13: DVO/VO in WF | AT13: {=SUMPRODUCT(SUBTOTAL(3,OFFSET($AT$16:$AT$194,ROW($AT$16:$AT$194)-ROW($AT$16),0,1)),--($AT$16:$AT$194=$AS13))} -> 0 | AV13: {=SUMPRODUCT(SUBTOTAL(3,OFFSET($AV$17:$AV$194,ROW($AV$17:$AV$194)-ROW($AV$17),0,1)),--($AV$17:$AV$194=$AV12))} -> 9 | AW13: {=SUMPRODUCT(SUBTOTAL(3,OFFSET($AW$17:$AW$194,ROW($AW$17:$AW$194)-ROW($AW$17),0,1)),--($AW$17:$AW$194=$AW12))} -> 70
BD14: CM / Claims Team | BF14: Planning Team | BH14: CM / Claims Team
A15: Details | J15: Claim Type | Q15: Claim Submitted by the Contractor | U15: 21 calendar days from Date of First Submission | Y15: Period of Consultation with Contractor re particulars, etc. (Period Varies) | AA15: Employer's Assessment (should be 30 calendar days from Date of Fully Detailed Claim) | AF15: Clause 3.5 | AJ15: DVO/VO /Contract Amendment | AM15: Rejected on Merit or Revise & Resubmit | AN15: Notice of Dissatisfaction Yes or No | AO15: Notice of Dispute Yes or No | AR15: Claim Status / Action / Remarks | AV15: Open Claims as of | AW15: Claims From | AY15: Contractor Claim / RSG Assessment / DVO | BC15: Claims Intermediate KPIs | BK15: 140 Days KPI (EOT or Cost Assessment Report Issued to Contractor) | BT15: 90 Days KPI (DVO/VO/CA Issued to Contractor) | CA15: =COUNTIF(CA18:CA194,"Y") -> 50 | CB15: =COUNTIF(CB18:CB194,"Y") -> 7 | CG15: =SUBTOTAL(9,CG17:CG194) -> 1.6353672e+08 | CH15: =SUBTOTAL(9,CH17:CH194) -> 25901926
A16: Program | B16: Item | C16: Assessment Type | D16: Contract No. | E16: Asset Code | F16: Project Name | G16: Scope | H16: Contractor Name | I16: Claim Type | J16: EOT | K16: Prolongation | L16: Disruption | M16: Acceleration | N16: NOD | O16: Other Claims | Q16: Claim Title | R16: Contractor's Claim (Reference) | S16: Contractor's Claim Submission (Date) | U16: RSG Initial Response (Reference) | V16: RSG Initial Response (Date) | W16: Period between Contractor's Submission & Engineer / Employer's Initial Response | Y16: Last Action Date / Type of Discussion [letters, workshops, emails, meetings, etc.] | AA16: Fully Detailed Claim (FDC) Submitted by Contractor (Reference) | AB16: Contractor's FDC Submission (Date) | AC16: Employer's FDC Response / Assessment Report (Reference) | AD16: Employer's FDC Response (Date) | AF16: Agree (Reference) | AG16: Agree (Date) | AH16: Determination (Reference) | AI16: Determination (Date) | AJ16: DVO/VO/CA (Reference) | AK16: DVO/VO/CA (Date) | AQ16: Discretionary EOT | AR16: Status 1 | AS16: Status 2 | AT16: Action | AU16: Remarks | AV16: 45291 | AW16: 45292 | AY16: Contractor's FDC Submission (Date) | AZ16: RSG Assessment Report (Date) | BA16: DVO/VO/ CA (Date) | BC16: EAR / HLEAR Start Date | BD16: EAR / HLEAR Pre-TIA (No. of Days and Date) | BF16: EAR / HLEAR TIA Assessment (No. of Days and Date) | BH16: EAR / HLEAR / COST EAR Finalization (No. of Days and Date) | BK16: KPI Report Closure Month (MM-YY) | BL16: Discretionary EOT Closure Month (MM-YY) | BM16: 140 days from Contractor's Claim FDC submission to DEOT issued | BN16: Days from Contractor's Claim FDC submission | BO16: Days taken for Final Claims Closed | BP16: Total Claims Closed | BQ16: Days taken for Final Claims Under Process > 140 days | BR16: Days taken for Final Claims Under Process > 140 days | BT16: KPI Report Closure Month (MM-YY) | BU16: 90 days from Assessment Report | BV16: Days taken for Final Claims Closed | BW16: Total Claims Closed | BX16: Days taken for Final Claims Under Process > 90 days | BY16: Total Claims Under Process > 90 days | CA16: Report Issued? | CB16: DVO/VO/CA Issued? | CC16: Date of Entry in the Tracker | CG16: Cost Claimd by the Contractor | CH16: AMAALA Assessment | CI16: Status A
A18: PROGRAM 01
A19: Program_01 | B19: 1 | C19: =IFERROR(INDEX(Program_01!$B:$B,MATCH($B19,Program_01!$A:$A,0)),"") -> FULL TIA EAR | D19: =IFERROR(INDEX(Program_01!D:D,MATCH($B19,Program_01!A:A,0)),"") -> 1TB01003C14 | E19: =IFERROR(INDEX(Program_01!$E:$E,MATCH($B19,Program_01!$A:$A,0)),"") -> 1.TB.01.003.01 | F19: =IFERROR(INDEX(Program_01!$F:$F,MATCH($B19,Program_01!$A:$A,0)),"") -> AMAALA Yacht Club | G19: =IFERROR(INDEX(Program_01!$G:$G,MATCH($B19,Program_01!$A:$A,0)),"") -> Triple Bay Piling - Beach, RSMLI, Yacht Club and Marina Village Precinct (Hotel 1 and 2) | H19: =IFERROR(INDEX(Program_01!$H:$H,MATCH($B19,Program_01!$A:$A,0)),"") -> NSCC International Saudi Contracting | I19: =IFERROR(IF($D19="","",INDEX($J$16:$O$16,MATCH(1,J19:O19,0))),"") -> EOT | J19: =IFERROR(INDEX(Program_01!$I:$I,MATCH($B19,Program_01!$A:$A,0)),"") -> 1 | K19: =IFERROR(INDEX(Program_01!$J:$J,MATCH($B19,Program_01!$A:$A,0)),"") -> 0 | L19: =IFERROR(INDEX(Program_01!$K:$K,MATCH($B19,Program_01!$A:$A,0)),"") -> 0 | M19: =IFERROR(INDEX(Program_01!$L:$L,MATCH($B19,Program_01!$A:$A,0)),"") -> 0 | N19: =IFERROR(INDEX(Program_01!$L:$L,MATCH($B19,Program_01!$A:$A,0)),"") -> 0 | O19: =IFERROR(INDEX(Program_01!$N:$N,MATCH($B19,Program_01!$A:$A,0)),"") -> 0 | Q19: =IFERROR(INDEX(Program_01!$C:$C,MATCH($B19,Program_01!$A:$A,0)),"") -> NSCC Consolidated Claim - All Plots (Time) | R19: =IFERROR(INDEX(Program_01!$V:$V,MATCH($B19,Program_01!$A:$A,0)),"") -> TB04400-005C13-NSC-LTR-0326 | S19: =IFERROR(INDEX(Program_01!$W:$W,MATCH($B19,Program_01!$A:$A,0)),"") -> 45045 | U19: =IFERROR(INDEX(Program_01!$Z:$Z,MATCH($B19,Program_01!$A:$A,0)),"") -> Not responded | V19: =IFERROR(INDEX(Program_01!$AA:$AA,MATCH($B19,Program_01!$A:$A,0)),"") -> N/A | W19: =IF(OR($S19="",$V19="N/A"),"",IF(AND($S19<>0,$V19=0),TODAY()-$S19,IF(AND($S19<>"",$V19<>""),$V19-$S19))) | Y19: =IFERROR(INDEX(Program_01!$BD:$BD,MATCH($B19,Program_01!$A:$A,0)),"") -> 0 | AA19: =IFERROR(IF((INDEX(Program_01!$AD:$AD,MATCH($B19,Program_01!$A:$A,0))=""),INDEX(Program_01!$V:$V,MATCH($B19,Program_01!$A:$A,0)),INDEX(Program_01!$AD:$AD,MATCH($B19,Program_01!$A:$A,0))),"") -> 1TB04400-005C13-NSC-LTR-0395 | AB19: =IFERROR(IF((INDEX(Program_01!$AE:$AE,MATCH($B19,Program_01!$A:$A,0))=""),INDEX(Program_01!$W:$W,MATCH($B19,Program_01!$A:$A,0)),INDEX(Program_01!$AE:$AE,MATCH($B19,Program_01!$A:$A,0))),"") -> 45241 | AC19: =IFERROR(IF($I19="EOT",INDEX(Program_01!$AN:$AN,MATCH($B19,Program_01!$A:$A,0)),INDEX(Program_01!$AY:$AY,MATCH($B19,Program_01!$A:$A,0))),"") -> TB04400-031D03-WSP-LTR-0138 | AD19: =IFERROR(IF($I19="EOT",INDEX(Program_01!$AO:$AO,MATCH($B19,Program_01!$A:$A,0)),INDEX(Program_01!$AZ:$AZ,MATCH($B19,Program_01!$A:$A,0))),"") -> 45243 | AH19: =IF(OR($D19="",$AS19="VO Issued",$AS19="Open"),"",IF(OR($AC19="Rejected",$AC19="Superseded",$AC19="Dealt Separately"),$AC19,IF($I19="EOT",INDEX(Program_01!$AR:$AR,MATCH($B19,Program_01!$A:$A,0)),INDEX(Program_01!$BB:$BB,MATCH($B19,Program_01!$A:$A,0))))) -> TB04400-031D03-WSP-LTR-0138 | AI19: =IF(OR($A19="",$B19="",$I19="",$AS19="VO Issued",$AS19="Open"),"",IF(OR($AD19="N/A"),$AD19,IF($I19="EOT",INDEX(Program_01!$AS:$AS,MATCH($B19,Program_01!$A:$A,0)),INDEX(Program_01!$BC:$BC,MATCH($B19,Program_01!$A:$A,0))))) -> 45243 | AJ19: =IF(OR($D19="",$I19="",$AS19="Determination Issued",$AS19="Rejected",$AS19="Open"),"",IF(OR($AH19="Rejected",$AH19="Dealt Separately",$AH19="Superseded",$AH19="Withdrawn"),"N/A",IF($I19="EOT",INDEX(Program_01!AR:AR,MATCH($B19,Program_01!A:A,0)),INDEX(Program_01!BB:BB,MATCH($B19,Program_01!A:A,0))))) | AK19: =IF(OR($A19="",$B19="",$I19="",$AS19="Determination Issued",$AS19="Rejected",$AS19="Open"),"",IF($AJ19="N/A","N/A",IF($I19="EOT",INDEX(Program_01!AS:AS,MATCH($B19,Program_01!A:A,0)),INDEX(Program_01!BC:BC,MATCH($B19,Program_01!A:A,0))))) | AM19: =IFERROR(INDEX(Program_01!$BT:$BT,MATCH($B19,Program_01!$A:$A,0)),"") -> 0 | AN19: =IFERROR(INDEX(Program_01!$BU:$BU,MATCH($B19,Program_01!$A:$A,0)),"") -> 0 | AO19: =IFERROR(INDEX(Program_01!$BV:$BV,MATCH($B19,Program_01!$A:$A,0)),"") -> 0 | AP19: =IF(OR($AN19="Yes",$AO19="Yes"),"1","") | AQ19: =IFERROR(INDEX(Program_01!$BN:$BN,MATCH($B19,Program_01!$A:$A,0)),"") -> 0 | AR19: =IFERROR(INDEX(Program_01!$BO:$BO,MATCH($B19,Program_01!$A:$A,0)),"") -> Assessment Report Issued | AS19: =IFERROR(INDEX(Program_01!$BP:$BP,MATCH($B19,Program_01!$A:$A,0)),"") -> Determination Issued | AT19: =IFERROR(INDEX(Program_01!$BQ:$BQ,MATCH($B19,Program_01!$A:$A,0)),"") -> Closed | AU19: =IFERROR(INDEX(Program_01!$BR:$BR,MATCH($B19,Program_01!$A:$A,0)),"") -> Assessment and determination issued on 13 Nov 23. | AV19: =IF($I19="","",IF($S19>$AV$16,"",IF($AS19="OPEN","OPEN",IF($AS19="","",IF(AND($AS19<>"OPEN",$AT19="CLOSED"),"CLOSED",IF(AND($AS19<>"OPEN",$AT19<>"CLOSED"),"OPEN","")))))) -> CLOSED | AW19: =IF($I19="","",IF($S19<$AW$16,"",IF($AS19="OPEN","OPEN",IF($AS19="","",IF(AND($AS19<>"OPEN",$AT19="CLOSED"),"CLOSED",IF(AND($AS19<>"OPEN",$AT19<>"CLOSED"),"OPEN","")))))) | AX19: =IF(OR($AV19="OPEN",$AV19="CLOSED"),$AV19,$AW19) -> CLOSED | AY19: =IF(C19="HLEAR",BC19,AB19) -> 45241 | AZ19: =IF($AD19=0,"",AD19) -> 45243 | BA19: =IF(AND($AI19="",$AK19=""),"",IF($AI19="",$AK19,$AI19)) -> 45243 | BC19: =IFERROR(INDEX(Program_01!BF:BF,MATCH($B19,Program_01!$A:$A,0)),"") -> 45241 | BD19: =IFERROR(INDEX(Program_01!BG:BG,MATCH($B19,Program_01!$A:$A,0)),"") -> N/A | BE19: =IFERROR(INDEX(Program_01!BH:BH,MATCH($B19,Program_01!$A:$A,0)),"") -> 0 | BF19: =IFERROR(INDEX(Program_01!BI:BI,MATCH($B19,Program_01!$A:$A,0)),"") -> 0 | BG19: =IFERROR(INDEX(Program_01!BJ:BJ,MATCH($B19,Program_01!$A:$A,0)),"") -> 0 | BH19: =IFERROR(INDEX(Program_01!BK:BK,MATCH($B19,Program_01!$A:$A,0)),"") -> 0 | BI19: =IFERROR(INDEX(Program_01!BL:BL,MATCH($B19,Program_01!$A:$A,0)),"") -> 0 | BK19: =IFERROR(IF(INDEX(Program_01!$BX:$BX,MATCH($B19,Program_01!$A:$A,0))=DATE(1900,1,0),"",INDEX(Program_01!$BX:$BX,MATCH($B19,Program_01!$A:$A,0))),"") -> 45260 | BL19: =IFERROR(IF(INDEX(Program_01!$BY:$BY,MATCH($B19,Program_01!$A:$A,0))=DATE(1900,1,0),"",INDEX(Program_01!$BY:$BY,MATCH($B19,Program_01!$A:$A,0))),"") | BM19: =IF(OR($AZ19="",$AZ19="N/A"),"",IF(AND($AZ19="",$AY19<>""),TODAY()-$AY19,$AZ19-$AY19)) -> 2 | BN19: =IF(OR($C19="DEOT",$C19="N/A",$I19=""),"",IF(OR($AM19="Revise & resubmit",$AT19="Awaiting Conclusion of EoT",$AR19="Not Applicable",$AY19=0,$AY19="TBA",$AZ19="N/A",AY19=0),0,IF(AND($AR19="Assessment Report Issued",$AT19<>""),$AZ19-$AY19,IF(AND($AR19="Pending",$AT19="Contractor"),"",IF(AND($AZ19="",$AY19<>""),TODAY()-$AY19,$AZ19-$AY19))))) -> 2 | BO19: =IF(OR($AR19<>"ASSESSMENT REPORT ISSUED"),"",IF($BN19<>"",$BN19,"")) -> 2 | BP19: =IF($AR19="ASSESSMENT REPORT ISSUED","1",IF(AND($AT19="Closed",$AR19<>"Pending"),"1","")) -> 1 | BQ19: =IF(AND($AR19="Pending",$BN19>140),$BN19,"") | BR19: =IF(BQ19="","","1") | BT19: =IFERROR(IF(INDEX(Program_01!$BZ:$BZ,MATCH($B19,Program_01!$A:$A,0))=DATE(1900,1,0),"",INDEX(Program_01!$BZ:$BZ,MATCH($B19,Program_01!$A:$A,0))),"") | BU19: =IF(OR($I19="",$AV19="",$AM19<>0,$BA19="N/A",$AZ19=""),"",IF(AND($BA19="",$AZ19<>""),TODAY()-$AZ19,$BA19-$AZ19)) -> 0 | BV19: =IF(OR($AS19="Determination Issued",$AS19="VO Issued"),$BU19,"") -> 0 | BW19: =IF(OR($AT19="CLOSED",$AS19="Determination Issued",$AS19="VO Issued"),"1","") -> 1 | BX19: =IF(OR($AS19="Determination Issued",$AS19="VO Issued",$AS19="Rejected",$AS19="Canceled",$AS19="Superseded",$AS19="Not Applicable",$BU19=""),"",IF($BU19>90,$BU19,"")) | BY19: =IF(BX19="","","1") | CA19: =IF($I19="","",IF(AND($AR19="Assessment Report Issued",$AZ19<>""),"Y","N")) -> Y | CB19: =IF($I19="","",IF(OR($AS19="Determination Issued",$AS19="VO Issued"),"Y","N")) -> Y | CC19: =IFERROR(INDEX(Program_01!$CE:$CE,MATCH($B19,Program_01!$A:$A,0)),"") -> 0 | CD19: =MAX(S19,CC19) -> 45045 | CG19: =IFERROR(INDEX(Program_01!$AT:$AT,MATCH($B19,Program_01!$A:$A,0)),"") -> 0 | CH19: =IFERROR(INDEX(Program_01!$AX:$AX,MATCH($B19,Program_01!$A:$A,0)),"") -> 0
A20: Program_01 | B20: 2 | C20: =IFERROR(INDEX(Program_01!$B:$B,MATCH($B20,Program_01!$A:$A,0)),"") -> COST EAR | D20: =IFERROR(INDEX(Program_01!$D:$D,MATCH($B20,Program_01!$A:$A,0)),"") -> 1TB01003C14 | E20: =IFERROR(INDEX(Program_01!$E:$E,MATCH($B20,Program_01!$A:$A,0)),"") -> 1.TB.01.003.01 | F20: =IFERROR(INDEX(Program_01!$F:$F,MATCH($B20,Program_01!$A:$A,0)),"") -> AMAALA Yacht Club | G20: =IFERROR(INDEX(Program_01!$G:$G,MATCH($B20,Program_01!$A:$A,0)),"") -> Triple Bay Piling - Beach, RSMLI, Yacht Club and Marina Village Precinct (Hotel 1 and 2) | H20: =IFERROR(INDEX(Program_01!$H:$H,MATCH($B20,Program_01!$A:$A,0)),"") -> NSCC International Saudi Contracting | I20: =IFERROR(IF($D20="","",INDEX($J$16:$O$16,MATCH(1,J20:O20,0))),"") -> Prolongation | J20: =IFERROR(INDEX(Program_01!$I:$I,MATCH($B20,Program_01!$A:$A,0)),"") -> 0 | K20: =IFERROR(INDEX(Program_01!$J:$J,MATCH($B20,Program_01!$A:$A,0)),"") -> 1 | L20: =IFERROR(INDEX(Program_01!$K:$K,MATCH($B20,Program_01!$A:$A,0)),"") -> 0 | M20: =IFERROR(INDEX(Program_01!$L:$L,MATCH($B20,Program_01!$A:$A,0)),"") -> 0 | N20: =IFERROR(INDEX(Program_01!$L:$L,MATCH($B20,Program_01!$A:$A,0)),"") -> 0 | O20: =IFERROR(INDEX(Program_01!$N:$N,MATCH($B20,Program_01!$A:$A,0)),"") -> 0 | Q20: =IFERROR(INDEX(Program_01!$C:$C,MATCH($B20,Program_01!$A:$A,0)),"") -> NSCC Consolidated Claim - All Plots (Cost) | R20: =IFERROR(INDEX(Program_01!$V:$V,MATCH($B20,Program_01!$A:$A,0)),"") -> 1TB04400-005C13-NSC-LTR-0326 | S20: =IFERROR(INDEX(Program_01!$W:$W,MATCH($B20,Program_01!$A:$A,0)),"") -> 45045 | U20: =IFERROR(INDEX(Program_01!$Z:$Z,MATCH($B20,Program_01!$A:$A,0)),"") -> Not responded | V20: =IFERROR(INDEX(Program_01!$AA:$AA,MATCH($B20,Program_01!$A:$A,0)),"") -> N/A | W20: =IF(OR($S20="",$V20="N/A"),"",IF(AND($S20<>0,$V20=0),TODAY()-$S20,IF(AND($S20<>"",$V20<>""),$V20-$S20))) | Y20: =IFERROR(INDEX(Program_01!$BD:$BD,MATCH($B20,Program_01!$A:$A,0)),"") -> 1TB04400-005C13-NSC-LTR-0326 dated 29 Apr 23 1TB04400-005C13-NSC-LTR-0386 dated 09 Oct 23 1TB04400-005C13-NSC-LTR-0393 dated 28 Oct 23 1TB04400-005C13-NSC-LTR-0395 dated 01 Nov 23 1TB04400-005C13-NSC-LTR-0400 dated 20 Feb 24 1TB04400-400000-WSP-LTR-0002 dated 26 Feb 24 requesting HO overhead particulars. 1TB04400-005C13-NSC-LTR-0401 dated 26 Feb 24 submission of requested documents. 1TB04400-005C13-NSC-LTR-0403 dated 04 Jul 24 | AA20: =IFERROR(IF((INDEX(Program_01!$AD:$AD,MATCH($B20,Program_01!$A:$A,0))=""),INDEX(Program_01!$V:$V,MATCH($B20,Program_01!$A:$A,0)),INDEX(Program_01!$AD:$AD,MATCH($B20,Program_01!$A:$A,0))),"") -> 1TB04400-005C13-NSC-LTR-0395 dated 11 Nov 23 1TB04400-005C13-NSC-LTR-0401 dated 26 Feb 24 1TB04400-005C13-NSC-LTR-0403 04 Jul 24 RFA Signoff | AB20: =IFERROR(IF((INDEX(Program_01!$AE:$AE,MATCH($B20,Program_01!$A:$A,0))=""),INDEX(Program_01!$W:$W,MATCH($B20,Program_01!$A:$A,0)),INDEX(Program_01!$AE:$AE,MATCH($B20,Program_01!$A:$A,0))),"") -> 45509 | AC20: =IFERROR(IF($I20="EOT",INDEX(Program_01!$AN:$AN,MATCH($B20,Program_01!$A:$A,0)),INDEX(Program_01!$AY:$AY,MATCH($B20,Program_01!$A:$A,0))),"") -> 1TB04400-400000-AMA-LTR-0056 | AD20: =IFERROR(IF($I20="EOT",INDEX(Program_01!$AO:$AO,MATCH($B20,Program_01!$A:$A,0)),INDEX(Program_01!$AZ:$AZ,MATCH($B20,Program_01!$A:$A,0))),"") -> 45578 | AH20: =IF(OR($D20="",$AS20="VO Issued",$AS20="Open"),"",IF(OR($AC20="Rejected",$AC20="Superseded",$AC20="Dealt Separately"),$AC20,IF($I20="EOT",INDEX(Program_01!$AR:$AR,MATCH($B20,Program_01!$A:$A,0)),INDEX(Program_01!$BB:$BB,MATCH($B20,Program_01!$A:$A,0))))) -> 1TB04400-400000-AMA-DVO-CM-0002 - DVO 013 | AI20: =IF(OR($A20="",$B20="",$I20="",$AS20="VO Issued",$AS20="Open"),"",IF(OR($AD20="N/A"),$AD20,IF($I20="EOT",INDEX(Program_01!$AS:$AS,MATCH($B20,Program_01!$A:$A,0)),INDEX(Program_01!$BC:$BC,MATCH($B20,Program_01!$A:$A,0))))) -> 45585 | AJ20: =IF(OR($D20="",$I20="",$AS20="Determination Issued",$AS20="Rejected",$AS20="Open"),"",IF(OR($AH20="Rejected",$AH20="Dealt Separately",$AH20="Superseded",$AH20="Withdrawn"),"N/A",IF($I20="EOT",INDEX(Program_01!AR:AR,MATCH($B20,Program_01!A:A,0)),INDEX(Program_01!BB:BB,MATCH($B20,Program_01!A:A,0))))) -> 1TB04400-400000-AMA-DVO-CM-0002 - DVO 013 | AK20: =IF(OR($A20="",$B20="",$I20="",$AS20="Determination Issued",$AS20="Rejected",$AS20="Open"),"",IF($AJ20="N/A","N/A",IF($I20="EOT",INDEX(Program_01!AS:AS,MATCH($B20,Program_01!A:A,0)),INDEX(Program_01!BC:BC,MATCH($B20,Program_01!A:A,0))))) -> 45585 | AM20: =IFERROR(INDEX(Program_01!$BT:$BT,MATCH($B20,Program_01!$A:$A,0)),"") -> 0 | AN20: =IFERROR(INDEX(Program_01!$BU:$BU,MATCH($B20,Program_01!$A:$A,0)),"") -> 0 | AO20: =IFERROR(INDEX(Program_01!$BV:$BV,MATCH($B20,Program_01!$A:$A,0)),"") -> 0 | AP20: =IF(OR($AN20="Yes",$AO20="Yes"),"1","") | AQ20: =IFERROR(INDEX(Program_01!$BN:$BN,MATCH($B20,Program_01!$A:$A,0)),"") -> 0 | AR20: =IFERROR(INDEX(Program_01!$BO:$BO,MATCH($B20,Program_01!$A:$A,0)),"") -> Assessment Report Issued | AS20: =IFERROR(INDEX(Program_01!$BP:$BP,MATCH($B20,Program_01!$A:$A,0)),"") -> DVO Issued | AT20: =IFERROR(INDEX(Program_01!$BQ:$BQ,MATCH($B20,Program_01!$A:$A,0)),"") -> Closed | AU20: =IFERROR(INDEX(Program_01!$BR:$BR,MATCH($B20,Program_01!$A:$A,0)),"") -> 29 Jul 24: Commercial leads and senior managment meeting with NSCC to close out final account 12 August 2024 : Final Account Settlment RFA currently in progress, once approved the commercial claims report will be updated to make reference to the approved RFA and submitted for approval. 26 Aug 24: No update available (Blake on Leave) 8 Sep 2024 - Commercial report is currently in WF for approval reflecting the approved RFA final settlement amount RFA 1TB04400-400000-AMA-RFA-CM-0004 dated 5 Aug 24 24 Sep 24: Assessment report in WF-004674 07 Oct 24: Assessment report approved by GCEO. However, it will not be issued to the contractor. as the EoT Costs contained within, form part of the previously agreed and GCEO signed off final account settlement of SAR 108,561,603. a DVO for the Final account settlemetent under preperation. commercial to prepare teh cover letter & issue it to the contractor ASAP 13 Oct 24: Report issued to NSCC via letter ref 1TB04400-400000-AMA-LTR-0056 14 Oct 24: NSCC issued the acceptance letter, Commercial to issue the final account DVO 09 Oct 24: DVO issued to contractor. 10 Oct 24: DVO signed by the contractor NOTE: RFA for Final Account Settlment Signed off and therefore this item is now considered closed | AV20: =IF($I20="","",IF($S20>$AV$16,"",IF($AS20="OPEN","OPEN",IF($AS20="","",IF(AND($AS20<>"OPEN",$AT20="CLOSED"),"CLOSED",IF(AND($AS20<>"OPEN",$AT20<>"CLOSED"),"OPEN","")))))) -> CLOSED | AW20: =IF($I20="","",IF($S20<$AW$16,"",IF($AS20="OPEN","OPEN",IF($AS20="","",IF(AND($AS20<>"OPEN",$AT20="CLOSED"),"CLOSED",IF(AND($AS20<>"OPEN",$AT20<>"CLOSED"),"OPEN","")))))) | AX20: =IF(OR($AV20="OPEN",$AV20="CLOSED"),$AV20,$AW20) -> CLOSED | AY20: =IF(C20="HLEAR",BC20,AB20) -> 45509 | AZ20: =IF($AD20=0,"",AD20) -> 45578 | BA20: =IF(AND($AI20="",$AK20=""),"",IF($AI20="",$AK20,$AI20)) -> 45585 | BC20: =IFERROR(INDEX(Program_01!BF:BF,MATCH($B20,Program_01!$A:$A,0)),"") -> 45509 | BD20: =IFERROR(INDEX(Program_01!BG:BG,MATCH($B20,Program_01!$A:$A,0)),"") -> N/A | BE20: =IFERROR(INDEX(Program_01!BH:BH,MATCH($B20,Program_01!$A:$A,0)),"") -> 0 | BF20: =IFERROR(INDEX(Program_01!BI:BI,MATCH($B20,Program_01!$A:$A,0)),"") -> N/A | BG20: =IFERROR(INDEX(Program_01!BJ:BJ,MATCH($B20,Program_01!$A:$A,0)),"") -> 0 | BH20: =IFERROR(INDEX(Program_01!BK:BK,MATCH($B20,Program_01!$A:$A,0)),"") -> 0 | BI20: =IFERROR(INDEX(Program_01!BL:BL,MATCH($B20,Program_01!$A:$A,0)),"") -> 0 | BK20: =IFERROR(IF(INDEX(Program_01!$BX:$BX,MATCH($B20,Program_01!$A:$A,0))=DATE(1900,1,0),"",INDEX(Program_01!$BX:$BX,MATCH($B20,Program_01!$A:$A,0))),"") -> 45578 | BL20: =IFERROR(IF(INDEX(Program_01!$BY:$BY,MATCH($B20,Program_01!$A:$A,0))=DATE(1900,1,0),"",INDEX(Program_01!$BY:$BY,MATCH($B20,Program_01!$A:$A,0))),"") | BM20: =IF(OR($AZ20="",$AZ20="N/A"),"",IF(AND($AZ20="",$AY20<>""),TODAY()-$AY20,$AZ20-$AY20)) -> 69 | BN20: =IF(OR($C20="DEOT",$C20="N/A",$I20=""),"",IF(OR($AM20="Revise & resubmit",$AT20="Awaiting Conclusion of EoT",$AR20="Not Applicable",$AY20=0,$AY20="TBA",$AZ20="N/A",AY20=0),0,IF(AND($AR20="Assessment Report Issued",$AT20<>""),$AZ20-$AY20,IF(AND($AR20="Pending",$AT20="Contractor"),"",IF(AND($AZ20="",$AY20<>""),TODAY()-$AY20,$AZ20-$AY20))))) -> 69 | BO20: =IF(OR($AR20<>"ASSESSMENT REPORT ISSUED"),"",IF($BN20<>"",$BN20,"")) -> 69 | BP20: =IF($AR20="ASSESSMENT REPORT ISSUED","1",IF(AND($AT20="Closed",$AR20<>"Pending"),"1","")) -> 1 | BQ20: =IF(AND($AR20="Pending",$BN20>140),$BN20,"") | BR20: =IF(BQ20="","","1") | BT20: =IFERROR(IF(INDEX(Program_01!$BZ:$BZ,MATCH($B20,Program_01!$A:$A,0))=DATE(1900,1,0),"",INDEX(Program_01!$BZ:$BZ,MATCH($B20,Program_01!$A:$A,0))),"") -> 45585 | BU20: =IF(OR($I20="",$AV20="",$AM20<>0,$BA20="N/A",$AZ20=""),"",IF(AND($BA20="",$AZ20<>""),TODAY()-$AZ20,$BA20-$AZ20)) -> 7 | BV20: =IF(OR($AS20="Determination Issued",$AS20="VO Issued"),$BU20,"") | BW20: =IF(OR($AT20="CLOSED",$AS20="Determination Issued",$AS20="VO Issued"),"1","") -> 1 | BX20: =IF(OR($AS20="Determination Issued",$AS20="VO Issued",$AS20="Rejected",$AS20="Canceled",$AS20="Superseded",$AS20="Not Applicable",$BU20=""),"",IF($BU20>90,$BU20,"")) | BY20: =IF(BX20="","","1") | CA20: =IF($I20="","",IF(AND($AR20="Assessment Report Issued",$AZ20<>""),"Y","N")) -> Y | CB20: =IF($I20="","",IF(OR($AS20="Determination Issued",$AS20="VO Issued"),"Y","N")) -> N | CC20: =IFERROR(INDEX(Program_01!$CE:$CE,MATCH($B20,Program_01!$A:$A,0)),"") -> 0 | CD20: =MAX(S20,CC20) -> 45045 | CG20: =IFERROR(INDEX(Program_01!$AT:$AT,MATCH($B20,Program_01!$A:$A,0)),"") -> 653085.79 | CH20: =IFERROR(INDEX(Program_01!$AX:$AX,MATCH($B20,Program_01!$A:$A,0)),"") -> 10071304 | CI20: Assessment Report Issued
A21: Program_01 | B21: 3 | C21: =IFERROR(INDEX(Program_01!$B:$B,MATCH($B21,Program_01!$A:$A,0)),"") -> FULL TIA EAR | D21: =IFERROR(INDEX(Program_01!$D:$D,MATCH($B21,Program_01!$A:$A,0)),"") -> 1TB01002C01 | E21: =IFERROR(INDEX(Program_01!$E:$E,MATCH($B21,Program_01!$A:$A,0)),"") -> 1.TB.01.002.01 | F21: =IFERROR(INDEX(Program_01!$F:$F,MATCH($B21,Program_01!$A:$A,0)),"") -> Marina Lifestyle Hotel & Village | G21: =IFERROR(INDEX(Program_01!$G:$G,MATCH($B21,Program_01!$A:$A,0)),"") -> Triple Bay Wide Ground Improvement | H21: =IFERROR(INDEX(Program_01!$H:$H,MATCH($B21,Program_01!$A:$A,0)),"") -> Soil Improvement Contracting | I21: =IFERROR(IF($D21="","",INDEX($J$16:$O$16,MATCH(1,J21:O21,0))),"") -> EOT | J21: =IFERROR(INDEX(Program_01!$I:$I,MATCH($B21,Program_01!$A:$A,0)),"") -> 1 | K21: =IFERROR(INDEX(Program_01!$J:$J,MATCH($B21,Program_01!$A:$A,0)),"") -> 0 | L21: =IFERROR(INDEX(Program_01!$K:$K,MATCH($B21,Program_01!$A:$A,0)),"") -> 0 | M21: =IFERROR(INDEX(Program_01!$L:$L,MATCH($B21,Program_01!$A:$A,0)),"") -> 0 | N21: =IFERROR(INDEX(Program_01!$L:$L,MATCH($B21,Program_01!$A:$A,0)),"") -> 0 | O21: =IFERROR(INDEX(Program_01!$N:$N,MATCH($B21,Program_01!$A:$A,0)),"") -> 0 | Q21: =IFERROR(INDEX(Program_01!$C:$C,MATCH($B21,Program_01!$A:$A,0)),"") -> Consolidated Claim - EOT (Delay in IFC's) | R21: =IFERROR(INDEX(Program_01!$V:$V,MATCH($B21,Program_01!$A:$A,0)),"") -> 1TB04004-004C03-SIC-LTR-0018 | S21: =IFERROR(INDEX(Program_01!$W:$W,MATCH($B21,Program_01!$A:$A,0)),"") -> 44702 | U21: =IFERROR(INDEX(Program_01!$Z:$Z,MATCH($B21,Program_01!$A:$A,0)),"") -> 1TB04004-004C03-SAP-LTR-0027 | V21: =IFERROR(INDEX(Program_01!$AA:$AA,MATCH($B21,Program_01!$A:$A,0)),"") -> 44710 | W21: =IF(OR($S21="",$V21="N/A"),"",IF(AND($S21<>0,$V21=0),TODAY()-$S21,IF(AND($S21<>"",$V21<>""),$V21-$S21))) -> 8 | Y21: =IFERROR(INDEX(Program_01!$BD:$BD,MATCH($B21,Program_01!$A:$A,0)),"") -> WF-016414 Name: TB Wide - Ground Improvement Works - SIC - Marina Lifestyle Hotel - Employer's Assessment Report - EOT 06 (1TB04004-004C03-AMA-RPT-CM-0005) 09 May 24: Contractor accepted the Employer's EOT assessment report via letter ref 1TB04004-004CO3-SIC-LTR-113 | AA21: =IFERROR(IF((INDEX(Program_01!$AD:$AD,MATCH($B21,Program_01!$A:$A,0))=""),INDEX(Program_01!$V:$V,MATCH($B21,Program_01!$A:$A,0)),INDEX(Program_01!$AD:$AD,MATCH($B21,Program_01!$A:$A,0))),"") -> 1TB04004-004C03-SIC-LTR-0043 dated 03-Sep-2022 1TB04004-004C03-SIC-LTR-0103 | AB21: =IFERROR(IF((INDEX(Program_01!$AE:$AE,MATCH($B21,Program_01!$A:$A,0))=""),INDEX(Program_01!$W:$W,MATCH($B21,Program_01!$A:$A,0)),INDEX(Program_01!$AE:$AE,MATCH($B21,Program_01!$A:$A,0))),"") -> 45111 | AC21: =IFERROR(IF($I21="EOT",INDEX(Program_01!$AN:$AN,MATCH($B21,Program_01!$A:$A,0)),INDEX(Program_01!$AY:$AY,MATCH($B21,Program_01!$A:$A,0))),"") -> 1TB04004-004C03-AMA-LTR-0007 | AD21: =IFERROR(IF($I21="EOT",INDEX(Program_01!$AO:$AO,MATCH($B21,Program_01!$A:$A,0)),INDEX(Program_01!$AZ:$AZ,MATCH($B21,Program_01!$A:$A,0))),"") -> 45407 | AH21: =IF(OR($D21="",$AS21="VO Issued",$AS21="Open"),"",IF(OR($AC21="Rejected",$AC21="Superseded",$AC21="Dealt Separately"),$AC21,IF($I21="EOT",INDEX(Program_01!$AR:$AR,MATCH($B21,Program_01!$A:$A,0)),INDEX(Program_01!$BB:$BB,MATCH($B21,Program_01!$A:$A,0))))) -> AMA04004-GENCORR-000738 1TB04004-004C03-AMA-DVO-CM-0004[C0]-MLH - EOT No.6 for GI Works (Time only) | AI21: =IF(OR($A21="",$B21="",$I21="",$AS21="VO Issued",$AS21="Open"),"",IF(OR($AD21="N/A"),$AD21,IF($I21="EOT",INDEX(Program_01!$AS:$AS,MATCH($B21,Program_01!$A:$A,0)),INDEX(Program_01!$BC:$BC,MATCH($B21,Program_01!$A:$A,0))))) -> 45545 | AJ21: =IF(OR($D21="",$I21="",$AS21="Determination Issued",$AS21="Rejected",$AS21="Open"),"",IF(OR($AH21="Rejected",$AH21="Dealt Separately",$AH21="Superseded",$AH21="Withdrawn"),"N/A",IF($I21="EOT",INDEX(Program_01!AR:AR,MATCH($B21,Program_01!A:A,0)),INDEX(Program_01!BB:BB,MATCH($B21,Program_01!A:A,0))))) -> AMA04004-GENCORR-000738 1TB04004-004C03-AMA-DVO-CM-0004[C0]-MLH - EOT No.6 for GI Works (Time only) | AK21: =IF(OR($A21="",$B21="",$I21="",$AS21="Determination Issued",$AS21="Rejected",$AS21="Open"),"",IF($AJ21="N/A","N/A",IF($I21="EOT",INDEX(Program_01!AS:AS,MATCH($B21,Program_01!A:A,0)),INDEX(Program_01!BC:BC,MATCH($B21,Program_01!A:A,0))))) -> 45545 | AM21: =IFERROR(INDEX(Program_01!$BT:$BT,MATCH($B21,Program_01!$A:$A,0)),"") -> 0 | AN21: =IFERROR(INDEX(Program_01!$BU:$BU,MATCH($B21,Program_01!$A:$A,0)),"") -> 0 | AO21: =IFERROR(INDEX(Program_01!$BV:$BV,MATCH($B21,Program_01!$A:$A,0)),"") -> 0 | AP21: =IF(OR($AN21="Yes",$AO21="Yes"),"1","") | AQ21: =IFERROR(INDEX(Program_01!$BN:$BN,MATCH($B21,Program_01!$A:$A,0)),"") -> 0 | AR21: =IFERROR(INDEX(Program_01!$BO:$BO,MATCH($B21,Program_01!$A:$A,0)),"") -> Assessment Report Issued | AS21: =IFERROR(INDEX(Program_01!$BP:$BP,MATCH($B21,Program_01!$A:$A,0)),"") -> DVO Issued | AT21: =IFERROR(INDEX(Program_01!$BQ:$BQ,MATCH($B21,Program_01!$A:$A,0)),"") -> Closed | AU21: =IFERROR(INDEX(Program_01!$BR:$BR,MATCH($B21,Program_01!$A:$A,0)),"") -> 22 Apr 24: WF currently with Fahad for approval 25 Apr 24: Assessment report issued to the contractor. awaiting acceptance on the same 06 May 24: ditto 09 May 24: Contractor accepted the Employer's EOT assessment report via letter ref 1TB04004-004CO3-SIC-LTR-113. Commercial to prepare VO/DVO following to PVO approval 07 Jul 24: VO under preperation, targeted to finalize it by today 15-July-24 PVO/VO drafted, targeted to put in WF today 29 Jul 24: PVO/ VO in WF (WF-016540) 10 Aug 24: Still in WF 25 Aug 24: WF approved by CEO on 25th Aug. targeteded to issue it EOD 27 Aug 24: VO issued to contractor 28 Aug 24: VO signed by contractor and sent back to commercial. Commercial to prepare DVO 08 Sep 2024 DVO put in the workflow on 05 Sep 24, WF-016564 Early Works 10 Sep 24: DVO issued to contractor via mail ref AMA04004-GENCORR-000738. contractor to return signed copy | AV21: =IF($I21="","",IF($S21>$AV$16,"",IF($AS21="OPEN","OPEN",IF($AS21="","",IF(AND($AS21<>"OPEN",$AT21="CLOSED"),"CLOSED",IF(AND($AS21<>"OPEN",$AT21<>"CLOSED"),"OPEN","")))))) -> CLOSED | AW21: =IF($I21="","",IF($S21<$AW$16,"",IF($AS21="OPEN","OPEN",IF($AS21="","",IF(AND($AS21<>"OPEN",$AT21="CLOSED"),"CLOSED",IF(AND($AS21<>"OPEN",$AT21<>"CLOSED"),"OPEN","")))))) | AX21: =IF(OR($AV21="OPEN",$AV21="CLOSED"),$AV21,$AW21) -> CLOSED | AY21: =IF(C21="HLEAR",BC21,AB21) -> 45111 | AZ21: =IF($AD21=0,"",AD21) -> 45407 | BA21: =IF(AND($AI21="",$AK21=""),"",IF($AI21="",$AK21,$AI21)) -> 45545 | BC21: =IFERROR(INDEX(Program_01!BF:BF,MATCH($B21,Program_01!$A:$A,0)),"") -> 45111 | BD21: =IFERROR(INDEX(Program_01!BG:BG,MATCH($B21,Program_01!$A:$A,0)),"") -> N/A | BE21: =IFERROR(INDEX(Program_01!BH:BH,MATCH($B21,Program_01!$A:$A,0)),"") -> 0 | BF21: =IFERROR(INDEX(Program_01!BI:BI,MATCH($B21,Program_01!$A:$A,0)),"") -> 0 | BG21: =IFERROR(INDEX(Program_01!BJ:BJ,MATCH($B21,Program_01!$A:$A,0)),"") -> 0 | BH21: =IFERROR(INDEX(Program_01!BK:BK,MATCH($B21,Program_01!$A:$A,0)),"") -> 0 | BI21: =IFERROR(INDEX(Program_01!BL:BL,MATCH($B21,Program_01!$A:$A,0)),"") -> 0 | BK21: =IFERROR(IF(INDEX(Program_01!$BX:$BX,MATCH($B21,Program_01!$A:$A,0))=DATE(1900,1,0),"",INDEX(Program_01!$BX:$BX,MATCH($B21,Program_01!$A:$A,0))),"") -> 45407 | BL21: =IFERROR(IF(INDEX(Program_01!$BY:$BY,MATCH($B21,Program_01!$A:$A,0))=DATE(1900,1,0),"",INDEX(Program_01!$BY:$BY,MATCH($B21,Program_01!$A:$A,0))),"") | BM21: =IF(OR($AZ21="",$AZ21="N/A"),"",IF(AND($AZ21="",$AY21<>""),TODAY()-$AY21,$AZ21-$AY21)) -> 296 | BN21: =IF(OR($C21="DEOT",$C21="N/A",$I21=""),"",IF(OR($AM21="Revise & resubmit",$AT21="Awaiting Conclusion of EoT",$AR21="Not Applicable",$AY21=0,$AY21="TBA",$AZ21="N/A",AY21=0),0,IF(AND($AR21="Assessment Report Issued",$AT21<>""),$AZ21-$AY21,IF(AND($AR21="Pending",$AT21="Contractor"),"",IF(AND($AZ21="",$AY21<>""),TODAY()-$AY21,$AZ21-$AY21))))) -> 296 | BO21: =IF(OR($AR21<>"ASSESSMENT REPORT ISSUED"),"",IF($BN21<>"",$BN21,"")) -> 296 | BP21: =IF($AR21="ASSESSMENT REPORT ISSUED","1",IF(AND($AT21="Closed",$AR21<>"Pending"),"1","")) -> 1 | BQ21: =IF(AND($AR21="Pending",$BN21>140),$BN21,"") | BR21: =IF(BQ21="","","1") | BT21: =IFERROR(IF(INDEX(Program_01!$BZ:$BZ,MATCH($B21,Program_01!$A:$A,0))=DATE(1900,1,0),"",INDEX(Program_01!$BZ:$BZ,MATCH($B21,Program_01!$A:$A,0))),"") -> 45545 | BU21: =IF(OR($I21="",$AV21="",$AM21<>0,$BA21="N/A",$AZ21=""),"",IF(AND($BA21="",$AZ21<>""),TODAY()-$AZ21,$BA21-$AZ21)) -> 138 | BV21: =IF(OR($AS21="Determination Issued",$AS21="VO Issued"),$BU21,"") | BW21: =IF(OR($AT21="CLOSED",$AS21="Determination Issued",$AS21="VO Issued"),"1","") -> 1 | BX21: =IF(OR($AS21="Determination Issued",$AS21="VO Issued",$AS21="Rejected",$AS21="Canceled",$AS21="Superseded",$AS21="Not Applicable",$BU21=""),"",IF($BU21>90,$BU21,"")) -> 138 | BY21: =IF(BX21="","","1") -> 1 | CA21: =IF($I21="","",IF(AND($AR21="Assessment Report Issued",$AZ21<>""),"Y","N")) -> Y | CB21: =IF($I21="","",IF(OR($AS21="Determination Issued",$AS21="VO Issued"),"Y","N")) -> N | CC21: =IFERROR(INDEX(Program_01!$CE:$CE,MATCH($B21,Program_01!$A:$A,0)),"") -> 0 | CD21: =MAX(S21,CC21) -> 44702 | CG21: =IFERROR(INDEX(Program_01!$AT:$AT,MATCH($B21,Program_01!$A:$A,0)),"") -> 0 | CH21: =IFERROR(INDEX(Program_01!$AX:$AX,MATCH($B21,Program_01!$A:$A,0)),"") -> 0
A22: Program_01 | B22: 4 | C22: =IFERROR(INDEX(Program_01!$B:$B,MATCH($B22,Program_01!$A:$A,0)),"") -> COST EAR | D22: =IFERROR(INDEX(Program_01!$D:$D,MATCH($B22,Program_01!$A:$A,0)),"") -> 1TB01002C01 | E22: =IFERROR(INDEX(Program_01!$E:$E,MATCH($B22,Program_01!$A:$A,0)),"") -> 1.TB.01.002.01 | F22: =IFERROR(INDEX(Program_01!$F:$F,MATCH($B22,Program_01!$A:$A,0)),"") -> Marina Lifestyle Hotel & Village | G22: =IFERROR(INDEX(Program_01!$G:$G,MATCH($B22,Program_01!$A:$A,0)),"") -> Triple Bay Wide Ground Improvement | H22: =IFERROR(INDEX(Program_01!$H:$H,MATCH($B22,Program_01!$A:$A,0)),"") -> Soil Improvement Contracting | I22: =IFERROR(IF($D22="","",INDEX($J$16:$O$16,MATCH(1,J22:O22,0))),"") -> Prolongation | J22: =IFERROR(INDEX(Program_01!$I:$I,MATCH($B22,Program_01!$A:$A,0)),"") -> 0 | K22: =IFERROR(INDEX(Program_01!$J:$J,MATCH($B22,Program_01!$A:$A,0)),"") -> 1 | L22: =IFERROR(INDEX(Program_01!$K:$K,MATCH($B22,Program_01!$A:$A,0)),"") -> 0 | M22: =IFERROR(INDEX(Program_01!$L:$L,MATCH($B22,Program_01!$A:$A,0)),"") -> 0 | N22: =IFERROR(INDEX(Program_01!$L:$L,MATCH($B22,Program_01!$A:$A,0)),"") -> 0 | O22: =IFERROR(INDEX(Program_01!$N:$N,MATCH($B22,Program_01!$A:$A,0)),"") -> 0 | Q22: =IFERROR(INDEX(Program_01!$C:$C,MATCH($B22,Program_01!$A:$A,0)),"") -> Consolidated Claim - Prolongation Costs (Delay in IFC's) | R22: =IFERROR(INDEX(Program_01!$V:$V,MATCH($B22,Program_01!$A:$A,0)),"") -> 1TB04004-004C03-SIC-LTR-0018 | S22: =IFERROR(INDEX(Program_01!$W:$W,MATCH($B22,Program_01!$A:$A,0)),"") -> 44702 | U22: =IFERROR(INDEX(Program_01!$Z:$Z,MATCH($B22,Program_01!$A:$A,0)),"") -> 1TB04004-004C03-SAP-LTR-0027 | V22: =IFERROR(INDEX(Program_01!$AA:$AA,MATCH($B22,Program_01!$A:$A,0)),"") -> 44710 | W22: =IF(OR($S22="",$V22="N/A"),"",IF(AND($S22<>0,$V22=0),TODAY()-$S22,IF(AND($S22<>"",$V22<>""),$V22-$S22))) -> 8 | Y22: =IFERROR(INDEX(Program_01!$BD:$BD,MATCH($B22,Program_01!$A:$A,0)),"") -> 1TB04004-004C03-AMA-LTR-0007 dated 25 Apr 24 11TB04004-004CO3-SIC-LTR-113 dated 09 May 24 AMA04004-VAR-OR-000002 issued on 22 Sep 24 AMA04004-DVOR-000001 issued on 22 Sep 24 | AA22: =IFERROR(IF((INDEX(Program_01!$AD:$AD,MATCH($B22,Program_01!$A:$A,0))=""),INDEX(Program_01!$V:$V,MATCH($B22,Program_01!$A:$A,0)),INDEX(Program_01!$AD:$AD,MATCH($B22,Program_01!$A:$A,0))),"") -> 1TB04004-004C03-SIC-LTR-0043 dated 03-Sep-2022 1TB04004-004C03-SIC-LTR-0103 dated 04 Jul 23 1TB04004-004CO3-SIC-LTR-113 09 May 24 further particulars received via email on 15 Jul 24 | AB22: =IFERROR(IF((INDEX(Program_01!$AE:$AE,MATCH($B22,Program_01!$A:$A,0))=""),INDEX(Program_01!$W:$W,MATCH($B22,Program_01!$A:$A,0)),INDEX(Program_01!$AE:$AE,MATCH($B22,Program_01!$A:$A,0))),"") -> 45488 | AC22: =IFERROR(IF($I22="EOT",INDEX(Program_01!$AN:$AN,MATCH($B22,Program_01!$A:$A,0)),INDEX(Program_01!$AY:$AY,MATCH($B22,Program_01!$A:$A,0))),"") -> 1TB04004-004C03-AMA-RPT-CM-0006 1TB04004-004C03-AMA-LTR-0009 | AD22: =IFERROR(IF($I22="EOT",INDEX(Program_01!$AO:$AO,MATCH($B22,Program_01!$A:$A,0)),INDEX(Program_01!$AZ:$AZ,MATCH($B22,Program_01!$A:$A,0))),"") -> 45542 | AH22: =IF(OR($D22="",$AS22="VO Issued",$AS22="Open"),"",IF(OR($AC22="Rejected",$AC22="Superseded",$AC22="Dealt Separately"),$AC22,IF($I22="EOT",INDEX(Program_01!$AR:$AR,MATCH($B22,Program_01!$A:$A,0)),INDEX(Program_01!$BB:$BB,MATCH($B22,Program_01!$A:$A,0))))) -> AMA04004-DVOR-000001 issued on 22 Sep 24 | AI22: =IF(OR($A22="",$B22="",$I22="",$AS22="VO Issued",$AS22="Open"),"",IF(OR($AD22="N/A"),$AD22,IF($I22="EOT",INDEX(Program_01!$AS:$AS,MATCH($B22,Program_01!$A:$A,0)),INDEX(Program_01!$BC:$BC,MATCH($B22,Program_01!$A:$A,0))))) -> 45557 | AJ22: =IF(OR($D22="",$I22="",$AS22="Determination Issued",$AS22="Rejected",$AS22="Open"),"",IF(OR($AH22="Rejected",$AH22="Dealt Separately",$AH22="Superseded",$AH22="Withdrawn"),"N/A",IF($I22="EOT",INDEX(Program_01!AR:AR,MATCH($B22,Program_01!A:A,0)),INDEX(Program_01!BB:BB,MATCH($B22,Program_01!A:A,0))))) -> AMA04004-DVOR-000001 issued on 22 Sep 24 | AK22: =IF(OR($A22="",$B22="",$I22="",$AS22="Determination Issued",$AS22="Rejected",$AS22="Open"),"",IF($AJ22="N/A","N/A",IF($I22="EOT",INDEX(Program_01!AS:AS,MATCH($B22,Program_01!A:A,0)),INDEX(Program_01!BC:BC,MATCH($B22,Program_01!A:A,0))))) -> 45557 | AM22: =IFERROR(INDEX(Program_01!$BT:$BT,MATCH($B22,Program_01!$A:$A,0)),"") -> 0 | AN22: =IFERROR(INDEX(Program_01!$BU:$BU,MATCH($B22,Program_01!$A:$A,0)),"") -> 0 | AO22: =IFERROR(INDEX(Program_01!$BV:$BV,MATCH($B22,Program_01!$A:$A,0)),"") -> 0 | AP22: =IF(OR($AN22="Yes",$AO22="Yes"),"1","") | AQ22: =IFERROR(INDEX(Program_01!$BN:$BN,MATCH($B22,Program_01!$A:$A,0)),"") -> 0 | AR22: =IFERROR(INDEX(Program_01!$BO:$BO,MATCH($B22,Program_01!$A:$A,0)),"") -> Assessment Report Issued | AS22: =IFERROR(INDEX(Program_01!$BP:$BP,MATCH($B22,Program_01!$A:$A,0)),"") -> DVO Issued | AT22: =IFERROR(INDEX(Program_01!$BQ:$BQ,MATCH($B22,Program_01!$A:$A,0)),"") -> Closed | AU22: =IFERROR(INDEX(Program_01!$BR:$BR,MATCH($B22,Program_01!$A:$A,0)),"") -> 28 May 24: PG advised commercial to provide brief narrative on each of the heads of claims for costs 2-June-24 -The cost assessment report was issued to PG for review. Report was sent back to commercial with comments. 7-Jul-24:Invoices received from SIC and is updating their report to reflect Paul G's comments. targeted to finalize the report and to send it by COB tomorrow for PG's review. 14-July-24 Cost Assessmnet targeted to be sent to Paul G by EOD 27 Jul 24: Sent to claim team for review. 29 Jul 24: report under review with claims 10 Aug 24: WC & PII cost to be reevaluated as per claims comments. contractor provided the additional insurance details on 15 Jul 24 via email 20 Aug 24: Assessment report put in WF (WF-016555) on 19 Aug 24 26 Aug 24: Still in WF 02 Sep 24: WF approved by GCEO, to be issued to the contractor EoD 08 Sep 24: Cost Assessment issued to Contractor for acceptance, after which VO / DVO shall be processed. 09 Sep 24: Contractor aknowledged the assessment report. commercial to prepare PVO/VO & DVO. targeted to put in WF 10 Sep 24: PVO / VO & DVO put in WF (WF-016566) 24 Sep 24: VO & DVO issued to contractor on 22 Sep 24 | AV22: =IF($I22="","",IF($S22>$AV$16,"",IF($AS22="OPEN","OPEN",IF($AS22="","",IF(AND($AS22<>"OPEN",$AT22="CLOSED"),"CLOSED",IF(AND($AS22<>"OPEN",$AT22<>"CLOSED"),"OPEN","")))))) -> CLOSED | AW22: =IF($I22="","",IF($S22<$AW$16,"",IF($AS22="OPEN","OPEN",IF($AS22="","",IF(AND($AS22<>"OPEN",$AT22="CLOSED"),"CLOSED",IF(AND($AS22<>"OPEN",$AT22<>"CLOSED"),"OPEN","")))))) | AX22: =IF(OR($AV22="OPEN",$AV22="CLOSED"),$AV22,$AW22) -> CLOSED | AY22: =IF(C22="HLEAR",BC22,AB22) -> 45488 | AZ22: =IF($AD22=0,"",AD22) -> 45542 | BA22: =IF(AND($AI22="",$AK22=""),"",IF($AI22="",$AK22,$AI22)) -> 45557 | BC22: =IFERROR(INDEX(Program_01!BF:BF,MATCH($B22,Program_01!$A:$A,0)),"") -> 45488 | BD22: =IFERROR(INDEX(Program_01!BG:BG,MATCH($B22,Program_01!$A:$A,0)),"") -> N/A | BE22: =IFERROR(INDEX(Program_01!BH:BH,MATCH($B22,Program_01!$A:$A,0)),"") -> 0 | BF22: =IFERROR(INDEX(Program_01!BI:BI,MATCH($B22,Program_01!$A:$A,0)),"") -> N/A | BG22: =IFERROR(INDEX(Program_01!BJ:BJ,MATCH($B22,Program_01!$A:$A,0)),"") -> 0 | BH22: =IFERROR(INDEX(Program_01!BK:BK,MATCH($B22,Program_01!$A:$A,0)),"") -> 0 | BI22: =IFERROR(INDEX(Program_01!BL:BL,MATCH($B22,Program_01!$A:$A,0)),"") -> 0 | BK22: =IFERROR(IF(INDEX(Program_01!$BX:$BX,MATCH($B22,Program_01!$A:$A,0))=DATE(1900,1,0),"",INDEX(Program_01!$BX:$BX,MATCH($B22,Program_01!$A:$A,0))),"") -> 45539 | BL22: =IFERROR(IF(INDEX(Program_01!$BY:$BY,MATCH($B22,Program_01!$A:$A,0))=DATE(1900,1,0),"",INDEX(Program_01!$BY:$BY,MATCH($B22,Program_01!$A:$A,0))),"") | BM22: =IF(OR($AZ22="",$AZ22="N/A"),"",IF(AND($AZ22="",$AY22<>""),TODAY()-$AY22,$AZ22-$AY22)) -> 54 | BN22: =IF(OR($C22="DEOT",$C22="N/A",$I22=""),"",IF(OR($AM22="Revise & resubmit",$AT22="Awaiting Conclusion of EoT",$AR22="Not Applicable",$AY22=0,$AY22="TBA",$AZ22="N/A",AY22=0),0,IF(AND($AR22="Assessment Report Issued",$AT22<>""),$AZ22-$AY22,IF(AND($AR22="Pending",$AT22="Contractor"),"",IF(AND($AZ22="",$AY22<>""),TODAY()-$AY22,$AZ22-$AY22))))) -> 54 | BO22: =IF(OR($AR22<>"ASSESSMENT REPORT ISSUED"),"",IF($BN22<>"",$BN22,"")) -> 54 | BP22: =IF($AR22="ASSESSMENT REPORT ISSUED","1",IF(AND($AT22="Closed",$AR22<>"Pending"),"1","")) -> 1 | BQ22: =IF(AND($AR22="Pending",$BN22>140),$BN22,"") | BR22: =IF(BQ22="","","1") | BT22: =IFERROR(IF(INDEX(Program_01!$BZ:$BZ,MATCH($B22,Program_01!$A:$A,0))=DATE(1900,1,0),"",INDEX(Program_01!$BZ:$BZ,MATCH($B22,Program_01!$A:$A,0))),"") -> 45557 | BU22: =IF(OR($I22="",$AV22="",$AM22<>0,$BA22="N/A",$AZ22=""),"",IF(AND($BA22="",$AZ22<>""),TODAY()-$AZ22,$BA22-$AZ22)) -> 15 | BV22: =IF(OR($AS22="Determination Issued",$AS22="VO Issued"),$BU22,"") | BW22: =IF(OR($AT22="CLOSED",$AS22="Determination Issued",$AS22="VO Issued"),"1","") -> 1 | BX22: =IF(OR($AS22="Determination Issued",$AS22="VO Issued",$AS22="Rejected",$AS22="Canceled",$AS22="Superseded",$AS22="Not Applicable",$BU22=""),"",IF($BU22>90,$BU22,"")) | BY22: =IF(BX22="","","1") | CA22: =IF($I22="","",IF(AND($AR22="Assessment Report Issued",$AZ22<>""),"Y","N")) -> Y | CB22: =IF($I22="","",IF(OR($AS22="Determination Issued",$AS22="VO Issued"),"Y","N")) -> N | CC22: =IFERROR(INDEX(Program_01!$CE:$CE,MATCH($B22,Program_01!$A:$A,0)),"") -> 0 | CD22: =MAX(S22,CC22) -> 44702 | CG22: =IFERROR(INDEX(Program_01!$AT:$AT,MATCH($B22,Program_01!$A:$A,0)),"") -> 2201256 | CH22: =IFERROR(INDEX(Program_01!$AX:$AX,MATCH($B22,Program_01!$A:$A,0)),"") -> 1003204.7 | CI22: Assessment Report Issued
A23: Program_01 | B23: 5 | C23: =IFERROR(INDEX(Program_01!$B:$B,MATCH($B23,Program_01!$A:$A,0)),"") -> FULL TIA EAR | D23: =IFERROR(INDEX(Program_01!$D:$D,MATCH($B23,Program_01!$A:$A,0)),"") -> 1TB01006C03 | E23: =IFERROR(INDEX(Program_01!$E:$E,MATCH($B23,Program_01!$A:$A,0)),"") -> 1.TB.01.006.99 | F23: =IFERROR(INDEX(Program_01!$F:$F,MATCH($B23,Program_01!$A:$A,0)),"") -> Village Boutique Hotel | G23: =IFERROR(INDEX(Program_01!$G:$G,MATCH($B23,Program_01!$A:$A,0)),"") -> Concrete Structure and Civil Works for Village Boutique Hotel | H23: =IFERROR(INDEX(Program_01!$H:$H,MATCH($B23,Program_01!$A:$A,0)),"") -> Mounes Mohamed Al Shayeb and Partners for Civil Construction - MOBCO | I23: =IFERROR(IF($D23="","",INDEX($J$16:$O$16,MATCH(1,J23:O23,0))),"") -> EOT | J23: =IFERROR(INDEX(Program_01!$I:$I,MATCH($B23,Program_01!$A:$A,0)),"") -> 1 | K23: =IFERROR(INDEX(Program_01!$J:$J,MATCH($B23,Program_01!$A:$A,0)),"") -> 0 | L23: =IFERROR(INDEX(Program_01!$K:$K,MATCH($B23,Program_01!$A:$A,0)),"") -> 0 | M23: =IFERROR(INDEX(Program_01!$L:$L,MATCH($B23,Program_01!$A:$A,0)),"") -> 0 | N23: =IFERROR(INDEX(Program_01!$L:$L,MATCH($B23,Program_01!$A:$A,0)),"") -> 0 | O23: =IFERROR(INDEX(Program_01!$N:$N,MATCH($B23,Program_01!$A:$A,0)),"") -> 0 | Q23: =IFERROR(INDEX(Program_01!$C:$C,MATCH($B23,Program_01!$A:$A,0)),"") -> Consolidated Claim - EOT Claim (Delay in IFC's, Delays in Allocating Mobilization Area, Delay in Site Hand-over) | R23: =IFERROR(INDEX(Program_01!$V:$V,MATCH($B23,Program_01!$A:$A,0)),"") -> 1TB01006-006C03-MOO-LTR-0024 dated 20-Jul-23 Update of Interim EOT No. 01 1TB01006-006C03-MOO-LTR-0030 MOO01006-CLM-000001 | S23: =IFERROR(INDEX(Program_01!$W:$W,MATCH($B23,Program_01!$A:$A,0)),"") -> 45155 | U23: =IFERROR(INDEX(Program_01!$Z:$Z,MATCH($B23,Program_01!$A:$A,0)),"") -> 1TB01006-006C03-AMA-LTR-0054 | V23: =IFERROR(INDEX(Program_01!$AA:$AA,MATCH($B23,Program_01!$A:$A,0)),"") -> 45193 | W23: =IF(OR($S23="",$V23="N/A"),"",IF(AND($S23<>0,$V23=0),TODAY()-$S23,IF(AND($S23<>"",$V23<>""),$V23-$S23))) -> 38 | Y23: =IFERROR(INDEX(Program_01!$BD:$BD,MATCH($B23,Program_01!$A:$A,0)),"") -> Determination was issued to Contractor on 14 Nov 2023 | AA23: =IFERROR(IF((INDEX(Program_01!$AD:$AD,MATCH($B23,Program_01!$A:$A,0))=""),INDEX(Program_01!$V:$V,MATCH($B23,Program_01!$A:$A,0)),INDEX(Program_01!$AD:$AD,MATCH($B23,Program_01!$A:$A,0))),"") -> 1TB01006-006C03-MOO-LTR-0024 dated 20-Jul-23 Update of Interim EOT No. 01 1TB01006-006C03-MOO-LTR-0030 MOO01006-CLM-000001 | AB23: =IFERROR(IF((INDEX(Program_01!$AE:$AE,MATCH($B23,Program_01!$A:$A,0))=""),INDEX(Program_01!$W:$W,MATCH($B23,Program_01!$A:$A,0)),INDEX(Program_01!$AE:$AE,MATCH($B23,Program_01!$A:$A,0))),"") -> 45155 | AC23: =IFERROR(IF($I23="EOT",INDEX(Program_01!$AN:$AN,MATCH($B23,Program_01!$A:$A,0)),INDEX(Program_01!$AY:$AY,MATCH($B23,Program_01!$A:$A,0))),"") -> 1TB01006-006C03-AMA-LTR-0088 | AD23: =IFERROR(IF($I23="EOT",INDEX(Program_01!$AO:$AO,MATCH($B23,Program_01!$A:$A,0)),INDEX(Program_01!$AZ:$AZ,MATCH($B23,Program_01!$A:$A,0))),"") -> 45244 | AH23: =IF(OR($D23="",$AS23="VO Issued",$AS23="Open"),"",IF(OR($AC23="Rejected",$AC23="Superseded",$AC23="Dealt Separately"),$AC23,IF($I23="EOT",INDEX(Program_01!$AR:$AR,MATCH($B23,Program_01!$A:$A,0)),INDEX(Program_01!$BB:$BB,MATCH($B23,Program_01!$A:$A,0))))) -> 1TB01006-006C03-AMA-LTR-0088 | AI23: =IF(OR($A23="",$B23="",$I23="",$AS23="VO Issued",$AS23="Open"),"",IF(OR($AD23="N/A"),$AD23,IF($I23="EOT",INDEX(Program_01!$AS:$AS,MATCH($B23,Program_01!$A:$A,0)),INDEX(Program_01!$BC:$BC,MATCH($B23,Program_01!$A:$A,0))))) -> 45244 | AJ23: =IF(OR($D23="",$I23="",$AS23="Determination Issued",$AS23="Rejected",$AS23="Open"),"",IF(OR($AH23="Rejected",$AH23="Dealt Separately",$AH23="Superseded",$AH23="Withdrawn"),"N/A",IF($I23="EOT",INDEX(Program_01!AR:AR,MATCH($B23,Program_01!A:A,0)),INDEX(Program_01!BB:BB,MATCH($B23,Program_01!A:A,0))))) | AK23: =IF(OR($A23="",$B23="",$I23="",$AS23="Determination Issued",$AS23="Rejected",$AS23="Open"),"",IF($AJ23="N/A","N/A",IF($I23="EOT",INDEX(Program_01!AS:AS,MATCH($B23,Program_01!A:A,0)),INDEX(Program_01!BC:BC,MATCH($B23,Program_01!A:A,0))))) | AM23: =IFERROR(INDEX(Program_01!$BT:$BT,MATCH($B23,Program_01!$A:$A,0)),"") -> 0 | AN23: =IFERROR(INDEX(Program_01!$BU:$BU,MATCH($B23,Program_01!$A:$A,0)),"") -> Yes | AO23: =IFERROR(INDEX(Program_01!$BV:$BV,MATCH($B23,Program_01!$A:$A,0)),"") -> 0 | AP23: =IF(OR($AN23="Yes",$AO23="Yes"),"1","") -> 1 | AQ23: =IFERROR(INDEX(Program_01!$BN:$BN,MATCH($B23,Program_01!$A:$A,0)),"") -> 0 | AR23: =IFERROR(INDEX(Program_01!$BO:$BO,MATCH($B23,Program_01!$A:$A,0)),"") -> Assessment Report Issued | AS23: =IFERROR(INDEX(Program_01!$BP:$BP,MATCH($B23,Program_01!$A:$A,0)),"") -> Determination Issued | AT23: =IFERROR(INDEX(Program_01!$BQ:$BQ,MATCH($B23,Program_01!$A:$A,0)),"") -> Closed | AU23: =IFERROR(INDEX(Program_01!$BR:$BR,MATCH($B23,Program_01!$A:$A,0)),"") -> Closed. | AV23: =IF($I23="","",IF($S23>$AV$16,"",IF($AS23="OPEN","OPEN",IF($AS23="","",IF(AND($AS23<>"OPEN",$AT23="CLOSED"),"CLOSED",IF(AND($AS23<>"OPEN",$AT23<>"CLOSED"),"OPEN","")))))) -> CLOSED | AW23: =IF($I23="","",IF($S23<$AW$16,"",IF($AS23="OPEN","OPEN",IF($AS23="","",IF(AND($AS23<>"OPEN",$AT23="CLOSED"),"CLOSED",IF(AND($AS23<>"OPEN",$AT23<>"CLOSED"),"OPEN","")))))) | AX23: =IF(OR($AV23="OPEN",$AV23="CLOSED"),$AV23,$AW23) -> CLOSED | AY23: =IF(C23="HLEAR",BC23,AB23) -> 45155 | AZ23: =IF($AD23=0,"",AD23) -> 45244 | BA23: =IF(AND($AI23="",$AK23=""),"",IF($AI23="",$AK23,$AI23)) -> 45244 | BC23: =IFERROR(INDEX(Program_01!BF:BF,MATCH($B23,Program_01!$A:$A,0)),"") -> 45155 | BD23: =IFERROR(INDEX(Program_01!BG:BG,MATCH($B23,Program_01!$A:$A,0)),"") -> N/A | BE23: =IFERROR(INDEX(Program_01!BH:BH,MATCH($B23,Program_01!$A:$A,0)),"") -> 0 | BF23: =IFERROR(INDEX(Program_01!BI:BI,MATCH($B23,Program_01!$A:$A,0)),"") -> 0 | BG23: =IFERROR(INDEX(Program_01!BJ:BJ,MATCH($B23,Program_01!$A:$A,0)),"") -> 0 | BH23: =IFERROR(INDEX(Program_01!BK:BK,MATCH($B23,Program_01!$A:$A,0)),"") -> 0 | BI23: =IFERROR(INDEX(Program_01!BL:BL,MATCH($B23,Program_01!$A:$A,0)),"") -> 0 | BK23: =IFERROR(IF(INDEX(Program_01!$BX:$BX,MATCH($B23,Program_01!$A:$A,0))=DATE(1900,1,0),"",INDEX(Program_01!$BX:$BX,MATCH($B23,Program_01!$A:$A,0))),"") -> 45291 | BL23: =IFERROR(IF(INDEX(Program_01!$BY:$BY,MATCH($B23,Program_01!$A:$A,0))=DATE(1900,1,0),"",INDEX(Program_01!$BY:$BY,MATCH($B23,Program_01!$A:$A,0))),"") | BM23: =IF(OR($AZ23="",$AZ23="N/A"),"",IF(AND($AZ23="",$AY23<>""),TODAY()-$AY23,$AZ23-$AY23)) -> 89 | BN23: =IF(OR($C23="DEOT",$C23="N/A",$I23=""),"",IF(OR($AM23="Revise & resubmit",$AT23="Awaiting Conclusion of EoT",$AR23="Not Applicable",$AY23=0,$AY23="TBA",$AZ23="N/A",AY23=0),0,IF(AND($AR23="Assessment Report Issued",$AT23<>""),$AZ23-$AY23,IF(AND($AR23="Pending",$AT23="Contractor"),"",IF(AND($AZ23="",$AY23<>""),TODAY()-$AY23,$AZ23-$AY23))))) -> 89 | BO23: =IF(OR($AR23<>"ASSESSMENT REPORT ISSUED"),"",IF($BN23<>"",$BN23,"")) -> 89 | BP23: =IF($AR23="ASSESSMENT REPORT ISSUED","1",IF(AND($AT23="Closed",$AR23<>"Pending"),"1","")) -> 1 | BQ23: =IF(AND($AR23="Pending",$BN23>140),$BN23,"") | BR23: =IF(BQ23="","","1") | BT23: =IFERROR(IF(INDEX(Program_01!$BZ:$BZ,MATCH($B23,Program_01!$A:$A,0))=DATE(1900,1,0),"",INDEX(Program_01!$BZ:$BZ,MATCH($B23,Program_01!$A:$A,0))),"") | BU23: =IF(OR($I23="",$AV23="",$AM23<>0,$BA23="N/A",$AZ23=""),"",IF(AND($BA23="",$AZ23<>""),TODAY()-$AZ23,$BA23-$AZ23)) -> 0 | BV23: =IF(OR($AS23="Determination Issued",$AS23="VO Issued"),$BU23,"") -> 0 | BW23: =IF(OR($AT23="CLOSED",$AS23="Determination Issued",$AS23="VO Issued"),"1","") -> 1 | BX23: =IF(OR($AS23="Determination Issued",$AS23="VO Issued",$AS23="Rejected",$AS23="Canceled",$AS23="Superseded",$AS23="Not Applicable",$BU23=""),"",IF($BU23>90,$BU23,"")) | BY23: =IF(BX23="","","1") | CA23: =IF($I23="","",IF(AND($AR23="Assessment Report Issued",$AZ23<>""),"Y","N")) -> Y | CB23: =IF($I23="","",IF(OR($AS23="Determination Issued",$AS23="VO Issued"),"Y","N")) -> Y | CC23: =IFERROR(INDEX(Program_01!$CE:$CE,MATCH($B23,Program_01!$A:$A,0)),"") -> 0 | CD23: =MAX(S23,CC23) -> 45155 | CG23: =IFERROR(INDEX(Program_01!$AT:$AT,MATCH($B23,Program_01!$A:$A,0)),"") -> 0 | CH23: =IFERROR(INDEX(Program_01!$AX:$AX,MATCH($B23,Program_01!$A:$A,0)),"") -> 0
A24: Program_01 | B24: 6 | C24: =IFERROR(INDEX(Program_01!$B:$B,MATCH($B24,Program_01!$A:$A,0)),"") -> COST EAR | D24: =IFERROR(INDEX(Program_01!$D:$D,MATCH($B24,Program_01!$A:$A,0)),"") -> 1TB01005C02 | E24: =IFERROR(INDEX(Program_01!$E:$E,MATCH($B24,Program_01!$A:$A,0)),"") -> 1.TB.01.005.01 | F24: =IFERROR(INDEX(Program_01!$F:$F,MATCH($B24,Program_01!$A:$A,0)),"") -> Red Sea Marine Life Institute | G24: =IFERROR(INDEX(Program_01!$G:$G,MATCH($B24,Program_01!$A:$A,0)),"") -> Construction Contract - Structural Concrete, Wet Trades, Dewatering, Earthworks & BOH Finishes | H24: =IFERROR(INDEX(Program_01!$H:$H,MATCH($B24,Program_01!$A:$A,0)),"") -> Saudi Arabian Baytur Construction Company | I24: =IFERROR(IF($D24="","",INDEX($J$16:$O$16,MATCH(1,J24:O24,0))),"") -> Other Claims | J24: =IFERROR(INDEX(Program_01!$I:$I,MATCH($B24,Program_01!$A:$A,0)),"") -> 0 | K24: =IFERROR(INDEX(Program_01!$J:$J,MATCH($B24,Program_01!$A:$A,0)),"") -> 0 | L24: =IFERROR(INDEX(Program_01!$K:$K,MATCH($B24,Program_01!$A:$A,0)),"") -> 0 | M24: =IFERROR(INDEX(Program_01!$L:$L,MATCH($B24,Program_01!$A:$A,0)),"") -> 0 | N24: =IFERROR(INDEX(Program_01!$L:$L,MATCH($B24,Program_01!$A:$A,0)),"") -> 0 | O24: =IFERROR(INDEX(Program_01!$N:$N,MATCH($B24,Program_01!$A:$A,0)),"") -> 1 | Q24: =IFERROR(INDEX(Program_01!$C:$C,MATCH($B24,Program_01!$A:$A,0)),"") -> Notice of Disatisfaction - Secant Piling (Temporary Works) | R24: =IFERROR(INDEX(Program_01!$V:$V,MATCH($B24,Program_01!$A:$A,0)),"") -> 1TB01005-005C02-SAB-LTR-0044 | S24: =IFERROR(INDEX(Program_01!$W:$W,MATCH($B24,Program_01!$A:$A,0)),"") -> 45277 | U24: =IFERROR(INDEX(Program_01!$Z:$Z,MATCH($B24,Program_01!$A:$A,0)),"") -> Not responded | V24: =IFERROR(INDEX(Program_01!$AA:$AA,MATCH($B24,Program_01!$A:$A,0)),"") -> N/A | W24: =IF(OR($S24="",$V24="N/A"),"",IF(AND($S24<>0,$V24=0),TODAY()-$S24,IF(AND($S24<>"",$V24<>""),$V24-$S24))) | Y24: =IFERROR(INDEX(Program_01!$BD:$BD,MATCH($B24,Program_01!$A:$A,0)),"") -> 0 | AA24: =IFERROR(IF((INDEX(Program_01!$AD:$AD,MATCH($B24,Program_01!$A:$A,0))=""),INDEX(Program_01!$V:$V,MATCH($B24,Program_01!$A:$A,0)),INDEX(Program_01!$AD:$AD,MATCH($B24,Program_01!$A:$A,0))),"") -> 1TB01005-005C02-SAB-LTR-0044 | AB24: =IFERROR(IF((INDEX(Program_01!$AE:$AE,MATCH($B24,Program_01!$A:$A,0))=""),INDEX(Program_01!$W:$W,MATCH($B24,Program_01!$A:$A,0)),INDEX(Program_01!$AE:$AE,MATCH($B24,Program_01!$A:$A,0))),"") -> 45277 | AC24: =IFERROR(IF($I24="EOT",INDEX(Program_01!$AN:$AN,MATCH($B24,Program_01!$A:$A,0)),INDEX(Program_01!$AY:$AY,MATCH($B24,Program_01!$A:$A,0))),"") -> 1TB01005-005C02-AMA-LTR-0069 dated 7 Dec 23 | AD24: =IFERROR(IF($I24="EOT",INDEX(Program_01!$AO:$AO,MATCH($B24,Program_01!$A:$A,0)),INDEX(Program_01!$AZ:$AZ,MATCH($B24,Program_01!$A:$A,0))),"") -> N/A | AH24: =IF(OR($D24="",$AS24="VO Issued",$AS24="Open"),"",IF(OR($AC24="Rejected",$AC24="Superseded",$AC24="Dealt Separately"),$AC24,IF($I24="EOT",INDEX(Program_01!$AR:$AR,MATCH($B24,Program_01!$A:$A,0)),INDEX(Program_01!$BB:$BB,MATCH($B24,Program_01!$A:$A,0))))) -> Rejected | AI24: =IF(OR($A24="",$B24="",$I24="",$AS24="VO Issued",$AS24="Open"),"",IF(OR($AD24="N/A"),$AD24,IF($I24="EOT",INDEX(Program_01!$AS:$AS,MATCH($B24,Program_01!$A:$A,0)),INDEX(Program_01!$BC:$BC,MATCH($B24,Program_01!$A:$A,0))))) -> N/A | AJ24: =IF(OR($D24="",$I24="",$AS24="Determination Issued",$AS24="Rejected",$AS24="Open"),"",IF(OR($AH24="Rejected",$AH24="Dealt Separately",$AH24="Superseded",$AH24="Withdrawn"),"N/A",IF($I24="EOT",INDEX(Program_01!AR:AR,MATCH($B24,Program_01!A:A,0)),INDEX(Program_01!BB:BB,MATCH($B24,Program_01!A:A,0))))) -> N/A | AK24: =IF(OR($A24="",$B24="",$I24="",$AS24="Determination Issued",$AS24="Rejected",$AS24="Open"),"",IF($AJ24="N/A","N/A",IF($I24="EOT",INDEX(Program_01!AS:AS,MATCH($B24,Program_01!A:A,0)),INDEX(Program_01!BC:BC,MATCH($B24,Program_01!A:A,0))))) -> N/A | AM24: =IFERROR(INDEX(Program_01!$BT:$BT,MATCH($B24,Program_01!$A:$A,0)),"") -> Merit | AN24: =IFERROR(INDEX(Program_01!$BU:$BU,MATCH($B24,Program_01!$A:$A,0)),"") -> Yes | AO24: =IFERROR(INDEX(Program_01!$BV:$BV,MATCH($B24,Program_01!$A:$A,0)),"") -> 0 | AP24: =IF(OR($AN24="Yes",$AO24="Yes"),"1","") -> 1 | AQ24: =IFERROR(INDEX(Program_01!$BN:$BN,MATCH($B24,Program_01!$A:$A,0)),"") -> 0 | AR24: =IFERROR(INDEX(Program_01!$BO:$BO,MATCH($B24,Program_01!$A:$A,0)),"") -> Canceled | AS24: =IFERROR(INDEX(Program_01!$BP:$BP,MATCH($B24,Program_01!$A:$A,0)),"") -> Canceled | AT24: =IFERROR(INDEX(Program_01!$BQ:$BQ,MATCH($B24,Program_01!$A:$A,0)),"") -> Closed | AU24: =IFERROR(INDEX(Program_01!$BR:$BR,MATCH($B24,Program_01!$A:$A,0)),"") -> Note: this submission cannot be considered as a formal notice of disatifaction for the engineer's determination and hence considered cancelled / rejected Notice of Disatisfaction to RSG's determination. 14-Jan-24: Contractor claimed additional costs related to breaking of secant piling - this was rejected by the employer refer to letter 1TB01005-005C02-AMA-LTR-0069 15-Jan-24: Commercial team shared the Notice and other documents related to Claims and Legal Team. 29-Jan-24: Ongoing action for re-assessment. RFC is currently being prepared. 12-Feb-24 - Ditto 26-Feb-24: Ditto 10-Mar-24 - RFC approved, proceeding to PVO 19-Mar-24: PVO rejected by Senior Project Director (Revise and Resubmit status). 27-Mar-24: Commercial team to formally inform the contractor regardrding the rejection. 05-May-24: As per the Senior Project Director (RSMLI), the variation claim for temporary openings has been rejected. Hence, the associated claim should be rejected, and an official response will be issued. | AV24: =IF($I24="","",IF($S24>$AV$16,"",IF($AS24="OPEN","OPEN",IF($AS24="","",IF(AND($AS24<>"OPEN",$AT24="CLOSED"),"CLOSED",IF(AND($AS24<>"OPEN",$AT24<>"CLOSED"),"OPEN","")))))) -> CLOSED | AW24: =IF($I24="","",IF($S24<$AW$16,"",IF($AS24="OPEN","OPEN",IF($AS24="","",IF(AND($AS24<>"OPEN",$AT24="CLOSED"),"CLOSED",IF(AND($AS24<>"OPEN",$AT24<>"CLOSED"),"OPEN","")))))) | AX24: =IF(OR($AV24="OPEN",$AV24="CLOSED"),$AV24,$AW24) -> CLOSED | AY24: =IF(C24="HLEAR",BC24,AB24) -> 45277 | AZ24: =IF($AD24=0,"",AD24) -> N/A | BA24: =IF(AND($AI24="",$AK24=""),"",IF($AI24="",$AK24,$AI24)) -> N/A | BC24: =IFERROR(INDEX(Program_01!BF:BF,MATCH($B24,Program_01!$A:$A,0)),"") -> 45277 | BD24: =IFERROR(INDEX(Program_01!BG:BG,MATCH($B24,Program_01!$A:$A,0)),"") -> N/A | BE24: =IFERROR(INDEX(Program_01!BH:BH,MATCH($B24,Program_01!$A:$A,0)),"") -> 0 | BF24: =IFERROR(INDEX(Program_01!BI:BI,MATCH($B24,Program_01!$A:$A,0)),"") -> N/A | BG24: =IFERROR(INDEX(Program_01!BJ:BJ,MATCH($B24,Program_01!$A:$A,0)),"") -> 0 | BH24: =IFERROR(INDEX(Program_01!BK:BK,MATCH($B24,Program_01!$A:$A,0)),"") -> 0 | BI24: =IFERROR(INDEX(Program_01!BL:BL,MATCH($B24,Program_01!$A:$A,0)),"") -> 0 | BK24: =IFERROR(IF(INDEX(Program_01!$BX:$BX,MATCH($B24,Program_01!$A:$A,0))=DATE(1900,1,0),"",INDEX(Program_01!$BX:$BX,MATCH($B24,Program_01!$A:$A,0))),"") -> 45404 | BL24: =IFERROR(IF(INDEX(Program_01!$BY:$BY,MATCH($B24,Program_01!$A:$A,0))=DATE(1900,1,0),"",INDEX(Program_01!$BY:$BY,MATCH($B24,Program_01!$A:$A,0))),"") | BM24: =IF(OR($AZ24="",$AZ24="N/A"),"",IF(AND($AZ24="",$AY24<>""),TODAY()-$AY24,$AZ24-$AY24)) | BN24: =IF(OR($C24="DEOT",$C24="N/A",$I24=""),"",IF(OR($AM24="Revise & resubmit",$AT24="Awaiting Conclusion of EoT",$AR24="Not Applicable",$AY24=0,$AY24="TBA",$AZ24="N/A",AY24=0),0,IF(AND($AR24="Assessment Report Issued",$AT24<>""),$AZ24-$AY24,IF(AND($AR24="Pending",$AT24="Contractor"),"",IF(AND($AZ24="",$AY24<>""),TODAY()-$AY24,$AZ24-$AY24))))) -> 0 | BO24: =IF(OR($AR24<>"ASSESSMENT REPORT ISSUED"),"",IF($BN24<>"",$BN24,"")) | BP24: =IF($AR24="ASSESSMENT REPORT ISSUED","1",IF(AND($AT24="Closed",$AR24<>"Pending"),"1","")) -> 1 | BQ24: =IF(AND($AR24="Pending",$BN24>140),$BN24,"") | BR24: =IF(BQ24="","","1") | BT24: =IFERROR(IF(INDEX(Program_01!$BZ:$BZ,MATCH($B24,Program_01!$A:$A,0))=DATE(1900,1,0),"",INDEX(Program_01!$BZ:$BZ,MATCH($B24,Program_01!$A:$A,0))),"") | BU24: =IF(OR($I24="",$AV24="",$AM24<>0,$BA24="N/A",$AZ24=""),"",IF(AND($BA24="",$AZ24<>""),TODAY()-$AZ24,$BA24-$AZ24)) | BV24: =IF(OR($AS24="Determination Issued",$AS24="VO Issued"),$BU24,"") | BW24: =IF(OR($AT24="CLOSED",$AS24="Determination Issued",$AS24="VO Issued"),"1","") -> 1 | BX24: =IF(OR($AS24="Determination Issued",$AS24="VO Issued",$AS24="Rejected",$AS24="Canceled",$AS24="Superseded",$AS24="Not Applicable",$BU24=""),"",IF($BU24>90,$BU24,"")) | BY24: =IF(BX24="","","1") | CA24: =IF($I24="","",IF(AND($AR24="Assessment Report Issued",$AZ24<>""),"Y","N")) -> N | CB24: =IF($I24="","",IF(OR($AS24="Determination Issued",$AS24="VO Issued"),"Y","N")) -> N | CC24: =IFERROR(INDEX(Program_01!$CE:$CE,MATCH($B24,Program_01!$A:$A,0)),"") -> 0 | CD24: =MAX(S24,CC24) -> 45277 | CG24: =IFERROR(INDEX(Program_01!$AT:$AT,MATCH($B24,Program_01!$A:$A,0)),"") -> N/A | CH24: =IFERROR(INDEX(Program_01!$AX:$AX,MATCH($B24,Program_01!$A:$A,0)),"") -> 0
A25: Program_01 | B25: 7 | C25: =IFERROR(INDEX(Program_01!$B:$B,MATCH($B25,Program_01!$A:$A,0)),"") -> FULL TIA EAR | D25: =IFERROR(INDEX(Program_01!$D:$D,MATCH($B25,Program_01!$A:$A,0)),"") -> 1TB01031C02 | E25: =IFERROR(INDEX(Program_01!$E:$E,MATCH($B25,Program_01!$A:$A,0)),"") -> 1.TB.01.031.01 | F25: =IFERROR(INDEX(Program_01!$F:$F,MATCH($B25,Program_01!$A:$A,0)),"") -> The Marina | G25: =IFERROR(INDEX(Program_01!$G:$G,MATCH($B25,Program_01!$A:$A,0)),"") -> Triple Bay Marina Basin - Design and Build Main Contract | H25: =IFERROR(INDEX(Program_01!$H:$H,MATCH($B25,Program_01!$A:$A,0)),"") -> Alsaad General Contracting Company | I25: =IFERROR(IF($D25="","",INDEX($J$16:$O$16,MATCH(1,J25:O25,0))),"") -> EOT | J25: =IFERROR(INDEX(Program_01!$I:$I,MATCH($B25,Program_01!$A:$A,0)),"") -> 1 | K25: =IFERROR(INDEX(Program_01!$J:$J,MATCH($B25,Program_01!$A:$A,0)),"") -> 0 | L25: =IFERROR(INDEX(Program_01!$K:$K,MATCH($B25,Program_01!$A:$A,0)),"") -> 0 | M25: =IFERROR(INDEX(Program_01!$L:$L,MATCH($B25,Program_01!$A:$A,0)),"") -> 0 | N25: =IFERROR(INDEX(Program_01!$L:$L,MATCH($B25,Program_01!$A:$A,0)),"") -> 0 | O25: =IFERROR(INDEX(Program_01!$N:$N,MATCH($B25,Program_01!$A:$A,0)),"") -> 0 | Q25: =IFERROR(INDEX(Program_01!$C:$C,MATCH($B25,Program_01!$A:$A,0)),"") -> Notice of Disatisfaction - Engineer's Instruction No. 5, 7, 9 & 10 (EOT) | R25: =IFERROR(INDEX(Program_01!$V:$V,MATCH($B25,Program_01!$A:$A,0)),"") -> 1TB01031-031C02-ALS-LTR-0231 | S25: =IFERROR(INDEX(Program_01!$W:$W,MATCH($B25,Program_01!$A:$A,0)),"") -> 45085 | U25: =IFERROR(INDEX(Program_01!$Z:$Z,MATCH($B25,Program_01!$A:$A,0)),"") -> 1TB01031-031D03-WSP-LTR-0301 | V25: =IFERROR(INDEX(Program_01!$AA:$AA,MATCH($B25,Program_01!$A:$A,0)),"") -> 45119 | W25: =IF(OR($S25="",$V25="N/A"),"",IF(AND($S25<>0,$V25=0),TODAY()-$S25,IF(AND($S25<>"",$V25<>""),$V25-$S25))) -> 34 | Y25: =IFERROR(INDEX(Program_01!$BD:$BD,MATCH($B25,Program_01!$A:$A,0)),"") -> WSP-LTR-000021 dated 1 Dec 21 SGC-LTR-000015 dated 25 Nov 21 ALS01031-GENCORR-000346 dated 04 Dec 2023 AMA01031-GENCORR-000747 dated 12 Oct 23 ALS01031-GENCORR-000355 dated 19 Dec 23 AMA01031-GENCORR-000772 dated 19 Dec 23 ALS01031-GENCORR-000372 dated 19 Feb 24 AMA01031-GENCORR-000818 dated 22 Feb 24 ALS01031-GENCORR-000412 dated 6 Jul 24 ALS01031-GENCORR-000416 dated 29 Jul 24 ALS01031-GENCORR-000417 dated 30 Jul 24 | AA25: =IFERROR(IF((INDEX(Program_01!$AD:$AD,MATCH($B25,Program_01!$A:$A,0))=""),INDEX(Program_01!$V:$V,MATCH($B25,Program_01!$A:$A,0)),INDEX(Program_01!$AD:$AD,MATCH($B25,Program_01!$A:$A,0))),"") -> ALS01031-GENCORR-000412 dated 6 Jul 24 ALS01031-GENCORR-000416 29 Jul 24 ALS01031-GENCORR-000417 | AB25: =IFERROR(IF((INDEX(Program_01!$AE:$AE,MATCH($B25,Program_01!$A:$A,0))=""),INDEX(Program_01!$W:$W,MATCH($B25,Program_01!$A:$A,0)),INDEX(Program_01!$AE:$AE,MATCH($B25,Program_01!$A:$A,0))),"") -> 45503 | AC25: =IFERROR(IF($I25="EOT",INDEX(Program_01!$AN:$AN,MATCH($B25,Program_01!$A:$A,0)),INDEX(Program_01!$AY:$AY,MATCH($B25,Program_01!$A:$A,0))),"") -> N/A | AD25: =IFERROR(IF($I25="EOT",INDEX(Program_01!$AO:$AO,MATCH($B25,Program_01!$A:$A,0)),INDEX(Program_01!$AZ:$AZ,MATCH($B25,Program_01!$A:$A,0))),"") -> N/A | AH25: =IF(OR($D25="",$AS25="VO Issued",$AS25="Open"),"",IF(OR($AC25="Rejected",$AC25="Superseded",$AC25="Dealt Separately"),$AC25,IF($I25="EOT",INDEX(Program_01!$AR:$AR,MATCH($B25,Program_01!$A:$A,0)),INDEX(Program_01!$BB:$BB,MATCH($B25,Program_01!$A:$A,0))))) -> 0 | AI25: =IF(OR($A25="",$B25="",$I25="",$AS25="VO Issued",$AS25="Open"),"",IF(OR($AD25="N/A"),$AD25,IF($I25="EOT",INDEX(Program_01!$AS:$AS,MATCH($B25,Program_01!$A:$A,0)),INDEX(Program_01!$BC:$BC,MATCH($B25,Program_01!$A:$A,0))))) -> N/A | AJ25: =IF(OR($D25="",$I25="",$AS25="Determination Issued",$AS25="Rejected",$AS25="Open"),"",IF(OR($AH25="Rejected",$AH25="Dealt Separately",$AH25="Superseded",$AH25="Withdrawn"),"N/A",IF($I25="EOT",INDEX(Program_01!AR:AR,MATCH($B25,Program_01!A:A,0)),INDEX(Program_01!BB:BB,MATCH($B25,Program_01!A:A,0))))) -> 0 | AK25: =IF(OR($A25="",$B25="",$I25="",$AS25="Determination Issued",$AS25="Rejected",$AS25="Open"),"",IF($AJ25="N/A","N/A",IF($I25="EOT",INDEX(Program_01!AS:AS,MATCH($B25,Program_01!A:A,0)),INDEX(Program_01!BC:BC,MATCH($B25,Program_01!A:A,0))))) -> 0 | AM25: =IFERROR(INDEX(Program_01!$BT:$BT,MATCH($B25,Program_01!$A:$A,0)),"") -> 0 | AN25: =IFERROR(INDEX(Program_01!$BU:$BU,MATCH($B25,Program_01!$A:$A,0)),"") -> Yes | AO25: =IFERROR(INDEX(Program_01!$BV:$BV,MATCH($B25,Program_01!$A:$A,0)),"") -> 0 | AP25: =IF(OR($AN25="Yes",$AO25="Yes"),"1","") -> 1 | AQ25: =IFERROR(INDEX(Program_01!$BN:$BN,MATCH($B25,Program_01!$A:$A,0)),"") -> 0 | AR25: =IFERROR(INDEX(Program_01!$BO:$BO,MATCH($B25,Program_01!$A:$A,0)),"") -> Not Applicable | AS25: =IFERROR(INDEX(Program_01!$BP:$BP,MATCH($B25,Program_01!$A:$A,0)),"") -> Dealt Separately | AT25: =IFERROR(INDEX(Program_01!$BQ:$BQ,MATCH($B25,Program_01!$A:$A,0)),"") -> Closed | AU25: =IFERROR(INDEX(Program_01!$BR:$BR,MATCH($B25,Program_01!$A:$A,0)),"") -> 19-Mar-24 - The initial assessment was informally issued to Alsaad, and we are awaiting its comments. We also request further information/supporting documents from Alsaad. 22 Apr 24: a meeting was held on 21 Apr 24, contractor scheduled a meeting with planning to dicuss the window analysis. a letter was issued to the contractor to extend the contract for 2 months without cost through a VO. 06 May 24: action with contractor 03 Jun 24: Ditto 24 Jun 24: Ditto, awaiting response from contractor 15 Jul 24: Ditto, in the meantime Commercial to send a reminder to the contractor 29 Jul 24: Ditto 30 Jul 24: Contractor submitted a consolidated claim that includes fixed jetties VO (item 31 below) for the 80 days along with the updated program of work. DVO for EOT - 1 has been issued for 324 days | AV25: =IF($I25="","",IF($S25>$AV$16,"",IF($AS25="OPEN","OPEN",IF($AS25="","",IF(AND($AS25<>"OPEN",$AT25="CLOSED"),"CLOSED",IF(AND($AS25<>"OPEN",$AT25<>"CLOSED"),"OPEN","")))))) -> CLOSED | AW25: =IF($I25="","",IF($S25<$AW$16,"",IF($AS25="OPEN","OPEN",IF($AS25="","",IF(AND($AS25<>"OPEN",$AT25="CLOSED"),"CLOSED",IF(AND($AS25<>"OPEN",$AT25<>"CLOSED"),"OPEN","")))))) | AX25: =IF(OR($AV25="OPEN",$AV25="CLOSED"),$AV25,$AW25) -> CLOSED | AY25: =IF(C25="HLEAR",BC25,AB25) -> 45503 | AZ25: =IF($AD25=0,"",AD25) -> N/A | BA25: =IF(AND($AI25="",$AK25=""),"",IF($AI25="",$AK25,$AI25)) -> N/A | BC25: =IFERROR(INDEX(Program_01!BF:BF,MATCH($B25,Program_01!$A:$A,0)),"") -> 45503 | BD25: =IFERROR(INDEX(Program_01!BG:BG,MATCH($B25,Program_01!$A:$A,0)),"") -> N/A | BE25: =IFERROR(INDEX(Program_01!BH:BH,MATCH($B25,Program_01!$A:$A,0)),"") -> 0 | BF25: =IFERROR(INDEX(Program_01!BI:BI,MATCH($B25,Program_01!$A:$A,0)),"") -> 0 | BG25: =IFERROR(INDEX(Program_01!BJ:BJ,MATCH($B25,Program_01!$A:$A,0)),"") -> 0 | BH25: =IFERROR(INDEX(Program_01!BK:BK,MATCH($B25,Program_01!$A:$A,0)),"") -> 0 | BI25: =IFERROR(INDEX(Program_01!BL:BL,MATCH($B25,Program_01!$A:$A,0)),"") -> 0 | BK25: =IFERROR(IF(INDEX(Program_01!$BX:$BX,MATCH($B25,Program_01!$A:$A,0))=DATE(1900,1,0),"",INDEX(Program_01!$BX:$BX,MATCH($B25,Program_01!$A:$A,0))),"") -> 45512 | BL25: =IFERROR(IF(INDEX(Program_01!$BY:$BY,MATCH($B25,Program_01!$A:$A,0))=DATE(1900,1,0),"",INDEX(Program_01!$BY:$BY,MATCH($B25,Program_01!$A:$A,0))),"") | BM25: =IF(OR($AZ25="",$AZ25="N/A"),"",IF(AND($AZ25="",$AY25<>""),TODAY()-$AY25,$AZ25-$AY25)) | BN25: =IF(OR($C25="DEOT",$C25="N/A",$I25=""),"",IF(OR($AM25="Revise & resubmit",$AT25="Awaiting Conclusion of EoT",$AR25="Not Applicable",$AY25=0,$AY25="TBA",$AZ25="N/A",AY25=0),0,IF(AND($AR25="Assessment Report Issued",$AT25<>""),$AZ25-$AY25,IF(AND($AR25="Pending",$AT25="Contractor"),"",IF(AND($AZ25="",$AY25<>""),TODAY()-$AY25,$AZ25-$AY25))))) -> 0 | BO25: =IF(OR($AR25<>"ASSESSMENT REPORT ISSUED"),"",IF($BN25<>"",$BN25,"")) | BP25: =IF($AR25="ASSESSMENT REPORT ISSUED","1",IF(AND($AT25="Closed",$AR25<>"Pending"),"1","")) -> 1 | BQ25: =IF(AND($AR25="Pending",$BN25>140),$BN25,"") | BR25: =IF(BQ25="","","1") | BT25: =IFERROR(IF(INDEX(Program_01!$BZ:$BZ,MATCH($B25,Program_01!$A:$A,0))=DATE(1900,1,0),"",INDEX(Program_01!$BZ:$BZ,MATCH($B25,Program_01!$A:$A,0))),"") | BU25: =IF(OR($I25="",$AV25="",$AM25<>0,$BA25="N/A",$AZ25=""),"",IF(AND($BA25="",$AZ25<>""),TODAY()-$AZ25,$BA25-$AZ25)) | BV25: =IF(OR($AS25="Determination Issued",$AS25="VO Issued"),$BU25,"") | BW25: =IF(OR($AT25="CLOSED",$AS25="Determination Issued",$AS25="VO Issued"),"1","") -> 1 | BX25: =IF(OR($AS25="Determination Issued",$AS25="VO Issued",$AS25="Rejected",$AS25="Canceled",$AS25="Superseded",$AS25="Not Applicable",$BU25=""),"",IF($BU25>90,$BU25,"")) | BY25: =IF(BX25="","","1") | CA25: =IF($I25="","",IF(AND($AR25="Assessment Report Issued",$AZ25<>""),"Y","N")) -> N | CB25: =IF($I25="","",IF(OR($AS25="Determination Issued",$AS25="VO Issued"),"Y","N")) -> N | CC25: =IFERROR(INDEX(Program_01!$CE:$CE,MATCH($B25,Program_01!$A:$A,0)),"") -> 0 | CD25: =MAX(S25,CC25) -> 45085 | CG25: =IFERROR(INDEX(Program_01!$AT:$AT,MATCH($B25,Program_01!$A:$A,0)),"") -> 0 | CH25: =IFERROR(INDEX(Program_01!$AX:$AX,MATCH($B25,Program_01!$A:$A,0)),"") -> 0
A26: Program_01 | B26: 8 | C26: =IFERROR(INDEX(Program_01!$B:$B,MATCH($B26,Program_01!$A:$A,0)),"") -> COST EAR | D26: =IFERROR(INDEX(Program_01!$D:$D,MATCH($B26,Program_01!$A:$A,0)),"") -> 1TB01031C02 | E26: =IFERROR(INDEX(Program_01!$E:$E,MATCH($B26,Program_01!$A:$A,0)),"") -> 1.TB.01.031.01 | F26: =IFERROR(INDEX(Program_01!$F:$F,MATCH($B26,Program_01!$A:$A,0)),"") -> The Marina | G26: =IFERROR(INDEX(Program_01!$G:$G,MATCH($B26,Program_01!$A:$A,0)),"") -> Triple Bay Marina Basin - Design and Build Main Contract | H26: =IFERROR(INDEX(Program_01!$H:$H,MATCH($B26,Program_01!$A:$A,0)),"") -> Alsaad General Contracting Company | I26: =IFERROR(IF($D26="","",INDEX($J$16:$O$16,MATCH(1,J26:O26,0))),"") -> Prolongation | J26: =IFERROR(INDEX(Program_01!$I:$I,MATCH($B26,Program_01!$A:$A,0)),"") -> 0 | K26: =IFERROR(INDEX(Program_01!$J:$J,MATCH($B26,Program_01!$A:$A,0)),"") -> 1 | L26: =IFERROR(INDEX(Program_01!$K:$K,MATCH($B26,Program_01!$A:$A,0)),"") -> 0 | M26: =IFERROR(INDEX(Program_01!$L:$L,MATCH($B26,Program_01!$A:$A,0)),"") -> 0 | N26: =IFERROR(INDEX(Program_01!$L:$L,MATCH($B26,Program_01!$A:$A,0)),"") -> 0 | O26: =IFERROR(INDEX(Program_01!$N:$N,MATCH($B26,Program_01!$A:$A,0)),"") -> 0 | Q26: =IFERROR(INDEX(Program_01!$C:$C,MATCH($B26,Program_01!$A:$A,0)),"") -> EOT 1 Prolongation Engineer's Instruction No. 5, 7, 9 & 10 | R26: =IFERROR(INDEX(Program_01!$V:$V,MATCH($B26,Program_01!$A:$A,0)),"") -> 1TB01031-031C02-ALS-LTR-0231 | S26: =IFERROR(INDEX(Program_01!$W:$W,MATCH($B26,Program_01!$A:$A,0)),"") -> 45085 | U26: =IFERROR(INDEX(Program_01!$Z:$Z,MATCH($B26,Program_01!$A:$A,0)),"") -> 1TB01031-031D03-WSP-LTR-0301 | V26: =IFERROR(INDEX(Program_01!$AA:$AA,MATCH($B26,Program_01!$A:$A,0)),"") -> 45119 | W26: =IF(OR($S26="",$V26="N/A"),"",IF(AND($S26<>0,$V26=0),TODAY()-$S26,IF(AND($S26<>"",$V26<>""),$V26-$S26))) -> 34 | Y26: =IFERROR(INDEX(Program_01!$BD:$BD,MATCH($B26,Program_01!$A:$A,0)),"") -> WSP-LTR-000021 dated 1 Dec 21 SGC-LTR-000015 dated 25 Nov 21 ALS01031-GENCORR-000346 dated 04 Dec 2023 AMA01031-GENCORR-000747 dated 12 Oct 23 ALS01031-GENCORR-000355 dated 19 Dec 23 AMA01031-GENCORR-000772 dated 19 Dec 23 ALS01031-GENCORR-000372 dated 19 Feb 24 AMA01031-GENCORR-000818 dated 22 Feb 24 1TB01031-031C02-AMA-LTR-0028 dated 20 Oct 24 ALS01031-GENCORR-000430 dated 18 Nov 24 (confirmation of contractor's agreement to the determination of One Hundred three (103) days Extension to the Time for Completion of the Works with “Zero” Cost Impact on final Contract Value received for “EOT-02" via Aconex ref. 1TB01031-031C02-AMA-LTR-0028 dated October 20, 2024) 1TB01031-031C02-AMA-LTR-0043 dated O8 May 2025 | AA26: =IFERROR(IF((INDEX(Program_01!$AD:$AD,MATCH($B26,Program_01!$A:$A,0))=""),INDEX(Program_01!$V:$V,MATCH($B26,Program_01!$A:$A,0)),INDEX(Program_01!$AD:$AD,MATCH($B26,Program_01!$A:$A,0))),"") -> ALS01031-GENCORR-000412 dated 6 Jul 24 ALS01031-GENCORR-000416 29 Jul 24 ALS01031-GENCORR-000417 30 Jul 24 ALS01031-GENCORR-000419 08 Aug 24 ALS01031-GENCORR-000430 on 18 Nov 24 1TB01031-031C02-ALS-LTR-0311 | AB26: =IFERROR(IF((INDEX(Program_01!$AE:$AE,MATCH($B26,Program_01!$A:$A,0))=""),INDEX(Program_01!$W:$W,MATCH($B26,Program_01!$A:$A,0)),INDEX(Program_01!$AE:$AE,MATCH($B26,Program_01!$A:$A,0))),"") -> 45851 | AC26: =IFERROR(IF($I26="EOT",INDEX(Program_01!$AN:$AN,MATCH($B26,Program_01!$A:$A,0)),INDEX(Program_01!$AY:$AY,MATCH($B26,Program_01!$A:$A,0))),"") -> N/A | AD26: =IFERROR(IF($I26="EOT",INDEX(Program_01!$AO:$AO,MATCH($B26,Program_01!$A:$A,0)),INDEX(Program_01!$AZ:$AZ,MATCH($B26,Program_01!$A:$A,0))),"") -> N/A | AH26: =IF(OR($D26="",$AS26="VO Issued",$AS26="Open"),"",IF(OR($AC26="Rejected",$AC26="Superseded",$AC26="Dealt Separately"),$AC26,IF($I26="EOT",INDEX(Program_01!$AR:$AR,MATCH($B26,Program_01!$A:$A,0)),INDEX(Program_01!$BB:$BB,MATCH($B26,Program_01!$A:$A,0))))) -> 0 | AI26: =IF(OR($A26="",$B26="",$I26="",$AS26="VO Issued",$AS26="Open"),"",IF(OR($AD26="N/A"),$AD26,IF($I26="EOT",INDEX(Program_01!$AS:$AS,MATCH($B26,Program_01!$A:$A,0)),INDEX(Program_01!$BC:$BC,MATCH($B26,Program_01!$A:$A,0))))) -> N/A | AJ26: =IF(OR($D26="",$I26="",$AS26="Determination Issued",$AS26="Rejected",$AS26="Open"),"",IF(OR($AH26="Rejected",$AH26="Dealt Separately",$AH26="Superseded",$AH26="Withdrawn"),"N/A",IF($I26="EOT",INDEX(Program_01!AR:AR,MATCH($B26,Program_01!A:A,0)),INDEX(Program_01!BB:BB,MATCH($B26,Program_01!A:A,0))))) -> 0 | AK26: =IF(OR($A26="",$B26="",$I26="",$AS26="Determination Issued",$AS26="Rejected",$AS26="Open"),"",IF($AJ26="N/A","N/A",IF($I26="EOT",INDEX(Program_01!AS:AS,MATCH($B26,Program_01!A:A,0)),INDEX(Program_01!BC:BC,MATCH($B26,Program_01!A:A,0))))) -> 0 | AM26: =IFERROR(INDEX(Program_01!$BT:$BT,MATCH($B26,Program_01!$A:$A,0)),"") -> 0 | AN26: =IFERROR(INDEX(Program_01!$BU:$BU,MATCH($B26,Program_01!$A:$A,0)),"") -> 0 | AO26: =IFERROR(INDEX(Program_01!$BV:$BV,MATCH($B26,Program_01!$A:$A,0)),"") -> 0 | AP26: =IF(OR($AN26="Yes",$AO26="Yes"),"1","") | AQ26: =IFERROR(INDEX(Program_01!$BN:$BN,MATCH($B26,Program_01!$A:$A,0)),"") -> 0 | AR26: =IFERROR(INDEX(Program_01!$BO:$BO,MATCH($B26,Program_01!$A:$A,0)),"") -> Not Applicable | AS26: =IFERROR(INDEX(Program_01!$BP:$BP,MATCH($B26,Program_01!$A:$A,0)),"") -> Dealt Separately | AT26: =IFERROR(INDEX(Program_01!$BQ:$BQ,MATCH($B26,Program_01!$A:$A,0)),"") -> Closed | AU26: =IFERROR(INDEX(Program_01!$BR:$BR,MATCH($B26,Program_01!$A:$A,0)),"") -> 14 Jul 25: The Contractor responded via 1TB01031-031C02-ALS-LTR-0311 on 13 Jul by rejecting the Employer’s ten-day deadline, asserting that all required substantiations were already submitted and discussed in prior meetings, contractor further requests a final meeting to resolve the matter, and seeks release of the undisputed SAR 7.29 million. 24-July-25: Al Saad has accepted the Employer's Assessment of SAR 7.29M in the meeting held with ED commercial on 24th July 2025. Formal acceptance is awaited from Al Saad. 27 Jul 25: Ditto 10 Aug 25: RSG Commercial is in the process of EOT Cost report and Determination will follow after report approval 25 Aug 25: EOT Cost Report sent to Claims Team on 24 August 2025 26 Aug 25: Commercial to arrange a meeting to discuss what costs we allow and the substantiation we require 04 Sep 25: revised concurrency analysis for Alsaad from the site planning team sent to Forensic planning for review 08 Sep 25: meeting scheduled for 08 Sep 25 btw claims & commercial to discuss & finalise, action still with planning to review the 22 days. Targeted to revert by 11 Sep 25 15 Sep 25: Targeted to conclude the final review by 16 Sep 25 29 Sep 25: Planning to confirm by end of the day 02 Oct 25: Forensic Planning finalised the re-assessment of the 22 days concurrent delay and concluded to a reduction of 21 days. Draft report sent to commercial for finalisation 04 OCT 25:Further clarifications from the Claim team regarding the prolongation cost assessment from Nigel have been addressed, and the final response is awaited. 06 Oct 25: email sent to commercial to provide further particulars and review the excel sheet 08 Oct 25: Commercial responded with additional documents and clarifications 09 Oct 25: EOT cost summary excel sent back to commercial to review the ‘MIS’ tab for the months from April ’22 to Aug ’22 and Nov ’22 20 Oct 25: Request for Approval – Final Account Settlement for Al Saad General Cont put in WF-015055 03 Nov 25: Fianl account issued to Al SAAD via 1TB01031-031C02-AMA-RFA-CM-0016, awaiting acceptance from contractor 17 Nov 25: Ditto 29 Nov 25: RFA has been approved to process the final payment via 1TB01031-031C02-AMA-RFA-CM-0016, awaiting approval of TOC to process FAS 01 Dec 25: This item considered closed as it is deemed to be closed by an RFA NOTE: it has been decided that an assessment report will no longer be prepared and instead will be processed as a RFA. | AV26: =IF($I26="","",IF($S26>$AV$16,"",IF($AS26="OPEN","OPEN",IF($AS26="","",IF(AND($AS26<>"OPEN",$AT26="CLOSED"),"CLOSED",IF(AND($AS26<>"OPEN",$AT26<>"CLOSED"),"OPEN","")))))) -> CLOSED | AW26: =IF($I26="","",IF($S26<$AW$16,"",IF($AS26="OPEN","OPEN",IF($AS26="","",IF(AND($AS26<>"OPEN",$AT26="CLOSED"),"CLOSED",IF(AND($AS26<>"OPEN",$AT26<>"CLOSED"),"OPEN","")))))) | AX26: =IF(OR($AV26="OPEN",$AV26="CLOSED"),$AV26,$AW26) -> CLOSED | AY26: =IF(C26="HLEAR",BC26,AB26) -> 45851 | AZ26: =IF($AD26=0,"",AD26) -> N/A | BA26: =IF(AND($AI26="",$AK26=""),"",IF($AI26="",$AK26,$AI26)) -> N/A | BC26: =IFERROR(INDEX(Program_01!BF:BF,MATCH($B26,Program_01!$A:$A,0)),"") -> 45851 | BD26: =IFERROR(INDEX(Program_01!BG:BG,MATCH($B26,Program_01!$A:$A,0)),"") -> N/A | BE26: =IFERROR(INDEX(Program_01!BH:BH,MATCH($B26,Program_01!$A:$A,0)),"") -> 0 | BF26: =IFERROR(INDEX(Program_01!BI:BI,MATCH($B26,Program_01!$A:$A,0)),"") -> N/A | BG26: =IFERROR(INDEX(Program_01!BJ:BJ,MATCH($B26,Program_01!$A:$A,0)),"") -> 0 | BH26: =IFERROR(INDEX(Program_01!BK:BK,MATCH($B26,Program_01!$A:$A,0)),"") -> 0 | BI26: =IFERROR(INDEX(Program_01!BL:BL,MATCH($B26,Program_01!$A:$A,0)),"") -> 0 | BK26: =IFERROR(IF(INDEX(Program_01!$BX:$BX,MATCH($B26,Program_01!$A:$A,0))=DATE(1900,1,0),"",INDEX(Program_01!$BX:$BX,MATCH($B26,Program_01!$A:$A,0))),"") -> 45992 | BL26: =IFERROR(IF(INDEX(Program_01!$BY:$BY,MATCH($B26,Program_01!$A:$A,0))=DATE(1900,1,0),"",INDEX(Program_01!$BY:$BY,MATCH($B26,Program_01!$A:$A,0))),"") | BM26: =IF(OR($AZ26="",$AZ26="N/A"),"",IF(AND($AZ26="",$AY26<>""),TODAY()-$AY26,$AZ26-$AY26)) | BN26: =IF(OR($C26="DEOT",$C26="N/A",$I26=""),"",IF(OR($AM26="Revise & resubmit",$AT26="Awaiting Conclusion of EoT",$AR26="Not Applicable",$AY26=0,$AY26="TBA",$AZ26="N/A",AY26=0),0,IF(AND($AR26="Assessment Report Issued",$AT26<>""),$AZ26-$AY26,IF(AND($AR26="Pending",$AT26="Contractor"),"",IF(AND($AZ26="",$AY26<>""),TODAY()-$AY26,$AZ26-$AY26))))) -> 0 | BO26: =IF(OR($AR26<>"ASSESSMENT REPORT ISSUED"),"",IF($BN26<>"",$BN26,"")) | BP26: =IF($AR26="ASSESSMENT REPORT ISSUED","1",IF(AND($AT26="Closed",$AR26<>"Pending"),"1","")) -> 1 | BQ26: =IF(AND($AR26="Pending",$BN26>140),$BN26,"") | BR26: =IF(BQ26="","","1") | BT26: =IFERROR(IF(INDEX(Program_01!$BZ:$BZ,MATCH($B26,Program_01!$A:$A,0))=DATE(1900,1,0),"",INDEX(Program_01!$BZ:$BZ,MATCH($B26,Program_01!$A:$A,0))),"") | BU26: =IF(OR($I26="",$AV26="",$AM26<>0,$BA26="N/A",$AZ26=""),"",IF(AND($BA26="",$AZ26<>""),TODAY()-$AZ26,$BA26-$AZ26)) | BV26: =IF(OR($AS26="Determination Issued",$AS26="VO Issued"),$BU26,"") | BW26: =IF(OR($AT26="CLOSED",$AS26="Determination Issued",$AS26="VO Issued"),"1","") -> 1 | BX26: =IF(OR($AS26="Determination Issued",$AS26="VO Issued",$AS26="Rejected",$AS26="Canceled",$AS26="Superseded",$AS26="Not Applicable",$BU26=""),"",IF($BU26>90,$BU26,"")) | BY26: =IF(BX26="","","1") | CA26: =IF($I26="","",IF(AND($AR26="Assessment Report Issued",$AZ26<>""),"Y","N")) -> N | CB26: =IF($I26="","",IF(OR($AS26="Determination Issued",$AS26="VO Issued"),"Y","N")) -> N | CC26: =IFERROR(INDEX(Program_01!$CE:$CE,MATCH($B26,Program_01!$A:$A,0)),"") -> 0 | CD26: =MAX(S26,CC26) -> 45085 | CG26: =IFERROR(INDEX(Program_01!$AT:$AT,MATCH($B26,Program_01!$A:$A,0)),"") -> 46455402 | CH26: =IFERROR(INDEX(Program_01!$AX:$AX,MATCH($B26,Program_01!$A:$A,0)),"") -> 14631531 | CI26: Dealt Separately
A27: Program_01 | B27: 9 | C27: =IFERROR(INDEX(Program_01!$B:$B,MATCH($B27,Program_01!$A:$A,0)),"") -> FULL TIA EAR | D27: =IFERROR(INDEX(Program_01!$D:$D,MATCH($B27,Program_01!$A:$A,0)),"") -> 1TB01006C03 | E27: =IFERROR(INDEX(Program_01!$E:$E,MATCH($B27,Program_01!$A:$A,0)),"") -> 1.TB.01.006.99 | F27: =IFERROR(INDEX(Program_01!$F:$F,MATCH($B27,Program_01!$A:$A,0)),"") -> Village Boutique Hotel | G27: =IFERROR(INDEX(Program_01!$G:$G,MATCH($B27,Program_01!$A:$A,0)),"") -> Concrete Structure and Civil Works for Village Boutique Hotel | H27: =IFERROR(INDEX(Program_01!$H:$H,MATCH($B27,Program_01!$A:$A,0)),"") -> Mounes Mohamed Al Shayeb and Partners for Civil Construction - MOBCO | I27: =IFERROR(IF($D27="","",INDEX($J$16:$O$16,MATCH(1,J27:O27,0))),"") -> EOT | J27: =IFERROR(INDEX(Program_01!$I:$I,MATCH($B27,Program_01!$A:$A,0)),"") -> 1 | K27: =IFERROR(INDEX(Program_01!$J:$J,MATCH($B27,Program_01!$A:$A,0)),"") -> 0 | L27: =IFERROR(INDEX(Program_01!$K:$K,MATCH($B27,Program_01!$A:$A,0)),"") -> 0 | M27: =IFERROR(INDEX(Program_01!$L:$L,MATCH($B27,Program_01!$A:$A,0)),"") -> 0 | N27: =IFERROR(INDEX(Program_01!$L:$L,MATCH($B27,Program_01!$A:$A,0)),"") -> 0 | O27: =IFERROR(INDEX(Program_01!$N:$N,MATCH($B27,Program_01!$A:$A,0)),"") -> 0 | Q27: =IFERROR(INDEX(Program_01!$C:$C,MATCH($B27,Program_01!$A:$A,0)),"") -> EOT Claim No. 3 - up to Nov 10, 2023 (Delay in Issuing IFC Drawings, Delay in Providing Benchmarks and coordination drawings with SANSRS Coordinates, Delay in providing access (site handover) - update of Item 5 | R27: =IFERROR(INDEX(Program_01!$V:$V,MATCH($B27,Program_01!$A:$A,0)),"") -> 1TB01006-006C03-MOO-LTR-0063 | S27: =IFERROR(INDEX(Program_01!$W:$W,MATCH($B27,Program_01!$A:$A,0)),"") -> 45258 | U27: =IFERROR(INDEX(Program_01!$Z:$Z,MATCH($B27,Program_01!$A:$A,0)),"") -> 1TB01006-006C03-AMA-LTR-0113 | V27: =IFERROR(INDEX(Program_01!$AA:$AA,MATCH($B27,Program_01!$A:$A,0)),"") -> 45312 | W27: =IF(OR($S27="",$V27="N/A"),"",IF(AND($S27<>0,$V27=0),TODAY()-$S27,IF(AND($S27<>"",$V27<>""),$V27-$S27))) -> 54 | Y27: =IFERROR(INDEX(Program_01!$BD:$BD,MATCH($B27,Program_01!$A:$A,0)),"") -> 1TB01006-006C03-AMA-LTR-0120 dated 04 Feb 24 Rejected,Revise and Resubmit Contractor submissted a revised claim with a new cut off date as EOT 4, however, the actual claim is still EOT 3 Contractor submitted EOT 5 under letter 1TB01006-006C03-MOO-LTR-0098 dated 12 June 2024 which was rejects the claim in its entirety under Clause 20.1.7 as it does not comply with the requirements of Clause 20.1 (Contractor’s Claims), Clause 8.4 (Extension of Time) or Clause 8.5 (Time Impact Analysis). Consequently, the Contractor is required to resubmit its fully detailed claim within 20 Business Days of this letter. 10 Nov 24: Contractor issued a letter to follow up on Employer's review on the claim via letter 1TB01006-006C03-MOO-LTR-0113 on 07 Nov 24 1TB01006-006C03-AMA-LTR-0148 dated 29 Jan 25 1TB01006-006C03-MOO-LTR-0118 dated 20 Feb 25 | AA27: =IFERROR(IF((INDEX(Program_01!$AD:$AD,MATCH($B27,Program_01!$A:$A,0))=""),INDEX(Program_01!$V:$V,MATCH($B27,Program_01!$A:$A,0)),INDEX(Program_01!$AD:$AD,MATCH($B27,Program_01!$A:$A,0))),"") -> 1TB01006-006C03-MOO-LTR-0082 dated 28 Jan 24 1TB01006-006C03-MOO-LTR-0094 dated 05 Apr 24 1TB01006-006C03-MOO-LTR-0098 dated 14 Jun 24 1TB01006-006C03-MOO-LTR-0100 dated 25 Jul 24 1TB01006-006C03-MOO-LTR-0110 dated 29Sep 24 1TB01006-006C03-MOO-LTR-0118 | AB27: =IFERROR(IF((INDEX(Program_01!$AE:$AE,MATCH($B27,Program_01!$A:$A,0))=""),INDEX(Program_01!$W:$W,MATCH($B27,Program_01!$A:$A,0)),INDEX(Program_01!$AE:$AE,MATCH($B27,Program_01!$A:$A,0))),"") -> 45708 | AC27: =IFERROR(IF($I27="EOT",INDEX(Program_01!$AN:$AN,MATCH($B27,Program_01!$A:$A,0)),INDEX(Program_01!$AY:$AY,MATCH($B27,Program_01!$A:$A,0))),"") -> 1TB01006-006C03-AMA-LTR-0159 | AD27: =IFERROR(IF($I27="EOT",INDEX(Program_01!$AO:$AO,MATCH($B27,Program_01!$A:$A,0)),INDEX(Program_01!$AZ:$AZ,MATCH($B27,Program_01!$A:$A,0))),"") -> 45896 | AH27: =IF(OR($D27="",$AS27="VO Issued",$AS27="Open"),"",IF(OR($AC27="Rejected",$AC27="Superseded",$AC27="Dealt Separately"),$AC27,IF($I27="EOT",INDEX(Program_01!$AR:$AR,MATCH($B27,Program_01!$A:$A,0)),INDEX(Program_01!$BB:$BB,MATCH($B27,Program_01!$A:$A,0))))) -> 0 | AI27: =IF(OR($A27="",$B27="",$I27="",$AS27="VO Issued",$AS27="Open"),"",IF(OR($AD27="N/A"),$AD27,IF($I27="EOT",INDEX(Program_01!$AS:$AS,MATCH($B27,Program_01!$A:$A,0)),INDEX(Program_01!$BC:$BC,MATCH($B27,Program_01!$A:$A,0))))) -> 0 | AJ27: =IF(OR($D27="",$I27="",$AS27="Determination Issued",$AS27="Rejected",$AS27="Open"),"",IF(OR($AH27="Rejected",$AH27="Dealt Separately",$AH27="Superseded",$AH27="Withdrawn"),"N/A",IF($I27="EOT",INDEX(Program_01!AR:AR,MATCH($B27,Program_01!A:A,0)),INDEX(Program_01!BB:BB,MATCH($B27,Program_01!A:A,0))))) -> 0 | AK27: =IF(OR($A27="",$B27="",$I27="",$AS27="Determination Issued",$AS27="Rejected",$AS27="Open"),"",IF($AJ27="N/A","N/A",IF($I27="EOT",INDEX(Program_01!AS:AS,MATCH($B27,Program_01!A:A,0)),INDEX(Program_01!BC:BC,MATCH($B27,Program_01!A:A,0))))) -> 0 | AM27: =IFERROR(INDEX(Program_01!$BT:$BT,MATCH($B27,Program_01!$A:$A,0)),"") -> 0 | AN27: =IFERROR(INDEX(Program_01!$BU:$BU,MATCH($B27,Program_01!$A:$A,0)),"") -> Yes | AO27: =IFERROR(INDEX(Program_01!$BV:$BV,MATCH($B27,Program_01!$A:$A,0)),"") -> 0 | AP27: =IF(OR($AN27="Yes",$AO27="Yes"),"1","") -> 1 | AQ27: =IFERROR(INDEX(Program_01!$BN:$BN,MATCH($B27,Program_01!$A:$A,0)),"") -> 0 | AR27: =IFERROR(INDEX(Program_01!$BO:$BO,MATCH($B27,Program_01!$A:$A,0)),"") -> Assessment Report Issued | AS27: =IFERROR(INDEX(Program_01!$BP:$BP,MATCH($B27,Program_01!$A:$A,0)),"") -> EI Issued | AT27: =IFERROR(INDEX(Program_01!$BQ:$BQ,MATCH($B27,Program_01!$A:$A,0)),"") -> Closed | AU27: =IFERROR(INDEX(Program_01!$BR:$BR,MATCH($B27,Program_01!$A:$A,0)),"") -> 27 Oct 25: Shaju to follow up 02 Nov 25 - Planning responded to Notice of Disatisfaction, dissmissing the challnge with valid arguments, letterin the WF-037710 04 Nov 25 - Response to Notice of Disatisfaction was issued Ref. 1TB01006-006C03-AMA-LTR-0164 17 Nov 25: Awaiting response from contractor 01 Dec 25: Ditto, commercial to issue a follow up letter, if a response is not received within 2 weeks, comm to determine 13 Dec 25 - Follow-up letter was sent (Ref. 1TB01006-006C03-AMA-LTR-0170). Contractor responded expressing disagreement (Ref.1TB01006-006C03-MOO-LTR-0141). Letter was sent to Planning to respond 06 Jan 26: Planning provided their input to be incorporated in the reponse 07 Jan 26: Draft response put in Workflow (WF-040043) 12 Jan 26: currently with Stuart P 14 Jan 26 - Resposne to Notice of Dissatisfcation sent on 14 Jan 26 (Ref. 1TB01006-006C03-AMA-LTR-0177) 27 Jan 26: awaiting response from contractor 09 Feb 26: Ditto, Commercial to issue a follow up letter to the contractor 23 Feb 26: follow up letter in WF-041504 08 March 26: Follow-up letter sent to Contractor Ref. 1TB01006-006C03-AMA-LTR-00179 06 April 26: Ditto, awaiting contractor's response 20 April 2026: Awaiting Contractor's response 04 May 26: Commercial to check with delivery team regarding the DD and followwing to that comm to issue a follow up letter if required 14 May 26: Determination letter and EI drafted and to go into workflow (WF- 044034 for ED letter \ WF-044032 for EI). 18 May 26: Ditto 31 May 26: Determination letter and EI Issued : Ref. 1TB01006-006C03-AMA-LTR-0182 | AV27: =IF($I27="","",IF($S27>$AV$16,"",IF($AS27="OPEN","OPEN",IF($AS27="","",IF(AND($AS27<>"OPEN",$AT27="CLOSED"),"CLOSED",IF(AND($AS27<>"OPEN",$AT27<>"CLOSED"),"OPEN","")))))) -> CLOSED | AW27: =IF($I27="","",IF($S27<$AW$16,"",IF($AS27="OPEN","OPEN",IF($AS27="","",IF(AND($AS27<>"OPEN",$AT27="CLOSED"),"CLOSED",IF(AND($AS27<>"OPEN",$AT27<>"CLOSED"),"OPEN","")))))) | AX27: =IF(OR($AV27="OPEN",$AV27="CLOSED"),$AV27,$AW27) -> CLOSED | AY27: =IF(C27="HLEAR",BC27,AB27) -> 45708 | AZ27: =IF($AD27=0,"",AD27) -> 45896 | BA27: =IF(AND($AI27="",$AK27=""),"",IF($AI27="",$AK27,$AI27)) -> 0 | BC27: =IFERROR(INDEX(Program_01!BF:BF,MATCH($B27,Program_01!$A:$A,0)),"") -> 45708 | BD27: =IFERROR(INDEX(Program_01!BG:BG,MATCH($B27,Program_01!$A:$A,0)),"") -> N/A | BE27: =IFERROR(INDEX(Program_01!BH:BH,MATCH($B27,Program_01!$A:$A,0)),"") -> 45805 | BF27: =IFERROR(INDEX(Program_01!BI:BI,MATCH($B27,Program_01!$A:$A,0)),"") -> 47 | BG27: =IFERROR(INDEX(Program_01!BJ:BJ,MATCH($B27,Program_01!$A:$A,0)),"") -> 45852 | BH27: =IFERROR(INDEX(Program_01!BK:BK,MATCH($B27,Program_01!$A:$A,0)),"") -> 14 | BI27: =IFERROR(INDEX(Program_01!BL:BL,MATCH($B27,Program_01!$A:$A,0)),"") -> 45866 | BK27: =IFERROR(IF(INDEX(Program_01!$BX:$BX,MATCH($B27,Program_01!$A:$A,0))=DATE(1900,1,0),"",INDEX(Program_01!$BX:$BX,MATCH($B27,Program_01!$A:$A,0))),"") -> 45896 | BL27: =IFERROR(IF(INDEX(Program_01!$BY:$BY,MATCH($B27,Program_01!$A:$A,0))=DATE(1900,1,0),"",INDEX(Program_01!$BY:$BY,MATCH($B27,Program_01!$A:$A,0))),"") | BM27: =IF(OR($AZ27="",$AZ27="N/A"),"",IF(AND($AZ27="",$AY27<>""),TODAY()-$AY27,$AZ27-$AY27)) -> 188 | BN27: =IF(OR($C27="DEOT",$C27="N/A",$I27=""),"",IF(OR($AM27="Revise & resubmit",$AT27="Awaiting Conclusion of EoT",$AR27="Not Applicable",$AY27=0,$AY27="TBA",$AZ27="N/A",AY27=0),0,IF(AND($AR27="Assessment Report Issued",$AT27<>""),$AZ27-$AY27,IF(AND($AR27="Pending",$AT27="Contractor"),"",IF(AND($AZ27="",$AY27<>""),TODAY()-$AY27,$AZ27-$AY27))))) -> 188 | BO27: =IF(OR($AR27<>"ASSESSMENT REPORT ISSUED"),"",IF($BN27<>"",$BN27,"")) -> 188 | BP27: =IF($AR27="ASSESSMENT REPORT ISSUED","1",IF(AND($AT27="Closed",$AR27<>"Pending"),"1","")) -> 1 | BQ27: =IF(AND($AR27="Pending",$BN27>140),$BN27,"") | BR27: =IF(BQ27="","","1") | BT27: =IFERROR(IF(INDEX(Program_01!$BZ:$BZ,MATCH($B27,Program_01!$A:$A,0))=DATE(1900,1,0),"",INDEX(Program_01!$BZ:$BZ,MATCH($B27,Program_01!$A:$A,0))),"") | BU27: =IF(OR($I27="",$AV27="",$AM27<>0,$BA27="N/A",$AZ27=""),"",IF(AND($BA27="",$AZ27<>""),TODAY()-$AZ27,$BA27-$AZ27)) -> -45896 | BV27: =IF(OR($AS27="Determination Issued",$AS27="VO Issued"),$BU27,"") | BW27: =IF(OR($AT27="CLOSED",$AS27="Determination Issued",$AS27="VO Issued"),"1","") -> 1 | BX27: =IF(OR($AS27="Determination Issued",$AS27="VO Issued",$AS27="Rejected",$AS27="Canceled",$AS27="Superseded",$AS27="Not Applicable",$BU27=""),"",IF($BU27>90,$BU27,"")) | BY27: =IF(BX27="","","1") | CA27: =IF($I27="","",IF(AND($AR27="Assessment Report Issued",$AZ27<>""),"Y","N")) -> Y | CB27: =IF($I27="","",IF(OR($AS27="Determination Issued",$AS27="VO Issued"),"Y","N")) -> N | CC27: =IFERROR(INDEX(Program_01!$CE:$CE,MATCH($B27,Program_01!$A:$A,0)),"") -> 45258 | CD27: =MAX(S27,CC27) -> 45258 | CG27: =IFERROR(INDEX(Program_01!$AT:$AT,MATCH($B27,Program_01!$A:$A,0)),"") -> 0 | CH27: =IFERROR(INDEX(Program_01!$AX:$AX,MATCH($B27,Program_01!$A:$A,0)),"") -> 0
A28: Program_01 | B28: 10 | C28: =IFERROR(INDEX(Program_01!$B:$B,MATCH($B28,Program_01!$A:$A,0)),"") -> COST EAR | D28: =IFERROR(INDEX(Program_01!$D:$D,MATCH($B28,Program_01!$A:$A,0)),"") -> 1TB01031C02 | E28: =IFERROR(INDEX(Program_01!$E:$E,MATCH($B28,Program_01!$A:$A,0)),"") -> 1.TB.01.031.01 | F28: =IFERROR(INDEX(Program_01!$F:$F,MATCH($B28,Program_01!$A:$A,0)),"") -> The Marina | G28: =IFERROR(INDEX(Program_01!$G:$G,MATCH($B28,Program_01!$A:$A,0)),"") -> Triple Bay Marina Basin - Design and Build Main Contract | H28: =IFERROR(INDEX(Program_01!$H:$H,MATCH($B28,Program_01!$A:$A,0)),"") -> Alsaad General Contracting Company | I28: =IFERROR(IF($D28="","",INDEX($J$16:$O$16,MATCH(1,J28:O28,0))),"") -> Other Claims | J28: =IFERROR(INDEX(Program_01!$I:$I,MATCH($B28,Program_01!$A:$A,0)),"") -> 0 | K28: =IFERROR(INDEX(Program_01!$J:$J,MATCH($B28,Program_01!$A:$A,0)),"") -> 0 | L28: =IFERROR(INDEX(Program_01!$K:$K,MATCH($B28,Program_01!$A:$A,0)),"") -> 0 | M28: =IFERROR(INDEX(Program_01!$L:$L,MATCH($B28,Program_01!$A:$A,0)),"") -> 0 | N28: =IFERROR(INDEX(Program_01!$L:$L,MATCH($B28,Program_01!$A:$A,0)),"") -> 0 | O28: =IFERROR(INDEX(Program_01!$N:$N,MATCH($B28,Program_01!$A:$A,0)),"") -> 1 | Q28: =IFERROR(INDEX(Program_01!$C:$C,MATCH($B28,Program_01!$A:$A,0)),"") -> Notice of Dissatisfaction on Engineer's Determination - Works carried out by Binyah | R28: =IFERROR(INDEX(Program_01!$V:$V,MATCH($B28,Program_01!$A:$A,0)),"") -> 1TB01031-031C02-ALS-LTR-0283 | S28: =IFERROR(INDEX(Program_01!$W:$W,MATCH($B28,Program_01!$A:$A,0)),"") -> 45313 | U28: =IFERROR(INDEX(Program_01!$Z:$Z,MATCH($B28,Program_01!$A:$A,0)),"") -> Initial response not required | V28: =IFERROR(INDEX(Program_01!$AA:$AA,MATCH($B28,Program_01!$A:$A,0)),"") -> N/A | W28: =IF(OR($S28="",$V28="N/A"),"",IF(AND($S28<>0,$V28=0),TODAY()-$S28,IF(AND($S28<>"",$V28<>""),$V28-$S28))) | Y28: =IFERROR(INDEX(Program_01!$BD:$BD,MATCH($B28,Program_01!$A:$A,0)),"") -> 1TB01031-031D03-WSP-EIN-CM-0021 dated10 Dec 23 1TB01031-031D03-WSP-LTR-0408 dated 10 Dec 23 DVO-028 -EI-035 Additional Resources to ALS.pdf 1TB01031-031D03-WSP-LTR-0410 dated 11 Dec 23 1TB01031-031C02-ALS-LTR-0282 dated 09 Jan 24 1TB01031-031D03-WSP-LTR-0429 dated 31 Jan 24 1TB01031-031D03-WSP-LTR-0437 dated 12 Feb 24 1TB01031-031D03-WSP-LTR-0423 dated 13 Jan 24 1TB01031-031C02-ALS-LTR-0283 dated 22 Jan 24 | AA28: =IFERROR(IF((INDEX(Program_01!$AD:$AD,MATCH($B28,Program_01!$A:$A,0))=""),INDEX(Program_01!$V:$V,MATCH($B28,Program_01!$A:$A,0)),INDEX(Program_01!$AD:$AD,MATCH($B28,Program_01!$A:$A,0))),"") -> 1TB01031-031C02-ALS-LTR-0283 | AB28: =IFERROR(IF((INDEX(Program_01!$AE:$AE,MATCH($B28,Program_01!$A:$A,0))=""),INDEX(Program_01!$W:$W,MATCH($B28,Program_01!$A:$A,0)),INDEX(Program_01!$AE:$AE,MATCH($B28,Program_01!$A:$A,0))),"") -> 45313 | AC28: =IFERROR(IF($I28="EOT",INDEX(Program_01!$AN:$AN,MATCH($B28,Program_01!$A:$A,0)),INDEX(Program_01!$AY:$AY,MATCH($B28,Program_01!$A:$A,0))),"") -> N/A | AD28: =IFERROR(IF($I28="EOT",INDEX(Program_01!$AO:$AO,MATCH($B28,Program_01!$A:$A,0)),INDEX(Program_01!$AZ:$AZ,MATCH($B28,Program_01!$A:$A,0))),"") -> 0 | AH28: =IF(OR($D28="",$AS28="VO Issued",$AS28="Open"),"",IF(OR($AC28="Rejected",$AC28="Superseded",$AC28="Dealt Separately"),$AC28,IF($I28="EOT",INDEX(Program_01!$AR:$AR,MATCH($B28,Program_01!$A:$A,0)),INDEX(Program_01!$BB:$BB,MATCH($B28,Program_01!$A:$A,0))))) -> 0 | AI28: =IF(OR($A28="",$B28="",$I28="",$AS28="VO Issued",$AS28="Open"),"",IF(OR($AD28="N/A"),$AD28,IF($I28="EOT",INDEX(Program_01!$AS:$AS,MATCH($B28,Program_01!$A:$A,0)),INDEX(Program_01!$BC:$BC,MATCH($B28,Program_01!$A:$A,0))))) -> 0 | AJ28: =IF(OR($D28="",$I28="",$AS28="Determination Issued",$AS28="Rejected",$AS28="Open"),"",IF(OR($AH28="Rejected",$AH28="Dealt Separately",$AH28="Superseded",$AH28="Withdrawn"),"N/A",IF($I28="EOT",INDEX(Program_01!AR:AR,MATCH($B28,Program_01!A:A,0)),INDEX(Program_01!BB:BB,MATCH($B28,Program_01!A:A,0))))) -> 0 | AK28: =IF(OR($A28="",$B28="",$I28="",$AS28="Determination Issued",$AS28="Rejected",$AS28="Open"),"",IF($AJ28="N/A","N/A",IF($I28="EOT",INDEX(Program_01!AS:AS,MATCH($B28,Program_01!A:A,0)),INDEX(Program_01!BC:BC,MATCH($B28,Program_01!A:A,0))))) -> 0 | AM28: =IFERROR(INDEX(Program_01!$BT:$BT,MATCH($B28,Program_01!$A:$A,0)),"") -> 0 | AN28: =IFERROR(INDEX(Program_01!$BU:$BU,MATCH($B28,Program_01!$A:$A,0)),"") -> Yes | AO28: =IFERROR(INDEX(Program_01!$BV:$BV,MATCH($B28,Program_01!$A:$A,0)),"") -> 0 | AP28: =IF(OR($AN28="Yes",$AO28="Yes"),"1","") -> 1 | AQ28: =IFERROR(INDEX(Program_01!$BN:$BN,MATCH($B28,Program_01!$A:$A,0)),"") -> 0 | AR28: =IFERROR(INDEX(Program_01!$BO:$BO,MATCH($B28,Program_01!$A:$A,0)),"") -> Not Applicable | AS28: =IFERROR(INDEX(Program_01!$BP:$BP,MATCH($B28,Program_01!$A:$A,0)),"") -> Dealt Separately | AT28: =IFERROR(INDEX(Program_01!$BQ:$BQ,MATCH($B28,Program_01!$A:$A,0)),"") -> Closed | AU28: =IFERROR(INDEX(Program_01!$BR:$BR,MATCH($B28,Program_01!$A:$A,0)),"") -> 22 Dec 24: Ditto 13 Dec 24: Sasho had a discussion with the contractor to withdraw the letter. awaiting formal letter from contractor 27 Jan 25: this item to be moved to disputes tab note: to be removed from the list 10 Mar 25: Ditto, with Sasho 24 Mar 25: Ditto 07 Apr 25: Ditto 09 Apr 25: No further comments required as its a potential dispute 22 Apr 25: Ditto 04 May 25: Ditto, BK to speak with NE on the week commencing on the 18th of may to close the claim 19 May 25: Ditto 01-June-25: Ditto, FA in proccess. It is not expected that the Contractor will reopen this issue. 16 Jun 25: Ditto 30 Jun 25: Ditto, to be resolved with final account 14 July 25: Ditto 24 July 25: Drafting FA aggrement at the moment, wording ensures giving up the rights on all the open and potential claims. 12 Aug 25: Ditto 23 Aug 25: Contractor has accepted the Final Account statement via Email, this implies any NOD issued by the contractor is withdrawn. Official letter of withrawal will be requested to the Contractor, once FAS is signed and closed 08 Sep 25: Ditto 07 Oct 25: Ditto 03 Nov 25: Ditto 17 Nov 25: Ditto 01 Dec 25: Ditto, to be closed as final account has been finalised | AV28: =IF($I28="","",IF($S28>$AV$16,"",IF($AS28="OPEN","OPEN",IF($AS28="","",IF(AND($AS28<>"OPEN",$AT28="CLOSED"),"CLOSED",IF(AND($AS28<>"OPEN",$AT28<>"CLOSED"),"OPEN","")))))) | AW28: =IF($I28="","",IF($S28<$AW$16,"",IF($AS28="OPEN","OPEN",IF($AS28="","",IF(AND($AS28<>"OPEN",$AT28="CLOSED"),"CLOSED",IF(AND($AS28<>"OPEN",$AT28<>"CLOSED"),"OPEN","")))))) -> CLOSED | AX28: =IF(OR($AV28="OPEN",$AV28="CLOSED"),$AV28,$AW28) -> CLOSED | AY28: =IF(C28="HLEAR",BC28,AB28) -> 45313 | AZ28: =IF($AD28=0,"",AD28) | BA28: =IF(AND($AI28="",$AK28=""),"",IF($AI28="",$AK28,$AI28)) -> 0 | BC28: =IFERROR(INDEX(Program_01!BF:BF,MATCH($B28,Program_01!$A:$A,0)),"") -> 45313 | BD28: =IFERROR(INDEX(Program_01!BG:BG,MATCH($B28,Program_01!$A:$A,0)),"") -> N/A | BE28: =IFERROR(INDEX(Program_01!BH:BH,MATCH($B28,Program_01!$A:$A,0)),"") -> 0 | BF28: =IFERROR(INDEX(Program_01!BI:BI,MATCH($B28,Program_01!$A:$A,0)),"") -> N/A | BG28: =IFERROR(INDEX(Program_01!BJ:BJ,MATCH($B28,Program_01!$A:$A,0)),"") -> 0 | BH28: =IFERROR(INDEX(Program_01!BK:BK,MATCH($B28,Program_01!$A:$A,0)),"") -> 0 | BI28: =IFERROR(INDEX(Program_01!BL:BL,MATCH($B28,Program_01!$A:$A,0)),"") -> 0 | BK28: =IFERROR(IF(INDEX(Program_01!$BX:$BX,MATCH($B28,Program_01!$A:$A,0))=DATE(1900,1,0),"",INDEX(Program_01!$BX:$BX,MATCH($B28,Program_01!$A:$A,0))),"") -> 45992 | BL28: =IFERROR(IF(INDEX(Program_01!$BY:$BY,MATCH($B28,Program_01!$A:$A,0))=DATE(1900,1,0),"",INDEX(Program_01!$BY:$BY,MATCH($B28,Program_01!$A:$A,0))),"") | BM28: =IF(OR($AZ28="",$AZ28="N/A"),"",IF(AND($AZ28="",$AY28<>""),TODAY()-$AY28,$AZ28-$AY28)) | BN28: =IF(OR($C28="DEOT",$C28="N/A",$I28=""),"",IF(OR($AM28="Revise & resubmit",$AT28="Awaiting Conclusion of EoT",$AR28="Not Applicable",$AY28=0,$AY28="TBA",$AZ28="N/A",AY28=0),0,IF(AND($AR28="Assessment Report Issued",$AT28<>""),$AZ28-$AY28,IF(AND($AR28="Pending",$AT28="Contractor"),"",IF(AND($AZ28="",$AY28<>""),TODAY()-$AY28,$AZ28-$AY28))))) -> 0 | BO28: =IF(OR($AR28<>"ASSESSMENT REPORT ISSUED"),"",IF($BN28<>"",$BN28,"")) | BP28: =IF($AR28="ASSESSMENT REPORT ISSUED","1",IF(AND($AT28="Closed",$AR28<>"Pending"),"1","")) -> 1 | BQ28: =IF(AND($AR28="Pending",$BN28>140),$BN28,"") | BR28: =IF(BQ28="","","1") | BT28: =IFERROR(IF(INDEX(Program_01!$BZ:$BZ,MATCH($B28,Program_01!$A:$A,0))=DATE(1900,1,0),"",INDEX(Program_01!$BZ:$BZ,MATCH($B28,Program_01!$A:$A,0))),"") | BU28: =IF(OR($I28="",$AV28="",$AM28<>0,$BA28="N/A",$AZ28=""),"",IF(AND($BA28="",$AZ28<>""),TODAY()-$AZ28,$BA28-$AZ28)) | BV28: =IF(OR($AS28="Determination Issued",$AS28="VO Issued"),$BU28,"") | BW28: =IF(OR($AT28="CLOSED",$AS28="Determination Issued",$AS28="VO Issued"),"1","") -> 1 | BX28: =IF(OR($AS28="Determination Issued",$AS28="VO Issued",$AS28="Rejected",$AS28="Canceled",$AS28="Superseded",$AS28="Not Applicable",$BU28=""),"",IF($BU28>90,$BU28,"")) | BY28: =IF(BX28="","","1") | CA28: =IF($I28="","",IF(AND($AR28="Assessment Report Issued",$AZ28<>""),"Y","N")) -> N | CB28: =IF($I28="","",IF(OR($AS28="Determination Issued",$AS28="VO Issued"),"Y","N")) -> N | CC28: =IFERROR(INDEX(Program_01!$CE:$CE,MATCH($B28,Program_01!$A:$A,0)),"") -> 45313 | CD28: =MAX(S28,CC28) -> 45313 | CG28: =IFERROR(INDEX(Program_01!$AT:$AT,MATCH($B28,Program_01!$A:$A,0)),"") -> N/A | CH28: =IFERROR(INDEX(Program_01!$AX:$AX,MATCH($B28,Program_01!$A:$A,0)),"") -> 0
A29: Program_01 | B29: 11 | C29: =IFERROR(INDEX(Program_01!$B:$B,MATCH($B29,Program_01!$A:$A,0)),"") -> COST EAR | D29: =IFERROR(INDEX(Program_01!$D:$D,MATCH($B29,Program_01!$A:$A,0)),"") -> 1TB01005C02 | E29: =IFERROR(INDEX(Program_01!$E:$E,MATCH($B29,Program_01!$A:$A,0)),"") -> 1.TB.01.005.01 | F29: =IFERROR(INDEX(Program_01!$F:$F,MATCH($B29,Program_01!$A:$A,0)),"") -> Red Sea Marine Life Institute | G29: =IFERROR(INDEX(Program_01!$G:$G,MATCH($B29,Program_01!$A:$A,0)),"") -> Construction Contract - Structural Concrete, Wet Trades, Dewatering, Earthworks & BOH Finishes | H29: =IFERROR(INDEX(Program_01!$H:$H,MATCH($B29,Program_01!$A:$A,0)),"") -> Saudi Arabian Baytur Construction Company | I29: =IFERROR(IF($D29="","",INDEX($J$16:$O$16,MATCH(1,J29:O29,0))),"") -> Other Claims | J29: =IFERROR(INDEX(Program_01!$I:$I,MATCH($B29,Program_01!$A:$A,0)),"") -> 0 | K29: =IFERROR(INDEX(Program_01!$J:$J,MATCH($B29,Program_01!$A:$A,0)),"") -> 0 | L29: =IFERROR(INDEX(Program_01!$K:$K,MATCH($B29,Program_01!$A:$A,0)),"") -> 0 | M29: =IFERROR(INDEX(Program_01!$L:$L,MATCH($B29,Program_01!$A:$A,0)),"") -> 0 | N29: =IFERROR(INDEX(Program_01!$L:$L,MATCH($B29,Program_01!$A:$A,0)),"") -> 0 | O29: =IFERROR(INDEX(Program_01!$N:$N,MATCH($B29,Program_01!$A:$A,0)),"") -> 1 | Q29: =IFERROR(INDEX(Program_01!$C:$C,MATCH($B29,Program_01!$A:$A,0)),"") -> Application of Interim Extension of Time Claim No.01 - Temporary Opening in the Retaining Walls & Slab | R29: =IFERROR(INDEX(Program_01!$V:$V,MATCH($B29,Program_01!$A:$A,0)),"") -> 1TB01005-005C02-SAB-LTR-0069 | S29: =IFERROR(INDEX(Program_01!$W:$W,MATCH($B29,Program_01!$A:$A,0)),"") -> 45316 | U29: =IFERROR(INDEX(Program_01!$Z:$Z,MATCH($B29,Program_01!$A:$A,0)),"") -> 1TB01005-005C02-AMA-LTR-0112 | V29: =IFERROR(INDEX(Program_01!$AA:$AA,MATCH($B29,Program_01!$A:$A,0)),"") -> 45434 | W29: =IF(OR($S29="",$V29="N/A"),"",IF(AND($S29<>0,$V29=0),TODAY()-$S29,IF(AND($S29<>"",$V29<>""),$V29-$S29))) -> 118 | Y29: =IFERROR(INDEX(Program_01!$BD:$BD,MATCH($B29,Program_01!$A:$A,0)),"") -> 0 | AA29: =IFERROR(IF((INDEX(Program_01!$AD:$AD,MATCH($B29,Program_01!$A:$A,0))=""),INDEX(Program_01!$V:$V,MATCH($B29,Program_01!$A:$A,0)),INDEX(Program_01!$AD:$AD,MATCH($B29,Program_01!$A:$A,0))),"") -> 1TB01005-005C02-SAB-LTR-0069 | AB29: =IFERROR(IF((INDEX(Program_01!$AE:$AE,MATCH($B29,Program_01!$A:$A,0))=""),INDEX(Program_01!$W:$W,MATCH($B29,Program_01!$A:$A,0)),INDEX(Program_01!$AE:$AE,MATCH($B29,Program_01!$A:$A,0))),"") -> 45316 | AC29: =IFERROR(IF($I29="EOT",INDEX(Program_01!$AN:$AN,MATCH($B29,Program_01!$A:$A,0)),INDEX(Program_01!$AY:$AY,MATCH($B29,Program_01!$A:$A,0))),"") -> N/A | AD29: =IFERROR(IF($I29="EOT",INDEX(Program_01!$AO:$AO,MATCH($B29,Program_01!$A:$A,0)),INDEX(Program_01!$AZ:$AZ,MATCH($B29,Program_01!$A:$A,0))),"") -> 0 | AH29: =IF(OR($D29="",$AS29="VO Issued",$AS29="Open"),"",IF(OR($AC29="Rejected",$AC29="Superseded",$AC29="Dealt Separately"),$AC29,IF($I29="EOT",INDEX(Program_01!$AR:$AR,MATCH($B29,Program_01!$A:$A,0)),INDEX(Program_01!$BB:$BB,MATCH($B29,Program_01!$A:$A,0))))) -> 0 | AI29: =IF(OR($A29="",$B29="",$I29="",$AS29="VO Issued",$AS29="Open"),"",IF(OR($AD29="N/A"),$AD29,IF($I29="EOT",INDEX(Program_01!$AS:$AS,MATCH($B29,Program_01!$A:$A,0)),INDEX(Program_01!$BC:$BC,MATCH($B29,Program_01!$A:$A,0))))) -> 0 | AJ29: =IF(OR($D29="",$I29="",$AS29="Determination Issued",$AS29="Rejected",$AS29="Open"),"",IF(OR($AH29="Rejected",$AH29="Dealt Separately",$AH29="Superseded",$AH29="Withdrawn"),"N/A",IF($I29="EOT",INDEX(Program_01!AR:AR,MATCH($B29,Program_01!A:A,0)),INDEX(Program_01!BB:BB,MATCH($B29,Program_01!A:A,0))))) -> 0 | AK29: =IF(OR($A29="",$B29="",$I29="",$AS29="Determination Issued",$AS29="Rejected",$AS29="Open"),"",IF($AJ29="N/A","N/A",IF($I29="EOT",INDEX(Program_01!AS:AS,MATCH($B29,Program_01!A:A,0)),INDEX(Program_01!BC:BC,MATCH($B29,Program_01!A:A,0))))) -> 0 | AM29: =IFERROR(INDEX(Program_01!$BT:$BT,MATCH($B29,Program_01!$A:$A,0)),"") -> 0 | AN29: =IFERROR(INDEX(Program_01!$BU:$BU,MATCH($B29,Program_01!$A:$A,0)),"") -> 0 | AO29: =IFERROR(INDEX(Program_01!$BV:$BV,MATCH($B29,Program_01!$A:$A,0)),"") -> 0 | AP29: =IF(OR($AN29="Yes",$AO29="Yes"),"1","") | AQ29: =IFERROR(INDEX(Program_01!$BN:$BN,MATCH($B29,Program_01!$A:$A,0)),"") -> 0 | AR29: =IFERROR(INDEX(Program_01!$BO:$BO,MATCH($B29,Program_01!$A:$A,0)),"") -> Not Applicable | AS29: =IFERROR(INDEX(Program_01!$BP:$BP,MATCH($B29,Program_01!$A:$A,0)),"") -> Canceled | AT29: =IFERROR(INDEX(Program_01!$BQ:$BQ,MATCH($B29,Program_01!$A:$A,0)),"") -> Closed | AU29: =IFERROR(INDEX(Program_01!$BR:$BR,MATCH($B29,Program_01!$A:$A,0)),"") -> Note: this submission cannot be considered as a format EoT submission and hence considered cancelled / rejected Commercial records this is not a EOT, although the contractor mentioned it is a EOT item RFC was raised and approved PVO for wall opening rejected by Delivery - Temporary Works should be included Commercial currently gathering information, as we understand that these works were instructed over and above Temporary Works 10 Mar 24 - PVO to be uploaded again. Contractor has entitlement 25 Mar 24: PVO rejected by Senior Project Director on 23-Mar-24 (Revise and Resubmit status). 27-Mar-24: Commercial team to formally inform the contractor regardrding the rejection. 05-May-24: As per the Senior Project Director (RSMLI), the variation claim for temporary openings has been rejected. Hence, the associated EOT claim should be rejected, and an official response will be issued. 22 May 24: 1TB01005-005C02-AMA-LTR-0112 a response rejecting the claim was issued to the contractor | AV29: =IF($I29="","",IF($S29>$AV$16,"",IF($AS29="OPEN","OPEN",IF($AS29="","",IF(AND($AS29<>"OPEN",$AT29="CLOSED"),"CLOSED",IF(AND($AS29<>"OPEN",$AT29<>"CLOSED"),"OPEN","")))))) | AW29: =IF($I29="","",IF($S29<$AW$16,"",IF($AS29="OPEN","OPEN",IF($AS29="","",IF(AND($AS29<>"OPEN",$AT29="CLOSED"),"CLOSED",IF(AND($AS29<>"OPEN",$AT29<>"CLOSED"),"OPEN","")))))) -> CLOSED | AX29: =IF(OR($AV29="OPEN",$AV29="CLOSED"),$AV29,$AW29) -> CLOSED | AY29: =IF(C29="HLEAR",BC29,AB29) -> 45316 | AZ29: =IF($AD29=0,"",AD29) | BA29: =IF(AND($AI29="",$AK29=""),"",IF($AI29="",$AK29,$AI29)) -> 0 | BC29: =IFERROR(INDEX(Program_01!BF:BF,MATCH($B29,Program_01!$A:$A,0)),"") -> 45316 | BD29: =IFERROR(INDEX(Program_01!BG:BG,MATCH($B29,Program_01!$A:$A,0)),"") -> N/A | BE29: =IFERROR(INDEX(Program_01!BH:BH,MATCH($B29,Program_01!$A:$A,0)),"") -> 0 | BF29: =IFERROR(INDEX(Program_01!BI:BI,MATCH($B29,Program_01!$A:$A,0)),"") -> N/A | BG29: =IFERROR(INDEX(Program_01!BJ:BJ,MATCH($B29,Program_01!$A:$A,0)),"") -> 0 | BH29: =IFERROR(INDEX(Program_01!BK:BK,MATCH($B29,Program_01!$A:$A,0)),"") -> 0 | BI29: =IFERROR(INDEX(Program_01!BL:BL,MATCH($B29,Program_01!$A:$A,0)),"") -> 0 | BK29: =IFERROR(IF(INDEX(Program_01!$BX:$BX,MATCH($B29,Program_01!$A:$A,0))=DATE(1900,1,0),"",INDEX(Program_01!$BX:$BX,MATCH($B29,Program_01!$A:$A,0))),"") -> 45404 | BL29: =IFERROR(IF(INDEX(Program_01!$BY:$BY,MATCH($B29,Program_01!$A:$A,0))=DATE(1900,1,0),"",INDEX(Program_01!$BY:$BY,MATCH($B29,Program_01!$A:$A,0))),"") | BM29: =IF(OR($AZ29="",$AZ29="N/A"),"",IF(AND($AZ29="",$AY29<>""),TODAY()-$AY29,$AZ29-$AY29)) | BN29: =IF(OR($C29="DEOT",$C29="N/A",$I29=""),"",IF(OR($AM29="Revise & resubmit",$AT29="Awaiting Conclusion of EoT",$AR29="Not Applicable",$AY29=0,$AY29="TBA",$AZ29="N/A",AY29=0),0,IF(AND($AR29="Assessment Report Issued",$AT29<>""),$AZ29-$AY29,IF(AND($AR29="Pending",$AT29="Contractor"),"",IF(AND($AZ29="",$AY29<>""),TODAY()-$AY29,$AZ29-$AY29))))) -> 0 | BO29: =IF(OR($AR29<>"ASSESSMENT REPORT ISSUED"),"",IF($BN29<>"",$BN29,"")) | BP29: =IF($AR29="ASSESSMENT REPORT ISSUED","1",IF(AND($AT29="Closed",$AR29<>"Pending"),"1","")) -> 1 | BQ29: =IF(AND($AR29="Pending",$BN29>140),$BN29,"") | BR29: =IF(BQ29="","","1") | BT29: =IFERROR(IF(INDEX(Program_01!$BZ:$BZ,MATCH($B29,Program_01!$A:$A,0))=DATE(1900,1,0),"",INDEX(Program_01!$BZ:$BZ,MATCH($B29,Program_01!$A:$A,0))),"") | BU29: =IF(OR($I29="",$AV29="",$AM29<>0,$BA29="N/A",$AZ29=""),"",IF(AND($BA29="",$AZ29<>""),TODAY()-$AZ29,$BA29-$AZ29)) | BV29: =IF(OR($AS29="Determination Issued",$AS29="VO Issued"),$BU29,"") | BW29: =IF(OR($AT29="CLOSED",$AS29="Determination Issued",$AS29="VO Issued"),"1","") -> 1 | BX29: =IF(OR($AS29="Determination Issued",$AS29="VO Issued",$AS29="Rejected",$AS29="Canceled",$AS29="Superseded",$AS29="Not Applicable",$BU29=""),"",IF($BU29>90,$BU29,"")) | BY29: =IF(BX29="","","1") | CA29: =IF($I29="","",IF(AND($AR29="Assessment Report Issued",$AZ29<>""),"Y","N")) -> N | CB29: =IF($I29="","",IF(OR($AS29="Determination Issued",$AS29="VO Issued"),"Y","N")) -> N | CC29: =IFERROR(INDEX(Program_01!$CE:$CE,MATCH($B29,Program_01!$A:$A,0)),"") -> 0 | CD29: =MAX(S29,CC29) -> 45316 | CG29: =IFERROR(INDEX(Program_01!$AT:$AT,MATCH($B29,Program_01!$A:$A,0)),"") -> N/A | CH29: =IFERROR(INDEX(Program_01!$AX:$AX,MATCH($B29,Program_01!$A:$A,0)),"") -> 0
A30: Program_01 | B30: 12 | C30: =IFERROR(INDEX(Program_01!$B:$B,MATCH($B30,Program_01!$A:$A,0)),"") -> COST EAR | D30: =IFERROR(INDEX(Program_01!$D:$D,MATCH($B30,Program_01!$A:$A,0)),"") -> 1TB01003C03 | E30: =IFERROR(INDEX(Program_01!$E:$E,MATCH($B30,Program_01!$A:$A,0)),"") -> 1.TB.01.003.01 | F30: =IFERROR(INDEX(Program_01!$F:$F,MATCH($B30,Program_01!$A:$A,0)),"") -> AMAALA Yacht Club | G30: =IFERROR(INDEX(Program_01!$G:$G,MATCH($B30,Program_01!$A:$A,0)),"") -> Construction Contract - Site Enabling, Civil Works, Structural Concrete, Structural Steel, BOH Finishes, Building Envelope, MEP Including Tertiary Infrastructure & ICT/ELV | H30: =IFERROR(INDEX(Program_01!$H:$H,MATCH($B30,Program_01!$A:$A,0)),"") -> Saudi Arabian Baytur Construction Company | I30: =IFERROR(IF($D30="","",INDEX($J$16:$O$16,MATCH(1,J30:O30,0))),"") -> Other Claims | J30: =IFERROR(INDEX(Program_01!$I:$I,MATCH($B30,Program_01!$A:$A,0)),"") -> 0 | K30: =IFERROR(INDEX(Program_01!$J:$J,MATCH($B30,Program_01!$A:$A,0)),"") -> 0 | L30: =IFERROR(INDEX(Program_01!$K:$K,MATCH($B30,Program_01!$A:$A,0)),"") -> 0 | M30: =IFERROR(INDEX(Program_01!$L:$L,MATCH($B30,Program_01!$A:$A,0)),"") -> 0 | N30: =IFERROR(INDEX(Program_01!$L:$L,MATCH($B30,Program_01!$A:$A,0)),"") -> 0 | O30: =IFERROR(INDEX(Program_01!$N:$N,MATCH($B30,Program_01!$A:$A,0)),"") -> 1 | Q30: =IFERROR(INDEX(Program_01!$C:$C,MATCH($B30,Program_01!$A:$A,0)),"") -> Employer's Instructions - Rate of Progress, Notice of Dispute Sub-Clause 20.2.1 | R30: =IFERROR(INDEX(Program_01!$V:$V,MATCH($B30,Program_01!$A:$A,0)),"") -> 1TB01003-003C03-SAB-LTR-0068 (Notice of Dispute Letter) | S30: =IFERROR(INDEX(Program_01!$W:$W,MATCH($B30,Program_01!$A:$A,0)),"") -> 45330 | U30: =IFERROR(INDEX(Program_01!$Z:$Z,MATCH($B30,Program_01!$A:$A,0)),"") -> 1TB01003-003C03-AMA-LTR-0134 | V30: =IFERROR(INDEX(Program_01!$AA:$AA,MATCH($B30,Program_01!$A:$A,0)),"") -> 45350 | W30: =IF(OR($S30="",$V30="N/A"),"",IF(AND($S30<>0,$V30=0),TODAY()-$S30,IF(AND($S30<>"",$V30<>""),$V30-$S30))) -> 20 | Y30: =IFERROR(INDEX(Program_01!$BD:$BD,MATCH($B30,Program_01!$A:$A,0)),"") -> Dispute meeting had on 29 Feb 24 1TB01003-003C03-SAB-LTR-0076 dated 29 Feb 24 1TB01003-003C03-SAB-LTR-0079 dated 02 Mar 24 1TB01003-003C03-AMA-LTR-0144 dated 24 Mar 24 25 Mar 24: Amaala responded under 1TB01003-003C03-AMA-LTR-0145. 27 Mar 24: Conrtactor responded under 1TB01003-003C03-SAB-LTR-0084. 01 May 24: Amaala responded under 1TB01003-003C03-AMA-LTR-0154. 04 May 24: Conrtactor responded under 1TB01003-003C03-SAB-LTR-0088. 1TB01003-003C03-AMA-LTR-0168 Issued on 20 May 24 clarifying the Contractor the dispute mechanisms and that the Employer does not consider this matter to be a dispute at this stage | AA30: =IFERROR(IF((INDEX(Program_01!$AD:$AD,MATCH($B30,Program_01!$A:$A,0))=""),INDEX(Program_01!$V:$V,MATCH($B30,Program_01!$A:$A,0)),INDEX(Program_01!$AD:$AD,MATCH($B30,Program_01!$A:$A,0))),"") -> 1TB01003-003C03-SAB-LTR-0076 | AB30: =IFERROR(IF((INDEX(Program_01!$AE:$AE,MATCH($B30,Program_01!$A:$A,0))=""),INDEX(Program_01!$W:$W,MATCH($B30,Program_01!$A:$A,0)),INDEX(Program_01!$AE:$AE,MATCH($B30,Program_01!$A:$A,0))),"") -> 45351 | AC30: =IFERROR(IF($I30="EOT",INDEX(Program_01!$AN:$AN,MATCH($B30,Program_01!$A:$A,0)),INDEX(Program_01!$AY:$AY,MATCH($B30,Program_01!$A:$A,0))),"") -> 0 | AD30: =IFERROR(IF($I30="EOT",INDEX(Program_01!$AO:$AO,MATCH($B30,Program_01!$A:$A,0)),INDEX(Program_01!$AZ:$AZ,MATCH($B30,Program_01!$A:$A,0))),"") -> 0 | AH30: =IF(OR($D30="",$AS30="VO Issued",$AS30="Open"),"",IF(OR($AC30="Rejected",$AC30="Superseded",$AC30="Dealt Separately"),$AC30,IF($I30="EOT",INDEX(Program_01!$AR:$AR,MATCH($B30,Program_01!$A:$A,0)),INDEX(Program_01!$BB:$BB,MATCH($B30,Program_01!$A:$A,0))))) -> 0 | AI30: =IF(OR($A30="",$B30="",$I30="",$AS30="VO Issued",$AS30="Open"),"",IF(OR($AD30="N/A"),$AD30,IF($I30="EOT",INDEX(Program_01!$AS:$AS,MATCH($B30,Program_01!$A:$A,0)),INDEX(Program_01!$BC:$BC,MATCH($B30,Program_01!$A:$A,0))))) -> 0 | AJ30: =IF(OR($D30="",$I30="",$AS30="Determination Issued",$AS30="Rejected",$AS30="Open"),"",IF(OR($AH30="Rejected",$AH30="Dealt Separately",$AH30="Superseded",$AH30="Withdrawn"),"N/A",IF($I30="EOT",INDEX(Program_01!AR:AR,MATCH($B30,Program_01!A:A,0)),INDEX(Program_01!BB:BB,MATCH($B30,Program_01!A:A,0))))) -> 0 | AK30: =IF(OR($A30="",$B30="",$I30="",$AS30="Determination Issued",$AS30="Rejected",$AS30="Open"),"",IF($AJ30="N/A","N/A",IF($I30="EOT",INDEX(Program_01!AS:AS,MATCH($B30,Program_01!A:A,0)),INDEX(Program_01!BC:BC,MATCH($B30,Program_01!A:A,0))))) -> 0 | AM30: =IFERROR(INDEX(Program_01!$BT:$BT,MATCH($B30,Program_01!$A:$A,0)),"") -> 0 | AN30: =IFERROR(INDEX(Program_01!$BU:$BU,MATCH($B30,Program_01!$A:$A,0)),"") -> 0 | AO30: =IFERROR(INDEX(Program_01!$BV:$BV,MATCH($B30,Program_01!$A:$A,0)),"") -> Yes | AP30: =IF(OR($AN30="Yes",$AO30="Yes"),"1","") -> 1 | AQ30: =IFERROR(INDEX(Program_01!$BN:$BN,MATCH($B30,Program_01!$A:$A,0)),"") -> 0 | AR30: =IFERROR(INDEX(Program_01!$BO:$BO,MATCH($B30,Program_01!$A:$A,0)),"") -> Not Applicable | AS30: =IFERROR(INDEX(Program_01!$BP:$BP,MATCH($B30,Program_01!$A:$A,0)),"") -> Dealt Separately | AT30: =IFERROR(INDEX(Program_01!$BQ:$BQ,MATCH($B30,Program_01!$A:$A,0)),"") -> Closed | AU30: =IFERROR(INDEX(Program_01!$BR:$BR,MATCH($B30,Program_01!$A:$A,0)),"") -> The Contractor submitted several Notice of Claim and the Notice of Dispute via Aconex ref. 1TB01003-003C03-SAB-LTR-0068 dated 08 February 2024. Amaala is in the process of responding to the dispute letter. 26 Feb 24: Response letter in WF. Commercial to chase once issued, follow up email to be sent to the contractor to arrange a meeting. 28 Feb 24: Amaala issued a letter for a meeting to discuss and resolve the disputes and the contractor responded on 29 Feb 24 showing their dissagreement to our letter. 10 Mar 24: Amaala is in the process of responding to the contactor's comments. by 12 Mar 24 25 Mar 24: Amaala responded to the Contractor's comments on the meeting under 1TB01003-003C03-AMA-LTR-0144 on 24 March 24. 22 Apr 24: commercial to continue issuing delay notices to the contractor 06 May 24: response letter under preperation on the contractor's recent response 20 May 24: AMAALA responsed to the contractor's letter clarifying the Contractor, the dispute mechanisms and that the Employer does not consider this matter to be a dispute at this stage 03 Jun 24: this matter is considered closed under the letter 1TB01003-003C03-AMA-LTR-0168. | AV30: =IF($I30="","",IF($S30>$AV$16,"",IF($AS30="OPEN","OPEN",IF($AS30="","",IF(AND($AS30<>"OPEN",$AT30="CLOSED"),"CLOSED",IF(AND($AS30<>"OPEN",$AT30<>"CLOSED"),"OPEN","")))))) | AW30: =IF($I30="","",IF($S30<$AW$16,"",IF($AS30="OPEN","OPEN",IF($AS30="","",IF(AND($AS30<>"OPEN",$AT30="CLOSED"),"CLOSED",IF(AND($AS30<>"OPEN",$AT30<>"CLOSED"),"OPEN","")))))) -> CLOSED | AX30: =IF(OR($AV30="OPEN",$AV30="CLOSED"),$AV30,$AW30) -> CLOSED | AY30: =IF(C30="HLEAR",BC30,AB30) -> 45351 | AZ30: =IF($AD30=0,"",AD30) | BA30: =IF(AND($AI30="",$AK30=""),"",IF($AI30="",$AK30,$AI30)) -> 0 | BC30: =IFERROR(INDEX(Program_01!BF:BF,MATCH($B30,Program_01!$A:$A,0)),"") -> 45351 | BD30: =IFERROR(INDEX(Program_01!BG:BG,MATCH($B30,Program_01!$A:$A,0)),"") -> N/A | BE30: =IFERROR(INDEX(Program_01!BH:BH,MATCH($B30,Program_01!$A:$A,0)),"") -> 0 | BF30: =IFERROR(INDEX(Program_01!BI:BI,MATCH($B30,Program_01!$A:$A,0)),"") -> N/A | BG30: =IFERROR(INDEX(Program_01!BJ:BJ,MATCH($B30,Program_01!$A:$A,0)),"") -> 0 | BH30: =IFERROR(INDEX(Program_01!BK:BK,MATCH($B30,Program_01!$A:$A,0)),"") -> 0 | BI30: =IFERROR(INDEX(Program_01!BL:BL,MATCH($B30,Program_01!$A:$A,0)),"") -> 0 | BK30: =IFERROR(IF(INDEX(Program_01!$BX:$BX,MATCH($B30,Program_01!$A:$A,0))=DATE(1900,1,0),"",INDEX(Program_01!$BX:$BX,MATCH($B30,Program_01!$A:$A,0))),"") -> 45446 | BL30: =IFERROR(IF(INDEX(Program_01!$BY:$BY,MATCH($B30,Program_01!$A:$A,0))=DATE(1900,1,0),"",INDEX(Program_01!$BY:$BY,MATCH($B30,Program_01!$A:$A,0))),"") | BM30: =IF(OR($AZ30="",$AZ30="N/A"),"",IF(AND($AZ30="",$AY30<>""),TODAY()-$AY30,$AZ30-$AY30)) | BN30: =IF(OR($C30="DEOT",$C30="N/A",$I30=""),"",IF(OR($AM30="Revise & resubmit",$AT30="Awaiting Conclusion of EoT",$AR30="Not Applicable",$AY30=0,$AY30="TBA",$AZ30="N/A",AY30=0),0,IF(AND($AR30="Assessment Report Issued",$AT30<>""),$AZ30-$AY30,IF(AND($AR30="Pending",$AT30="Contractor"),"",IF(AND($AZ30="",$AY30<>""),TODAY()-$AY30,$AZ30-$AY30))))) -> 0 | BO30: =IF(OR($AR30<>"ASSESSMENT REPORT ISSUED"),"",IF($BN30<>"",$BN30,"")) | BP30: =IF($AR30="ASSESSMENT REPORT ISSUED","1",IF(AND($AT30="Closed",$AR30<>"Pending"),"1","")) -> 1 | BQ30: =IF(AND($AR30="Pending",$BN30>140),$BN30,"") | BR30: =IF(BQ30="","","1") | BT30: =IFERROR(IF(INDEX(Program_01!$BZ:$BZ,MATCH($B30,Program_01!$A:$A,0))=DATE(1900,1,0),"",INDEX(Program_01!$BZ:$BZ,MATCH($B30,Program_01!$A:$A,0))),"") | BU30: =IF(OR($I30="",$AV30="",$AM30<>0,$BA30="N/A",$AZ30=""),"",IF(AND($BA30="",$AZ30<>""),TODAY()-$AZ30,$BA30-$AZ30)) | BV30: =IF(OR($AS30="Determination Issued",$AS30="VO Issued"),$BU30,"") | BW30: =IF(OR($AT30="CLOSED",$AS30="Determination Issued",$AS30="VO Issued"),"1","") -> 1 | BX30: =IF(OR($AS30="Determination Issued",$AS30="VO Issued",$AS30="Rejected",$AS30="Canceled",$AS30="Superseded",$AS30="Not Applicable",$BU30=""),"",IF($BU30>90,$BU30,"")) | BY30: =IF(BX30="","","1") | CA30: =IF($I30="","",IF(AND($AR30="Assessment Report Issued",$AZ30<>""),"Y","N")) -> N | CB30: =IF($I30="","",IF(OR($AS30="Determination Issued",$AS30="VO Issued"),"Y","N")) -> N | CC30: =IFERROR(INDEX(Program_01!$CE:$CE,MATCH($B30,Program_01!$A:$A,0)),"") -> 45348 | CD30: =MAX(S30,CC30) -> 45348 | CG30: =IFERROR(INDEX(Program_01!$AT:$AT,MATCH($B30,Program_01!$A:$A,0)),"") -> N/A | CH30: =IFERROR(INDEX(Program_01!$AX:$AX,MATCH($B30,Program_01!$A:$A,0)),"") -> 0
A31: Program_01 | B31: 13 | C31: =IFERROR(INDEX(Program_01!$B:$B,MATCH($B31,Program_01!$A:$A,0)),"") -> FULL TIA EAR | D31: =IFERROR(INDEX(Program_01!$D:$D,MATCH($B31,Program_01!$A:$A,0)),"") -> 1TB01005C17 | E31: =IFERROR(INDEX(Program_01!$E:$E,MATCH($B31,Program_01!$A:$A,0)),"") -> 1.TB.01.005.01 | F31: =IFERROR(INDEX(Program_01!$F:$F,MATCH($B31,Program_01!$A:$A,0)),"") -> Red Sea Marine Life Institute | G31: =IFERROR(INDEX(Program_01!$G:$G,MATCH($B31,Program_01!$A:$A,0)),"") -> Marine Life Operation Facility for Marina Village | H31: =IFERROR(INDEX(Program_01!$H:$H,MATCH($B31,Program_01!$A:$A,0)),"") -> Hassan Hamdi Al Harbi Contracting Est. (HASCO) | I31: =IFERROR(IF($D31="","",INDEX($J$16:$O$16,MATCH(1,J31:O31,0))),"") -> EOT | J31: =IFERROR(INDEX(Program_01!$I:$I,MATCH($B31,Program_01!$A:$A,0)),"") -> 1 | K31: =IFERROR(INDEX(Program_01!$J:$J,MATCH($B31,Program_01!$A:$A,0)),"") -> 0 | L31: =IFERROR(INDEX(Program_01!$K:$K,MATCH($B31,Program_01!$A:$A,0)),"") -> 0 | M31: =IFERROR(INDEX(Program_01!$L:$L,MATCH($B31,Program_01!$A:$A,0)),"") -> 0 | N31: =IFERROR(INDEX(Program_01!$L:$L,MATCH($B31,Program_01!$A:$A,0)),"") -> 0 | O31: =IFERROR(INDEX(Program_01!$N:$N,MATCH($B31,Program_01!$A:$A,0)),"") -> 0 | Q31: =IFERROR(INDEX(Program_01!$C:$C,MATCH($B31,Program_01!$A:$A,0)),"") -> Settlement of Payment for Additional Cost and Time for Relocation of Jetty EOT 1 | R31: =IFERROR(INDEX(Program_01!$V:$V,MATCH($B31,Program_01!$A:$A,0)),"") -> 1TB01005-005C17-HAH-LTR-0040 | S31: =IFERROR(INDEX(Program_01!$W:$W,MATCH($B31,Program_01!$A:$A,0)),"") -> 45326 | U31: =IFERROR(INDEX(Program_01!$Z:$Z,MATCH($B31,Program_01!$A:$A,0)),"") -> 1TB01005-005C17-AMA-LTR-0041 | V31: =IFERROR(INDEX(Program_01!$AA:$AA,MATCH($B31,Program_01!$A:$A,0)),"") -> 45364 | W31: =IF(OR($S31="",$V31="N/A"),"",IF(AND($S31<>0,$V31=0),TODAY()-$S31,IF(AND($S31<>"",$V31<>""),$V31-$S31))) -> 38 | Y31: =IFERROR(INDEX(Program_01!$BD:$BD,MATCH($B31,Program_01!$A:$A,0)),"") -> 1TB01005-005C17-HAH-LTR-0040 dated 04 Feb 2024 1TB01005-005C17-AMA-LTR-0041 dated 13 Mar 2024 1TB01005-005C17-HAH-LTR-0044 dated 16 March 2024 (requesting for 4 days time) HAH01005-GENCORR-000059 dated 20 March 2024 (requesting more time) 1TB01005-005C17-HAH-LTR-0046 dated 01 May 2024 (revised detailed submission) 1TB01005-005C17-AMA-LTR-0042 dated 24 Jun 24 AMA01005-GENCORR-001996 dated 04 Oct 24 | AA31: =IFERROR(IF((INDEX(Program_01!$AD:$AD,MATCH($B31,Program_01!$A:$A,0))=""),INDEX(Program_01!$V:$V,MATCH($B31,Program_01!$A:$A,0)),INDEX(Program_01!$AD:$AD,MATCH($B31,Program_01!$A:$A,0))),"") -> 1TB01005-005C17-HAH-LTR-0046 dated 1 May 24 HAH01005-GENCORR-000067 on 18 Sep 24 Letter issued to contractor about employer's decision to proceed with the assessment in the absence of a revised claim (1TB01005-005C17-AMA-LTR-0044) (issued on 28 Jul 25) HAH01005-GENCORR-000067 | AB31: =IFERROR(IF((INDEX(Program_01!$AE:$AE,MATCH($B31,Program_01!$A:$A,0))=""),INDEX(Program_01!$W:$W,MATCH($B31,Program_01!$A:$A,0)),INDEX(Program_01!$AE:$AE,MATCH($B31,Program_01!$A:$A,0))),"") -> 45918 | AC31: =IFERROR(IF($I31="EOT",INDEX(Program_01!$AN:$AN,MATCH($B31,Program_01!$A:$A,0)),INDEX(Program_01!$AY:$AY,MATCH($B31,Program_01!$A:$A,0))),"") -> 1TB01005-005C17-AMA-LTR-0046 | AD31: =IFERROR(IF($I31="EOT",INDEX(Program_01!$AO:$AO,MATCH($B31,Program_01!$A:$A,0)),INDEX(Program_01!$AZ:$AZ,MATCH($B31,Program_01!$A:$A,0))),"") -> 45959 | AH31: =IF(OR($D31="",$AS31="VO Issued",$AS31="Open"),"",IF(OR($AC31="Rejected",$AC31="Superseded",$AC31="Dealt Separately"),$AC31,IF($I31="EOT",INDEX(Program_01!$AR:$AR,MATCH($B31,Program_01!$A:$A,0)),INDEX(Program_01!$BB:$BB,MATCH($B31,Program_01!$A:$A,0))))) -> 0 | AI31: =IF(OR($A31="",$B31="",$I31="",$AS31="VO Issued",$AS31="Open"),"",IF(OR($AD31="N/A"),$AD31,IF($I31="EOT",INDEX(Program_01!$AS:$AS,MATCH($B31,Program_01!$A:$A,0)),INDEX(Program_01!$BC:$BC,MATCH($B31,Program_01!$A:$A,0))))) -> 0 | AJ31: =IF(OR($D31="",$I31="",$AS31="Determination Issued",$AS31="Rejected",$AS31="Open"),"",IF(OR($AH31="Rejected",$AH31="Dealt Separately",$AH31="Superseded",$AH31="Withdrawn"),"N/A",IF($I31="EOT",INDEX(Program_01!AR:AR,MATCH($B31,Program_01!A:A,0)),INDEX(Program_01!BB:BB,MATCH($B31,Program_01!A:A,0))))) -> 0 | AK31: =IF(OR($A31="",$B31="",$I31="",$AS31="Determination Issued",$AS31="Rejected",$AS31="Open"),"",IF($AJ31="N/A","N/A",IF($I31="EOT",INDEX(Program_01!AS:AS,MATCH($B31,Program_01!A:A,0)),INDEX(Program_01!BC:BC,MATCH($B31,Program_01!A:A,0))))) -> 0 | AM31: =IFERROR(INDEX(Program_01!$BT:$BT,MATCH($B31,Program_01!$A:$A,0)),"") -> 0 | AN31: =IFERROR(INDEX(Program_01!$BU:$BU,MATCH($B31,Program_01!$A:$A,0)),"") -> 0 | AO31: =IFERROR(INDEX(Program_01!$BV:$BV,MATCH($B31,Program_01!$A:$A,0)),"") -> 0 | AP31: =IF(OR($AN31="Yes",$AO31="Yes"),"1","") | AQ31: =IFERROR(INDEX(Program_01!$BN:$BN,MATCH($B31,Program_01!$A:$A,0)),"") -> 0 | AR31: =IFERROR(INDEX(Program_01!$BO:$BO,MATCH($B31,Program_01!$A:$A,0)),"") -> Assessment Report Issued | AS31: =IFERROR(INDEX(Program_01!$BP:$BP,MATCH($B31,Program_01!$A:$A,0)),"") -> DVO Issued | AT31: =IFERROR(INDEX(Program_01!$BQ:$BQ,MATCH($B31,Program_01!$A:$A,0)),"") -> Closed | AU31: =IFERROR(INDEX(Program_01!$BR:$BR,MATCH($B31,Program_01!$A:$A,0)),"") -> 30 June 25: Commercial to issue report to planning by 3rd July. 14 Jul 25: Report delayed but will be issued by the Site team on 17 Jul at the very latest. 21 Jul 25: Draft report sent to claims team for review, commercial has been advised that we write to them that we are proceeding with the assessment with the available data in the absence of a revised claim from the contrator 27 July 2025 Ditto. Targeted to revert by 5 Aug 2025 12 Aug 25: targeted to revert by 14 Aug 25 18 Aug 25: Draft report sent back to commercial with comments, after finalisation, commercial to submit the draft with planning to commence TIA || Draft report sent to Planing to conduct TIA 23 Aug 25: Sent for planning assessment 20 Aug 25, targetd to finalise by 26 Aug 25 26 Aug 25: TIA incorporated - TOC in Aconex rejected rejected and therefore should be amended to reflect the recommended 70-day EOT, as no VO has been referenced to support the extension to 13 Oct 2023 27 Aug 25: Planning provided the xer file to support the concurrency 06 Sept 25: TIA incorporated, Draft EAR sent to claims for approval 08 Sep 25: under reviewwith claims 27 Sep 25: Draft EAR sent back to commercial with comments & amendments for commercial to address. 28 Sep 25: Final Draft sent to claims for review & approval // Draft sent to KM on 30 Sep 25 06 Oct 25: Ditto - Nb FA number has now been agreed with Contractor and paperwork for this is progressing 06 Oct 25: Final Draft EAR approved and sent back to commercial to initiate WF 07 Oct 25: EAR put in WF-035199 17 Oct 25: EAR approval with planning for approval since 08 October 20 Oct 25: EAR approved, commercial to prepare the cover letter and initiate the WF for issuance 29 Oct 25: EAR issued to contractor via 1TB01005-005C17-AMA-LTR-0046 03 Nov 25: awaiting response from contractor 14 Nov 25: Contractor has accepted EAR (1TB01005-005C17-HAH-LTR-0048) 17 Nov 25: Commercial to issue EI, targeted to issue by 20 Nov 25 28 Nov 25: VO/DVO confirms the EoT award - HAH01005-GENCORR-000069 | AV31: =IF($I31="","",IF($S31>$AV$16,"",IF($AS31="OPEN","OPEN",IF($AS31="","",IF(AND($AS31<>"OPEN",$AT31="CLOSED"),"CLOSED",IF(AND($AS31<>"OPEN",$AT31<>"CLOSED"),"OPEN","")))))) | AW31: =IF($I31="","",IF($S31<$AW$16,"",IF($AS31="OPEN","OPEN",IF($AS31="","",IF(AND($AS31<>"OPEN",$AT31="CLOSED"),"CLOSED",IF(AND($AS31<>"OPEN",$AT31<>"CLOSED"),"OPEN","")))))) -> CLOSED | AX31: =IF(OR($AV31="OPEN",$AV31="CLOSED"),$AV31,$AW31) -> CLOSED | AY31: =IF(C31="HLEAR",BC31,AB31) -> 45918 | AZ31: =IF($AD31=0,"",AD31) -> 45959 | BA31: =IF(AND($AI31="",$AK31=""),"",IF($AI31="",$AK31,$AI31)) -> 0 | BC31: =IFERROR(INDEX(Program_01!BF:BF,MATCH($B31,Program_01!$A:$A,0)),"") -> 45918 | BD31: =IFERROR(INDEX(Program_01!BG:BG,MATCH($B31,Program_01!$A:$A,0)),"") -> N/A | BE31: =IFERROR(INDEX(Program_01!BH:BH,MATCH($B31,Program_01!$A:$A,0)),"") -> 0 | BF31: =IFERROR(INDEX(Program_01!BI:BI,MATCH($B31,Program_01!$A:$A,0)),"") -> 0 | BG31: =IFERROR(INDEX(Program_01!BJ:BJ,MATCH($B31,Program_01!$A:$A,0)),"") -> 0 | BH31: =IFERROR(INDEX(Program_01!BK:BK,MATCH($B31,Program_01!$A:$A,0)),"") -> 0 | BI31: =IFERROR(INDEX(Program_01!BL:BL,MATCH($B31,Program_01!$A:$A,0)),"") -> 0 | BK31: =IFERROR(IF(INDEX(Program_01!$BX:$BX,MATCH($B31,Program_01!$A:$A,0))=DATE(1900,1,0),"",INDEX(Program_01!$BX:$BX,MATCH($B31,Program_01!$A:$A,0))),"") -> 45959 | BL31: =IFERROR(IF(INDEX(Program_01!$BY:$BY,MATCH($B31,Program_01!$A:$A,0))=DATE(1900,1,0),"",INDEX(Program_01!$BY:$BY,MATCH($B31,Program_01!$A:$A,0))),"") | BM31: =IF(OR($AZ31="",$AZ31="N/A"),"",IF(AND($AZ31="",$AY31<>""),TODAY()-$AY31,$AZ31-$AY31)) -> 41 | BN31: =IF(OR($C31="DEOT",$C31="N/A",$I31=""),"",IF(OR($AM31="Revise & resubmit",$AT31="Awaiting Conclusion of EoT",$AR31="Not Applicable",$AY31=0,$AY31="TBA",$AZ31="N/A",AY31=0),0,IF(AND($AR31="Assessment Report Issued",$AT31<>""),$AZ31-$AY31,IF(AND($AR31="Pending",$AT31="Contractor"),"",IF(AND($AZ31="",$AY31<>""),TODAY()-$AY31,$AZ31-$AY31))))) -> 41 | BO31: =IF(OR($AR31<>"ASSESSMENT REPORT ISSUED"),"",IF($BN31<>"",$BN31,"")) -> 41 | BP31: =IF($AR31="ASSESSMENT REPORT ISSUED","1",IF(AND($AT31="Closed",$AR31<>"Pending"),"1","")) -> 1 | BQ31: =IF(AND($AR31="Pending",$BN31>140),$BN31,"") | BR31: =IF(BQ31="","","1") | BT31: =IFERROR(IF(INDEX(Program_01!$BZ:$BZ,MATCH($B31,Program_01!$A:$A,0))=DATE(1900,1,0),"",INDEX(Program_01!$BZ:$BZ,MATCH($B31,Program_01!$A:$A,0))),"") | BU31: =IF(OR($I31="",$AV31="",$AM31<>0,$BA31="N/A",$AZ31=""),"",IF(AND($BA31="",$AZ31<>""),TODAY()-$AZ31,$BA31-$AZ31)) | BV31: =IF(OR($AS31="Determination Issued",$AS31="VO Issued"),$BU31,"") | BW31: =IF(OR($AT31="CLOSED",$AS31="Determination Issued",$AS31="VO Issued"),"1","") -> 1 | BX31: =IF(OR($AS31="Determination Issued",$AS31="VO Issued",$AS31="Rejected",$AS31="Canceled",$AS31="Superseded",$AS31="Not Applicable",$BU31=""),"",IF($BU31>90,$BU31,"")) | BY31: =IF(BX31="","","1") | CA31: =IF($I31="","",IF(AND($AR31="Assessment Report Issued",$AZ31<>""),"Y","N")) -> Y | CB31: =IF($I31="","",IF(OR($AS31="Determination Issued",$AS31="VO Issued"),"Y","N")) -> N | CC31: =IFERROR(INDEX(Program_01!$CE:$CE,MATCH($B31,Program_01!$A:$A,0)),"") -> 45362 | CD31: =MAX(S31,CC31) -> 45362 | CG31: =IFERROR(INDEX(Program_01!$AT:$AT,MATCH($B31,Program_01!$A:$A,0)),"") -> 0 | CH31: =IFERROR(INDEX(Program_01!$AX:$AX,MATCH($B31,Program_01!$A:$A,0)),"") -> 0
A32: Program_01 | B32: 14 | C32: =IFERROR(INDEX(Program_01!$B:$B,MATCH($B32,Program_01!$A:$A,0)),"") -> COST EAR | D32: =IFERROR(INDEX(Program_01!$D:$D,MATCH($B32,Program_01!$A:$A,0)),"") -> 1TB01005C17 | E32: =IFERROR(INDEX(Program_01!$E:$E,MATCH($B32,Program_01!$A:$A,0)),"") -> 1.TB.01.005.01 | F32: =IFERROR(INDEX(Program_01!$F:$F,MATCH($B32,Program_01!$A:$A,0)),"") -> Red Sea Marine Life Institute | G32: =IFERROR(INDEX(Program_01!$G:$G,MATCH($B32,Program_01!$A:$A,0)),"") -> Marine Life Operation Facility for Marina Village | H32: =IFERROR(INDEX(Program_01!$H:$H,MATCH($B32,Program_01!$A:$A,0)),"") -> Hassan Hamdi Al Harbi Contracting Est. (HASCO) | I32: =IFERROR(IF($D32="","",INDEX($J$16:$O$16,MATCH(1,J32:O32,0))),"") -> Prolongation | J32: =IFERROR(INDEX(Program_01!$I:$I,MATCH($B32,Program_01!$A:$A,0)),"") -> 0 | K32: =IFERROR(INDEX(Program_01!$J:$J,MATCH($B32,Program_01!$A:$A,0)),"") -> 1 | L32: =IFERROR(INDEX(Program_01!$K:$K,MATCH($B32,Program_01!$A:$A,0)),"") -> 0 | M32: =IFERROR(INDEX(Program_01!$L:$L,MATCH($B32,Program_01!$A:$A,0)),"") -> 0 | N32: =IFERROR(INDEX(Program_01!$L:$L,MATCH($B32,Program_01!$A:$A,0)),"") -> 0 | O32: =IFERROR(INDEX(Program_01!$N:$N,MATCH($B32,Program_01!$A:$A,0)),"") -> 0 | Q32: =IFERROR(INDEX(Program_01!$C:$C,MATCH($B32,Program_01!$A:$A,0)),"") -> Settlement of Payment for Additional Cost and Time for Relocation of Jetty Prolongation | R32: =IFERROR(INDEX(Program_01!$V:$V,MATCH($B32,Program_01!$A:$A,0)),"") -> 1TB01005-005C17-HAH-LTR-0040 | S32: =IFERROR(INDEX(Program_01!$W:$W,MATCH($B32,Program_01!$A:$A,0)),"") -> 45326 | U32: =IFERROR(INDEX(Program_01!$Z:$Z,MATCH($B32,Program_01!$A:$A,0)),"") -> 1TB01005-005C17-AMA-LTR-0041 | V32: =IFERROR(INDEX(Program_01!$AA:$AA,MATCH($B32,Program_01!$A:$A,0)),"") -> 45364 | W32: =IF(OR($S32="",$V32="N/A"),"",IF(AND($S32<>0,$V32=0),TODAY()-$S32,IF(AND($S32<>"",$V32<>""),$V32-$S32))) -> 38 | Y32: =IFERROR(INDEX(Program_01!$BD:$BD,MATCH($B32,Program_01!$A:$A,0)),"") -> 0 | AA32: =IFERROR(IF((INDEX(Program_01!$AD:$AD,MATCH($B32,Program_01!$A:$A,0))=""),INDEX(Program_01!$V:$V,MATCH($B32,Program_01!$A:$A,0)),INDEX(Program_01!$AD:$AD,MATCH($B32,Program_01!$A:$A,0))),"") -> 1TB01005-005C17-HAH-LTR-0046 dated 1 May 24 HAH01005-GENCORR-000067 | AB32: =IFERROR(IF((INDEX(Program_01!$AE:$AE,MATCH($B32,Program_01!$A:$A,0))=""),INDEX(Program_01!$W:$W,MATCH($B32,Program_01!$A:$A,0)),INDEX(Program_01!$AE:$AE,MATCH($B32,Program_01!$A:$A,0))),"") -> 45553 | AC32: =IFERROR(IF($I32="EOT",INDEX(Program_01!$AN:$AN,MATCH($B32,Program_01!$A:$A,0)),INDEX(Program_01!$AY:$AY,MATCH($B32,Program_01!$A:$A,0))),"") -> 1TB01005-005C17-AMA-DVO-CM-0002 | AD32: =IFERROR(IF($I32="EOT",INDEX(Program_01!$AO:$AO,MATCH($B32,Program_01!$A:$A,0)),INDEX(Program_01!$AZ:$AZ,MATCH($B32,Program_01!$A:$A,0))),"") -> 45945 | AH32: =IF(OR($D32="",$AS32="VO Issued",$AS32="Open"),"",IF(OR($AC32="Rejected",$AC32="Superseded",$AC32="Dealt Separately"),$AC32,IF($I32="EOT",INDEX(Program_01!$AR:$AR,MATCH($B32,Program_01!$A:$A,0)),INDEX(Program_01!$BB:$BB,MATCH($B32,Program_01!$A:$A,0))))) -> 0 | AI32: =IF(OR($A32="",$B32="",$I32="",$AS32="VO Issued",$AS32="Open"),"",IF(OR($AD32="N/A"),$AD32,IF($I32="EOT",INDEX(Program_01!$AS:$AS,MATCH($B32,Program_01!$A:$A,0)),INDEX(Program_01!$BC:$BC,MATCH($B32,Program_01!$A:$A,0))))) -> 0 | AJ32: =IF(OR($D32="",$I32="",$AS32="Determination Issued",$AS32="Rejected",$AS32="Open"),"",IF(OR($AH32="Rejected",$AH32="Dealt Separately",$AH32="Superseded",$AH32="Withdrawn"),"N/A",IF($I32="EOT",INDEX(Program_01!AR:AR,MATCH($B32,Program_01!A:A,0)),INDEX(Program_01!BB:BB,MATCH($B32,Program_01!A:A,0))))) -> 0 | AK32: =IF(OR($A32="",$B32="",$I32="",$AS32="Determination Issued",$AS32="Rejected",$AS32="Open"),"",IF($AJ32="N/A","N/A",IF($I32="EOT",INDEX(Program_01!AS:AS,MATCH($B32,Program_01!A:A,0)),INDEX(Program_01!BC:BC,MATCH($B32,Program_01!A:A,0))))) -> 0 | AM32: =IFERROR(INDEX(Program_01!$BT:$BT,MATCH($B32,Program_01!$A:$A,0)),"") -> 0 | AN32: =IFERROR(INDEX(Program_01!$BU:$BU,MATCH($B32,Program_01!$A:$A,0)),"") -> 0 | AO32: =IFERROR(INDEX(Program_01!$BV:$BV,MATCH($B32,Program_01!$A:$A,0)),"") -> 0 | AP32: =IF(OR($AN32="Yes",$AO32="Yes"),"1","") | AQ32: =IFERROR(INDEX(Program_01!$BN:$BN,MATCH($B32,Program_01!$A:$A,0)),"") -> 0 | AR32: =IFERROR(INDEX(Program_01!$BO:$BO,MATCH($B32,Program_01!$A:$A,0)),"") -> Not Applicable | AS32: =IFERROR(INDEX(Program_01!$BP:$BP,MATCH($B32,Program_01!$A:$A,0)),"") -> DVO Issued | AT32: =IFERROR(INDEX(Program_01!$BQ:$BQ,MATCH($B32,Program_01!$A:$A,0)),"") -> Closed | AU32: =IFERROR(INDEX(Program_01!$BR:$BR,MATCH($B32,Program_01!$A:$A,0)),"") -> 08 Sep 24: Cost claim awaiting conclusion of EoT 24 Sep 24: Contractor resubmitted the claim on 18 Sep 24. commercial to review. Meeting held with HASCO on 17 Sept 24 and RSG to review costs submitted and provide comments by 28 Sept 24. Further meeting to be arranged to try and conclude. 04 Oct 24: a meeting was arranged with HASCO for October 9, and the outcome will be shared with the Claims team. 17 Nov 24: The meeting with HASCO on 12 November 2024, involving RSMLI Senior Directors, was cancelled by HASCO last minute and remains unscheduled. A revised close-out strategy is required, and the Senior Project Director will only be available for a meeting mid-December. 04 Dec 24 - Meeting arranged for 17th December to agree a final account. 11 Jan 25 - same comment as above line item 26 Jan 25: Ditto as above 28 Jan 25: Assessment to be completed; target date 6th Feb 23 Feb 25: Same comment as Item 13 Ditto 19 Apr 25: No further submission from HASCO. Internal assessment and report on-going. 04 May 25: Targeted to finalise the report by end of June 2025. 18 May 25: Ditto 03 Nov 25: comm to update status 17 Nov 25: DVO in relation to this prolongation cost was issued to DVO (1TB01005-005C17-AMA-DVO-CM-0002 ). hence this line item has been closed | AV32: =IF($I32="","",IF($S32>$AV$16,"",IF($AS32="OPEN","OPEN",IF($AS32="","",IF(AND($AS32<>"OPEN",$AT32="CLOSED"),"CLOSED",IF(AND($AS32<>"OPEN",$AT32<>"CLOSED"),"OPEN","")))))) | AW32: =IF($I32="","",IF($S32<$AW$16,"",IF($AS32="OPEN","OPEN",IF($AS32="","",IF(AND($AS32<>"OPEN",$AT32="CLOSED"),"CLOSED",IF(AND($AS32<>"OPEN",$AT32<>"CLOSED"),"OPEN","")))))) -> CLOSED | AX32: =IF(OR($AV32="OPEN",$AV32="CLOSED"),$AV32,$AW32) -> CLOSED | AY32: =IF(C32="HLEAR",BC32,AB32) -> 45553 | AZ32: =IF($AD32=0,"",AD32) -> 45945 | BA32: =IF(AND($AI32="",$AK32=""),"",IF($AI32="",$AK32,$AI32)) -> 0 | BC32: =IFERROR(INDEX(Program_01!BF:BF,MATCH($B32,Program_01!$A:$A,0)),"") -> 45553 | BD32: =IFERROR(INDEX(Program_01!BG:BG,MATCH($B32,Program_01!$A:$A,0)),"") -> N/A | BE32: =IFERROR(INDEX(Program_01!BH:BH,MATCH($B32,Program_01!$A:$A,0)),"") -> 0 | BF32: =IFERROR(INDEX(Program_01!BI:BI,MATCH($B32,Program_01!$A:$A,0)),"") -> N/A | BG32: =IFERROR(INDEX(Program_01!BJ:BJ,MATCH($B32,Program_01!$A:$A,0)),"") -> 0 | BH32: =IFERROR(INDEX(Program_01!BK:BK,MATCH($B32,Program_01!$A:$A,0)),"") -> 0 | BI32: =IFERROR(INDEX(Program_01!BL:BL,MATCH($B32,Program_01!$A:$A,0)),"") -> 0 | BK32: =IFERROR(IF(INDEX(Program_01!$BX:$BX,MATCH($B32,Program_01!$A:$A,0))=DATE(1900,1,0),"",INDEX(Program_01!$BX:$BX,MATCH($B32,Program_01!$A:$A,0))),"") -> 45978 | BL32: =IFERROR(IF(INDEX(Program_01!$BY:$BY,MATCH($B32,Program_01!$A:$A,0))=DATE(1900,1,0),"",INDEX(Program_01!$BY:$BY,MATCH($B32,Program_01!$A:$A,0))),"") | BM32: =IF(OR($AZ32="",$AZ32="N/A"),"",IF(AND($AZ32="",$AY32<>""),TODAY()-$AY32,$AZ32-$AY32)) -> 392 | BN32: =IF(OR($C32="DEOT",$C32="N/A",$I32=""),"",IF(OR($AM32="Revise & resubmit",$AT32="Awaiting Conclusion of EoT",$AR32="Not Applicable",$AY32=0,$AY32="TBA",$AZ32="N/A",AY32=0),0,IF(AND($AR32="Assessment Report Issued",$AT32<>""),$AZ32-$AY32,IF(AND($AR32="Pending",$AT32="Contractor"),"",IF(AND($AZ32="",$AY32<>""),TODAY()-$AY32,$AZ32-$AY32))))) -> 0 | BO32: =IF(OR($AR32<>"ASSESSMENT REPORT ISSUED"),"",IF($BN32<>"",$BN32,"")) | BP32: =IF($AR32="ASSESSMENT REPORT ISSUED","1",IF(AND($AT32="Closed",$AR32<>"Pending"),"1","")) -> 1 | BQ32: =IF(AND($AR32="Pending",$BN32>140),$BN32,"") | BR32: =IF(BQ32="","","1") | BT32: =IFERROR(IF(INDEX(Program_01!$BZ:$BZ,MATCH($B32,Program_01!$A:$A,0))=DATE(1900,1,0),"",INDEX(Program_01!$BZ:$BZ,MATCH($B32,Program_01!$A:$A,0))),"") | BU32: =IF(OR($I32="",$AV32="",$AM32<>0,$BA32="N/A",$AZ32=""),"",IF(AND($BA32="",$AZ32<>""),TODAY()-$AZ32,$BA32-$AZ32)) | BV32: =IF(OR($AS32="Determination Issued",$AS32="VO Issued"),$BU32,"") | BW32: =IF(OR($AT32="CLOSED",$AS32="Determination Issued",$AS32="VO Issued"),"1","") -> 1 | BX32: =IF(OR($AS32="Determination Issued",$AS32="VO Issued",$AS32="Rejected",$AS32="Canceled",$AS32="Superseded",$AS32="Not Applicable",$BU32=""),"",IF($BU32>90,$BU32,"")) | BY32: =IF(BX32="","","1") | CA32: =IF($I32="","",IF(AND($AR32="Assessment Report Issued",$AZ32<>""),"Y","N")) -> N | CB32: =IF($I32="","",IF(OR($AS32="Determination Issued",$AS32="VO Issued"),"Y","N")) -> N | CC32: =IFERROR(INDEX(Program_01!$CE:$CE,MATCH($B32,Program_01!$A:$A,0)),"") -> 45362 | CD32: =MAX(S32,CC32) -> 45362 | CG32: =IFERROR(INDEX(Program_01!$AT:$AT,MATCH($B32,Program_01!$A:$A,0)),"") -> 1160000 | CH32: =IFERROR(INDEX(Program_01!$AX:$AX,MATCH($B32,Program_01!$A:$A,0)),"") -> 100000 | CI32: Dealt Separately
